Workbook

Sheet Summary
A1: Paladin (ScalpX) — trading information extracted from posted images
A2: Channel #🔮｜paladin, 2026-05-06 to 2026-08-21. Every one of the 320 images (incl. 2 screen recordings) was viewed and transcribed; numbers are copied from the image, never inferred.
A4: Coverage
A5: Images analysed | B5: =COUNTA(Images!A2:A100000) -> 320
A6: Images with trading information | B6: =COUNTIF(Images!D2:D100000,"yes") -> 318
A7: Images with no trading information | B7: =COUNTIF(Images!D2:D100000,"no") -> 2
A8: Trade rows extracted | B8: =COUNTA(Trades!C2:C100000) -> 335
A9: Price charts captured | B9: =COUNTA(Charts!A2:A100000) -> 24
A10: Rows flagged medium confidence | B10: =COUNTIF(Images!Q2:Q100000,"medium") -> 38
A12: Field fill rate (of trade rows)
A13: Entry price | B13: =COUNT(Trades!H2:H100000) -> 224 | C13: =IF($B$8=0,"-",B13/$B$8) -> 0.66865672
A14: Exit / close price | B14: =COUNT(Trades!I2:I100000) -> 223 | C14: =IF($B$8=0,"-",B14/$B$8) -> 0.66567164
A15: ROI % | B15: =COUNT(Trades!K2:K100000) -> 268 | C15: =IF($B$8=0,"-",B15/$B$8) -> 0.8
A16: Leverage | B16: =COUNT(Trades!F2:F100000) -> 234 | C16: =IF($B$8=0,"-",B16/$B$8) -> 0.69850746
A17: Side (long/short) | B17: =COUNTIF(Trades!E2:E100000,"long")+COUNTIF(Trades!E2:E100000,"short") -> 307 | C17: =IF($B$8=0,"-",B17/$B$8) -> 0.91641791
A18: Stop loss | B18: =COUNT(Trades!O2:O100000) -> 4 | C18: =IF($B$8=0,"-",B18/$B$8) -> 0.011940299
A19: Take profit | B19: =COUNTA(Trades!P2:P100000) -> 3 | C19: =IF($B$8=0,"-",B19/$B$8) -> 0.0089552239
A20: Liquidation price | B20: =COUNT(Trades!Q2:Q100000) -> 3 | C20: =IF($B$8=0,"-",B20/$B$8) -> 0.0089552239
A21: PnL in USD | B21: =COUNT(Trades!L2:L100000) -> 10 | C21: =IF($B$8=0,"-",B21/$B$8) -> 0.029850746
A22: Stop losses and take profits are almost never in the images — he writes them in the message text instead (323 messages mention an SL, 280 mention a TP/target).
A24: Most traded symbols (by trade rows)
A25: Symbol | B25: Rows | C25: Long | D25: Short | E25: Avg ROI % shown
A26: BTC | B26: =COUNTIF(Trades!$D$2:$D$100000,$A26) -> 144 | C26: =COUNTIFS(Trades!$D$2:$D$100000,$A26,Trades!$E$2:$E$100000,"long") -> 113 | D26: =COUNTIFS(Trades!$D$2:$D$100000,$A26,Trades!$E$2:$E$100000,"short") -> 15 | E26: =IFERROR(AVERAGEIF(Trades!$D$2:$D$100000,$A26,Trades!$K$2:$K$100000),"-") -> 219.20604
A27: ETH | B27: =COUNTIF(Trades!$D$2:$D$100000,$A27) -> 18 | C27: =COUNTIFS(Trades!$D$2:$D$100000,$A27,Trades!$E$2:$E$100000,"long") -> 10 | D27: =COUNTIFS(Trades!$D$2:$D$100000,$A27,Trades!$E$2:$E$100000,"short") -> 5 | E27: =IFERROR(AVERAGEIF(Trades!$D$2:$D$100000,$A27,Trades!$K$2:$K$100000),"-") -> 173.065
A28: SOL | B28: =COUNTIF(Trades!$D$2:$D$100000,$A28) -> 16 | C28: =COUNTIFS(Trades!$D$2:$D$100000,$A28,Trades!$E$2:$E$100000,"long") -> 14 | D28: =COUNTIFS(Trades!$D$2:$D$100000,$A28,Trades!$E$2:$E$100000,"short") -> 1 | E28: =IFERROR(AVERAGEIF(Trades!$D$2:$D$100000,$A28,Trades!$K$2:$K$100000),"-") -> 216.87667
A29: SUI | B29: =COUNTIF(Trades!$D$2:$D$100000,$A29) -> 16 | C29: =COUNTIFS(Trades!$D$2:$D$100000,$A29,Trades!$E$2:$E$100000,"long") -> 15 | D29: =COUNTIFS(Trades!$D$2:$D$100000,$A29,Trades!$E$2:$E$100000,"short") -> 0 | E29: =IFERROR(AVERAGEIF(Trades!$D$2:$D$100000,$A29,Trades!$K$2:$K$100000),"-") -> 580.80308
A30: HYPE | B30: =COUNTIF(Trades!$D$2:$D$100000,$A30) -> 14 | C30: =COUNTIFS(Trades!$D$2:$D$100000,$A30,Trades!$E$2:$E$100000,"long") -> 11 | D30: =COUNTIFS(Trades!$D$2:$D$100000,$A30,Trades!$E$2:$E$100000,"short") -> 2 | E30: =IFERROR(AVERAGEIF(Trades!$D$2:$D$100000,$A30,Trades!$K$2:$K$100000),"-") -> 197.3225
A31: ZEC | B31: =COUNTIF(Trades!$D$2:$D$100000,$A31) -> 14 | C31: =COUNTIFS(Trades!$D$2:$D$100000,$A31,Trades!$E$2:$E$100000,"long") -> 10 | D31: =COUNTIFS(Trades!$D$2:$D$100000,$A31,Trades!$E$2:$E$100000,"short") -> 4 | E31: =IFERROR(AVERAGEIF(Trades!$D$2:$D$100000,$A31,Trades!$K$2:$K$100000),"-") -> 202.76308
A32: XRP | B32: =COUNTIF(Trades!$D$2:$D$100000,$A32) -> 8 | C32: =COUNTIFS(Trades!$D$2:$D$100000,$A32,Trades!$E$2:$E$100000,"long") -> 7 | D32: =COUNTIFS(Trades!$D$2:$D$100000,$A32,Trades!$E$2:$E$100000,"short") -> 0 | E32: =IFERROR(AVERAGEIF(Trades!$D$2:$D$100000,$A32,Trades!$K$2:$K$100000),"-") -> 148.2
A33: WLD | B33: =COUNTIF(Trades!$D$2:$D$100000,$A33) -> 7 | C33: =COUNTIFS(Trades!$D$2:$D$100000,$A33,Trades!$E$2:$E$100000,"long") -> 6 | D33: =COUNTIFS(Trades!$D$2:$D$100000,$A33,Trades!$E$2:$E$100000,"short") -> 1 | E33: =IFERROR(AVERAGEIF(Trades!$D$2:$D$100000,$A33,Trades!$K$2:$K$100000),"-") -> 353.64167
A34: STABLE | B34: =COUNTIF(Trades!$D$2:$D$100000,$A34) -> 5 | C34: =COUNTIFS(Trades!$D$2:$D$100000,$A34,Trades!$E$2:$E$100000,"long") -> 5 | D34: =COUNTIFS(Trades!$D$2:$D$100000,$A34,Trades!$E$2:$E$100000,"short") -> 0 | E34: =IFERROR(AVERAGEIF(Trades!$D$2:$D$100000,$A34,Trades!$K$2:$K$100000),"-") -> 206.1
A35: FIL | B35: =COUNTIF(Trades!$D$2:$D$100000,$A35) -> 5 | C35: =COUNTIFS(Trades!$D$2:$D$100000,$A35,Trades!$E$2:$E$100000,"long") -> 5 | D35: =COUNTIFS(Trades!$D$2:$D$100000,$A35,Trades!$E$2:$E$100000,"short") -> 0 | E35: =IFERROR(AVERAGEIF(Trades!$D$2:$D$100000,$A35,Trades!$K$2:$K$100000),"-") -> 100.52
A36: TAO | B36: =COUNTIF(Trades!$D$2:$D$100000,$A36) -> 5 | C36: =COUNTIFS(Trades!$D$2:$D$100000,$A36,Trades!$E$2:$E$100000,"long") -> 5 | D36: =COUNTIFS(Trades!$D$2:$D$100000,$A36,Trades!$E$2:$E$100000,"short") -> 0 | E36: =IFERROR(AVERAGEIF(Trades!$D$2:$D$100000,$A36,Trades!$K$2:$K$100000),"-") -> 157.892
A37: BNB | B37: =COUNTIF(Trades!$D$2:$D$100000,$A37) -> 5 | C37: =COUNTIFS(Trades!$D$2:$D$100000,$A37,Trades!$E$2:$E$100000,"long") -> 5 | D37: =COUNTIFS(Trades!$D$2:$D$100000,$A37,Trades!$E$2:$E$100000,"short") -> 0 | E37: =IFERROR(AVERAGEIF(Trades!$D$2:$D$100000,$A37,Trades!$K$2:$K$100000),"-") -> 176.565
... A40: BEAT | B40: =COUNTIF(Trades!$D$2:$D$100000,$A40) -> 4 | C40: =COUNTIFS(Trades!$D$2:$D$100000,$A40,Trades!$E$2:$E$100000,"long") -> 0 | D40: =COUNTIFS(Trades!$D$2:$D$100000,$A40,Trades!$E$2:$E$100000,"short") -> 4 | E40: =IFERROR(AVERAGEIF(Trades!$D$2:$D$100000,$A40,Trades!$K$2:$K$100000),"-") -> 530.98333
A42: Leverage used (where the image shows it)
A43: Leverage | B43: Trade rows
A44: 3 | B44: =COUNTIF(Trades!$F$2:$F$100000,$A44) -> 4
A45: 10 | B45: =COUNTIF(Trades!$F$2:$F$100000,$A45) -> 7
A46: 20 | B46: =COUNTIF(Trades!$F$2:$F$100000,$A46) -> 14
A47: 25 | B47: =COUNTIF(Trades!$F$2:$F$100000,$A47) -> 10
A48: 30 | B48: =COUNTIF(Trades!$F$2:$F$100000,$A48) -> 2
A49: 40 | B49: =COUNTIF(Trades!$F$2:$F$100000,$A49) -> 2
A50: 49 | B50: =COUNTIF(Trades!$F$2:$F$100000,$A50) -> 1
A51: 50 | B51: =COUNTIF(Trades!$F$2:$F$100000,$A51) -> 26
A52: 75 | B52: =COUNTIF(Trades!$F$2:$F$100000,$A52) -> 31
A53: 90 | B53: =COUNTIF(Trades!$F$2:$F$100000,$A53) -> 2
A54: 100 | B54: =COUNTIF(Trades!$F$2:$F$100000,$A54) -> 40
A55: 125 | B55: =COUNTIF(Trades!$F$2:$F$100000,$A55) -> 6
... A61: 500 | B61: =COUNTIF(Trades!$F$2:$F$100000,$A61) -> 2
A63: How to read this workbook
A64: Trades — one row per position visible in an image (335 rows). Blank cells mean the value was not shown in that image; nothing here is inferred or calculated.
A65: Images — one row per image (320), including the message he posted with it, a verbatim transcription of the text in the image, and what a chart was showing.
A66: Charts — the 24 price charts only, with timeframe, indicators, levels and drawings.
A67: Confidence "medium" and the Issues column flag crops where the symbol, platform or a price had to be read from context rather than from the image itself.
A68: Image file names match the files in the images folder; the Discord link opens the original message.

Sheet Trades
A1: Date | B1: Time | C1: Symbol | D1: Base | E1: Side | F1: Leverage | G1: Margin mode | H1: Entry price | I1: Exit price | J1: Exit price type | K1: ROI % | L1: PnL USD | M1: Position size | N1: Margin USD | O1: Stop loss | P1: Take profits | Q1: Liq. price | R1: Status | S1: Platform | T1: Image type | U1: Trade notes | V1: Message posted with image | W1: Image file | X1: Confidence | Y1: Discord link
A2: 2026-05-06 | B2: 23:47:41 | C2: ASTERUSDT | D2: ASTER | R2: closed | S2: Discord | T2: discord_message_screenshot | U2: Listed as a winning trade in the recap (symbol written as base ticker only). | V2: I have been trading for the past month in journals and here's my progress so far **25** trades **22** Wins **3** BE **0** loss Can track it all in the journal -> https://discord.com/channels/1042855255089623100/1496387902140321885/1501536396127633418 @Paladin Notify | W2: 001_2026-05-06_234741_Screenshot_20260507-014653.png | X2: high | Y2: https://discord.com/channels/1042855255089623100/1501271173588193290/1501686917828448277
A3: 2026-05-06 | B3: 23:47:41 | C3: AXSUSDT | D3: AXS | R3: closed | S3: Discord | T3: discord_message_screenshot | U3: Listed as a winning trade in the recap. | V3: I have been trading for the past month in journals and here's my progress so far **25** trades **22** Wins **3** BE **0** loss Can track it all in the journal -> https://discord.com/channels/1042855255089623100/1496387902140321885/1501536396127633418 @Paladin Notify | W3: 001_2026-05-06_234741_Screenshot_20260507-014653.png | X3: high | Y3: https://discord.com/channels/1042855255089623100/1501271173588193290/1501686917828448277
A4: 2026-05-06 | B4: 23:47:41 | C4: IRYSUSDT | D4: IRYS | R4: closed | S4: Discord | T4: discord_message_screenshot | U4: Listed as a winning trade in the recap. | V4: I have been trading for the past month in journals and here's my progress so far **25** trades **22** Wins **3** BE **0** loss Can track it all in the journal -> https://discord.com/channels/1042855255089623100/1496387902140321885/1501536396127633418 @Paladin Notify | W4: 001_2026-05-06_234741_Screenshot_20260507-014653.png | X4: high | Y4: https://discord.com/channels/1042855255089623100/1501271173588193290/1501686917828448277
A5: 2026-05-06 | B5: 23:47:41 | C5: BTCUSDT | D5: BTC | R5: closed | S5: Discord | T5: discord_message_screenshot | U5: Listed as a winning trade in the recap (BTC win 1 of 13 listed). | V5: I have been trading for the past month in journals and here's my progress so far **25** trades **22** Wins **3** BE **0** loss Can track it all in the journal -> https://discord.com/channels/1042855255089623100/1496387902140321885/1501536396127633418 @Paladin Notify | W5: 001_2026-05-06_234741_Screenshot_20260507-014653.png | X5: high | Y5: https://discord.com/channels/1042855255089623100/1501271173588193290/1501686917828448277
A6: 2026-05-06 | B6: 23:47:41 | C6: BTCUSDT | D6: BTC | R6: closed | S6: Discord | T6: discord_message_screenshot | U6: Listed as a winning trade in the recap (BTC win 2 of 13 listed). | V6: I have been trading for the past month in journals and here's my progress so far **25** trades **22** Wins **3** BE **0** loss Can track it all in the journal -> https://discord.com/channels/1042855255089623100/1496387902140321885/1501536396127633418 @Paladin Notify | W6: 001_2026-05-06_234741_Screenshot_20260507-014653.png | X6: high | Y6: https://discord.com/channels/1042855255089623100/1501271173588193290/1501686917828448277
A7: 2026-05-06 | B7: 23:47:41 | C7: BTCUSDT | D7: BTC | R7: closed | S7: Discord | T7: discord_message_screenshot | U7: Listed as a winning trade in the recap (BTC win 3 of 13 listed). | V7: I have been trading for the past month in journals and here's my progress so far **25** trades **22** Wins **3** BE **0** loss Can track it all in the journal -> https://discord.com/channels/1042855255089623100/1496387902140321885/1501536396127633418 @Paladin Notify | W7: 001_2026-05-06_234741_Screenshot_20260507-014653.png | X7: high | Y7: https://discord.com/channels/1042855255089623100/1501271173588193290/1501686917828448277
A8: 2026-05-06 | B8: 23:47:41 | C8: ETHUSDT | D8: ETH | R8: closed | S8: Discord | T8: discord_message_screenshot | U8: Listed as a winning trade in the recap (ETH win 1 of 3 listed). | V8: I have been trading for the past month in journals and here's my progress so far **25** trades **22** Wins **3** BE **0** loss Can track it all in the journal -> https://discord.com/channels/1042855255089623100/1496387902140321885/1501536396127633418 @Paladin Notify | W8: 001_2026-05-06_234741_Screenshot_20260507-014653.png | X8: high | Y8: https://discord.com/channels/1042855255089623100/1501271173588193290/1501686917828448277
A9: 2026-05-06 | B9: 23:47:41 | C9: HYPEUSDT | D9: HYPE | R9: closed | S9: Discord | T9: discord_message_screenshot | U9: Listed as a winning trade in the recap. | V9: I have been trading for the past month in journals and here's my progress so far **25** trades **22** Wins **3** BE **0** loss Can track it all in the journal -> https://discord.com/channels/1042855255089623100/1496387902140321885/1501536396127633418 @Paladin Notify | W9: 001_2026-05-06_234741_Screenshot_20260507-014653.png | X9: high | Y9: https://discord.com/channels/1042855255089623100/1501271173588193290/1501686917828448277
A10: 2026-05-06 | B10: 23:47:41 | C10: PEPEUSDT | D10: PEPE | R10: closed | S10: Discord | T10: discord_message_screenshot | U10: Listed as a winning trade in the recap. | V10: I have been trading for the past month in journals and here's my progress so far **25** trades **22** Wins **3** BE **0** loss Can track it all in the journal -> https://discord.com/channels/1042855255089623100/1496387902140321885/1501536396127633418 @Paladin Notify | W10: 001_2026-05-06_234741_Screenshot_20260507-014653.png | X10: high | Y10: https://discord.com/channels/1042855255089623100/1501271173588193290/1501686917828448277
A11: 2026-05-06 | B11: 23:47:41 | C11: ETHUSDT | D11: ETH | R11: closed | S11: Discord | T11: discord_message_screenshot | U11: Listed as a winning trade in the recap (ETH win 2 of 3 listed). | V11: I have been trading for the past month in journals and here's my progress so far **25** trades **22** Wins **3** BE **0** loss Can track it all in the journal -> https://discord.com/channels/1042855255089623100/1496387902140321885/1501536396127633418 @Paladin Notify | W11: 001_2026-05-06_234741_Screenshot_20260507-014653.png | X11: high | Y11: https://discord.com/channels/1042855255089623100/1501271173588193290/1501686917828448277
A12: 2026-05-06 | B12: 23:47:41 | C12: BTCUSDT | D12: BTC | R12: closed | S12: Discord | T12: discord_message_screenshot | U12: Listed as a winning trade in the recap (BTC win 4 of 13 listed). | V12: I have been trading for the past month in journals and here's my progress so far **25** trades **22** Wins **3** BE **0** loss Can track it all in the journal -> https://discord.com/channels/1042855255089623100/1496387902140321885/1501536396127633418 @Paladin Notify | W12: 001_2026-05-06_234741_Screenshot_20260507-014653.png | X12: high | Y12: https://discord.com/channels/1042855255089623100/1501271173588193290/1501686917828448277
A13: 2026-05-06 | B13: 23:47:41 | C13: BTCUSDT | D13: BTC | R13: closed | S13: Discord | T13: discord_message_screenshot | U13: Listed as a winning trade in the recap (BTC win 5 of 13 listed). | V13: I have been trading for the past month in journals and here's my progress so far **25** trades **22** Wins **3** BE **0** loss Can track it all in the journal -> https://discord.com/channels/1042855255089623100/1496387902140321885/1501536396127633418 @Paladin Notify | W13: 001_2026-05-06_234741_Screenshot_20260507-014653.png | X13: high | Y13: https://discord.com/channels/1042855255089623100/1501271173588193290/1501686917828448277
... A25: 2026-05-06 | B25: 23:47:41 | C25: BTCUSDT | D25: BTC | R25: closed | S25: Discord | T25: discord_message_screenshot | U25: Listed as a break-even (BE) trade in the recap. | V25: I have been trading for the past month in journals and here's my progress so far **25** trades **22** Wins **3** BE **0** loss Can track it all in the journal -> https://discord.com/channels/1042855255089623100/1496387902140321885/1501536396127633418 @Paladin Notify | W25: 001_2026-05-06_234741_Screenshot_20260507-014653.png | X25: high | Y25: https://discord.com/channels/1042855255089623100/1501271173588193290/1501686917828448277
A26: 2026-05-08 | B26: 13:48:41 | C26: BTCUSDT | D26: BTC | E26: long | H26: 79564.8 | R26: open | S26: unknown | T26: open_positions_screenshot | U26: Only the field 'Entry Price (USDT) 79,564.80' is visible. Symbol and side are NOT shown in the image: BTC is taken from the accompanying message context and 'long' from the message suggesting taking 20% profit at 80.5k above this entry. Note this entry (79,564.80) differs from the 79,764.40 entry shown on the later BTCUSDT Long 100X Bybit share cards (images 014/017). | V26: BTC started moving, you can take 20% @ 80.5k if you want, I'll update whenever I close! | W26: 002_2026-05-08_134841_Screenshot_20260508-1547142.png | X26: medium | Y26: https://discord.com/channels/1042855255089623100/1501271173588193290/1502260952098279615
A27: 2026-05-08 | B27: 18:44:20 | C27: UNIUSDT | D27: UNI | E27: long | F27: 50 | K27: 101.21 | R27: closed | S27: Bybit | T27: pnl_share_card | U27: Cropped share card: only header and ROI visible. Same card appears in full as image 015 (Entry 3.458 / Exit 3.528). Per message this was a 50% partial close (~0.7R); remaining half held with SL moved to BE 3.46, his own TP 3.7, followers could hold to 4 (those levels are from the message, not the image). | V27: Okay let's treat as our first win Closing 50% UNI for 0.7 R move, I'll take personally fully TP @ 3.7 You can hold till 4 SL @ BE 3.46 @Paladin Notify | W27: 003_2026-05-08_184420_Screenshot_20260508-203512.png | X27: medium | Y27: https://discord.com/channels/1042855255089623100/1501271173588193290/1502335355628687451
A28: 2026-05-09 | B28: 04:45:42 | C28: KERNELUSDT | D28: KERNEL | E28: long | F28: 20 | H28: 0.06454 | I28: 0.06615 | J28: mark | K28: 49.35 | R28: open | S28: Bybit | T28: pnl_share_card | U28: Card label reads 'Current Price' (position still open). Per message this is TP1 with the next TP at 0.0673 (not shown on the card). | V28: KERNEL TP1 here, next TP @ 0.0673 @Paladin Notify | W28: 009_2026-05-09_044542_Screenshot_20260509-064308.png | X28: high | Y28: https://discord.com/channels/1042855255089623100/1501271173588193290/1502486692232298586
A29: 2026-05-09 | B29: 04:48:32 | C29: KERNELUSDT | D29: KERNEL | E29: long | F29: 20 | H29: 0.06454 | I29: 0.06615 | J29: mark | K29: 49.35 | R29: open | S29: Bybit | T29: pnl_share_card | U29: Card label reads 'Current Price' (position still open). Identical screenshot to image 009 (same file name Screenshot_20260509-064308), re-posted in the batch of running trades. | V29: All trades running in good profits, take TP whenever you want, don't let them round trip. I'll update when I close. | W29: 010_2026-05-09_044832_Screenshot_20260509-064308.png | X29: high | Y29: https://discord.com/channels/1042855255089623100/1501271173588193290/1502487407654862971
A30: 2026-05-09 | B30: 04:48:32 | C30: AVNTUSDT | D30: AVNT | E30: long | F30: 50 | H30: 0.15851 | I30: 0.16787 | J30: mark | K30: 265.55 | R30: open | S30: Bybit | T30: pnl_share_card | U30: Card label reads 'Current Price' (position still open). | V30: All trades running in good profits, take TP whenever you want, don't let them round trip. I'll update when I close. | W30: 011_2026-05-09_044832_Screenshot_20260509-064552.png | X30: high | Y30: https://discord.com/channels/1042855255089623100/1501271173588193290/1502487407654862971
A31: 2026-05-09 | B31: 04:48:32 | C31: SNXUSDT | D31: SNX | E31: long | F31: 25 | H31: 0.3545 | I31: 0.3727 | J31: mark | K31: 118.67 | R31: open | S31: Bybit | T31: pnl_share_card | U31: Card label reads 'Current Price' (position still open). | V31: All trades running in good profits, take TP whenever you want, don't let them round trip. I'll update when I close. | W31: 012_2026-05-09_044832_Screenshot_20260509-064638.png | X31: high | Y31: https://discord.com/channels/1042855255089623100/1501271173588193290/1502487407654862971
A32: 2026-05-09 | B32: 04:48:32 | C32: ZROUSDT | D32: ZRO | E32: long | F32: 50 | H32: 1.4744 | I32: 1.4849 | J32: mark | K32: 34.43 | R32: open | S32: Bybit | T32: pnl_share_card | U32: Card label reads 'Current Price' (position still open). | V32: All trades running in good profits, take TP whenever you want, don't let them round trip. I'll update when I close. | W32: 013_2026-05-09_044832_Screenshot_20260509-064657.png | X32: high | Y32: https://discord.com/channels/1042855255089623100/1501271173588193290/1502487407654862971
A33: 2026-05-09 | B33: 04:48:32 | C33: BTCUSDT | D33: BTC | E33: long | F33: 100 | H33: 79764.4 | I33: 80333.9 | J33: mark | K33: 67.25 | R33: open | S33: Bybit | T33: pnl_share_card | U33: Card label reads 'Current Price' (position still open). Same position later closed at 80,341.20 (image 017). | V33: All trades running in good profits, take TP whenever you want, don't let them round trip. I'll update when I close. | W33: 014_2026-05-09_044832_Screenshot_20260509-064717.png | X33: high | Y33: https://discord.com/channels/1042855255089623100/1501271173588193290/1502487407654862971
A34: 2026-05-09 | B34: 04:48:32 | C34: UNIUSDT | D34: UNI | E34: long | F34: 50 | H34: 3.458 | I34: 3.528 | J34: close | K34: 101.21 | R34: closed | S34: Bybit | T34: pnl_share_card | U34: Card label reads 'Exit Price' (closed). Full version of the cropped card in image 003; this is the 50% partial close at ~0.7R announced on May 8 (the remainder was exited at 3.7 per his later message). | V34: All trades running in good profits, take TP whenever you want, don't let them round trip. I'll update when I close. | W34: 015_2026-05-09_044832_Screenshot_20260509-063448.png | X34: high | Y34: https://discord.com/channels/1042855255089623100/1501271173588193290/1502487407654862971
A35: 2026-05-09 | B35: 04:52:10 | C35: SYRUPUSDT | D35: SYRUP | E35: long | F35: 25 | H35: 0.25328 | I35: 0.26013 | J35: close | K35: 67.61 | R35: closed | S35: Bybit | T35: pnl_share_card | U35: Card label reads 'Exit Price' (closed). Per message this was a journal trade held for ~10 days and closed out of impatience despite conviction it would 'blow up'. | V35: Also closing this trade from Journals, 100% this is gonna blow up but I have been holding for 10 days, its getting annoying. https://discord.com/channels/1042855255089623100/1496387902140321885/1497875763314298912 @Paladin Notify | W35: 016_2026-05-09_045210_Screenshot_20260509-063054.png | X35: high | Y35: https://discord.com/channels/1042855255089623100/1501271173588193290/1502488322143162518
A36: 2026-05-09 | B36: 06:06:56 | C36: BTCUSDT | D36: BTC | E36: long | F36: 100 | H36: 79764.4 | I36: 80341.2 | J36: close | K36: 72.31 | R36: closed | S36: Bybit | T36: pnl_share_card | U36: Card label reads 'Exit Price' (closed). Same position shown open in image 014 (current 80,333.90 / +67.25%). | V36: Closing BTC @ 80.4k @Paladin Notify | W36: 017_2026-05-09_060656_Screenshot_20260509-080604.png | X36: high | Y36: https://discord.com/channels/1042855255089623100/1501271173588193290/1502507137337786561
A37: 2026-05-10 | B37: 18:45:44 | C37: ETHUSDT | D37: ETH | E37: long | F37: 100 | H37: 2311.73 | I37: 2340.53 | J37: close | K37: 124.58 | R37: closed | S37: Bybit | T37: pnl_share_card | U37: Card label reads 'Exit Price' (closed). Described in the message as a weekend scalp. | V37: Alright guys good enough for a weekend scalp, closing it here! @Paladin Notify | W37: 018_2026-05-10_184544_Screenshot_20260510-204502.png | X37: high | Y37: https://discord.com/channels/1042855255089623100/1501271173588193290/1503060481118568578
A38: 2026-05-10 | B38: 21:01:23 | C38: AVNTUSDT | D38: AVNT | E38: long | F38: 50 | H38: 0.15851 | I38: 0.16709 | J38: mark | K38: 246.69 | R38: open | S38: Bybit | T38: pnl_share_card | U38: Card label reads 'Current Price' (position still open). Per message this is TP1 with a full close planned at 0.1746 (not shown on the card). Same position as image 011 (then at 0.16787 / +265.55%). | V38: AVNT TP1 here, fully close @ 0.1746 @Paladin Notify | W38: 019_2026-05-10_210123_Screenshot_20260510-224944.png | X38: high | Y38: https://discord.com/channels/1042855255089623100/1501271173588193290/1503094618345181387
A39: 2026-05-10 | B39: 22:10:30 | C39: ZROUSDT | D39: ZRO | E39: long | F39: 50 | H39: 1.4744 | I39: 1.53 | J39: mark | K39: 178.94 | R39: open | S39: Bybit | T39: pnl_share_card | U39: Card label reads 'Current Price' (position still open). Per message he took 25% off here and plans a full exit around 1.55+ (not shown on the card). Same position as image 013 (then at 1.4849 / +34.43%). | V39: 25% here, fully exit around 1.55+ Will update if I see weakness @Paladin Notify | W39: 020_2026-05-10_221030_Screenshot_20260511-000006.png | X39: high | Y39: https://discord.com/channels/1042855255089623100/1501271173588193290/1503112014283673735
... A42: 2026-05-11 | B42: 09:12:24 | C42: ZROUSDT | D42: ZRO | E42: long | F42: 50 | H42: 1.4772 | I42: 1.5369 | J42: mark | K42: 189.93 | R42: open | S42: Bybit | T42: pnl_share_card | U42: Bybit rocket share card; price label is 'Current Price' (position open). No date, size or USD PnL shown. | V42: And the streak continues, 20% here not moving SL to entry. @Paladin Notify | W42: 023_2026-05-11_091224_17784798553272.jpg | X42: high | Y42: https://discord.com/channels/1042855255089623100/1501271173588193290/1503278586050777149
A43: 2026-05-11 | B43: 09:13:29 | C43: BTCUSDT | D43: BTC | E43: long | F43: 150 | K43: 51.78 | R43: open | S43: Blofin | T43: pnl_share_card | U43: Header reads 'Unrealized PnL' (open position). Card is cropped to the top part: entry price, mark price, date and size are not visible. 150X leverage and the card layout (pair | Long | 150X with a character figure on the right) match Blofin share cards. | V43: I have started to scale in BTC long as well will give out once I'm confident enough For an idea I'm long since 80.6k SL @ 79.5k | W43: 024_2026-05-11_091329_Screenshot_20260511-111236.png | X43: medium | Y43: https://discord.com/channels/1042855255089623100/1501271173588193290/1503278860400332892
A44: 2026-05-11 | B44: 12:32:58 | C44: ZROUSDT | D44: ZRO | E44: long | F44: 50 | H44: 1.4772 | I44: 1.5457 | J44: mark | K44: 215.72 | R44: open | S44: Bybit | T44: pnl_share_card | U44: Bybit rocket share card; price label is 'Current Price' (card generated while the position was still open, even though the message announces the TP was hit). Same entry 1.4772 as the earlier ZRO card. | V44: ZRO TP hit @Paladin Notify | W44: 025_2026-05-11_123258_17784899060412.jpg | X44: high | Y44: https://discord.com/channels/1042855255089623100/1501271173588193290/1503329058543370330
A45: 2026-05-11 | B45: 19:33:50 | C45: BTCUSDT | D45: BTC | E45: long | F45: 100 | H45: 80914.2 | I45: 81798.7 | J45: close | K45: 109.31 | R45: closed | S45: Bybit | T45: pnl_share_card | U45: Bybit rocket share card with 'Exit Price' label (closed trade). No date, size or USD PnL shown. | W45: 026_2026-05-11_193350_Screenshot_20260511-213326.png | X45: high | Y45: https://discord.com/channels/1042855255089623100/1501271173588193290/1503434974102163536
A46: 2026-05-12 | B46: 06:19:25 | C46: STABLEUSDT | D46: STABLE | E46: long | F46: 25 | H46: 0.03459 | I46: 0.036652 | J46: mark | K46: 144.12 | R46: open | S46: Bybit | T46: pnl_share_card | U46: Bybit rocket share card; price label is 'Current Price' (position open). OCR missed the ROI value; the card clearly shows +144.12%. | V46: TP1 @ 0.03737 | W46: 027_2026-05-12_061925_Screenshot_20260512-081814.png | X46: high | Y46: https://discord.com/channels/1042855255089623100/1501271173588193290/1503597441675558924
A47: 2026-05-12 | B47: 06:49:52 | C47: STABLEUSDT | D47: STABLE | E47: long | F47: 25 | H47: 0.03459 | I47: 0.03737 | J47: close | K47: 200.92 | R47: closed | S47: Bybit | T47: pnl_share_card | U47: Bybit rocket share card with 'Exit Price' label (closed). Exit 0.037370 equals the TP1 level he had announced (0.03737). | V47: I accidentally closed 100% here but 0.04 TP is valid, take at least 50% as this is resistance. @Paladin Notify | W47: 028_2026-05-12_064952_Screenshot_20260512-084847.png | X47: high | Y47: https://discord.com/channels/1042855255089623100/1501271173588193290/1503605103997882428
A48: 2026-05-12 | B48: 15:11:23 | C48: STABLEUSDT | D48: STABLE | E48: long | H48: 0.03453 | I48: 0.03884 | J48: last | L48: 43.1294 | M48: 10,000 | R48: open | S48: MEXC | T48: chart | U48: MEXC app: dashed green position line at 0.03453 with tag 'PNL +43.1294 | 10,000' (10,000 = contracts/STABLE size). Side inferred from positive PnL with price above the entry line; leverage not shown on the chart. Exit price = Last Price 0.03884 shown at the top. A red 'S' (sell) marker sits on the big green impulse candle near ~0.0378, likely a partial sell / TP fill. | V48: Guys I would like to clarify something since I shared this screenshot it says DEMO, I got like 5 DMs saying I'm trading on DEMO It is CFT funded account so it shows demo, I trade on other exchanges with real money. Even if it's demo are the trades hitting TPs or not? Just wanted to clarify it once. | W48: 030_2026-05-12_151123_Screenshot_20260512-170605.png | X48: high | Y48: https://discord.com/channels/1042855255089623100/1501271173588193290/1503731313855692950
A49: 2026-05-12 | B49: 15:11:23 | C49: STABLEUSDT | D49: STABLE | E49: long | F49: 20 | H49: 0.03453 | I49: 0.03886 | J49: mark | K49: 248.34 | L49: 43.2294 | R49: open | S49: MEXC | T49: pnl_share_card | U49: MEXC share card ('0% Liquidity NO.1' graphic). Price label is 'Fair Price' (MEXC's mark price) so the position was still open. PnL shown as +43.2294 USDT. No date shown. | V49: Guys I would like to clarify something since I shared this screenshot it says DEMO, I got like 5 DMs saying I'm trading on DEMO It is CFT funded account so it shows demo, I trade on other exchanges with real money. Even if it's demo are the trades hitting TPs or not? Just wanted to clarify it once. | W49: 031_2026-05-12_151123_Screenshot_20260512-170852.png | X49: high | Y49: https://discord.com/channels/1042855255089623100/1501271173588193290/1503731313855692950
A50: 2026-05-13 | B50: 06:13:16 | C50: STABLEUSDT | D50: STABLE | E50: long | F50: 20 | K50: 231.02 | R50: closed | S50: MEXC | T50: pnl_share_card | U50: Cropped MEXC 'Closed PNL' share card (same layout as the MEXC open-position card). Only header, pair, side, leverage and ROI are visible; entry/close price, USDT PnL and date are cut off. Decorative mini line graphic with green 'B' (buy) and red 'S' (sell) markers on the right. | V50: STABLE hit full TP of 0.04, 20% unleveraged move! @Paladin Notify | W50: 032_2026-05-13_061316_Screenshot_20260513-081109.png | X50: medium | Y50: https://discord.com/channels/1042855255089623100/1501271173588193290/1503958280999796848
A51: 2026-05-13 | B51: 12:11:15 | C51: SOLUSDT | D51: SOL | E51: long | F51: 100 | H51: 95.53 | I51: 95.7 | J51: close | K51: 17.79 | R51: closed | S51: Bybit | T51: pnl_share_card | U51: Bybit rocket share card with 'Exit Price' label (closed). Small move (0.17) amplified by 100x leverage. | V51: Closing SOL here personally, I want to be on the safe side and keep my streak. We already have 3 longs and they are running good enough, expect TPs soon InshaAllah! @Paladin Notify | W51: 033_2026-05-13_121115_Screenshot_20260513-140807.png | X51: high | Y51: https://discord.com/channels/1042855255089623100/1501271173588193290/1504048372351504406
A52: 2026-05-14 | B52: 17:30:30 | C52: SOLUSDT | D52: SOL | E52: long | F52: 100 | H52: 91.05 | I52: 91.46 | J52: close | K52: 45.03 | R52: closed | S52: Bybit | T52: pnl_share_card | U52: Bybit rocket share card with 'Exit Price' label (closed). No date, size or USD PnL shown. | V52: Closing SOL and XRP in minor profits BTC avg 79.2k with a DCA running in heavy profits @Paladin Notify | W52: 034_2026-05-14_173030_Screenshot_20260514-192753.png | X52: high | Y52: https://discord.com/channels/1042855255089623100/1501271173588193290/1504491099048251594
A53: 2026-05-14 | B53: 17:30:30 | C53: XRPUSDT | D53: XRP | E53: long | F53: 100 | H53: 1.4497 | I53: 1.4531 | J53: close | K53: 23.45 | R53: closed | S53: Bybit | T53: pnl_share_card | U53: Bybit rocket share card with 'Exit Price' label (closed). No date, size or USD PnL shown. | V53: Closing SOL and XRP in minor profits BTC avg 79.2k with a DCA running in heavy profits @Paladin Notify | W53: 035_2026-05-14_173030_Screenshot_20260514-192733.png | X53: high | Y53: https://discord.com/channels/1042855255089623100/1501271173588193290/1504491099048251594
A54: 2026-05-14 | B54: 17:38:18 | C54: BTCUSDT | D54: BTC | E54: long | F54: 100 | H54: 79284.35 | I54: 80199.5 | J54: mark | K54: 108.28 | R54: open | S54: Bybit | T54: pnl_share_card | U54: Bybit rocket share card; price label is 'Current Price' (position open). Entry 79,284.35 is the DCA average he referred to as 'avg 79.2k'. | V54: Holding onto these 🤘🏻 Let's pray we enjoy some fat profits on these! | W54: 036_2026-05-14_173818_Screenshot_20260514-193711.png | X54: high | Y54: https://discord.com/channels/1042855255089623100/1501271173588193290/1504493064947761242
A55: 2026-05-14 | B55: 17:38:18 | C55: ENSUSDT | D55: ENS | E55: long | F55: 50 | H55: 6.9 | I55: 7.107 | J55: mark | K55: 141.91 | R55: open | S55: Bybit | T55: pnl_share_card | U55: Bybit rocket share card; price label is 'Current Price' (position open). No date, size or USD PnL shown. | V55: Holding onto these 🤘🏻 Let's pray we enjoy some fat profits on these! | W55: 037_2026-05-14_173818_Screenshot_20260514-193728.png | X55: high | Y55: https://discord.com/channels/1042855255089623100/1501271173588193290/1504493064947761242
A56: 2026-05-14 | B56: 18:02:51 | C56: BTCUSDT | D56: BTC | E56: long | F56: 100 | H56: 79284.35 | I56: 80893.8 | J56: close | K56: 202.99 | R56: closed | S56: Bybit | T56: pnl_share_card | U56: Bybit rocket share card with 'Exit Price' label (closed). Same entry 79,284.35 as the open card posted ~25 minutes earlier; closed at 80,893.80. | V56: BTC closed at 81k guys, FATASS PROFITS! Made profits back from both SLs @Paladin Notify | W56: 040_2026-05-14_180251_Screenshot_20260514-200201.png | X56: high | Y56: https://discord.com/channels/1042855255089623100/1501271173588193290/1504499241316253918
A57: 2026-05-14 | B57: 18:03:36 | C57: ENSUSDT | D57: ENS | E57: long | F57: 50 | H57: 6.9 | I57: 7.171 | J57: mark | K57: 190.71 | R57: open | S57: Bybit | T57: pnl_share_card | U57: Card label is 'Current Price' (position still open when shared). Per the accompanying message he took 50% profit here and told followers they could close completely. | V57: Took 50% from this too, you can close completely @Paladin Notify | W57: 041_2026-05-14_180336_Screenshot_20260514-200301.png | X57: high | Y57: https://discord.com/channels/1042855255089623100/1501271173588193290/1504499432530509967
A58: 2026-05-14 | B58: 18:13:38 | C58: BTCUSDT | D58: BTC | E58: long | F58: 30 | H58: 79313.4 | I58: 80926.4 | J58: close | K58: 61 | R58: closed | S58: Blofin | T58: pnl_share_card | U58: BloFin standard share card (not the War of Whales template). 'Buy 30X' = long at 30x. Close time printed 2026-05-14 16:09:25. | V58: Man I'm happy not did I survived the dump but mentioned the plan on point! | W58: 042_2026-05-14_181338_Screenshot_20260514-201004.png | X58: high | Y58: https://discord.com/channels/1042855255089623100/1501271173588193290/1504501955467153569
A59: 2026-05-14 | B59: 18:13:42 | C59: BTCUSDT | D59: BTC | E59: long | F59: 250 | K59: 448.51 | R59: closed | S59: unknown | T59: pnl_share_card | U59: Cropped 'Closed PNL' share card; only the ROI is shown, no entry/close prices. Decorative sparkline on the right with a green 'B' (buy) marker at a dip and a red 'S' (sell) marker higher up to the right. 'BTCUSDT Perpetual | Long | 250X'. | W59: 043_2026-05-14_181342_Screenshot_20260514-200907.png | X59: high | Y59: https://discord.com/channels/1042855255089623100/1501271173588193290/1504501973599387790
A60: 2026-05-14 | B60: 19:03:51 | C60: BBUSDT | D60: BB | E60: long | F60: 50 | H60: 0.03583 | I60: 0.03709 | J60: last | K60: 179.47 | R60: open | S60: Discord | T60: screen_recording | U60: Bitunix share card posted by member 'MB' (MM role) 'Today at 6:24 AM' with text 'thank you paladin' (edited). Card footer 'MBZ 2026-05-13 21:22'. Shows 'Last Price' so position still open when shared. Follower's trade on Paladin's BB long call, not Paladin's own account. | V60: Thankyou guys! | W60: 044_2026-05-14_190351_screen-20260514-210325-1778774593947.mp4 | X60: high | Y60: https://discord.com/channels/1042855255089623100/1501271173588193290/1504514593899413596
A61: 2026-05-14 | B61: 19:03:51 | C61: BBUSDT | D61: BB | E61: long | F61: 20 | H61: 0.03282 | I61: 0.03444 | J61: close | K61: 98.72 | R61: closed | S61: Discord | T61: screen_recording | U61: BloFin share card posted by 'dekees' (VIP) 'Today at 5:50 PM' with text 'closed 50% thanks Paladin' (partial close of half the position). Referral Code BCJAsU, Sharing Time 05-14 14:49:52. 2 heart reactions. Follower's trade. | V61: Thankyou guys! | W61: 044_2026-05-14_190351_screen-20260514-210325-1778774593947.mp4 | X61: high | Y61: https://discord.com/channels/1042855255089623100/1501271173588193290/1504514593899413596
A62: 2026-05-14 | B62: 19:03:51 | C62: BTCUSDT | D62: BTC | E62: long | K62: 211.69 | R62: unknown | S62: Discord | T62: screen_recording | U62: Share card (exchange not identifiable: bitcoin logo, 'BTCUSDT Perpetual | Long', big 3D arrow graphic) posted by 'CJR' (SX, VIP) 'Today at 7:55 PM' tagging '@Paladin [Will not DM]' (edited). No prices or leverage on the card. Follower's trade. | V62: Thankyou guys! | W62: 044_2026-05-14_190351_screen-20260514-210325-1778774593947.mp4 | X62: high | Y62: https://discord.com/channels/1042855255089623100/1501271173588193290/1504514593899413596
A63: 2026-05-14 | B63: 19:03:51 | C63: INTCUSDT | D63: INTC | E63: short | K63: 219.73 | R63: unknown | S63: Discord | T63: screen_recording | U63: Same card style (Intel logo, 'INTCUSDT Perpetual | Short') posted by 'CJR' 'Today at 8:00 PM' tagging '@Nick Scalps' -- credited to Nick Scalps, not Paladin. No prices or leverage; a caption line at the bottom of the card is cut off/unreadable. | V63: Thankyou guys! | W63: 044_2026-05-14_190351_screen-20260514-210325-1778774593947.mp4 | X63: high | Y63: https://discord.com/channels/1042855255089623100/1501271173588193290/1504514593899413596
A64: 2026-05-14 | B64: 19:03:51 | C64: BTCUSDT | D64: BTC | E64: long | F64: 100 | K64: 252.15 | R64: closed | S64: Discord | T64: screen_recording | U64: MEXC share card in Spanish: 'BTCUSDT Perpetuo', 'Cerrar Long | 100X' (= Close Long), '+252.15%', 'Fecha 2026-05-14 16:03:08', 'Compartido el 2026-05-14 16:04:4?' (top line partly cut off), 'Código de Referencia 1hXLr'. Author line scrolled out of frame; most likely 'saralhr' 'Today at 8:06 PM' (the message between CJR 8:00 PM and dekees 8:08 PM). No prices on the card. Follower's trade. | V64: Thankyou guys! | W64: 044_2026-05-14_190351_screen-20260514-210325-1778774593947.mp4 | X64: high | Y64: https://discord.com/channels/1042855255089623100/1501271173588193290/1504514593899413596
A65: 2026-05-14 | B65: 19:03:51 | C65: XRPUSDT | D65: XRP | E65: long | F65: 50 | K65: 43.65 | R65: closed | S65: Discord | T65: screen_recording | U65: Second MEXC card (Spanish) from the same member/referral code 1hXLr: 'Racha de 2 victoria(s)' (2-win streak), 'Título desbloqueado: Despertador on-chain', 'PNL de cierre: XRPUSDT Perpetuo Long | 50X +43.65%', 'Compartido el 2026-05-14 16:05:06'. 1 heart reaction. Follower's trade. | V65: Thankyou guys! | W65: 044_2026-05-14_190351_screen-20260514-210325-1778774593947.mp4 | X65: high | Y65: https://discord.com/channels/1042855255089623100/1501271173588193290/1504514593899413596
A66: 2026-05-14 | B66: 19:03:51 | C66: ENSUSDT | D66: ENS | E66: long | F66: 20 | H66: 6.894 | I66: 7.153 | J66: close | K66: 75.13 | R66: closed | S66: Discord | T66: screen_recording | U66: BloFin share card posted by 'dekees' (VIP) 'Today at 8:08 PM' with text 'again Paladin🥰'. Referral Code BCJAsU, Sharing Time 05-14 17:07:03. 1 heart. Follower's trade on Paladin's ENS long. | V66: Thankyou guys! | W66: 044_2026-05-14_190351_screen-20260514-210325-1778774593947.mp4 | X66: high | Y66: https://discord.com/channels/1042855255089623100/1501271173588193290/1504514593899413596
A67: 2026-05-14 | B67: 19:03:51 | C67: BTCUSDT | D67: BTC | E67: long | F67: 75 | H67: 79108.1 | I67: 80983.9 | J67: close | K67: 177.83 | R67: closed | S67: Discord | T67: screen_recording | U67: BloFin share card ('BTCUSDT Perp', 'Buy 75X') posted by 'The CEOsCEO' (VIP) 'Today at 8:19 PM' with text '@Paladin [Will not DM] Thanks mate!'. Referral Code KYAIKx, Share Time 05/14 17:16:26. 1 heart. Follower's trade on Paladin's BTC long. | V67: Thankyou guys! | W67: 044_2026-05-14_190351_screen-20260514-210325-1778774593947.mp4 | X67: high | Y67: https://discord.com/channels/1042855255089623100/1501271173588193290/1504514593899413596
A68: 2026-05-14 | B68: 19:03:51 | C68: XRPUSDT | D68: XRP | E68: long | F68: 3 | H68: 1.4318 | I68: 1.4537 | J68: close | K68: 4.58 | R68: closed | S68: Discord | T68: screen_recording | U68: BingX 'Realized PnL' card posted by 'Jokerxo' 'Today at 8:19 PM' tagging '@Paladin [Will not DM]'. Account 'ja***s@gmail.com', card time 05/14 18:19, Referral Code EO3CKZ. 1 heart. Follower's trade (low 3X leverage). | V68: Thankyou guys! | W68: 044_2026-05-14_190351_screen-20260514-210325-1778774593947.mp4 | X68: high | Y68: https://discord.com/channels/1042855255089623100/1501271173588193290/1504514593899413596
A69: 2026-05-14 | B69: 19:03:51 | C69: BTCUSDT | D69: BTC | E69: long | F69: 100 | H69: 78977.2 | I69: 80488.5 | J69: close | K69: 175.73 | R69: closed | S69: Discord | T69: screen_recording | U69: MEXC share card posted by 'Netteffect11' (OG) 'Today at 8:46 PM' with text '@Paladin [Will not DM] 🔥👑'. 'Shared on 2026-05-15 01:42:15', 'BTCUSDT Perpetual', 'Low-fee saved you: 4.7289 USDT', 'Long | 100X', 'Avg Entry Price $78,977.2', 'Avg Close Price $80,488.5', 'Open Time 2026-05-14 02:00:48', 'Close Time 2026-05-15 01:03:00', Referral Code 1gPto. 1 heart. Follower's trade; gives the approximate open/close times of the BTC long (card times are in the member's own timezone). | V69: Thankyou guys! | W69: 044_2026-05-14_190351_screen-20260514-210325-1778774593947.mp4 | X69: high | Y69: https://discord.com/channels/1042855255089623100/1501271173588193290/1504514593899413596
A70: 2026-05-14 | B70: 19:03:51 | C70: BTCUSDT | D70: BTC | E70: long | F70: 3 | H70: 79815.6 | I70: 81195 | J70: close | K70: 5.18 | R70: closed | S70: Discord | T70: screen_recording | U70: BingX 'Realized PnL' card posted by 'Jokerxo' 'Today at 8:53 PM' tagging '@Paladin [Will not DM]'. Account 'ja***s@gmail.com', card time 05/14 18:53, Referral Code EO3CKZ. 1 heart. Last message in the channel at recording time. Follower's trade. | V70: Thankyou guys! | W70: 044_2026-05-14_190351_screen-20260514-210325-1778774593947.mp4 | X70: high | Y70: https://discord.com/channels/1042855255089623100/1501271173588193290/1504514593899413596
A71: 2026-05-14 | B71: 19:19:52 | C71: ENSUSDT | D71: ENS | E71: long | F71: 50 | H71: 6.9 | I71: 7.135 | J71: mark | K71: 161.15 | R71: open | S71: Bybit | T71: pnl_share_card | U71: Card label is 'Current Price' (share taken while the position was still open). Per the accompanying message he closed the remaining position here ('completely out'), having taken the first 50% earlier around 7.2 (see the +190.71% card at 7.171). Same ENSUSDT 50x long, entry 6.900. | V71: Completely out here after taking 50% earlier around 7.2 | W71: 045_2026-05-14_191952_Screenshot_20260514-211824.png | X71: high | Y71: https://discord.com/channels/1042855255089623100/1501271173588193290/1504518622083551303
A72: 2026-05-14 | B72: 21:54:01 | C72: XRPUSDT | D72: XRP | E72: long | R72: closed | S72: Blofin | T72: chart | U72: Only an exchange 'S' (sell/close) execution marker is visible on the chart, sitting on a green 1h candle roughly around 1.47 (estimated from the price axis), i.e. the long was closed in the early part of the breakout before price ran to 1.5431. Side inferred from the sell marker plus his message ('hit full TP ... closed early'). No entry, size or ROI printed. | V72: Fumbled XRP, hit full TP, was a great setup closed early but at least the idea was right! | W72: 047_2026-05-14_215401_Screenshot_20260514-235326.png | X72: high | Y72: https://discord.com/channels/1042855255089623100/1501271173588193290/1504557414853115985
A73: 2026-05-15 | B73: 03:20:30 | C73: BBUSDT | D73: BB | E73: long | F73: 25 | H73: 0.03538 | I73: 0.0371 | J73: mark | K73: 116.46 | R73: open | S73: Bybit | T73: pnl_share_card | U73: Card label is 'Current Price' (still open when shared). Per the accompanying message he had forgotten about this position and was closing it early for decent profit; HBAR and BTC positions still held. | V73: Totally forgot about this one, closing early for decent profits HBAR and BTC holding now. @Paladin Notify | W73: 048_2026-05-15_032030_Screenshot_20260515-051356.png | X73: high | Y73: https://discord.com/channels/1042855255089623100/1501271173588193290/1504639581050638448
A74: 2026-05-16 | B74: 10:05:03 | C74: BTCUSDT | D74: BTC | R74: planned | S74: Discord | T74: discord_message_screenshot | U74: Scenario plan, not an executed trade. Symbol not printed; BTC inferred from the price levels (77.7-78.1k). Bull case: first reversal zone 77.7-78.1k, a bounce there targets 79-80k for the weekend. Bear case: a 4h candle close below 77.7k targets 75-76k. | W74: 049_2026-05-16_100503_Screenshot_20260516-120450.png | X74: high | Y74: https://discord.com/channels/1042855255089623100/1501271173588193290/1505103774262493225
A75: 2026-05-17 | B75: 13:34:36 | C75: ETHUSDT | D75: ETH | E75: long | F75: 100 | H75: 2173.61 | I75: 2194.45 | J75: mark | K75: 90.57 | R75: open | S75: Bybit | T75: pnl_share_card | U75: Card label is 'Current Price' (open). Per the accompanying message the trade is over 1R and he suggests taking 25-50% partial here. | V75: ETH over 1R, you can take 25-50% here @Paladin Notify | W75: 050_2026-05-17_133436_Screenshot_20260517-153149.png | X75: high | Y75: https://discord.com/channels/1042855255089623100/1501271173588193290/1505518897707876503
A76: 2026-05-17 | B76: 13:37:15 | C76: BTCUSDT | D76: BTC | E76: long | F76: 150 | H76: 78041.3 | I76: 78494.9 | J76: mark | K76: 87.18 | R76: open | S76: Blofin | T76: pnl_share_card | U76: BloFin 'War of Whales 2026' template, 'Buy 150X' = long at 150x. Mark price shown, so still open. Referral code DwquXN. Posted as 'BTC moving too if anyone took that idea', i.e. a BTC long off the 77.7-78.1k reversal-zone plan. | V76: BTC moving too if anyone took that idea | W76: 051_2026-05-17_133715_blofin_1779014226326.png | X76: high | Y76: https://discord.com/channels/1042855255089623100/1501271173588193290/1505519562949394503
A77: 2026-05-19 | B77: 04:02:19 | C77: BOMEUSDT | D77: BOME | E77: long | F77: 25 | H77: 0.0005998 | I77: 0.0006203 | J77: mark | K77: 80.8 | R77: open | S77: Bybit | T77: pnl_share_card | U77: Card label is 'Current Price' (open). Per the accompanying message: take 25% here and move SL to entry; small accounts should close entirely here, or SL to entry and exit at the first TP. No SL/TP values printed on the card. | V77: Take 25% SL to entry, if you have a small account close entirely here or just SL to entry and exit at first TP. Hopefully we print big on ZEC! @Paladin Notify | W77: 052_2026-05-19_040219_Screenshot_20260519-055828.png | X77: high | Y77: https://discord.com/channels/1042855255089623100/1501271173588193290/1506099654516019330
A78: 2026-05-19 | B78: 04:26:18 | C78: ZECUSDT | D78: ZEC | E78: long | F78: 75 | H78: 545.99 | I78: 572.12 | J78: mark | K78: 358.87 | R78: open | S78: Blofin | T78: pnl_share_card | U78: BloFin 'War of Whales 2026' template, 'Buy 75X' = long at 75x; mark price shown, so still open. Referral code DwquXN. Per the accompanying message he took 20% here, moved SL to entry and is holding the majority for TPs. | V78: ZEC going hard, took 20% SL to entry, saving majority for TPs @Paladin Notify | W78: 053_2026-05-19_042618_blofin_1779153685809.png | X78: high | Y78: https://discord.com/channels/1042855255089623100/1501271173588193290/1506105688991207505
A79: 2026-05-19 | B79: 10:30:37 | C79: BOMEUSDT | D79: BOME | E79: long | F79: 25 | H79: 0.0005998 | I79: 0.000643 | J79: mark | K79: 165.91 | R79: open | S79: Bybit | T79: pnl_share_card | U79: Card label is 'Current Price' (share taken while open). Same BOMEUSDT 25x long (entry 0.0005998) shown earlier at +80.80%; per the accompanying message 'BOME exploded, TP' - this is where he took profit. | V79: Well BOME exploded, TP. @Paladin Notify | W79: 054_2026-05-19_103037_Screenshot_20260519-122717.png | X79: high | Y79: https://discord.com/channels/1042855255089623100/1501271173588193290/1506197374182228020
A80: 2026-05-19 | B80: 21:04:20 | C80: ZECUSDT | D80: ZEC | E80: long | F80: 75 | H80: 545.99 | I80: 581.92 | J80: close | K80: 493.44 | R80: closed | S80: Blofin | T80: pnl_share_card | U80: BloFin 'War of Whales 2026' template; 'Close Price' shown, so this portion is closed. Same ZECUSDT 75x long (entry 545.99) shown open at +358.87% earlier that morning. Per the accompanying message the TP hit around 1R, he booked the majority here and intends to full-TP at 592 (not printed on the card). | V80: ZEC TP hit, around 1R, booked majority here, I'll full TP @ 592 Decent day for a shit market @Paladin Notify | W80: 055_2026-05-19_210420_blofin_1779213774283.png | X80: high | Y80: https://discord.com/channels/1042855255089623100/1501271173588193290/1506356854207545494
A81: 2026-05-20 | B81: 04:16:21 | C81: BTCUSDT | D81: BTC | E81: long | F81: 150 | H81: 76704.7 | I81: 76853.8 | J81: mark | K81: 29.14 | R81: open | S81: Blofin | T81: pnl_share_card | U81: BloFin 'War of Whales 2026' template, 'Buy 150X' = long at 150x; mark price shown, so open. Entry 76,704.7 is an averaged entry after a DCA fill (per message). He expects 78k+ today. Referral code DwquXN. | V81: Still holding this BTC trade, DCA filled trade, expecting 78k+ today so should give some good good profits! | W81: 056_2026-05-20_041621_blofin_1779239695170.png | X81: high | Y81: https://discord.com/channels/1042855255089623100/1501271173588193290/1506465574434246768
A82: 2026-05-20 | B82: 09:20:54 | C82: ZECUSDT | D82: ZEC | E82: long | F82: 75 | H82: 580.25 | I82: 591.75 | J82: close | K82: 148.59 | R82: closed | S82: Blofin | T82: pnl_share_card | U82: BloFin 'War of Whales 2026' template; 'Close Price' shown, so closed. Entry 580.25 differs from the earlier ZEC long (545.99), so this is a separate/re-entered ZECUSDT 75x long closed at 591.75, essentially at the 592 full-TP level he had mentioned the night before. No message accompanied this image. | W82: 057_2026-05-20_092054_blofin_1779257847868.png | X82: high | Y82: https://discord.com/channels/1042855255089623100/1501271173588193290/1506542215424376922
A83: 2026-05-20 | B83: 16:23:21 | C83: BTCUSDT | D83: BTC | E83: long | F83: 150 | H83: 76704.7 | I83: 77450.5 | J83: mark | K83: 145.83 | R83: open | S83: Blofin | T83: pnl_share_card | U83: BloFin 'War of Whales 2026' template; mark price shown, so still open. Same BTCUSDT 150x long (entry 76,704.7) shown at +29.14% that morning. Per the accompanying message BTC has moved about 1R, he is aiming for around 78.5k, followers may take partials but he personally avoids partials on BTC. | V83: Guys BTC already have moved around 1R, I'm trying for around 78.5k around but don't wait for me you can take partials as you like. I personally avoid partials especially on BTC @Paladin Notify | W83: 058_2026-05-20_162321_blofin_1779282839848.png | X83: high | Y83: https://discord.com/channels/1042855255089623100/1501271173588193290/1506648527345025034
A84: 2026-05-21 | B84: 04:30:48 | C84: BTCUSDT | D84: BTC | E84: long | F84: 150 | H84: 76704.7 | I84: 77826.3 | J84: close | K84: 219.32 | R84: closed | S84: Blofin | T84: pnl_share_card | U84: BloFin 'War of Whales 2026' template; 'Close Price' shown, so closed. Final card of the DCA'd BTCUSDT 150x long (entry 76,704.7): closed at 77,826.3, short of the ~78.5k he was aiming for. Per the message: closed here, over 1R, with a DCA great profits. | V84: BTC closed here, over 1R + with a DCA great profits for me @Paladin Notify | W84: 059_2026-05-21_043048_blofin_1779326995023.png | X84: high | Y84: https://discord.com/channels/1042855255089623100/1501271173588193290/1506831598707019827
A85: 2026-05-21 | B85: 05:03:46 | C85: SUIUSDT | D85: SUI | E85: long | F85: 50 | H85: 1.0738 | I85: 1.1127 | J85: mark | K85: 170.83 | R85: open | S85: Bybit | T85: pnl_share_card | U85: Card label is 'Current Price' (open). Per the accompanying message his TP is at 1.14 and TP2 at 1.23 for anyone holding longer; these targets are not printed on the card. | V85: SUI running really well too, I'll TP @ 1.14 TP2 @ 1.23 if someone likes to hold longer | W85: 060_2026-05-21_050346_Screenshot_20260521-065728.png | X85: high | Y85: https://discord.com/channels/1042855255089623100/1501271173588193290/1506839893358284901
A86: 2026-05-21 | B86: 05:57:24 | C86: SUIUSDT | D86: SUI | E86: long | F86: 50 | H86: 1.0738 | I86: 1.14 | J86: close | K86: 308.25 | R86: closed | S86: Bybit | T86: pnl_share_card | U86: Card label is 'Exit Price' (closed). Exit 1.14000 matches exactly the TP1 of 1.14 he announced an hour earlier; per the message the TP was hit immediately after that message. Same SUIUSDT 50x long, entry 1.07380. | V86: SUI TP got hit immediately after this message. Good start of the day! @Paladin Notify | W86: 061_2026-05-21_055724_Screenshot_20260521-075544.png | X86: high | Y86: https://discord.com/channels/1042855255089623100/1501271173588193290/1506853391668613170
A87: 2026-05-21 | B87: 05:57:39 | C87: SUIUSDT | D87: SUI | E87: long | F87: 100 | H87: 1.0481 | I87: 1.1401 | J87: close | K87: 877.77 | R87: closed | S87: Blofin | T87: pnl_share_card | U87: Blofin 'WOW War of Whales 2026' share card, shown as 'Buy 100X'. Referral code DwquXN. Per the accompanying message this entry (1.0481) was a DCA add to his SUI long, closed at 1.1401. | V87: Entry from my DCA 👇🏻 | W87: 062_2026-05-21_055739_blofin_1779332116390.png | X87: high | Y87: https://discord.com/channels/1042855255089623100/1501271173588193290/1506853455929544744
A88: 2026-05-21 | B88: 20:21:34 | C88: BTCUSDT | D88: BTC | E88: long | F88: 150 | H88: 77065.1 | I88: 77854.8 | J88: mark | K88: 153.7 | R88: open | S88: Blofin | T88: pnl_share_card | U88: Blofin 'WOW War of Whales 2026' share card, 'Buy 150X', still open (Mark Price shown). Referral code on this card is hrk3ES, different from the DwquXN code on his other Blofin cards, so possibly a different Blofin account. | V88: I saw some in chat saying I'm getting rekt because everyone else is shorting 😐 @Paladin Notify | W88: 064_2026-05-21_202134_blofin_1779384057207.png | X88: high | Y88: https://discord.com/channels/1042855255089623100/1501271173588193290/1507070864791703704
A89: 2026-05-22 | B89: 16:02:49 | C89: 1000BONKUSDT | D89: 1000BONK | E89: long | F89: 75 | H89: 0.006158 | I89: 0.006323 | J89: close | K89: 199.88 | R89: closed | S89: Blofin | T89: pnl_share_card | U89: Blofin 'WOW War of Whales 2026' card, 'Buy 75X'. Referral code DwquXN. Per message this was TP1 where he took only 20-25% off and kept the majority of the position. | V89: BONK TP1, taking 20-25% only saving majority @Paladin Notify | W89: 066_2026-05-22_160249_blofin_1779454878921.png | X89: high | Y89: https://discord.com/channels/1042855255089623100/1501271173588193290/1507368138889494681
A90: 2026-05-22 | B90: 16:41:48 | C90: WLDUSDT | D90: WLD | E90: long | F90: 100 | H90: 0.284 | I90: 0.2908 | J90: mark | K90: 234.74 | R90: open | S90: Yubit | T90: pnl_share_card | U90: Card shows 'Fair Price' (this exchange's term for mark price) so the position was still open. Per message: WLD missed his TP by 0.002, was up 1.5R from the limit entry / 0.9R from CMP, and he advised taking 25-50% and moving SL to entry. | V90: WLD missed TP by 0.002, almost missed TP, moved up 1.5 R from limit, up 0.9 from CMP Take 25-50% SL to entry @Paladin Notify | W90: 067_2026-05-22_164148_Screenshot_20260522-183856.png | X90: high | Y90: https://discord.com/channels/1042855255089623100/1501271173588193290/1507377949874192516
A91: 2026-05-22 | B91: 18:35:51 | C91: WLDUSDT | D91: WLD | E91: long | F91: 100 | J91: close | K91: 542.25 | R91: closed | S91: Yubit | T91: pnl_share_card | U91: 'Closed PNL' header; entry/close prices not included in the crop. Earlier card (067) showed entry $0.284. Per message the TP was hit at 1.5R from the limit entry / 1R from CMP and he exited fully at the first TP. | V91: TP hit 1.5R from limit, 1R from CMP I'm out at first TP but confident weekend might give us ful TP @Paladin Notify | W91: 068_2026-05-22_183551_Screenshot_20260522-203419.png | X91: high | Y91: https://discord.com/channels/1042855255089623100/1501271173588193290/1507406648829022390
A92: 2026-05-23 | B92: 09:21:38 | C92: BEATUSDT | D92: BEAT | E92: short | F92: 100 | H92: 1.2875 | I92: 1.169 | J92: close | K92: 921.08 | R92: closed | S92: Yubit | T92: pnl_share_card | U92: Card header 'Close Short | 100X' with Avg Entry Price $1.2875 and Avg Close Price $1.169. Per message he was up 1.5R and closed 60% of the position to recover one earlier stop loss (a later Discord message says the trade went 2R and TP was taken at 1.7R). | V92: Up 1.5R, took 60% to recover 1SL @Paladin Notify | W92: 069_2026-05-23_092138_Screenshot_20260523-112019.png | X92: high | Y92: https://discord.com/channels/1042855255089623100/1501271173588193290/1507629563000258671
A93: 2026-05-23 | B93: 10:52:47 | C93: JCTUSDT | D93: JCT | E93: short | F93: 50 | H93: 0.004 | I93: 0.00387 | J93: mark | K93: 160.87 | R93: open | S93: Yubit | T93: pnl_share_card | U93: Shows 'Fair Price' (mark price) so still open. Per message JCT dumped nearly 0.5R; he took only 10% and moved SL to entry, advising 10-20% max partials on shorts because BTC may bounce. | V93: JCT dumped nearly 0.5 R, taking 10% only, SL to entry. BTC may bounce so securinh my shorts, take 10-20% MAX! @Paladin Notify | W93: 070_2026-05-23_105247_Screenshot_20260523-125146.png | X93: high | Y93: https://discord.com/channels/1042855255089623100/1501271173588193290/1507652503599059055
A94: 2026-05-23 | B94: 10:57:00 | C94: HYPEUSDT | D94: HYPE | E94: long | F94: 100 | H94: 54.991 | I94: 55.507 | J94: mark | K94: 93.83 | R94: open | S94: Yubit | T94: pnl_share_card | U94: Shows 'Fair Price' (mark price) so still open. Message: 'HYPE 0.5 R up'. | V94: And HYPE 0.5 R up :KEKLaugh: | W94: 071_2026-05-23_105700_Screenshot_20260523-125632.png | X94: high | Y94: https://discord.com/channels/1042855255089623100/1501271173588193290/1507653565022212139
A95: 2026-05-23 | B95: 11:50:21 | C95: HYPEUSDT | D95: HYPE | E95: long | F95: 100 | J95: close | K95: 204.57 | R95: closed | S95: Yubit | T95: pnl_share_card | U95: 'Closed PNL' header; prices not in the crop (entry was $54.991 per card 071). Per message he closed here at 1.2R and set 58 as the next TP for those still holding. | V95: HYPE up 1.2R, I'm out here, but 58 next TP for those holding @Paladin Notify | W95: 072_2026-05-23_115021_Screenshot_20260523-134519.png | X95: high | Y95: https://discord.com/channels/1042855255089623100/1501271173588193290/1507666989454200832
A96: 2026-05-23 | B96: 16:15:56 | C96: SUIUSDT | D96: SUI | E96: long | F96: 100 | H96: 1.0014 | I96: 1.0165 | J96: mark | K96: 150.91 | R96: open | S96: Blofin | T96: pnl_share_card | U96: Blofin 'WOW War of Whales 2026' card, 'Buy 100X', open (Mark Price shown). Referral code DwquXN. Message: '1R soon!' - per his later explanation this trade had SL 0.95 and TP 1.05 (entry ~1). | V96: 1R soon! | W96: 073_2026-05-23_161556_blofin_1779542139382.png | X96: high | Y96: https://discord.com/channels/1042855255089623100/1501271173588193290/1507733827601301525
A97: 2026-05-23 | B97: 16:36:55 | C97: SUIUSDT | D97: SUI | E97: long | H97: 1 | O97: 0.95 | P97: 1.05 | R97: open | S97: Discord | T97: discord_message_screenshot | U97: Stated as 'SUI is running from 1, SL 0.95 (-0.5) TP 1.05 (+0.5)' - entry '1' is his rounded figure for the live SUI long (actual entry 1.0014 on the Blofin cards); this defines a 1:1 R trade (1R = 0.05 move). | V97: For those who don't know what is R, I tried explaining in the simplest way! Also guys, I risk 1-2% on ALTs and 3-5% on BTC trades @Paladin Notify | W97: 074_2026-05-23_163655_Screenshot_20260523-183520.png | X97: high | Y97: https://discord.com/channels/1042855255089623100/1501271173588193290/1507739108884348969
A98: 2026-05-23 | B98: 16:36:55 | C98: BEATUSDT | D98: BEAT | E98: short | R98: closed | S98: Discord | T98: discord_message_screenshot | U98: Recap only: 'we did beat short it went 2R ... (We took TP @ 1.7 R)'. | V98: For those who don't know what is R, I tried explaining in the simplest way! Also guys, I risk 1-2% on ALTs and 3-5% on BTC trades @Paladin Notify | W98: 074_2026-05-23_163655_Screenshot_20260523-183520.png | X98: high | Y98: https://discord.com/channels/1042855255089623100/1501271173588193290/1507739108884348969
A99: 2026-05-23 | B99: 16:42:48 | C99: SUIUSDT | D99: SUI | F99: 100 | G99: cross | R99: unknown | S99: Blofin | T99: order_screenshot | U99: Blofin limit order form for SUIUSDT Perp (Cross, 100X) with Price(USDT) field = 1.1 and Amount field empty, unit SUI; buy/sell side not visible. Screenshot is a tutorial on the 'Futures Unit Setting' (By Amount in SUI vs By Cost in USDT), red hand-drawn marks under the 'SUI' unit selector; the 1.1 price is likely illustrative rather than a placed order. Available balance 794.72 USDT, SUI 24h change -9.33%, funding 0.0138%, last price 1.0172. | V99: Go to your exchanges and set by amount I'm doing this on blofin but every exchange has it the same. | W99: 077_2026-05-23_164248_Screenshot_20260523-184152.png | X99: high | Y99: https://discord.com/channels/1042855255089623100/1501271173588193290/1507740588563370145
A100: 2026-05-23 | B100: 17:16:47 | C100: BTCUSDT | D100: BTC | E100: long | F100: 20 | G100: cross | H100: 75166.5 | I100: 75159.2 | J100: mark | K100: -0.19 | L100: -0.0657 | M100: 0.0090 BTC | N100: 34.2309 | O100: 72200 | Q100: 65494.8 | R100: open | S100: Blofin | T100: open_positions_screenshot | U100: Position TP/SL shows '-- / 72,200.0' (no TP set, SL 72,200.0). Margin Rate 2.29%. Unrealized PnL -0.0657 USDT (≈ -$0.06). First trade of his 89.36 USDT BTC-scalp challenge account. | V100: First scalp trade. | W100: 079_2026-05-23_171647_Screenshot_20260523-191624.png | X100: high | Y100: https://discord.com/channels/1042855255089623100/1501271173588193290/1507749138832298015
A101: 2026-05-23 | B101: 21:18:48 | C101: SUIUSDT | D101: SUI | E101: long | F101: 100 | H101: 1.0014 | I101: 1.0539 | J101: mark | K101: 524.3 | R101: open | S101: Blofin | T101: pnl_share_card | U101: Blofin 'WOW War of Whales 2026' card, 'Buy 100X', Mark Price shown so position still open at card time. Referral code DwquXN. Message 'took some here' indicates a partial profit taken around 1.0539, slightly above the 1.05 TP he had described (entry ~1, SL 0.95, TP 1.05). | V101: Alright boys took some here @Paladin Notify | W101: 081_2026-05-23_211848_blofin_1779560270446.png | X101: high | Y101: https://discord.com/channels/1042855255089623100/1501271173588193290/1507810046959161707
A102: 2026-05-23 | B102: 23:42:34 | C102: FILUSDT | D102: FIL | E102: long | F102: 3 | H102: 0.955 | I102: 1 | J102: close | K102: 14.13 | R102: closed | S102: Blofin | T102: pnl_share_card | U102: Blofin 'WOW War of Whales 2026' share card. Low-leverage (3X) FIL long closed exactly at the 1.000 round number. Card generated 05-24 01:41:28. | V102: FIL TP @Paladin Notify | W102: 082_2026-05-23_234234_blofin_1779568888498.png | X102: high | Y102: https://discord.com/channels/1042855255089623100/1501271173588193290/1507846224202694776
A103: 2026-05-23 | B103: 23:42:51 | C103: BTCUSDT | D103: BTC | E103: long | F103: 150 | H103: 75197.2 | I103: 76903.8 | J103: mark | K103: 340.42 | R103: open | S103: Blofin | T103: pnl_share_card | U103: Blofin 'WOW War of Whales 2026' share card of an open position (Mark Price shown). Card generated 05-24 01:41:18. | V103: BTC feel free to trim wherever you want. @Paladin Notify | W103: 083_2026-05-23_234251_blofin_1779568879556.png | X103: high | Y103: https://discord.com/channels/1042855255089623100/1501271173588193290/1507846295732228228
A104: 2026-05-23 | B104: 23:43:25 | C104: SUIUSDT | D104: SUI | E104: long | F104: 100 | H104: 1.0014 | I104: 1.0803 | J104: mark | K104: 788.77 | R104: open | S104: Blofin | T104: pnl_share_card | U104: Blofin 'WOW War of Whales 2026' share card of an open position (Mark Price shown). Per the accompanying message he is near full TP but still holding the majority with a target of 1.1+. Card generated 05-24 01:42:58. | V104: SUI nearly full TP, still holding majority, Target 1.1+ @Paladin Notify | W104: 084_2026-05-23_234325_blofin_1779568979638.png | X104: high | Y104: https://discord.com/channels/1042855255089623100/1501271173588193290/1507846441123709070
A105: 2026-05-23 | B105: 23:57:10 | C105: BTCUSDT | D105: BTC | E105: long | F105: 200 | G105: cross | H105: 75166.5 | I105: 77072.3 | J105: mark | K105: 507.03 | L105: 17.1504 | M105: 0.0090 BTC | N105: 3.7884 | O105: 72220 | Q105: 65500.5 | R105: open | S105: Blofin | T105: open_positions_screenshot | U105: Unrealized PnL +17.1504 USDT (~ +$17.15), ROI +507.03%. Margin Rate 5.97%. Position TP/SL shows '-- / 72,220.0' (no TP set, stop loss at 72,220.0). 'Pending Orders (2)' collapsed. Entry 75,166.5 differs slightly from the 75,197.2 on his Blofin share cards - this appears to be a separate small (~$90) account at 200X. | V105: Making 20% of this :KEKLaugh: | W105: 086_2026-05-23_235710_Screenshot_20260524-015655.png | X105: high | Y105: https://discord.com/channels/1042855255089623100/1501271173588193290/1507849900690247901
A106: 2026-05-24 | B106: 00:01:23 | C106: BTCUSDT | D106: BTC | E106: long | F106: 150 | H106: 75197.2 | I106: 77348.4 | J106: mark | K106: 429.13 | R106: open | S106: Blofin | T106: pnl_share_card | U106: Blofin 'WOW War of Whales 2026' share card of the same open BTC long (entry 75,197.2), now at mark 77,348.4. Card generated 05-24 02:00:15. | V106: Bullish weekend | W106: 087_2026-05-24_000123_blofin_1779570016366.png | X106: high | Y106: https://discord.com/channels/1042855255089623100/1501271173588193290/1507850960737927168
A107: 2026-05-24 | B107: 00:09:16 | C107: SUIUSDT | D107: SUI | E107: long | F107: 250 | H107: 1.0006 | I107: 1.0909 | J107: mark | K107: 2148.71 | R107: open | S107: Yubit | T107: pnl_share_card | U107: Card shows 'Fair Price $1.0909' (mark-price equivalent) rather than a close price, so recorded as open per the rules; however the accompanying message says SUI hit full TP (2R), so this is the snapshot at or just before closing. Separate account/exchange from the Blofin 100X SUI position (entry 1.0006 vs 1.0014). | V107: Sorry for the spam but SUI hit full TP 2R since we barely took anything at TP1 @Paladin Notify | W107: 088_2026-05-24_000916_Screenshot_20260524-020832.png | X107: medium | Y107: https://discord.com/channels/1042855255089623100/1501271173588193290/1507852944312373341
A108: 2026-05-24 | B108: 00:09:23 | C108: SUIUSDT | D108: SUI | E108: long | F108: 100 | H108: 1.0014 | I108: 1.089 | J108: close | K108: 874.77 | R108: closed | S108: Blofin | T108: pnl_share_card | U108: Blofin 'WOW War of Whales 2026' share card; the SUI 100X long (entry 1.0014) is now fully closed at 1.0890. Card generated 05-24 02:05:50. | W108: 089_2026-05-24_000923_blofin_1779570355350.png | X108: high | Y108: https://discord.com/channels/1042855255089623100/1501271173588193290/1507852972460216501
A109: 2026-05-24 | B109: 00:12:10 | C109: BTCUSDT | D109: BTC | E109: long | F109: 150 | H109: 75197.2 | I109: 77036.2 | J109: mark | K109: 366.85 | R109: open | S109: Blofin | T109: pnl_share_card | U109: Blofin 'WOW War of Whales 2026' share card; BTC 150X long still open, mark 77,036.2 (pulled back from 77,348.4 shown ~11 minutes earlier). Card generated 05-24 02:11:19. Posted as part of a batch of four cards recapping the day's calls. | V109: C'mon guys at least post PNLs #💲｜profit-showcase today I gave you like 5R today @Paladin Notify | W109: 090_2026-05-24_001210_blofin_1779570679706.png | X109: high | Y109: https://discord.com/channels/1042855255089623100/1501271173588193290/1507853674855137532
A110: 2026-05-24 | B110: 00:12:10 | C110: BEATUSDT | D110: BEAT | E110: short | F110: 40 | H110: 1.2694 | I110: 1.1482 | J110: close | K110: 382.08 | R110: closed | S110: Blofin | T110: pnl_share_card | U110: Blofin 'WOW War of Whales 2026' share card; 'Sell 40X' = short. Closed BEAT short from 1.2694 to 1.1482. Card generated 05-24 02:11:15. | V110: C'mon guys at least post PNLs #💲｜profit-showcase today I gave you like 5R today @Paladin Notify | W110: 091_2026-05-24_001210_blofin_1779570675950.png | X110: high | Y110: https://discord.com/channels/1042855255089623100/1501271173588193290/1507853674855137532
A111: 2026-05-24 | B111: 00:12:10 | C111: SUIUSDT | D111: SUI | E111: long | F111: 100 | H111: 1.0014 | I111: 1.089 | J111: close | K111: 874.77 | R111: closed | S111: Blofin | T111: pnl_share_card | U111: Blofin 'WOW War of Whales 2026' share card; same closed SUI trade as the card generated at 02:05:50 (entry 1.0014, close 1.0890), re-generated 05-24 02:10:54 for the recap batch. | V111: C'mon guys at least post PNLs #💲｜profit-showcase today I gave you like 5R today @Paladin Notify | W111: 092_2026-05-24_001210_blofin_1779570654702.png | X111: high | Y111: https://discord.com/channels/1042855255089623100/1501271173588193290/1507853674855137532
A112: 2026-05-24 | B112: 00:12:10 | C112: FILUSDT | D112: FIL | E112: long | F112: 3 | H112: 0.955 | I112: 1 | J112: close | K112: 14.13 | R112: closed | S112: Blofin | T112: pnl_share_card | U112: Blofin 'WOW War of Whales 2026' share card; same closed FIL 3X trade as the card generated at 01:41:28 (entry 0.955, close 1.000), re-generated 05-24 02:10:56 for the recap batch. | V112: C'mon guys at least post PNLs #💲｜profit-showcase today I gave you like 5R today @Paladin Notify | W112: 093_2026-05-24_001210_blofin_1779570656635.png | X112: high | Y112: https://discord.com/channels/1042855255089623100/1501271173588193290/1507853674855137532
A113: 2026-05-24 | B113: 00:13:16 | C113: HYPEUSDT | D113: HYPE | E113: long | F113: 100 | K113: 204.57 | R113: closed | S113: Yubit | T113: pnl_share_card | U113: 'Closed PNL' card header. Only ROI is visible; entry/close prices are cut off by the crop. A decorative mini price line shows a green 'B' (buy) marker at a local low and a red 'S' (sell) marker higher up on the right. | V113: Actually 8R, gave 3R on HYPE too 🤘🏻 | W113: 094_2026-05-24_001316_Screenshot_20260524-021241.png | X113: medium | Y113: https://discord.com/channels/1042855255089623100/1501271173588193290/1507853951599644892
...

Sheet Images
A1: # | B1: Date | C1: Time | D1: Trading related | E1: Image type | F1: Platform | G1: Trades in image | H1: Symbols | I1: Chart timeframe | J1: Chart indicators | K1: Chart levels / drawings | L1: What the chart shows | M1: Description | N1: Text visible in image | O1: Message posted with image | P1: Date/time printed on image | Q1: Confidence | R1: Issues | S1: Image file | T1: Duplicate of | U1: Discord link
A2: 1 | B2: 2026-05-06 | C2: 23:47:41 | D2: yes | E2: discord_message_screenshot | F2: Discord | G2: 24 | H2: ALGOUSDT, ASTERUSDT, AXSUSDT, BTCUSDT, ETHUSDT, HYPEUSDT, IRYSUSDT, PEPEUSDT, SOLUSDT | M2: Screenshot of his own Discord recap message listing 25 journal trades by ticker (22 wins, 3 break-even, 0 losses) with a party emoji, followed by an embedded Binance Futures USDⓈ-M 'My Futures PnL' card showing Cumulative PNL % +90.94% for the period 2026-04-30 to 2026-05-07, a small gold cumulative-PnL sparkline (flat, dip, spike, dip, slight rise) and Win Rate 100.00%. Shows he is journaling on Binance Futures and trades mostly BTC with occasional alts (ETH, ASTER, AXS, IRYS, HYPE, PEPE, SOL, ALGO). | N2: So far, 25 trades 22 Winning trades (ASTER, AXS, IRYS, BTC, BTC, BTC, ETH, HYPE, PEPE, ETH, BTC, BTC, BTC, BTC, BTC, ETH, BTC, BTC, BTC, BTC, BTC) 3 BE trades (SOL, ALGO, BTC) 0 Loss (edited) 🎉 [Binance share card] My Futures PnL Cumulative PNL % Period: 2026-04-30 - 2026-05-07 +90.94% Win Rate 100.00% BINANCE FUTURES | USDⓈ-M Referral Code 550295426 | O2: I have been trading for the past month in journals and here's my progress so far **25** trades **22** Wins **3** BE **0** loss Can track it all in the journal -> https://discord.com/channels/1042855255089623100/1496387902140321885/1501536396127633418 @Paladin Notify | P2: Period: 2026-04-30 - 2026-05-07 | Q2: high | R2: Author name and message time are cropped out. The recap says 22 winning trades but only 21 tickers are listed in the parentheses (24 tickers total vs. 25 trades stated); trade entries reflect the 24 tickers actually listed. Tickers are given as base assets only (no quote currency); the sparkline is a PnL curve, not a price chart. | S2: 001_2026-05-06_234741_Screenshot_20260507-014653.png | U2: https://discord.com/channels/1042855255089623100/1501271173588193290/1501686917828448277
A3: 2 | B3: 2026-05-08 | C3: 13:48:41 | D3: yes | E3: open_positions_screenshot | F3: unknown | G3: 1 | H3: BTCUSDT | M3: A tiny crop of an exchange position/order field showing only 'Entry Price (USDT) 79,564.80' (dark UI, label style resembling Bybit's positions tab). Posted as BTC 'started moving' to show his entry level while suggesting followers take 20% off at 80.5k. | N3: Entry Price (USDT) 79,564.80 | O3: BTC started moving, you can take 20% @ 80.5k if you want, I'll update whenever I close! | Q3: medium | R3: Image is a small crop: no symbol, side, leverage, size, PnL or exchange branding visible; symbol/side inferred from message context only. Platform not identifiable with certainty. | S3: 002_2026-05-08_134841_Screenshot_20260508-1547142.png | U3: https://discord.com/channels/1042855255089623100/1501271173588193290/1502260952098279615
A4: 3 | B4: 2026-05-08 | C4: 18:44:20 | D4: yes | E4: pnl_share_card | F4: Bybit | G4: 1 | H4: UNIUSDT | M4: Top portion of a Bybit-style PnL share card for a UNIUSDT 50X long showing ROI +101.21%; posted when he closed 50% of the UNI position as the 'first win'. | N4: UNIUSDT Long 50.0X ROI +101.21% | O4: Okay let's treat as our first win Closing 50% UNI for 0.7 R move, I'll take personally fully TP @ 3.7 You can hold till 4 SL @ BE 3.46 @Paladin Notify | Q4: medium | R4: Card is cropped below the ROI: entry/exit prices, price-type label and exchange logo are not visible. Platform identified from the card style (identical to his other Bybit cards), not from a visible logo. | S4: 003_2026-05-08_184420_Screenshot_20260508-203512.png | U4: https://discord.com/channels/1042855255089623100/1501271173588193290/1502335355628687451
A5: 4 | B5: 2026-05-08 | C5: 19:41:13 | D5: yes | E5: chart | F5: Bybit | G5: 0 | I5: 15m | J5: EMA7 (3.614); EMA14 (3.577); EMA28 (3.537); volume with MA5 (138.12K) and MA10 (124.64K) | K5: exchange auto high marker 3.698 at the current candle; exchange auto low marker 3.392 near 13:15; current price line 3.687 with countdown 05:13; no user drawings | L5: UNIUSDT 15m in a vertical breakout: after grinding up along the EMAs all day, price went parabolic from ~3.47 around 18:45 to a new 24h high of 3.698 with a big volume spike on the last candles; EMAs stacked bullishly. He posted this as he exited UNI fully at 3.7, i.e. selling into the spike. | M5: Bybit app (Demo Trading watermark) 15m candlestick chart of UNIUSDT, up +7.52% on the day, showing a parabolic breakout to the 24h high 3.698 with last price 3.687 and a volume spike. Posted with his message that he is fully out of UNI at 3.7 for ~1.4R and expects $4 by the coming weekend/week. | N5: UNIUSDT ▾ +7.52% MM 0.65% Chart Overview Data Feed Last Traded Price ▾ 3.687 Mark Price 3.689 24h High 3.698 24h Low 3.383 24h Turnover 13.02M Time 15m 1h 4h 1D More ▾ | Depth EMA7: 3.614 EMA14: 3.577 EMA28: 3.537 3.698 3.687 05:13 3.621 3.545 3.468 3.392 BYBIT Demo Trading 10:30 13:15 16:00 18:45 21:30 00:15 VOLUME: 184.08K MA5: 138.12K MA10: 124.64K 298.48K | O5: Well UNI blew up, I'm fully out here @ 3.7 for around 1.4 R Think we see 4$ by coming weekend/week @Paladin Notify | P5: chart time axis 10:30, 13:15, 16:00, 18:45, 21:30, 00:15 (no date shown); candle countdown 05:13 | Q5: high | R5: The green 'MM 0.65%' badge next to the symbol is transcribed verbatim but its meaning is not stated on screen. Bottom of the volume pane is cut off. | S5: 004_2026-05-08_194113_Screenshot_20260508-213947.png | U5: https://discord.com/channels/1042855255089623100/1501271173588193290/1502349669571891250
A6: 5 | B6: 2026-05-09 | C6: 02:01:21 | D6: yes | E6: chart | F6: Bybit | G6: 0 | I6: 4h | J6: EMA7 (90.319); EMA14 (89.347); EMA28 (88.070) | K6: exchange auto high marker 92.760 at the latest candles; exchange auto low marker 82.740 near 05/01-05/02; current price line 92.240 with countdown 01:06:14; no user drawings | L6: SOLUSDT 4h in a steady uptrend from ~82.74 on May 1: base-building, then a strong impulse on May 5-6 to ~90, consolidation around 88-90 along EMA7/EMA14, and a large green 4h candle to a new 24h high 92.760 with the current candle slightly red at 92.240. Posted as one of the alts he said were 'popping off'. | M6: Bybit (Demo Trading) 4h chart of SOLUSDT, +4.79% on the day, breaking out to a 24h high of 92.760 with price at 92.240 above bullishly stacked EMAs. One of four alt charts he posted to show the coins he had mentioned were all moving up. | N6: SOLUSDT ▾ +4.79% MM 0.80% Chart Overview Data Feed Last Traded Price ▾ 92.240 Mark Price 92.240 24h High 92.760 24h Low 87.560 24h Turnover 907.66M Time 15m 1h 4h 1D More ▾ | Depth EMA7: 90.319 EMA14: 89.347 EMA28: 88.070 92.760 92.240 01:06:14 90.255 87.750 85.245 82.740 BYBIT Demo Trading 05/01 17:00 05/03 13:00 05/05 09:00 05/07 05:00 05/09 01:00 05/10 21 | O6: Look at them go, every ALT I mentioned here just popping off even ASTER started moving 🤣 Usually I'm already in too many trades and have to limit myself for giving positions because I feel like people don't care about risk management and jump in all in. But if I ever mention a coin and you can do some analysis, check them out! | P6: chart time axis 05/01 17:00, 05/03 13:00, 05/05 09:00, 05/07 05:00, 05/09 01:00, 05/10 21… (cut); candle countdown 01:06:14 | Q6: high | R6: Last time-axis label is cut off ('05/10 21'). 'MM 0.80%' badge meaning not stated on screen. | S6: 005_2026-05-09_020121_Screenshot_20260509-035346.png | U6: https://discord.com/channels/1042855255089623100/1501271173588193290/1502445332355878943
A7: 6 | B7: 2026-05-09 | C7: 02:01:21 | D7: yes | E7: chart | F7: Bybit | G7: 0 | I7: 1D | J7: EMA7 (1.4300); EMA14 (1.3897); EMA28 (1.3631) | K7: exchange auto high marker 1.6069 at the current daily candle; exchange auto low marker 1.1285 near 03/29-03/30; current price line 1.5902 with countdown 01:05:31; no user drawings | L7: NEARUSDT daily: bottom at 1.1285 in late March, rally to ~1.45 by mid-April, a pullback into early May toward ~1.25 (below the EMAs), then two very large green daily candles breaking out to a new high of 1.6069 with price at 1.5902 well above all EMAs. Posted as an example of alts he mentioned 'popping off'. | M7: Bybit (Demo Trading) daily chart of NEARUSDT, +8.81% on the day, showing a two-day vertical breakout from ~1.25 to 1.6069 with price at 1.5902. Part of his 'look at them go' batch of alt charts. | N7: NEARUSDT ▾ +8.81% MM 0.80% Chart Overview Data Feed Last Traded Price ▾ 1.5902 Mark Price 1.5902 24h High 1.6069 24h Low 1.4548 24h Turnover 64.14M Time 15m 1h 4h 1D More ▾ | Depth EMA7: 1.4300 EMA14: 1.3897 EMA28: 1.3631 1.6069 1.5902 01:05:31 1.4873 1.3677 1.2481 1.1285 BYBIT Demo Trading 03/25 04/05 04/16 04/27 05/08 05/1 | O7: Look at them go, every ALT I mentioned here just popping off even ASTER started moving 🤣 Usually I'm already in too many trades and have to limit myself for giving positions because I feel like people don't care about risk management and jump in all in. But if I ever mention a coin and you can do some analysis, check them out! | P7: chart time axis 03/25, 04/05, 04/16, 04/27, 05/08, 05/1… (cut); candle countdown 01:05:31 | Q7: high | R7: Last time-axis label is cut off. 'MM 0.80%' badge meaning not stated on screen. | S7: 006_2026-05-09_020121_Screenshot_20260509-035429.png | U7: https://discord.com/channels/1042855255089623100/1501271173588193290/1502445332355878943
A8: 7 | B8: 2026-05-09 | C8: 02:01:21 | D8: yes | E8: chart | F8: Bybit | G8: 0 | I8: 4h | J8: EMA7 (0.0020866); EMA14 (0.0020354); EMA28 (0.0019720) | K8: exchange auto high marker 0.0021932 at the current candles; exchange auto low marker 0.0017500 at the far left of the visible range; current price line 0.0021615 with countdown 01:05:12; no user drawings | L8: PUMPFUNUSDT 4h in a clean stair-step uptrend from 0.00175 to a 24h high of 0.0021932: consolidation, impulse, shallow pullbacks holding EMA7/EMA14, then a strong green push; current candle slightly red at 0.0021615 above all EMAs. Posted as an example of alts he mentioned 'popping off'. | M8: Bybit (Demo Trading) 4h chart of PUMPFUNUSDT, +9.37% on the day, in a steady uptrend to a new high 0.0021932 with price at 0.0021615. Part of his 'look at them go' batch of alt charts. | N8: PUMPFUNUSDT ▾ +9.37% MM 0.80% Chart Overview Data Feed Last Traded Price ▾ 0.0021615 Mark Price 0.0021615 24h High 0.0021932 24h Low 0.0019738 24h Turnover 19.85M Time 15m 1h 4h 1D More ▾ | Depth EMA7: 0.0020866 EMA14: 0.0020354 EMA28: 0.0019720 0.0021932 0.0021615 01:05:12 0.0020824 0.0019716 0.0018608 0.0017500 BYBIT Demo Trading | O8: Look at them go, every ALT I mentioned here just popping off even ASTER started moving 🤣 Usually I'm already in too many trades and have to limit myself for giving positions because I feel like people don't care about risk management and jump in all in. But if I ever mention a coin and you can do some analysis, check them out! | P8: candle countdown 01:05:12 (time axis cut off) | Q8: high | R8: Time axis is cut off at the bottom, so no dates are visible. 'MM 0.80%' badge meaning not stated on screen. | S8: 007_2026-05-09_020121_Screenshot_20260509-035449.png | U8: https://discord.com/channels/1042855255089623100/1501271173588193290/1502445332355878943
A9: 8 | B9: 2026-05-09 | C9: 02:01:21 | D9: yes | E9: chart | F9: Bybit | G9: 0 | I9: 4h | J9: EMA7 (0.6746); EMA14 (0.6727); EMA28 (0.6719) | K9: exchange auto high marker 0.6992 at the current candle (long upper wick); exchange auto low marker 0.6487 near 05/01-05/02; current price line 0.6893 with countdown 01:04:49; no user drawings | L9: ASTERUSDT 4h: a choppy week-long range roughly 0.655-0.70 with the three EMAs flat and bunched (0.6719-0.6746), a flush to ~0.655 on May 8, then a sharp two-candle rally that spiked to 0.6992 and left a long upper wick with price back at 0.6893. He pointed out that 'even ASTER started moving'. | M9: Bybit (Demo Trading) 4h chart of ASTERUSDT, +4.50% on the day, showing a ranging market that just spiked to 0.6992 (long upper wick) with price at 0.6893. Last of four alt charts posted to show the coins he had mentioned were moving. | N9: ASTERUSDT ▾ +4.50% MM 0.80% Chart Overview Data Feed Last Traded Price ▾ 0.6893 Mark Price 0.6894 24h High 0.6992 24h Low 0.6581 24h Turnover 12.81M Time 15m 1h 4h 1D More ▾ | Depth EMA7: 0.6746 EMA14: 0.6727 EMA28: 0.6719 0.6992 0.6893 01:04:49 0.6739 0.6613 0.6487 BYBIT Demo Trading 05/01 17:00 05/03 13:00 05/05 09:00 05/07 05:00 05/09 01:00 05/10 21 | O9: Look at them go, every ALT I mentioned here just popping off even ASTER started moving 🤣 Usually I'm already in too many trades and have to limit myself for giving positions because I feel like people don't care about risk management and jump in all in. But if I ever mention a coin and you can do some analysis, check them out! | P9: chart time axis 05/01 17:00, 05/03 13:00, 05/05 09:00, 05/07 05:00, 05/09 01:00, 05/10 21… (cut); candle countdown 01:04:49 | Q9: high | R9: Last time-axis label is cut off. 'MM 0.80%' badge meaning not stated on screen. | S9: 008_2026-05-09_020121_Screenshot_20260509-035511.png | U9: https://discord.com/channels/1042855255089623100/1501271173588193290/1502445332355878943
A10: 9 | B10: 2026-05-09 | C10: 04:45:42 | D10: yes | E10: pnl_share_card | F10: Bybit | G10: 1 | H10: KERNELUSDT | M10: Bybit PnL share card (rocket graphic) for an open KERNELUSDT 20X long: entry 0.06454, current price 0.06615, ROI +49.35%. Posted as 'KERNEL TP1 here' with next TP at 0.0673. | N10: KERNELUSDT Long 20.0X ROI +49.35% Entry Price 0.06454 Current Price 0.06615 BYBIT | O10: KERNEL TP1 here, next TP @ 0.0673 @Paladin Notify | Q10: high | S10: 009_2026-05-09_044542_Screenshot_20260509-064308.png | U10: https://discord.com/channels/1042855255089623100/1501271173588193290/1502486692232298586
A11: 10 | B11: 2026-05-09 | C11: 04:48:32 | D11: yes | E11: pnl_share_card | F11: Bybit | G11: 1 | H11: KERNELUSDT | M11: Bybit PnL share card for an open KERNELUSDT 20X long, entry 0.06454, current 0.06615, ROI +49.35% — a duplicate of image 009 re-posted with the 'all trades running in good profits, take TP whenever you want' message. | N11: KERNELUSDT Long 20.0X ROI +49.35% Entry Price 0.06454 Current Price 0.06615 BYBIT | O11: All trades running in good profits, take TP whenever you want, don't let them round trip. I'll update when I close. | Q11: high | R11: Duplicate of image 009. | S11: 010_2026-05-09_044832_Screenshot_20260509-064308.png | T11: 009_2026-05-09_044542_Screenshot_20260509-064308.png | U11: https://discord.com/channels/1042855255089623100/1501271173588193290/1502487407654862971
A12: 11 | B12: 2026-05-09 | C12: 04:48:32 | D12: yes | E12: pnl_share_card | F12: Bybit | G12: 1 | H12: AVNTUSDT | M12: Bybit PnL share card for an open AVNTUSDT 50X long: entry 0.15851, current price 0.16787, ROI +265.55%. Part of the batch of running trades he posted telling followers to take TP whenever they want and not let them round-trip. | N12: AVNTUSDT Long 50.0X ROI +265.55% Entry Price 0.15851 Current Price 0.16787 BYBIT | O12: All trades running in good profits, take TP whenever you want, don't let them round trip. I'll update when I close. | Q12: high | S12: 011_2026-05-09_044832_Screenshot_20260509-064552.png | U12: https://discord.com/channels/1042855255089623100/1501271173588193290/1502487407654862971
A13: 12 | B13: 2026-05-09 | C13: 04:48:32 | D13: yes | E13: pnl_share_card | F13: Bybit | G13: 1 | H13: SNXUSDT | M13: Bybit PnL share card for an open SNXUSDT 25X long: entry 0.3545, current price 0.3727, ROI +118.67%. Part of the batch of running trades posted with 'take TP whenever you want, don't let them round trip'. | N13: SNXUSDT Long 25.0X ROI +118.67% Entry Price 0.3545 Current Price 0.3727 BYBIT | O13: All trades running in good profits, take TP whenever you want, don't let them round trip. I'll update when I close. | Q13: high | S13: 012_2026-05-09_044832_Screenshot_20260509-064638.png | U13: https://discord.com/channels/1042855255089623100/1501271173588193290/1502487407654862971
A14: 13 | B14: 2026-05-09 | C14: 04:48:32 | D14: yes | E14: pnl_share_card | F14: Bybit | G14: 1 | H14: ZROUSDT | M14: Bybit PnL share card for an open ZROUSDT 50X long: entry 1.4744, current price 1.4849, ROI +34.43%. Part of the batch of running trades posted on May 9. | N14: ZROUSDT Long 50.0X ROI +34.43% Entry Price 1.4744 Current Price 1.4849 BYBIT | O14: All trades running in good profits, take TP whenever you want, don't let them round trip. I'll update when I close. | Q14: high | S14: 013_2026-05-09_044832_Screenshot_20260509-064657.png | U14: https://discord.com/channels/1042855255089623100/1501271173588193290/1502487407654862971
A15: 14 | B15: 2026-05-09 | C15: 04:48:32 | D15: yes | E15: pnl_share_card | F15: Bybit | G15: 1 | H15: BTCUSDT | M15: Bybit PnL share card for an open BTCUSDT 100X long: entry 79,764.40, current price 80,333.90, ROI +67.25%. Part of the batch of running trades posted on May 9. | N15: BTCUSDT Long 100.0X ROI +67.25% Entry Price 79,764.40 Current Price 80,333.90 BYBIT | O15: All trades running in good profits, take TP whenever you want, don't let them round trip. I'll update when I close. | Q15: high | S15: 014_2026-05-09_044832_Screenshot_20260509-064717.png | U15: https://discord.com/channels/1042855255089623100/1501271173588193290/1502487407654862971
A16: 15 | B16: 2026-05-09 | C16: 04:48:32 | D16: yes | E16: pnl_share_card | F16: Bybit | G16: 1 | H16: UNIUSDT | M16: Bybit PnL share card for a closed UNIUSDT 50X long: entry 3.458, exit 3.528, ROI +101.21%. Re-posted within the May 9 batch of trade cards; it documents the earlier UNI partial close. | N16: UNIUSDT Long 50.0X ROI +101.21% Entry Price 3.458 Exit Price 3.528 BYBIT | O16: All trades running in good profits, take TP whenever you want, don't let them round trip. I'll update when I close. | Q16: high | S16: 015_2026-05-09_044832_Screenshot_20260509-063448.png | U16: https://discord.com/channels/1042855255089623100/1501271173588193290/1502487407654862971
A17: 16 | B17: 2026-05-09 | C17: 04:52:10 | D17: yes | E17: pnl_share_card | F17: Bybit | G17: 1 | H17: SYRUPUSDT | M17: Bybit PnL share card for a closed SYRUPUSDT 25X long: entry 0.25328, exit 0.26013, ROI +67.61%. Posted when closing this Journals trade after holding it 10 days because it was 'getting annoying'. | N17: SYRUPUSDT Long 25.0X ROI +67.61% Entry Price 0.25328 Exit Price 0.26013 BYBIT | O17: Also closing this trade from Journals, 100% this is gonna blow up but I have been holding for 10 days, its getting annoying. https://discord.com/channels/1042855255089623100/1496387902140321885/1497875763314298912 @Paladin Notify | Q17: high | S17: 016_2026-05-09_045210_Screenshot_20260509-063054.png | U17: https://discord.com/channels/1042855255089623100/1501271173588193290/1502488322143162518
A18: 17 | B18: 2026-05-09 | C18: 06:06:56 | D18: yes | E18: pnl_share_card | F18: Bybit | G18: 1 | H18: BTCUSDT | M18: Bybit PnL share card for a closed BTCUSDT 100X long: entry 79,764.40, exit 80,341.20, ROI +72.31%. Posted with 'Closing BTC @ 80.4k'. | N18: BTCUSDT Long 100.0X ROI +72.31% Entry Price 79,764.40 Exit Price 80,341.20 BYBIT | O18: Closing BTC @ 80.4k @Paladin Notify | Q18: high | S18: 017_2026-05-09_060656_Screenshot_20260509-080604.png | U18: https://discord.com/channels/1042855255089623100/1501271173588193290/1502507137337786561
A19: 18 | B19: 2026-05-10 | C19: 18:45:44 | D19: yes | E19: pnl_share_card | F19: Bybit | G19: 1 | H19: ETHUSDT | M19: Bybit PnL share card for a closed ETHUSDT 100X long: entry 2,311.73, exit 2,340.53, ROI +124.58%. Posted on Sunday May 10 as 'good enough for a weekend scalp, closing it here'. | N19: ETHUSDT Long 100.0X ROI +124.58% Entry Price 2,311.73 Exit Price 2,340.53 BYBIT | O19: Alright guys good enough for a weekend scalp, closing it here! @Paladin Notify | Q19: high | S19: 018_2026-05-10_184544_Screenshot_20260510-204502.png | U19: https://discord.com/channels/1042855255089623100/1501271173588193290/1503060481118568578
A20: 19 | B20: 2026-05-10 | C20: 21:01:23 | D20: yes | E20: pnl_share_card | F20: Bybit | G20: 1 | H20: AVNTUSDT | M20: Bybit PnL share card for the still-open AVNTUSDT 50X long: entry 0.15851, current price 0.16709, ROI +246.69%. Posted as 'AVNT TP1 here, fully close @ 0.1746'. | N20: AVNTUSDT Long 50.0X ROI +246.69% Entry Price 0.15851 Current Price 0.16709 BYBIT | O20: AVNT TP1 here, fully close @ 0.1746 @Paladin Notify | Q20: high | S20: 019_2026-05-10_210123_Screenshot_20260510-224944.png | U20: https://discord.com/channels/1042855255089623100/1501271173588193290/1503094618345181387
A21: 20 | B21: 2026-05-10 | C21: 22:10:30 | D21: yes | E21: pnl_share_card | F21: Bybit | G21: 1 | H21: ZROUSDT | M21: Bybit PnL share card for the still-open ZROUSDT 50X long: entry 1.4744, current price 1.5300, ROI +178.94%. Posted with '25% here, fully exit around 1.55+, will update if I see weakness'. | N21: ZROUSDT Long 50.0X ROI +178.94% Entry Price 1.4744 Current Price 1.5300 BYBIT | O21: 25% here, fully exit around 1.55+ Will update if I see weakness @Paladin Notify | Q21: high | S21: 020_2026-05-10_221030_Screenshot_20260511-000006.png | U21: https://discord.com/channels/1042855255089623100/1501271173588193290/1503112014283673735
A22: 21 | B22: 2026-05-10 | C22: 23:33:31 | D22: yes | E22: pnl_share_card | F22: Bybit | G22: 1 | H22: SNXUSDT | M22: Bybit PnL share card for an open SNXUSDT 25x long at +55.80% ROI (entry 0.3545, current 0.3626). Posted with the message that he is closing SNX in some profit because he expects a pullback and plans to reopen after Monday. | N22: SNXUSDT Long 25.0X ROI +55.80% Entry Price 0.3545 Current Price 0.3626 BYBIT | O22: Closing SNX in some profits, we're gonna have a pullback will open again after Monday @Paladin Notify | Q22: high | S22: 021_2026-05-10_233331_Screenshot_20260511-013234.png | U22: https://discord.com/channels/1042855255089623100/1501271173588193290/1503132904983756810
A23: 22 | B23: 2026-05-11 | C23: 03:58:37 | D23: yes | E23: pnl_share_card | F23: Bybit | G23: 1 | H23: BTCUSDT | M23: Bybit share card of a closed BTCUSDT 100x short: entry 82,202.80, exit 81,302.90, +109.47% ROI. Posted as 'TPed, fast top short, closed' - a quick counter-trend short at a local top that he took profit on. | N23: BTCUSDT Short 100.0X ROI +109.47% Entry Price 82,202.80 Exit Price 81,302.90 BYBIT | O23: TPed, fast top short, closed. @Paladin Notify | Q23: high | S23: 022_2026-05-11_035837_Screenshot_20260511-055757.png | U23: https://discord.com/channels/1042855255089623100/1501271173588193290/1503199620715642910
A24: 23 | B24: 2026-05-11 | C24: 09:12:24 | D24: yes | E24: pnl_share_card | F24: Bybit | G24: 1 | H24: ZROUSDT | M24: Bybit share card for an open ZROUSDT 50x long at +189.93% ROI (entry 1.4772, current 1.5369). Message says the streak continues, 20% here, and that he is not moving the SL to entry - i.e. he keeps the original stop rather than protecting the trade at breakeven. | N24: ZROUSDT Long 50.0X ROI +189.93% Entry Price 1.4772 Current Price 1.5369 BYBIT | O24: And the streak continues, 20% here not moving SL to entry. @Paladin Notify | Q24: high | S24: 023_2026-05-11_091224_17784798553272.jpg | U24: https://discord.com/channels/1042855255089623100/1501271173588193290/1503278586050777149
A25: 24 | B25: 2026-05-11 | C25: 09:13:29 | D25: yes | E25: pnl_share_card | F25: Blofin | G25: 1 | H25: BTCUSDT | M25: Cropped Blofin-style share card showing an open BTCUSDT 150x long with +51.78% unrealized ROI. Message context: he has started scaling into a BTC long (long since 80.6k with SL at 79.5k) and will share it once confident enough. | N25: Unrealized PnL BTCUSDT | Long | 150X +51.78% | O25: I have started to scale in BTC long as well will give out once I'm confident enough For an idea I'm long since 80.6k SL @ 79.5k | Q25: medium | R25: Image is cropped; only header, pair/side/leverage and ROI are visible. Platform identified from card style (no logo visible). | S25: 024_2026-05-11_091329_Screenshot_20260511-111236.png | U25: https://discord.com/channels/1042855255089623100/1501271173588193290/1503278860400332892
A26: 25 | B26: 2026-05-11 | C26: 12:32:58 | D26: yes | E26: pnl_share_card | F26: Bybit | G26: 1 | H26: ZROUSDT | M26: Bybit share card for the ZROUSDT 50x long now at +215.72% ROI (entry 1.4772, current 1.5457), posted with 'ZRO TP hit' - the take-profit level was reached around 1.5457. | N26: ZROUSDT Long 50.0X ROI +215.72% Entry Price 1.4772 Current Price 1.5457 BYBIT | O26: ZRO TP hit @Paladin Notify | Q26: high | S26: 025_2026-05-11_123258_17784899060412.jpg | U26: https://discord.com/channels/1042855255089623100/1501271173588193290/1503329058543370330
A27: 26 | B27: 2026-05-11 | C27: 19:33:50 | D27: yes | E27: pnl_share_card | F27: Bybit | G27: 1 | H27: BTCUSDT | M27: Bybit share card of a closed BTCUSDT 100x long: entry 80,914.20, exit 81,798.70, +109.31% ROI. Posted without text; it is the BTC long he mentioned scaling into earlier that day (long since ~80.6k). | N27: BTCUSDT Long 100.0X ROI +109.31% Entry Price 80,914.20 Exit Price 81,798.70 BYBIT | Q27: high | S27: 026_2026-05-11_193350_Screenshot_20260511-213326.png | U27: https://discord.com/channels/1042855255089623100/1501271173588193290/1503434974102163536
A28: 27 | B28: 2026-05-12 | C28: 06:19:25 | D28: yes | E28: pnl_share_card | F28: Bybit | G28: 1 | H28: STABLEUSDT | M28: Bybit share card for an open STABLEUSDT 25x long at +144.12% ROI (entry 0.034590, current 0.036652). Posted with 'TP1 @ 0.03737', i.e. he sets the first take-profit target just above the current price. | N28: STABLEUSDT Long 25.0X ROI +144.12% Entry Price 0.034590 Current Price 0.036652 BYBIT | O28: TP1 @ 0.03737 | Q28: high | S28: 027_2026-05-12_061925_Screenshot_20260512-081814.png | U28: https://discord.com/channels/1042855255089623100/1501271173588193290/1503597441675558924
A29: 28 | B29: 2026-05-12 | C29: 06:49:52 | D29: yes | E29: pnl_share_card | F29: Bybit | G29: 1 | H29: STABLEUSDT | M29: Bybit share card of the STABLEUSDT 25x long closed at 0.037370 (entry 0.034590) for +200.92% ROI. Message: he accidentally closed 100% here but says the 0.04 TP is still valid and tells followers to take at least 50% at this level because it is resistance. | N29: STABLEUSDT Long 25.0X ROI +200.92% Entry Price 0.034590 Exit Price 0.037370 BYBIT | O29: I accidentally closed 100% here but 0.04 TP is valid, take at least 50% as this is resistance. @Paladin Notify | Q29: high | S29: 028_2026-05-12_064952_Screenshot_20260512-084847.png | U29: https://discord.com/channels/1042855255089623100/1501271173588193290/1503605103997882428
A30: 29 | B30: 2026-05-12 | C30: 06:51:54 | D30: yes | E30: chart | F30: Bybit | G30: 0 | I30: 1h | J30: EMA7: 0.035311 (yellow); EMA14: 0.034935 (blue); EMA28: 0.034676 (purple) | K30: auto high label 0.037953 at the top of the last candle; auto low label 0.033704 near 05/11 00:00; current price tag 0.037500 with countdown 16:48 on the right axis; price scale: 0.037953, 0.036890, 0.035828, 0.034766, 0.033704; no user drawings | L30: STABLEUSDT 1h candles on the Bybit app: after ranging roughly 0.0337-0.0355 for two days with the EMAs curling up, the current candle is a huge vertical green spike from ~0.0348 to the 24h high 0.037953 - the pump his long caught. 'Demo Trading' watermark (Bybit demo / CFT funded account). | M30: Bybit app 1h chart of STABLEUSDT right after the spike to 0.037953, posted with 'What a pump caught!'. Shows the base he bought (entry 0.034590 on the share cards) and the single explosive candle that hit his TP1; the Demo Trading watermark later prompted questions from followers. | N30: STABLEUSDT +8.85% MM 0.49% Chart Overview Data Feed Last Traded Price 0.037500 Mark Price 0.037499 24h High 0.037953 24h Low 0.034025 24h Turnover 2.21M Time 15m 1h 4h 1D More Depth EMA7: 0.035311 EMA14: 0.034935 EMA28: 0.034676 0.037953 0.037500 16:48 0.036890 0.035828 0.034766 0.033704 BYBIT Demo Trading 05/10 12:00 05/10 23:00 05/11 10:00 05/11 21:00 05/12 08:00 05/12 19 | O30: What a pump caught! | P30: x-axis labels: 05/10 12:00, 05/10 23:00, 05/11 10:00, 05/11 21:00, 05/12 08:00, 05/12 19:.. (candle-close countdown 16:48 next to the price tag) | Q30: high | R30: Right-most x-axis label is cut off ('05/12 19'). Candle bodies at the far left partially hidden by the BYBIT watermark. | S30: 029_2026-05-12_065154_Screenshot_20260512-0843132.png | U30: https://discord.com/channels/1042855255089623100/1501271173588193290/1503605617204531412
A31: 30 | B31: 2026-05-12 | C31: 15:11:23 | D31: yes | E31: chart | F31: MEXC | G31: 1 | H31: STABLEUSDT | I31: 1h | J31: EMA20: 0.03655 (pink); EMA50: 0.03538 (orange); EMA200: 0.03406 (blue) | K31: dashed green position/entry line at 0.03453 labeled 'PNL +43.1294 | 10,000'; red 'S' trade marker on the large green candle around 0.0378; auto high label 0.03896 on the latest candles; auto low label 0.03378 at the left; current price tag 0.03884 (green box) on the right axis with dashed line; price scale: 0.03900, 0.03750, 0.03600, 0.03450; no user drawings | L31: STABLEUSDT perpetual 1h chart on MEXC: price based around 0.034-0.035 along the EMA50, then exploded in one huge green candle to ~0.0378, pulled back to ~0.036 and continued up to a new high 0.03896. His long entry line at 0.03453 sits at the base, now ~+12% unleveraged with +43.13 USDT open PnL on a 10,000 position. | M31: MEXC app 1h chart of STABLEUSDT showing his open long from 0.03453 (PNL +43.1294 USDT, size 10,000) after the pump to 0.03896. Posted to clarify that the earlier 'Demo' screenshot was from a CFT funded account (which displays as demo) and that he trades the same calls with real money on other exchanges such as MEXC. | N31: STABLEUSDT Perpetual Markets AI Analysis Info Trading rules Last Price 0.03884 ≈0.038 USD +11.09% Fair Price 0.03884 24h High 0.03896 24h Low 0.03403 24h Vol(STABLE) 12.034M 24h Vol (USDT) 436.437K Why is the price of STABLE rising? Line 15m 1h 4h 1D Week More EMA20:0.03655 EMA50:0.03538 EMA200:0.03406 0.03900 0.03896 0.03884 0.03750 0.03600 0.03450 0.03453 S PNL +43.1294 | 10,000 0.03378 MEXC | O31: Guys I would like to clarify something since I shared this screenshot it says DEMO, I got like 5 DMs saying I'm trading on DEMO It is CFT funded account so it shows demo, I trade on other exchanges with real money. Even if it's demo are the trades hitting TPs or not? Just wanted to clarify it once. | Q31: high | R31: Platform is MEXC (not in the platform list, recorded as 'other'). Leverage of the position is not visible on this chart. Meaning of the red 'S' marker (sell fill) is inferred from MEXC chart conventions. | S31: 030_2026-05-12_151123_Screenshot_20260512-170605.png | U31: https://discord.com/channels/1042855255089623100/1501271173588193290/1503731313855692950
A32: 31 | B32: 2026-05-12 | C32: 15:11:23 | D32: yes | E32: pnl_share_card | F32: MEXC | G32: 1 | H32: STABLEUSDT | M32: MEXC PnL share card for the open STABLEUSDT 20x long: entry $0.03453, fair price $0.03886, +248.34% ROI, +43.2294 USDT. Posted together with the MEXC chart as proof that the STABLE trade was taken with real money on a real exchange, not only on the demo-labelled CFT account. | N32: STABLEUSDT Perpetual Long | 20X +248.34% +43.2294 USDT 0% Liquidity NO.1 Entry Price $0.03453 Fair Price $0.03886 | O32: Guys I would like to clarify something since I shared this screenshot it says DEMO, I got like 5 DMs saying I'm trading on DEMO It is CFT funded account so it shows demo, I trade on other exchanges with real money. Even if it's demo are the trades hitting TPs or not? Just wanted to clarify it once. | Q32: high | R32: Platform is MEXC (not in the platform list, recorded as 'other'). | S32: 031_2026-05-12_151123_Screenshot_20260512-170852.png | U32: https://discord.com/channels/1042855255089623100/1501271173588193290/1503731313855692950
A33: 32 | B33: 2026-05-13 | C33: 06:13:16 | D33: yes | E33: pnl_share_card | F33: MEXC | G33: 1 | H33: STABLEUSDT | M33: Cropped MEXC closed-PnL card: STABLEUSDT 20x long closed for +231.02% ROI. Message: STABLE hit the full TP of 0.04, a ~20% unleveraged move. | N33: Closed PNL STABLEUSDT Perpetual Long | 20X +231.02% B S | O33: STABLE hit full TP of 0.04, 20% unleveraged move! @Paladin Notify | Q33: medium | R33: Image is cropped; entry price, close price, USDT PnL and date are not visible. Platform is MEXC (recorded as 'other'). | S33: 032_2026-05-13_061316_Screenshot_20260513-081109.png | U33: https://discord.com/channels/1042855255089623100/1501271173588193290/1503958280999796848
A34: 33 | B34: 2026-05-13 | C34: 12:11:15 | D34: yes | E34: pnl_share_card | F34: Bybit | G34: 1 | H34: SOLUSDT | M34: Bybit share card of a SOLUSDT 100x long closed at 95.700 from entry 95.530 for +17.79% ROI. Message explains he closed SOL early to stay on the safe side and protect his winning streak, noting 3 other longs are already running and TPs are expected soon. | N34: SOLUSDT Long 100.0X ROI +17.79% Entry Price 95.530 Exit Price 95.700 BYBIT | O34: Closing SOL here personally, I want to be on the safe side and keep my streak. We already have 3 longs and they are running good enough, expect TPs soon InshaAllah! @Paladin Notify | Q34: high | S34: 033_2026-05-13_121115_Screenshot_20260513-140807.png | U34: https://discord.com/channels/1042855255089623100/1501271173588193290/1504048372351504406
A35: 34 | B35: 2026-05-14 | C35: 17:30:30 | D35: yes | E35: pnl_share_card | F35: Bybit | G35: 1 | H35: SOLUSDT | M35: Bybit share card of a SOLUSDT 100x long closed at 91.460 from entry 91.050, +45.03% ROI. Posted as 'Closing SOL and XRP in minor profits' while he keeps a BTC long (avg 79.2k with a DCA) running in heavy profit. | N35: SOLUSDT Long 100.0X ROI +45.03% Entry Price 91.050 Exit Price 91.460 BYBIT | O35: Closing SOL and XRP in minor profits BTC avg 79.2k with a DCA running in heavy profits @Paladin Notify | Q35: high | S35: 034_2026-05-14_173030_Screenshot_20260514-192753.png | U35: https://discord.com/channels/1042855255089623100/1501271173588193290/1504491099048251594
A36: 35 | B36: 2026-05-14 | C36: 17:30:30 | D36: yes | E36: pnl_share_card | F36: Bybit | G36: 1 | H36: XRPUSDT | M36: Bybit share card of an XRPUSDT 100x long closed at 1.4531 from entry 1.4497 for +23.45% ROI - the 'minor profit' XRP exit mentioned in the message. He later explained he got out near breakeven because the setup was invalidated and price almost touched his SL. | N36: XRPUSDT Long 100.0X ROI +23.45% Entry Price 1.4497 Exit Price 1.4531 BYBIT | O36: Closing SOL and XRP in minor profits BTC avg 79.2k with a DCA running in heavy profits @Paladin Notify | Q36: high | S36: 035_2026-05-14_173030_Screenshot_20260514-192733.png | U36: https://discord.com/channels/1042855255089623100/1501271173588193290/1504491099048251594
A37: 36 | B37: 2026-05-14 | C37: 17:38:18 | D37: yes | E37: pnl_share_card | F37: Bybit | G37: 1 | H37: BTCUSDT | M37: Bybit share card of an open BTCUSDT 100x long at +108.28% ROI (entry 79,284.35, current 80,199.50). Posted with 'Holding onto these' alongside an ENS long - he is letting the BTC DCA position run for a bigger target. | N37: BTCUSDT Long 100.0X ROI +108.28% Entry Price 79,284.35 Current Price 80,199.50 BYBIT | O37: Holding onto these 🤘🏻 Let's pray we enjoy some fat profits on these! | Q37: high | S37: 036_2026-05-14_173818_Screenshot_20260514-193711.png | U37: https://discord.com/channels/1042855255089623100/1501271173588193290/1504493064947761242
A38: 37 | B38: 2026-05-14 | C38: 17:38:18 | D38: yes | E38: pnl_share_card | F38: Bybit | G38: 1 | H38: ENSUSDT | M38: Bybit share card of an open ENSUSDT 50x long at +141.91% ROI (entry 6.900, current 7.107), posted together with the BTC long as the positions he is holding for 'fat profits'. | N38: ENSUSDT Long 50.0X ROI +141.91% Entry Price 6.900 Current Price 7.107 BYBIT | O38: Holding onto these 🤘🏻 Let's pray we enjoy some fat profits on these! | Q38: high | S38: 037_2026-05-14_173818_Screenshot_20260514-193728.png | U38: https://discord.com/channels/1042855255089623100/1501271173588193290/1504493064947761242
A39: 38 | B39: 2026-05-14 | C39: 17:47:29 | D39: yes | E39: chart | F39: Bybit | G39: 0 | I39: 1h | J39: EMA7: 1.4443 (yellow); EMA14: 1.4385 (blue); EMA28: 1.4366 (purple) | K39: auto high label 1.4661 at the top of the latest candle; current price tag 1.4654 with candle countdown 14:20 on the right axis; price scale: 1.4661, 1.4521, 1.4381, 1.4241; no user drawings; no position line | L39: XRPUSDT 1h on the Bybit app: a downtrend into a ~1.41-1.42 low, a slow grind back up through the EMAs (price reclaimed EMA7/14/28, which are now stacked bullishly), then two strong green candles pushing to the 24h high 1.4661 right after he closed his long at 1.4531. The chart has no drawings; the x-axis is cut off. | M39: Bybit app 1h chart of XRPUSDT breaking out to 1.4654 minutes after he closed his XRP long near breakeven. Message: 'As soon as I close XRP it booms' - he exited early because the setup was invalidated and price nearly hit his SL, framing the disciplined near-BE exit as better than taking the stop loss, while still expecting his target to be hit. | N39: XRPUSDT +2.79% MM 0.74% Chart Overview Data Feed Last Traded Price 1.4654 Mark Price 1.4655 24h High 1.4661 24h Low 1.4101 24h Turnover 324.42M Time 15m 1h 4h 1D More Depth EMA7: 1.4443 EMA14: 1.4385 EMA28: 1.4366 1.4661 1.4654 14:20 1.4521 1.4381 1.4241 | O39: As soon as I close XRP it booms, I'm pretty sure this will hit our target I exited early because it invalidated my setup, it almost touched my SL so better to be disciplined and get out around BE, much better than SL at least? | Q39: high | R39: Bottom of the chart (x-axis dates) is cut off. | S39: 038_2026-05-14_174729_Screenshot_20260514-194541.png | U39: https://discord.com/channels/1042855255089623100/1501271173588193290/1504495374503776269
A40: 39 | B40: 2026-05-14 | C40: 17:50:31 | D40: yes | E40: discord_message_screenshot | F40: Discord | G40: 0 | M40: Screenshot of his own earlier Discord message (4:44 PM) laying out a BTC scenario: dip to 78.5k, bounce, 'clarity' news hits, big pump to 81k-82k, then a slow dump back. Re-posted with 'Moving exactly like that isn't it? Higher' to show the roadmap is playing out while his BTC long (avg ~79.2k) is running. | N40: Paladin [Will not DM] Today at 4:44 PM Here's what I think, 78.5k > bounce > clarity news comes in > big boom pump to 81k-82k around then slow dump back to where we are 🔥 2 | O40: Moving exactly like that isn't it? Higher @Paladin Notify | P40: Today at 4:44 PM | Q40: high | R40: No symbol printed in the message; the 78.5k / 81k-82k levels refer to BTC by context. The 'clarity news' likely refers to the US CLARITY Act (crypto market-structure bill). | S40: 039_2026-05-14_175031_Screenshot_20260514-195004.png | U40: https://discord.com/channels/1042855255089623100/1501271173588193290/1504496137313189919
A41: 40 | B41: 2026-05-14 | C41: 18:02:51 | D41: yes | E41: pnl_share_card | F41: Bybit | G41: 1 | H41: BTCUSDT | M41: Bybit share card of the BTCUSDT 100x long closed at 80,893.80 from the DCA entry 79,284.35 for +202.99% ROI. Message: 'BTC closed at 81k guys, FATASS PROFITS! Made profits back from both SLs' - he took profit into the 81k-82k zone from his roadmap and says this recovered the two earlier stop-losses. | N41: BTCUSDT Long 100.0X ROI +202.99% Entry Price 79,284.35 Exit Price 80,893.80 BYBIT | O41: BTC closed at 81k guys, FATASS PROFITS! Made profits back from both SLs @Paladin Notify | Q41: high | S41: 040_2026-05-14_180251_Screenshot_20260514-200201.png | U41: https://discord.com/channels/1042855255089623100/1501271173588193290/1504499241316253918
A42: 41 | B42: 2026-05-14 | C42: 18:03:36 | D42: yes | E42: pnl_share_card | F42: Bybit | G42: 1 | H42: ENSUSDT | M42: Bybit ROI share card for an open ENSUSDT 50x long at +190.71% ROI, entry 6.900, current price 7.171. Posted at the moment he took a 50% partial and said the rest could be closed. | N42: ENSUSDT Long 50.0X ROI +190.71% Entry Price 6.900 Current Price 7.171 BYBIT | O42: Took 50% from this too, you can close completely @Paladin Notify | Q42: high | S42: 041_2026-05-14_180336_Screenshot_20260514-200301.png | U42: https://discord.com/channels/1042855255089623100/1501271173588193290/1504499432530509967
A43: 42 | B43: 2026-05-14 | C43: 18:13:38 | D43: yes | E43: pnl_share_card | F43: Blofin | G43: 1 | H43: BTCUSDT | M43: BloFin share card for a closed BTCUSDT 30x long: entry 79,313.4, closed at 80,926.4 for +61.00% ROI on 2026-05-14 16:09:25. Posted with his remark that he survived the dump and had called the plan on point. | N43: BloFin BTCUSDT Perp Buy 30X +61.00% Entry Price 79,313.4 Close Price 80,926.4 2026-05-14 16:09:25 | O43: Man I'm happy not did I survived the dump but mentioned the plan on point! | P43: 2026-05-14 16:09:25 | Q43: high | S43: 042_2026-05-14_181338_Screenshot_20260514-201004.png | U43: https://discord.com/channels/1042855255089623100/1501271173588193290/1504501955467153569
A44: 43 | B44: 2026-05-14 | C44: 18:13:42 | D44: yes | E44: pnl_share_card | F44: unknown | G44: 1 | H44: BTCUSDT | M44: Cropped closed-PnL share card showing a BTCUSDT perpetual long at 250x closed for +448.51% ROI; no exchange logo is visible. Posted seconds after the BloFin +61% BTC close, so it appears to be the same BTC long idea taken at higher leverage on another account/exchange. | N44: Closed PNL BTCUSDT Perpetual | Long | 250X +448.51% | Q44: high | R44: Exchange not identifiable (no branding in the crop); entry/close prices and timestamp not shown. | S44: 043_2026-05-14_181342_Screenshot_20260514-200907.png | U44: https://discord.com/channels/1042855255089623100/1501271173588193290/1504501973599387790
A45: 44 | B45: 2026-05-14 | C45: 19:03:51 | D45: yes | E45: screen_recording | F45: Discord | G45: 11 | H45: BBUSDT, BTCUSDT, ENSUSDT, INTCUSDT, XRPUSDT | M45: Phone screen recording (10 s) of Paladin scrolling top-to-bottom through his Discord server's '#profit-showcase' channel on 2026-05-14, where members post exchange PnL share cards (Bitunix, BloFin, MEXC, BingX, one unidentified exchange) thanking him: BBUSDT longs (+179.47% at 50X open, +98.72% at 20X half-closed), BTCUSDT longs around 79.0k-79.8k -> 80.5k-81.2k at 75X/100X (+177.83%, +175.73%, +252.15%, +211.69%) and at 3X (+5.18%), an ENSUSDT long 6.894 -> 7.153 (+75.13%), XRPUSDT longs (+43.65% at 50X, +4.58% at 3X), plus an INTCUSDT short (+219.73%) credited to 'Nick Scalps'. He posted it with 'Thankyou guys!' -- it documents follower results of his 13-14 May BB / BTC / ENS / XRP long calls, not his own positions. Discord times are in the phone's local timezone (about 2 h ahead of the Helsinki post time; recording file name says 21:03 vs 19:03 Helsinki). | N45: # $ | profit-showcase [Discord channel header, 3275 unread badge] MB [MM] Today at 6:24 AM: thank you paladin (edited) [Bitunix card] BBUSDT | Long 50X | +179.47% | Entry Price 0.03583 | Last Price 0.03709 | MBZ 2026-05-13 21:22 dekees [VIP] Today at 5:50 PM: closed 50% thanks Paladin [BloFin card] BBUSDT Perp | Long 20X | +98.72% | Entry Price 0.03282 | Close Price 0.03444 | Referral Code BCJAsU | Sharing Time: 05-14 14:49:52 | ❤️ 2 CJR [SX, VIP] Today at 7:55 PM: @Paladin [Will not DM] (edited) [card, exchange unknown] BTCUSDT Perpetual | Long | 211.69% CJR [SX, VIP] Today at 8:00 PM: @Nick Scalps [card, exchange unknown] INTCUSDT Perpetual | Short | 219.73% saralhr Today at 8:06 PM: [message body not in frame] [MEXC card, Spanish] Compartido el 2026-05-14 16:04:4? | BTCUSDT Perpetuo | Cerrar Long | 100X | +252.15% | Fecha 2026-05-14 16:03:08 | Código de Referencia 1hXLr | Regístrate para obtener $20, $50 de cobertura de pérdida en la primera operación y futuros sin tarifas [MEXC card, Spanish] Compartido el 2026-05-14 16:05:06 | Racha de 2 victoria(s) | Título desbloqueado: Despertador on-chain | PNL de cierre: XRPUSDT Perpetuo Long | 50X | +43.65% | Código de Referencia 1hXLr | Regístrate para obtener $20, $50 de cobertura de pérdida en la primera operación y futuros sin tarifas | ❤️ 1 dekees [VIP] Today at 8:08 PM: again Paladin🥰 [BloFin card] ENSUSDT Perp | Long 20X | +75.13% | Entry Price 6.894 | Close Price 7.153 | Referral Code BCJAsU | Sharing Time: 05-14 17:07:03 | ❤️ 1 The CEOsCEO [VIP] Today at 8:19 PM: @Paladin [Will not DM] Thanks mate! [BloFin card] BTCUSDT Perp | Buy 75X | +177.83% | Entry Price 79,108.1 | Close Price 80,983.9 | Referral Code: KYAIKx | Share Time: 05/14 17:16:26 | ❤️ 1 Jokerxo Today at 8:19 PM: @Paladin [Will not DM] [BingX card] Realized PnL | XRPUSDT | Long | 3X | +4.58% | Close Price 1.4537 | Entry Price 1.4318 | ja***s@gmail.com 05/14 18:19 | Referral Code EO3CKZ | ❤️ 1 Netteffect11 [OG] Today at 8:46 PM: @Paladin [Will not DM] 🔥👑 [MEXC card] Shared on 2026-05-15 01:42:15 | BTCUSDT Perpetual | Low-fee saved you: 4.7289 USDT | Long | 100X | +175.73% | Avg Entry Price $78,977.2 | Avg Close Price $80,488.5 | Open Time 2026-05-14 02:00:48 | Close Time 2026-05-15 01:03:00 | Referral Code 1gPto | Sign up to get $10, $50 first-trade loss coverage, & 0-fee Futures | ❤️ 1 Jokerxo Today at 8:53 PM: @Paladin [Will not DM] [BingX card] Realized PnL | BTCUSDT | Long | 3X | +5.18% | Close Price 81195 | Entry Price 79815.6 | ja***s@gmail.com 05/14 18:53 | Referral Code EO3CKZ | ❤️ 1 | O45: Thankyou guys! | P45: Discord message times 'Today at 6:24 AM' through 'Today at 8:53 PM' (phone local time, 'Today' = 2026-05-14); share-card times: 2026-05-13 21:22, 05-14 14:49:52, 2026-05-14 16:03:08, 2026-05-14 16:05:06, 05-14 17:07:03, 05/14 17:16:26, 05/14 18:19, 2026-05-15 01:42:15 (open 2026-05-14 02:00:48 / close 2026-05-15 01:03:00), 05/14 18:53 | Q45: high | R45: All trades are followers' share cards, not Paladin's own positions. Top line of the Spanish MEXC BTC card is cut off ('Compartido el 2026-05-14 16:04:4?'), and the author of the two Spanish MEXC cards is never in frame (inferred as 'saralhr', 8:06 PM, whose message text is also not visible). Exchange of CJR's two cards (BTCUSDT 211.69%, INTCUSDT 219.73%) is not identifiable and the small caption at the bottom of the INTC card is unreadable; those cards show no prices or leverage. Frames 1-3 are identical (static start of the recording). | S45: 044_2026-05-14_190351_screen-20260514-210325-1778774593947.mp4 | U45: https://discord.com/channels/1042855255089623100/1501271173588193290/1504514593899413596
A46: 45 | B46: 2026-05-14 | C46: 19:19:52 | D46: yes | E46: pnl_share_card | F46: Bybit | G46: 1 | H46: ENSUSDT | M46: Bybit ROI share card for the ENSUSDT 50x long (entry 6.900) now at +161.15% with current price 7.135, lower than the 7.171 shown about an hour earlier. He announced he was completely out here after taking 50% earlier around 7.2. | N46: ENSUSDT Long 50.0X ROI +161.15% Entry Price 6.900 Current Price 7.135 BYBIT | O46: Completely out here after taking 50% earlier around 7.2 | Q46: high | S46: 045_2026-05-14_191952_Screenshot_20260514-211824.png | U46: https://discord.com/channels/1042855255089623100/1501271173588193290/1504518622083551303
A47: 46 | B47: 2026-05-14 | C47: 20:12:39 | D47: yes | E47: other | F47: unknown | G47: 0 | M47: Tight crop of an exchange price ticker showing a last price of exactly 82,000.00 (≈81,972.48 USD, +0.85% on the day). Per his message this is BTC hitting 82k, the target he had called from 79k after the bounce around 78.5k (he credits the 'clarity act' news for the push). | N47: 82,000.00 ≈81,972.48 USD +0.85% | O47: Exactly as I mentioned, bounced around 78.5 and clarity act helped us push to 82k, told you at 79k, 82k is coming! | Q47: high | R47: Symbol is not visible in the crop; BTC is inferred from the accompanying message and the price level. Exchange not identifiable. | S47: 046_2026-05-14_201239_Screenshot_20260514-2205022.png | U47: https://discord.com/channels/1042855255089623100/1501271173588193290/1504531907482882189
A48: 47 | B48: 2026-05-14 | C48: 21:54:01 | D48: yes | E48: chart | F48: Blofin | G48: 1 | H48: XRPUSDT | I48: 1h | J48: EMA(20): 1.4572; EMA(50): 1.4471; EMA(200): 1.4341 | K48: exchange trade marker 'S' (sell) on a green candle around ~1.47 (estimated); candle high label 1.5431 (top of the rally); candle low label 1.4105 (swing low on the left-middle of the chart); last price tag 1.5367 with dotted line; price axis labels 1.5497, 1.5011, 1.4524, 1.4038; no user-drawn trendlines or zones | L48: XRPUSDT 1h: after a decline to a 1.4105 low and a flat base hugging the 20/50/200 EMAs, price reclaimed all three EMAs and went vertical to 1.5431 (+7.74% on the day). The S marker shows his long was closed early on the first breakout candles, well below the eventual top. | M48: BloFin XRPUSDT 1-hour chart after a vertical rally to 1.5431, last price 1.5367 (+7.74%), with EMA 20/50/200 overlaid. An 'S' sell marker around ~1.47 shows where he closed his XRP long early; his message says the idea was right and full TP was hit, but he 'fumbled' it by closing too soon. | N48: XRPUSDT Last Price 1.5367 ≈ $1.53 +7.74% Mark Price 1.5365 24h High 1.5431 24h Low 1.4149 24h Vol(XRP) 38.048M Funding Rate 0.0296% Line 15m 1h 4h 1D More EMA(20): 1.4572 EMA(50): 1.4471 EMA(200): 1.4341 1.5497 1.5431 1.5367 1.5011 S 1.4524 1.4105 1.4038 BloFin | O48: Fumbled XRP, hit full TP, was a great setup closed early but at least the idea was right! | Q48: high | R48: Exact price of the 'S' close marker is estimated from the axis (~1.47); the trade's entry, size and result are not shown. | S48: 047_2026-05-14_215401_Screenshot_20260514-235326.png | U48: https://discord.com/channels/1042855255089623100/1501271173588193290/1504557414853115985
A49: 48 | B49: 2026-05-15 | C49: 03:20:30 | D49: yes | E49: pnl_share_card | F49: Bybit | G49: 1 | H49: BBUSDT | M49: Bybit ROI share card for an open BBUSDT 25x long at +116.46% (entry 0.03538, current 0.03710). He says he forgot about this one and is closing early for decent profits while still holding HBAR and BTC. | N49: BBUSDT Long 25.0X ROI +116.46% Entry Price 0.03538 Current Price 0.03710 BYBIT | O49: Totally forgot about this one, closing early for decent profits HBAR and BTC holding now. @Paladin Notify | Q49: high | S49: 048_2026-05-15_032030_Screenshot_20260515-051356.png | U49: https://discord.com/channels/1042855255089623100/1501271173588193290/1504639581050638448
A50: 49 | B50: 2026-05-16 | C50: 10:05:03 | D50: yes | E50: discord_message_screenshot | F50: Discord | G50: 1 | H50: BTCUSDT | M50: Screenshot of his own Discord message laying out the BTC plan for the weekend: the first reversal zone is 77.7-78.1k, a bounce there targets 79-80k, while a 4h close below 77.7k opens 75-76k. Shows he keys his bias off 4h closes relative to a defined support zone. | N50: Paladin [Will not DM] Today at 12:04 PM Basically 1st zone of reversal 77.7-78.1k bounce -> 79-80k for weekend 4h close below 77.7k -> 75-76k | P50: Today at 12:04 PM | Q50: high | R50: Symbol (BTC) is inferred from the price levels; it is not written in the message. | S50: 049_2026-05-16_100503_Screenshot_20260516-120450.png | U50: https://discord.com/channels/1042855255089623100/1501271173588193290/1505103774262493225
A51: 50 | B51: 2026-05-17 | C51: 13:34:36 | D51: yes | E51: pnl_share_card | F51: Bybit | G51: 1 | H51: ETHUSDT | M51: Bybit ROI share card for an open ETHUSDT 100x long at +90.57% (entry 2,173.61, current 2,194.45). Posted as the trade passed 1R, with guidance to take 25-50% partial profit. | N51: ETHUSDT Long 100.0X ROI +90.57% Entry Price 2,173.61 Current Price 2,194.45 BYBIT | O51: ETH over 1R, you can take 25-50% here @Paladin Notify | Q51: high | S51: 050_2026-05-17_133436_Screenshot_20260517-153149.png | U51: https://discord.com/channels/1042855255089623100/1501271173588193290/1505518897707876503
A52: 51 | B52: 2026-05-17 | C52: 13:37:15 | D52: yes | E52: pnl_share_card | F52: Blofin | G52: 1 | H52: BTCUSDT | M52: BloFin War of Whales share card for an open BTCUSDT 150x long at +87.18% (entry 78,041.3, mark 78,494.9, 05-17 15:37:00). Shared alongside the ETH partial-profit call as the BTC idea from his reversal-zone plan started moving. | N52: WOW WAR OF WHALES 2026 BTCUSDT Perp Buy 150X +87.18% Entry Price 78,041.3 Mark Price 78,494.9 Referral Code DwquXN 05-17 15:37:00 | O52: BTC moving too if anyone took that idea | P52: 05-17 15:37:00 | Q52: high | S52: 051_2026-05-17_133715_blofin_1779014226326.png | U52: https://discord.com/channels/1042855255089623100/1501271173588193290/1505519562949394503
A53: 52 | B53: 2026-05-19 | C53: 04:02:19 | D53: yes | E53: pnl_share_card | F53: Bybit | G53: 1 | H53: BOMEUSDT | M53: Bybit ROI share card for an open BOMEUSDT 25x long at +80.80% (entry 0.0005998, current 0.0006203). Posted with risk-management guidance: take 25%, stop to entry, small accounts can close fully; he also mentions hoping ZEC prints big. | N53: BOMEUSDT Long 25.0X ROI +80.80% Entry Price 0.0005998 Current Price 0.0006203 BYBIT | O53: Take 25% SL to entry, if you have a small account close entirely here or just SL to entry and exit at first TP. Hopefully we print big on ZEC! @Paladin Notify | Q53: high | S53: 052_2026-05-19_040219_Screenshot_20260519-055828.png | U53: https://discord.com/channels/1042855255089623100/1501271173588193290/1506099654516019330
A54: 53 | B54: 2026-05-19 | C54: 04:26:18 | D54: yes | E54: pnl_share_card | F54: Blofin | G54: 1 | H54: ZECUSDT | M54: BloFin War of Whales share card for an open ZECUSDT 75x long at +358.87% (entry 545.99, mark 572.12, 05-19 06:21:23). He booked 20%, moved the stop to entry and kept the majority for take-profit targets. | N54: WOW WAR OF WHALES 2026 ZECUSDT Perp Buy 75X +358.87% Entry Price 545.99 Mark Price 572.12 Referral Code DwquXN 05-19 06:21:23 | O54: ZEC going hard, took 20% SL to entry, saving majority for TPs @Paladin Notify | P54: 05-19 06:21:23 | Q54: high | S54: 053_2026-05-19_042618_blofin_1779153685809.png | U54: https://discord.com/channels/1042855255089623100/1501271173588193290/1506105688991207505
A55: 54 | B55: 2026-05-19 | C55: 10:30:37 | D55: yes | E55: pnl_share_card | F55: Bybit | G55: 1 | H55: BOMEUSDT | M55: Bybit ROI share card for the BOMEUSDT 25x long now at +165.91% (entry 0.0005998, current 0.0006430), up from +80.80% about six hours earlier. Posted as the take-profit announcement after BOME 'exploded'. | N55: BOMEUSDT Long 25.0X ROI +165.91% Entry Price 0.0005998 Current Price 0.0006430 BYBIT | O55: Well BOME exploded, TP. @Paladin Notify | Q55: high | S55: 054_2026-05-19_103037_Screenshot_20260519-122717.png | U55: https://discord.com/channels/1042855255089623100/1501271173588193290/1506197374182228020
A56: 55 | B56: 2026-05-19 | C56: 21:04:20 | D56: yes | E56: pnl_share_card | F56: Blofin | G56: 1 | H56: ZECUSDT | M56: BloFin War of Whales share card for the ZECUSDT 75x long closed at 581.92 from entry 545.99 for +493.44% (05-19 23:02:42). He booked the majority at this TP (~1R) and said he would take the final portion at 592. | N56: WOW WAR OF WHALES 2026 ZECUSDT Perp Buy 75X +493.44% Entry Price 545.99 Close Price 581.92 Referral Code DwquXN 05-19 23:02:42 | O56: ZEC TP hit, around 1R, booked majority here, I'll full TP @ 592 Decent day for a shit market @Paladin Notify | P56: 05-19 23:02:42 | Q56: high | S56: 055_2026-05-19_210420_blofin_1779213774283.png | U56: https://discord.com/channels/1042855255089623100/1501271173588193290/1506356854207545494
A57: 56 | B57: 2026-05-20 | C57: 04:16:21 | D57: yes | E57: pnl_share_card | F57: Blofin | G57: 1 | H57: BTCUSDT | M57: BloFin War of Whales share card for an open BTCUSDT 150x long at +29.14% (entry 76,704.7 after a DCA fill, mark 76,853.8, 05-20 06:14:52). He is still holding, expecting 78k+ during the day. | N57: WOW WAR OF WHALES 2026 BTCUSDT Perp Buy 150X +29.14% Entry Price 76,704.7 Mark Price 76,853.8 Referral Code DwquXN 05-20 06:14:52 | O57: Still holding this BTC trade, DCA filled trade, expecting 78k+ today so should give some good good profits! | P57: 05-20 06:14:52 | Q57: high | S57: 056_2026-05-20_041621_blofin_1779239695170.png | U57: https://discord.com/channels/1042855255089623100/1501271173588193290/1506465574434246768
A58: 57 | B58: 2026-05-20 | C58: 09:20:54 | D58: yes | E58: pnl_share_card | F58: Blofin | G58: 1 | H58: ZECUSDT | M58: BloFin War of Whales share card for a ZECUSDT 75x long entered at 580.25 and closed at 591.75 for +148.59% (05-20 11:17:18), right at the 592 full-TP target he had announced. Posted without text. | N58: WOW WAR OF WHALES 2026 ZECUSDT Perp Buy 75X +148.59% Entry Price 580.25 Close Price 591.75 Referral Code DwquXN 05-20 11:17:18 | P58: 05-20 11:17:18 | Q58: high | S58: 057_2026-05-20_092054_blofin_1779257847868.png | U58: https://discord.com/channels/1042855255089623100/1501271173588193290/1506542215424376922
A59: 58 | B59: 2026-05-20 | C59: 16:23:21 | D59: yes | E59: pnl_share_card | F59: Blofin | G59: 1 | H59: BTCUSDT | M59: BloFin War of Whales share card for the open BTCUSDT 150x long now at +145.83% (entry 76,704.7, mark 77,450.5, 05-20 18:13:52). Around 1R in profit; he is holding for roughly 78.5k and notes he avoids partials on BTC. | N59: WOW WAR OF WHALES 2026 BTCUSDT Perp Buy 150X +145.83% Entry Price 76,704.7 Mark Price 77,450.5 Referral Code DwquXN 05-20 18:13:52 | O59: Guys BTC already have moved around 1R, I'm trying for around 78.5k around but don't wait for me you can take partials as you like. I personally avoid partials especially on BTC @Paladin Notify | P59: 05-20 18:13:52 | Q59: high | S59: 058_2026-05-20_162321_blofin_1779282839848.png | U59: https://discord.com/channels/1042855255089623100/1501271173588193290/1506648527345025034
A60: 59 | B60: 2026-05-21 | C60: 04:30:48 | D60: yes | E60: pnl_share_card | F60: Blofin | G60: 1 | H60: BTCUSDT | M60: BloFin War of Whales share card for the BTCUSDT 150x long closed at 77,826.3 from the DCA'd entry 76,704.7 for +219.32% (05-21 06:29:51). He closed the full position here, calling it over 1R with great profits thanks to the DCA. | N60: WOW WAR OF WHALES 2026 BTCUSDT Perp Buy 150X +219.32% Entry Price 76,704.7 Close Price 77,826.3 Referral Code DwquXN 05-21 06:29:51 | O60: BTC closed here, over 1R + with a DCA great profits for me @Paladin Notify | P60: 05-21 06:29:51 | Q60: high | S60: 059_2026-05-21_043048_blofin_1779326995023.png | U60: https://discord.com/channels/1042855255089623100/1501271173588193290/1506831598707019827
A61: 60 | B61: 2026-05-21 | C61: 05:03:46 | D61: yes | E61: pnl_share_card | F61: Bybit | G61: 1 | H61: SUIUSDT | M61: Bybit ROI share card for an open SUIUSDT 50x long at +170.83% (entry 1.07380, current 1.11270). Posted while the trade was running, with his take-profit plan of 1.14 (TP1) and 1.23 (TP2). | N61: SUIUSDT Long 50.0X ROI +170.83% Entry Price 1.07380 Current Price 1.11270 BYBIT | O61: SUI running really well too, I'll TP @ 1.14 TP2 @ 1.23 if someone likes to hold longer | Q61: high | S61: 060_2026-05-21_050346_Screenshot_20260521-065728.png | U61: https://discord.com/channels/1042855255089623100/1501271173588193290/1506839893358284901
A62: 61 | B62: 2026-05-21 | C62: 05:57:24 | D62: yes | E62: pnl_share_card | F62: Bybit | G62: 1 | H62: SUIUSDT | M62: Bybit ROI share card for the SUIUSDT 50x long closed at exactly 1.14000 (his stated TP1) from entry 1.07380 for +308.25%. Confirms the take-profit order filled right after his earlier update. | N62: SUIUSDT Long 50.0X ROI +308.25% Entry Price 1.07380 Exit Price 1.14000 BYBIT | O62: SUI TP got hit immediately after this message. Good start of the day! @Paladin Notify | Q62: high | S62: 061_2026-05-21_055724_Screenshot_20260521-075544.png | U62: https://discord.com/channels/1042855255089623100/1501271173588193290/1506853391668613170
A63: 62 | B63: 2026-05-21 | C63: 05:57:39 | D63: yes | E63: pnl_share_card | F63: Blofin | G63: 1 | H63: SUIUSDT | M63: Blofin PnL share card for a closed SUIUSDT 100X long: entry 1.0481, close 1.1401, +877.77% ROI, closed 05-21 07:55:15. Posted as 'Entry from my DCA', i.e. this was the DCA (averaged-in) leg of his SUI long, closed in profit. | N63: WOW WAR OF WHALES 2026 SUIUSDT Perp Buy 100X +877.77% Entry Price 1.0481 Close Price 1.1401 Referral Code DwquXN 05-21 07:55:15 | O63: Entry from my DCA 👇🏻 | P63: 05-21 07:55:15 | Q63: high | S63: 062_2026-05-21_055739_blofin_1779332116390.png | U63: https://discord.com/channels/1042855255089623100/1501271173588193290/1506853455929544744
A64: 63 | B64: 2026-05-21 | C64: 06:14:08 | D64: yes | E64: discord_message_screenshot | F64: Discord | G64: 0 | M64: Screenshot of a Discord DM exchange: a member asks why Paladin does not take partial profits on BTC, and Paladin explains his trade-management philosophy: he exits 100% at TP1 because partials get round-tripped while a stop loss is always a 100% loss, his trades are mostly 0.5-1R, and taking full TP makes his R accounting simple (one loss recovered by two 100% TP wins). | N64: (first message, author name cropped off at top): Hey Paladin, just saw you mention you don't like to take partial profits in BTC. Was just curious why? Thanks for posting in ScalpX it seems like every trade you take is a home run! Keep it up 💪🏻🤠 Paladin [Will not DM] May 21, 2026 8:06 AM First of all, appreciate the compliment! I don't like partials because partials can hurt For example I take 50% TP then it comes back and hits my BE I wasted 50% of the profits? Okay understandable But whenever I hit SL I get a 100% SL You round trip more on partials than you make Plus I don't do high RR trading, my trades are mostly 0.5-1R trades I take 100% it helps me keep track of my R, if I lose 1 trade I know I'll make it back by 2 trades 100% TP Not 4 trades with 3 trades taking TP1 25% and 4th trade finally hitting my TP4 If TP1 is the most confident TP why not exit 100% there instead of round tripping? Yes you miss big moves to flex on pnl card but I don't have to stress about round trips Basically SL is 100% in partial TP trading and TPs are 25-50% Sorry for writing so much I hope you understood | O64: Someone asked this in my DMs why I don't like taking partials so putting it here is my point of view, of course you don't have to agree just my style. @Paladin Notify | P64: May 21, 2026 8:06 AM | Q64: high | R64: Top of the screenshot is cropped, so the author/avatar and timestamp of the first (question) message are not visible. | S64: 063_2026-05-21_061408_Screenshot_20260521-081221.png | U64: https://discord.com/channels/1042855255089623100/1501271173588193290/1506857601235816518
A65: 64 | B65: 2026-05-21 | C65: 20:21:34 | D65: yes | E65: pnl_share_card | F65: Blofin | G65: 1 | H65: BTCUSDT | M65: Blofin share card of an open BTCUSDT 150X long: entry 77,065.1, mark 77,854.8, +153.70% ROI at 05-21 22:20:56. Posted in response to chat claims that he was 'getting rekt because everyone else is shorting' - he was long BTC against the crowd and in profit. | N65: WOW WAR OF WHALES 2026 BTCUSDT Perp Buy 150X +153.70% Entry Price 77,065.1 Mark Price 77,854.8 Referral Code hrk3ES 05-21 22:20:56 | O65: I saw some in chat saying I'm getting rekt because everyone else is shorting 😐 @Paladin Notify | P65: 05-21 22:20:56 | Q65: high | S65: 064_2026-05-21_202134_blofin_1779384057207.png | U65: https://discord.com/channels/1042855255089623100/1501271173588193290/1507070864791703704
A66: 65 | B66: 2026-05-22 | C66: 11:59:59 | D66: no | E66: discord_message_screenshot | F66: Discord | G66: 0 | M66: Screenshot of the ScalpX bot's 'Roles & Notifications' message listing the reaction emoji for each trader's notification role (crystal ball 🔮 for Paladin, 404 reactions). Posted to tell members how to subscribe to his notifications; no trade data. | N66: Apr 5, 2026 Scalp X [BOT] Apr 5, 2026 3:08 AM Make sure you register for your favorite traders here! (edited) Roles & Notifications [SCALPX logo] React with the emoji for each role you want 🔔 React 🔥 for Chento React (yellow feather emoji) for uvwpvw React (SCALP logo emoji) for Nick Scalps React 🐪 for Yassin React (white roll emoji) for ! number React 🌺 for Madda React (grey $ emoji) for Dmitry React 🔮 for Paladin React (sunglasses emoji) for PILTR React 👔 for Thomas Reactions: 🔥 1023 | (SCALP logo) 384 | (feather) 391 | 🐪 426 | (white roll) 372 | 🌺 574 | ($) 492 | 🔮 404 | (sunglasses) 192 | 👔 147 | O66: Also a couple of DMs regarding not getting my notifications , or how to get them, you go and take it from #🐐｜get-notifications Just press 🔮 for my notifications Also you can choose others at a single time too for their notifications as everyone's doing their best here! @Paladin Notify | P66: Apr 5, 2026 3:08 AM | Q66: high | R66: Some reaction emoji are custom/ambiguous (feather-like emoji for uvwpvw, white roll for '! number', grey $ for Dmitry, dark sunglasses for PILTR) and are described rather than transcribed. | S66: 065_2026-05-22_115959_Screenshot_20260522-135719.png | U66: https://discord.com/channels/1042855255089623100/1501271173588193290/1507307024482959431
A67: 66 | B67: 2026-05-22 | C67: 16:02:49 | D67: yes | E67: pnl_share_card | F67: Blofin | G67: 1 | H67: 1000BONKUSDT | M67: Blofin share card for a 1000BONKUSDT 75X long closed at TP1: entry 0.006158, close 0.006323, +199.88% ROI at 05-22 18:01:16. Message says he took only 20-25% here and is holding the majority for more. | N67: WOW WAR OF WHALES 2026 1000BONKUSDT Perp Buy 75X +199.88% Entry Price 0.006158 Close Price 0.006323 Referral Code DwquXN 05-22 18:01:16 | O67: BONK TP1, taking 20-25% only saving majority @Paladin Notify | P67: 05-22 18:01:16 | Q67: high | S67: 066_2026-05-22_160249_blofin_1779454878921.png | U67: https://discord.com/channels/1042855255089623100/1501271173588193290/1507368138889494681
A68: 67 | B68: 2026-05-22 | C68: 16:41:48 | D68: yes | E68: pnl_share_card | F68: Yubit | G68: 1 | H68: WLDUSDT | M68: Exchange share card of an open WLDUSDT 100X long: entry $0.284, fair/mark price $0.2908, +234.74% ROI. Posted when WLD nearly tagged his TP (missed by 0.002); he recommended partial profit (25-50%) and stop to entry. | N68: WLDUSDT Perpetual Long | 100X +234.74% 0% Liquidity NO.1 Entry Price $0.284 Fair Price $0.2908 | O68: WLD missed TP by 0.002, almost missed TP, moved up 1.5 R from limit, up 0.9 from CMP Take 25-50% SL to entry @Paladin Notify | Q68: high | R68: No exchange logo visible in the crop; platform inferred from the card style ('0% / Liquidity NO.1' graphic, 'Perpetual', 'Fair Price' terminology) used on his non-Blofin cards. | S68: 067_2026-05-22_164148_Screenshot_20260522-183856.png | U68: https://discord.com/channels/1042855255089623100/1501271173588193290/1507377949874192516
A69: 68 | B69: 2026-05-22 | C69: 18:35:51 | D69: yes | E69: pnl_share_card | F69: Yubit | G69: 1 | H69: WLDUSDT | M69: Cropped 'Closed PNL' share card for the WLDUSDT 100X long, closed at +542.25% ROI, with a decorative sparkline marking the B (buy) and S (sell) points. Message: TP hit (1.5R from limit, 1R from CMP), he is out at first TP but thinks the weekend could reach full TP. | N69: Closed PNL WLDUSDT Perpetual Long | 100X +542.25% | O69: TP hit 1.5R from limit, 1R from CMP I'm out at first TP but confident weekend might give us ful TP @Paladin Notify | Q69: high | R69: Crop excludes entry and close prices. Platform inferred from card style (same family as the 'Fair Price' cards); no logo visible. | S69: 068_2026-05-22_183551_Screenshot_20260522-203419.png | U69: https://discord.com/channels/1042855255089623100/1501271173588193290/1507406648829022390
A70: 69 | B70: 2026-05-23 | C70: 09:21:38 | D70: yes | E70: pnl_share_card | F70: Yubit | G70: 1 | H70: BEATUSDT | M70: Share card for a (partially) closed BEATUSDT 100X short: avg entry $1.2875, avg close $1.169, +921.08% ROI. Message: up 1.5R, took 60% off to recover one previous SL. | N70: BEATUSDT Perpetual Close Short | 100X +921.08% Avg Entry Price $1.2875 Avg Close Price $1.169 | O70: Up 1.5R, took 60% to recover 1SL @Paladin Notify | Q70: high | R70: No exchange logo visible; platform inferred from card style. Center of the card is blank (graphic not rendered/cropped). | S70: 069_2026-05-23_092138_Screenshot_20260523-112019.png | U70: https://discord.com/channels/1042855255089623100/1501271173588193290/1507629563000258671
A71: 70 | B71: 2026-05-23 | C71: 10:52:47 | D71: yes | E71: pnl_share_card | F71: Yubit | G71: 1 | H71: JCTUSDT | M71: Share card of an open JCTUSDT 50X short: entry $0.004, fair/mark price $0.003870, +160.87% ROI. Posted as JCT dumped ~0.5R; he took 10% off, SL to entry, and warned to secure shorts lightly because BTC might bounce. | N71: JCTUSDT Perpetual Short | 50X +160.87% Entry Price $0.004 Fair Price $0.003870 | O71: JCT dumped nearly 0.5 R, taking 10% only, SL to entry. BTC may bounce so securinh my shorts, take 10-20% MAX! @Paladin Notify | Q71: high | R71: No exchange logo visible; platform inferred from card style. | S71: 070_2026-05-23_105247_Screenshot_20260523-125146.png | U71: https://discord.com/channels/1042855255089623100/1501271173588193290/1507652503599059055
A72: 71 | B72: 2026-05-23 | C72: 10:57:00 | D72: yes | E72: pnl_share_card | F72: Yubit | G72: 1 | H72: HYPEUSDT | M72: Share card of an open HYPEUSDT 100X long: entry $54.991, fair/mark price $55.507, +93.83% ROI, which he described as 0.5R up. | N72: HYPEUSDT Perpetual Long | 100X +93.83% Entry Price $54.991 Fair Price $55.507 | O72: And HYPE 0.5 R up :KEKLaugh: | Q72: high | R72: No exchange logo visible; platform inferred from card style. | S72: 071_2026-05-23_105700_Screenshot_20260523-125632.png | U72: https://discord.com/channels/1042855255089623100/1501271173588193290/1507653565022212139
A73: 72 | B73: 2026-05-23 | C73: 11:50:21 | D73: yes | E73: pnl_share_card | F73: Yubit | G73: 1 | H73: HYPEUSDT | M73: Cropped 'Closed PNL' card for the HYPEUSDT 100X long closed at +204.57% ROI (decorative sparkline with B/S markers). Message: HYPE up 1.2R, he is out here, next TP 58 for holders. | N73: Closed PNL HYPEUSDT Perpetual Long | 100X +204.57% | O73: HYPE up 1.2R, I'm out here, but 58 next TP for those holding @Paladin Notify | Q73: high | R73: Crop excludes entry and close prices. Platform inferred from card style; no logo visible. | S73: 072_2026-05-23_115021_Screenshot_20260523-134519.png | U73: https://discord.com/channels/1042855255089623100/1501271173588193290/1507666989454200832
A74: 73 | B74: 2026-05-23 | C74: 16:15:56 | D74: yes | E74: pnl_share_card | F74: Blofin | G74: 1 | H74: SUIUSDT | M74: Blofin share card of an open SUIUSDT 100X long: entry 1.0014, mark 1.0165, +150.91% ROI at 05-23 18:15:38. Posted with '1R soon!' - the +150% ROI was still short of 1R because his R is measured against the stop distance (SL 0.95 / TP 1.05). | N74: WOW WAR OF WHALES 2026 SUIUSDT Perp Buy 100X +150.91% Entry Price 1.0014 Mark Price 1.0165 Referral Code DwquXN 05-23 18:15:38 | O74: 1R soon! | P74: 05-23 18:15:38 | Q74: high | S74: 073_2026-05-23_161556_blofin_1779542139382.png | U74: https://discord.com/channels/1042855255089623100/1501271173588193290/1507733827601301525
A75: 74 | B75: 2026-05-23 | C75: 16:36:55 | D75: yes | E75: discord_message_screenshot | F75: Discord | G75: 2 | H75: BEATUSDT, SUIUSDT | M75: Discord screenshot where Paladin explains his R concept: 1R = profit equal to the stop-loss distance, ROI % is irrelevant to it. He gives the BEAT short (went 2R, TP taken at 1.7R) and the live SUI long (from 1, SL 0.95, TP 1.05) as examples, revealing that his SUI trade was a 1:1 risk/reward setup; the accompanying message adds that he risks 1-2% on alts and 3-5% on BTC. | N75: Diafonso 6:23 PM @Paladin [Will not DM] i am confused u said 1R soon, but you are up 150% arent u already 1R? or in this case 1.5R Paladin [Will not DM] [SX] [VIP] [OP] 6:29 PM Noooo That's ROI 1R is when you make profit equal to your SL. If SL is 100$ and TP is 100$ that makes 1R, if SL is 100$ and TP is 200$ that makes 2R If SL is 100$ and TP is 50$ that makes 0.5R For example we did beat short it went 2R, so SL was 100$ and TP 200$ (We took TP @ 1.7 R) Basically your trade have to move up same amount up against SL to score 1R For example you longed SOL at 100 SL is 95, TP is 105 See? SL is -5$, TP is +5$ Just like this rn SUI is running from 1 SL 0.95 (-0.5) TP 1.05 (+0.5) [reaction: ❤️ 1] | O75: For those who don't know what is R, I tried explaining in the simplest way! Also guys, I risk 1-2% on ALTs and 3-5% on BTC trades @Paladin Notify | P75: 6:23 PM / 6:29 PM | Q75: high | S75: 074_2026-05-23_163655_Screenshot_20260523-183520.png | U75: https://discord.com/channels/1042855255089623100/1501271173588193290/1507739108884348969
A76: 75 | B76: 2026-05-23 | C76: 16:38:14 | D76: yes | E76: other | F76: other | G76: 0 | M76: Link-preview image of the infinityalgo.com Position Size Calculator (default example: $10,000 balance, 2% risk, entry 50.00, SL 48.00 -> 100 shares, $200 risk). He shared it to tell followers to size positions by risk (1-2% alts, 3% BTC) so they never get liquidated. | N76: Position Size Calculator Calculate the optimal position size for your trades based on your account balance, risk tolerance, and stop loss. Proper position sizing is the foundation of successful risk management in trading. Risk Management | 100% Free | Instant Results Position Size Calculator Enter your trading parameters to calculate the optimal position size Account Balance: USD 10000 Risk Per Trade (%): 2 (Recommended: 1-3% per trade) Entry Price: 50.00 Stop Loss Price: 48.00 Position Size Results Position Size: 100 shares Risk Distance: $2.00 (4.0%) Risk Amount: $200.00 | O76: Also guys I take my trade using risk calculators such as https://infinityalgo.com/tools/calculators/position-size-calculator Learn to use risk calculator and I PROMISE YOU, YOU'LL END MONTHLY PROFITABLE WITH ME AND NEVER EVER GET LIQUIDATED. 1-2% ALTs 3% BTC | Q76: high | R76: Embed preview of a web page, not his own numbers (default example values). | S76: 075_2026-05-23_163814_EMBED_og-position-size-calculator.jpg | U76: https://discord.com/channels/1042855255089623100/1501271173588193290/1507739436178341980
A77: 76 | B77: 2026-05-23 | C77: 16:41:42 | D77: yes | E77: other | F77: other | G77: 0 | M77: Phone screenshot of the position-size calculator filled with his SUI example: risk 1% (of an implied $10,000 wallet), entry 1, stop loss 0.95, 200:1 leverage -> 2000 coins ($2,000 notional), $10 margin, $100 risk. Posted as a step-by-step on how he derives position size (coins/margin) from wallet, risk % and entry/SL before placing the order on the exchange. | N77: Risk Per Trade: [%] [$] 1 Entry Price: 1 Stop Loss: 0.95 Leverage (Optional): 200:1 Advanced Options Position Size 2000.000000 coins $2,000.00 total value Required Margin: $10.00 @ 200:1 Risk Amount: $100.00 | O77: How to use it? Step1: Write your wallet Step2: Write your risk % Step3: Write your Entry SL Step4: It gives you a position size, how much coins or margin to long Step5: Go to your exchange manually write down the coins or margin | Q77: high | R77: Account balance field is scrolled out of view (implied ~$10,000 from 1% = $100 risk, not shown). | S77: 076_2026-05-23_164142_Screenshot_20260523-184000.png | U77: https://discord.com/channels/1042855255089623100/1501271173588193290/1507740311013818418
A78: 77 | B78: 2026-05-23 | C78: 16:42:48 | D78: yes | E78: order_screenshot | F78: Blofin | G78: 1 | H78: SUIUSDT | M78: Blofin futures order screen for SUIUSDT Perp (Cross 100X, 794.72 USDT available, last price 1.0172, SUI down 9.33% on the day) with the 'Futures Unit Setting' sheet open and red marks highlighting 'By Amount' in SUI. Posted as the final step of his sizing tutorial: enter on the exchange by coin amount taken from the risk calculator. | N78: Futures | Copy | Bots SUIUSDT Perp -9.33% Cross | 100X Funding / Countdown 0.0138% / 02:18:09 Available 794.72 USDT Limit Price(USDT) 1.1 | BBO Amount SUI Reduced only Order book - Price (USDT) / Amount (SUI): 1.0178 41.813K | 1.0177 35.557K | 1.0176 21.397K | 1.0175 32.166K | 1.0174 46.602K | 1.0173 30.611K | 1.0172 3.875K | 1.0172 | 1.0171 Futures Unit Setting (selected) By Amount - Place an order by amount. Cost will change accordingly when you adjust the leverage. [SUI] [USDT] By Cost (USDT) - Place an order by cost (trading fee included). Cost won't change when you adjust the leverage. Actual cost for reduce orders may slightly differ. Confirm | O78: Go to your exchanges and set by amount I'm doing this on blofin but every exchange has it the same. | Q78: high | R78: Order side (buy/sell) is not visible; the 1.1 limit price appears to be a demo value. | S78: 077_2026-05-23_164248_Screenshot_20260523-184152.png | U78: https://discord.com/channels/1042855255089623100/1501271173588193290/1507740588563370145
A79: 78 | B79: 2026-05-23 | C79: 16:54:27 | D79: yes | E79: other | F79: Blofin | G79: 0 | M79: Cropped exchange wallet screenshot showing a total balance of 89.36 USDT - the small account he found and decided to use for a 'for fun' BTC-scalps-only 2x challenge, risking 10-20% per trade (explicitly not to be copied on a main account). | N79: Total Balance (USDT) 89.36 ≈ $89.36 | O79: I found this today in some account, for fun I'll do BTC scalp trades only on this and let's see if we can double it by BTC scalps only, alot of you have requested a 2x or funded challenge. Nothing serious just for fun, don't follow it on main account I'll try to risk 10-20% which isn't healthy for your main wallet. BTC trades only and we will try for 2x 😤 | Q79: medium | R79: No logo visible; platform inferred from UI style and the following Blofin position screenshot (079) of the same account. | S79: 078_2026-05-23_165427_Screenshot_20260523-185155.png | U79: https://discord.com/channels/1042855255089623100/1501271173588193290/1507743520738381854
A80: 79 | B80: 2026-05-23 | C80: 17:16:47 | D80: yes | E80: open_positions_screenshot | F80: Blofin | G80: 1 | H80: BTCUSDT | M80: Blofin open position: BTCUSDT long, cross 20X, size 0.0090 BTC, margin 34.2309 USDT, entry 75,166.5, mark 75,159.2, est. liquidation 65,494.8, stop loss 72,200.0 and no take profit set, ROI -0.19%. Posted as 'First scalp trade' of the small-account 2x challenge - a roughly 4% price stop at 20X on a third of the 89 USDT account. | N80: BTCUSDT Long | Cross | 20X Unrealized PnL (USDT) -0.0657 ≈ -$0.06 ROI -0.19% Size (BTC) 0.0090 Margin (USDT) 34.2309 Margin Rate 2.29% Entry Price 75,166.5 Mark Price 75,159.2 Est. Liq. Price 65,494.8 Position TP/SL -- / 72,200.0 | O80: First scalp trade. | Q80: high | S80: 079_2026-05-23_171647_Screenshot_20260523-191624.png | U80: https://discord.com/channels/1042855255089623100/1501271173588193290/1507749138832298015
A81: 80 | B81: 2026-05-23 | C81: 20:17:47 | D81: yes | E81: chart | F81: Blofin | G81: 0 | I81: 15m | J81: EMA(20): 56.777; EMA(50): 56.203; EMA(200): 56.170 | K81: auto high label 58.102 (swing high of the rally); auto low label 54.506 (swing low before the rally); current price line 57.636; price scale: 58.281, 56.963, 55.644, 54.326 | L81: After a choppy decline to the 54.506 low, HYPE rallied impulsively through all three EMAs to 58.102 and is consolidating around 57.6 just under that high, with EMA20 > EMA50 > EMA200 in a bullish stack. It documents his HYPE long (entry ~54.991) having reached the 58 take-profit area. | M81: Blofin 15-minute HYPEUSDT chart posted when he announced the HYPE TP was hit: price ran from 54.506 to 58.102 (his stated next TP was 58) and sits at 57.636. He notes the full move was 3RR without partials (2RR with), while he had already exited at ~1.1R - an example of when his 100%-at-first-TP rule costs upside. | N81: HYPEUSDT Last Price 57.636 ≈ $57.57 -0.32% Mark Price 57.635 24h High 58.550 24h Low 54.058 24h Vol(HYPE) 698.281K Funding Rate 0.0246% Line | 15m | 1h | 4h | 1D | More EMA(20): 56.777 EMA(50): 56.203 EMA(200): 56.170 58.281 58.102 57.636 56.963 55.644 54.506 54.326 BloFin | O81: HYPE TP hit, 3RR without partials, 2 RR with partials if you took it how I mentioned This is when taking 100% TP hurts, I exited at 1.1 R but anyhow I usually always take 100% on first TP @Paladin Notify | Q81: high | S81: 080_2026-05-23_201747_Screenshot_20260523-221619.png | U81: https://discord.com/channels/1042855255089623100/1501271173588193290/1507794690198736996
A82: 81 | B82: 2026-05-23 | C82: 21:18:48 | D82: yes | E82: pnl_share_card | F82: Blofin | G82: 1 | H82: SUIUSDT | M82: Blofin share card of the SUIUSDT 100X long from 1.0014 with mark price 1.0539, +524.30% ROI at 05-23 23:17:49 - the same trade as card 073 now past his 1.05 target (1R). Posted with 'Alright boys took some here', i.e. profit taken at this level. | N82: WOW WAR OF WHALES 2026 SUIUSDT Perp Buy 100X +524.30% Entry Price 1.0014 Mark Price 1.0539 Referral Code DwquXN 05-23 23:17:49 | O82: Alright boys took some here @Paladin Notify | P82: 05-23 23:17:49 | Q82: high | S82: 081_2026-05-23_211848_blofin_1779560270446.png | U82: https://discord.com/channels/1042855255089623100/1501271173588193290/1507810046959161707
A83: 82 | B83: 2026-05-23 | C83: 23:42:34 | D83: yes | E83: pnl_share_card | F83: Blofin | G83: 1 | H83: FILUSDT | M83: Blofin share card for a closed FILUSDT 3X long: entry 0.955, closed at 1.000 for +14.13% ROI. Posted with 'FIL TP' - he took profit on FIL at the 1.000 round-number level. | N83: WOW WAR OF WHALES 2026 FILUSDT Perp Buy 3X +14.13% Entry Price 0.955 Close Price 1.000 Referral Code DwquXN 05-24 01:41:28 | O83: FIL TP @Paladin Notify | P83: 05-24 01:41:28 | Q83: high | S83: 082_2026-05-23_234234_blofin_1779568888498.png | U83: https://discord.com/channels/1042855255089623100/1501271173588193290/1507846224202694776
A84: 83 | B84: 2026-05-23 | C84: 23:42:51 | D84: yes | E84: pnl_share_card | F84: Blofin | G84: 1 | H84: BTCUSDT | M84: Blofin share card of an open BTCUSDT 150X long from 75,197.2 with mark price 76,903.8 (+340.42% ROI). Posted with 'BTC feel free to trim wherever you want' - he is inviting partial profit-taking while staying in the trade. | N84: WOW WAR OF WHALES 2026 BTCUSDT Perp Buy 150X +340.42% Entry Price 75,197.2 Mark Price 76,903.8 Referral Code DwquXN 05-24 01:41:18 | O84: BTC feel free to trim wherever you want. @Paladin Notify | P84: 05-24 01:41:18 | Q84: high | S84: 083_2026-05-23_234251_blofin_1779568879556.png | U84: https://discord.com/channels/1042855255089623100/1501271173588193290/1507846295732228228
A85: 84 | B85: 2026-05-23 | C85: 23:43:25 | D85: yes | E85: pnl_share_card | F85: Blofin | G85: 1 | H85: SUIUSDT | M85: Blofin share card of an open SUIUSDT 100X long from 1.0014 with mark 1.0803 (+788.77% ROI). Posted with 'SUI nearly full TP, still holding majority, Target 1.1+' - partial profit taken, runner kept toward 1.1. | N85: WOW WAR OF WHALES 2026 SUIUSDT Perp Buy 100X +788.77% Entry Price 1.0014 Mark Price 1.0803 Referral Code DwquXN 05-24 01:42:58 | O85: SUI nearly full TP, still holding majority, Target 1.1+ @Paladin Notify | P85: 05-24 01:42:58 | Q85: high | S85: 084_2026-05-23_234325_blofin_1779568979638.png | U85: https://discord.com/channels/1042855255089623100/1501271173588193290/1507846441123709070
A86: 85 | B86: 2026-05-23 | C86: 23:50:00 | D86: yes | E86: discord_message_screenshot | F86: Discord | G86: 0 | M86: Screenshot of Paladin's own earlier Discord message (timestamped 'Yesterday at 10:29 PM', i.e. the evening of ~22 May) laying out his geopolitical reasoning for expecting a ceasefire extension: Hajj/Eid timing, Gulf states wanting calm, Pakistan brokering talks with China and Iran. Reposted as proof that he anticipated the positive news behind the pump ('Mentioned this in the VIPs, expecting good news, trump just announced it...'). No trade data; shows he factors macro/geopolitical catalysts into his bullish bias. | N86: Paladin [Will not... [SX] [VIP] [OP] Yesterday at 10:29 PM Hajj, Muslims pilgrimage and Eid incoming, Gulf countries trying to extend at least this period Plus Pakistan in action again going to China and Iran for peace talks, feels like we will settle soon (unless Israel messes up) [heart reaction] 1 | O86: Mentioned this in the VIPs, expecting good news, trump just announced it, ceasefire continuation on the request of gulf stayed that's why we pumped | P86: Yesterday at 10:29 PM | Q86: high | R86: Author display name is truncated ('Paladin [Will not...'); badge labels read SX, VIP, OP. | S86: 085_2026-05-23_235000_Screenshot_20260524-014858.png | U86: https://discord.com/channels/1042855255089623100/1501271173588193290/1507848097404027102
A87: 86 | B87: 2026-05-23 | C87: 23:57:10 | D87: yes | E87: open_positions_screenshot | F87: Blofin | G87: 1 | H87: BTCUSDT | M87: Exchange positions tab showing an open BTCUSDT 200X cross long of 0.0090 BTC from 75,166.5, mark 77,072.3, unrealized +17.15 USDT (+507.03% ROI) on 3.7884 USDT margin, liquidation 65,500.5 and a stop loss at 72,220.0. Posted with 'Making 20% of this' - the ~$17 gain is about 20% of this small account. | N87: BTCUSDT Long | Cross | 200X Unrealized PnL (USDT) +17.1504 ≈ +$17.15 ROI +507.03% Size (BTC) 0.0090 Margin (USDT) 3.7884 Margin Rate 5.97% Entry Price 75,166.5 Mark Price 77,072.3 Est. Liq. Price 65,500.5 Position TP/SL -- / 72,220.0 Pending Orders (2) | O87: Making 20% of this :KEKLaugh: | Q87: high | R87: The two pending orders are collapsed and not visible. Platform inferred from the Blofin-style UI (Est. Liq. Price / Margin Rate / Position TP/SL layout). | S87: 086_2026-05-23_235710_Screenshot_20260524-015655.png | U87: https://discord.com/channels/1042855255089623100/1501271173588193290/1507849900690247901
A88: 87 | B88: 2026-05-24 | C88: 00:01:23 | D88: yes | E88: pnl_share_card | F88: Blofin | G88: 1 | H88: BTCUSDT | M88: Blofin share card of the open BTCUSDT 150X long from 75,197.2 with mark 77,348.4 (+429.13% ROI). Posted with 'Bullish weekend' - he is holding into the weekend expecting continuation. | N88: WOW WAR OF WHALES 2026 BTCUSDT Perp Buy 150X +429.13% Entry Price 75,197.2 Mark Price 77,348.4 Referral Code DwquXN 05-24 02:00:15 | O88: Bullish weekend | P88: 05-24 02:00:15 | Q88: high | S88: 087_2026-05-24_000123_blofin_1779570016366.png | U88: https://discord.com/channels/1042855255089623100/1501271173588193290/1507850960737927168
A89: 88 | B89: 2026-05-24 | C89: 00:09:16 | D89: yes | E89: pnl_share_card | F89: Yubit | G89: 1 | H89: SUIUSDT | M89: Share card of a SUIUSDT 250X long from $1.0006 with fair price $1.0909 showing +2,148.71% ROI. Posted with 'Sorry for the spam but SUI hit full TP 2R since we barely took anything at TP1' - he closed the SUI long in full at ~1.09 (about 2R) after taking only a small partial at TP1. | N89: SUIUSDT Perpetual Long | 250X +2,148.71% Entry Price $1.0006 Fair Price $1.0909 | O89: Sorry for the spam but SUI hit full TP 2R since we barely took anything at TP1 @Paladin Notify | Q89: medium | R89: Cropped screenshot with no exchange logo; platform inferred from the card style ('Perpetual', 'Long | 250X', 'Fair Price') which matches the non-Blofin (Yubit) cards in this export - not Blofin and not Binance. Whether the position was already closed is ambiguous (fair price, not close price). | S89: 088_2026-05-24_000916_Screenshot_20260524-020832.png | U89: https://discord.com/channels/1042855255089623100/1501271173588193290/1507852944312373341
A90: 89 | B90: 2026-05-24 | C90: 00:09:23 | D90: yes | E90: pnl_share_card | F90: Blofin | G90: 1 | H90: SUIUSDT | M90: Blofin share card for the closed SUIUSDT 100X long: entry 1.0014, closed at 1.0890 for +874.77% ROI. Posted seconds after the 'SUI hit full TP 2R' message, confirming the full exit around 1.09. | N90: WOW WAR OF WHALES 2026 SUIUSDT Perp Buy 100X +874.77% Entry Price 1.0014 Close Price 1.0890 Referral Code DwquXN 05-24 02:05:50 | P90: 05-24 02:05:50 | Q90: high | S90: 089_2026-05-24_000923_blofin_1779570355350.png | U90: https://discord.com/channels/1042855255089623100/1501271173588193290/1507852972460216501
A91: 90 | B91: 2026-05-24 | C91: 00:12:10 | D91: yes | E91: pnl_share_card | F91: Blofin | G91: 1 | H91: BTCUSDT | M91: Blofin share card of the still-open BTCUSDT 150X long from 75,197.2, mark 77,036.2 (+366.85% ROI). One of four cards posted together with 'C'mon guys at least post PNLs... today I gave you like 5R today' - a recap of the day's winning calls. | N91: WOW WAR OF WHALES 2026 BTCUSDT Perp Buy 150X +366.85% Entry Price 75,197.2 Mark Price 77,036.2 Referral Code DwquXN 05-24 02:11:19 | O91: C'mon guys at least post PNLs #💲｜profit-showcase today I gave you like 5R today @Paladin Notify | P91: 05-24 02:11:19 | Q91: high | S91: 090_2026-05-24_001210_blofin_1779570679706.png | U91: https://discord.com/channels/1042855255089623100/1501271173588193290/1507853674855137532
A92: 91 | B92: 2026-05-24 | C92: 00:12:10 | D92: yes | E92: pnl_share_card | F92: Blofin | G92: 1 | H92: BEATUSDT | M92: Blofin share card for a closed BEATUSDT 40X short: entry 1.2694, closed at 1.1482 for +382.08% ROI. Part of the four-card recap of the day's calls ('today I gave you like 5R'). | N92: WOW WAR OF WHALES 2026 BEATUSDT Perp Sell 40X +382.08% Entry Price 1.2694 Close Price 1.1482 Referral Code DwquXN 05-24 02:11:15 | O92: C'mon guys at least post PNLs #💲｜profit-showcase today I gave you like 5R today @Paladin Notify | P92: 05-24 02:11:15 | Q92: high | S92: 091_2026-05-24_001210_blofin_1779570675950.png | U92: https://discord.com/channels/1042855255089623100/1501271173588193290/1507853674855137532
A93: 92 | B93: 2026-05-24 | C93: 00:12:10 | D93: yes | E93: pnl_share_card | F93: Blofin | G93: 1 | H93: SUIUSDT | M93: Blofin share card for the closed SUIUSDT 100X long (entry 1.0014, close 1.0890, +874.77% ROI), re-shared as part of the four-card day recap. | N93: WOW WAR OF WHALES 2026 SUIUSDT Perp Buy 100X +874.77% Entry Price 1.0014 Close Price 1.0890 Referral Code DwquXN 05-24 02:10:54 | O93: C'mon guys at least post PNLs #💲｜profit-showcase today I gave you like 5R today @Paladin Notify | P93: 05-24 02:10:54 | Q93: high | S93: 092_2026-05-24_001210_blofin_1779570654702.png | U93: https://discord.com/channels/1042855255089623100/1501271173588193290/1507853674855137532
A94: 93 | B94: 2026-05-24 | C94: 00:12:10 | D94: yes | E94: pnl_share_card | F94: Blofin | G94: 1 | H94: FILUSDT | M94: Blofin share card for the closed FILUSDT 3X long (entry 0.955, close 1.000, +14.13% ROI), re-shared as part of the four-card day recap. | N94: WOW WAR OF WHALES 2026 FILUSDT Perp Buy 3X +14.13% Entry Price 0.955 Close Price 1.000 Referral Code DwquXN 05-24 02:10:56 | O94: C'mon guys at least post PNLs #💲｜profit-showcase today I gave you like 5R today @Paladin Notify | P94: 05-24 02:10:56 | Q94: high | S94: 093_2026-05-24_001210_blofin_1779570656635.png | U94: https://discord.com/channels/1042855255089623100/1501271173588193290/1507853674855137532
A95: 94 | B95: 2026-05-24 | C95: 00:13:16 | D95: yes | E95: pnl_share_card | F95: Yubit | G95: 1 | H95: HYPEUSDT | M95: Tightly cropped 'Closed PNL' share card for a HYPEUSDT 100X long closed for +204.57% ROI, with a small sparkline marking the buy (B) near a dip and the sell (S) higher. Posted with 'Actually 8R, gave 3R on HYPE too' - adding the HYPE win to his tally of the day's calls. | N95: Closed PNL HYPEUSDT Perpetual | Long | 100X +204.57% B S | O95: Actually 8R, gave 3R on HYPE too 🤘🏻 | Q95: medium | R95: Entry and close prices are not in the crop. No exchange logo; platform inferred from the same card style as the 'Fair Price' SUI card (non-Blofin, non-Binance). | S95: 094_2026-05-24_001316_Screenshot_20260524-021241.png | U95: https://discord.com/channels/1042855255089623100/1501271173588193290/1507853951599644892
A96: 95 | B96: 2026-05-24 | C96: 00:49:01 | D96: yes | E96: screen_recording | F96: Discord | G96: 16 | H96: BTCUSDT, FILUSDCUSDT, FILUSDT, HYPEUSDT, SUIUSDT | M96: Phone screen recording (13 s) of Paladin scrolling down the '#profit-showcase' Discord channel (3372 unread) in the early hours of 2026-05-24 (phone local time ~02:48, about 2 h ahead of the Helsinki post time): members thank him with PnL share cards from PrimeXBT, Ourbit, BloFin (incl. 'WOW War of Whales 2026' cards), MEXC, Pionex and KCEX plus one closed-positions list. The recurring trades are his 23 May calls: HYPE long (~55.0-56.0 -> ~55.9-58.0, +75% to +442%), FIL long (0.953-0.96 -> 0.996-1.000, +88% to +242%), SUI long (~0.998-1.0013 -> 1.09, +88% to +465%) and BTC long (74.7k-75.5k -> 76.1k-77.1k, +49% to +868%), mostly at 20X-75X; one member posted a 100X HYPE short (+701.28%, entry 59.393) asking 'PNL porn?'. The scroll ends at the newest message (below 'NEW MESSAGES'), a PrimeXBT 0.090 BTC long at +868.26% / +147.08 USDT. Posted with 'Thank you for your trust guys, lovely to see this'; shows follower results, not his own positions. | N96: # $ | profit-showcase [Discord channel header, 3372 unread badge] Shawarma Yesterday at 9:55 PM: Thank you ser @Paladin [Will not DM] [PrimeXBT card] HYPE / USDT | Long | +442.35% | Entry price 56.015 | Close price 57.981 | PRIME XBT -- All-in-one app for Crypto, Investing, and Trading | ❤️ 2 hellwavez [SX, VIP] Yesterday at 11:27 PM: PNL porn? [OURBIT card, Italian] HellWaveZ | HYPE USDT | Perp | Short | 100X | +701.28% | Prezzo di entrata $59.393 | Prezzo Equo $55.061 | 20H 05M | Unisciti a Ourbit, il SuperCEX di Memecoin | Codice Referral YE4MAC | [custom emoji] 1 --- May 24, 2026 --- Nate Today at 2:12 AM: Thanks Paladin!!! [BloFin card] FILUSDT Perp | Long 30X | +144.65% | Entry Price 0.954 | Close Price 1.000 | Referral Code: K6FqR3 | Share Time: 05/23 16:58:39 | ❤️ 1 SirBandylegs Today at 2:13 AM: @Paladin [Will not DM] TY! [MEXC card] Shared on 2026-05-23 23:12:26 (UTC+2) | SUIUSDT Perpetual | Long | 10x | +88.34% | Referral code 2h7YA | Sign up to get $10, $50 first-trade loss coverage, & 0-fee Futures | ❤️ 1 ateek944 Today at 2:13 AM: @Paladin [Will not DM] my first trade with full tp (edited) [WOW War of Whales 2026 card] ateek944 | BTCUSDT Perp | Buy 20X | +49.41% | Entry Price 75,175.3 | Mark Price 77,032.7 | Referral Code CnsOQb | 05-24 02:42:37 | ❤️ 1 misfitnl Today at 2:13 AM: Thanks Paladin [WOW War of Whales 2026 card] FILUSDT Perp | Long 20X | +88.05% | Entry Price 0.954 | Close Price 0.996 | Referral Code: dzMIKU | 05/23 23:12:56 | ❤️ 1 D3vil Today at 2:13 AM: Thanks @Paladin [Will not DM] [Pionex card] HYPE/USDT Perpetual | Buy | 50X | Profit rate in USDT +75.16% | Avg. Price 55.031 | Avg. close 55.916 | Lasting 1h 23m | DevilUnited's referral code 0eacBj9WgjM | Download Pionex App [Pionex card] FIL/USDT Perpetual | Buy | 50X | Profit rate in USDT +241.64% | Avg. Price 0.953 | Avg. close 1.000 | Lasting 5h 22m | DevilUnited's referral code 0eacBj9WgjM [Pionex card] BTC/USDT Futures Lite | Buy | 75X | Profit rate in USDT +197.39% | Avg. Price 74,785.1 | Last Price 76,799.9 | Lasting 9h 7m | DevilUnited's referral code 0eacBj9WgjM [Pionex card] SUI/USDT Perpetual | Buy | 50X | Profit rate in USDT +464.62% | Avg. Price 1.0013 | Last Price 1.0934 | Lasting 12h 34m | DevilUnited's referral code 0eacBj9WgjM | ❤️ 1 Pokedust Today at 2:14 AM: 💪🏼 [KCEX card] dt***2@outlook.com | BTC/USDT | Long 75X Closed | +116.53% | Avg Entry Price $75,535.5 | Avg Close Price $76,733.2 | Invite Code U3NN04 | 2026-05-23 17:12:42 | Fees as low as 0.01% | ❤️ 1 archersid18 [SX] Today at 2:17 AM: @Paladin [Will not DM] I was so down and out. Thanks! [WOW War of Whales 2026 card] SUIUSDT Perp | Buy 20X | +185.02% | Entry Price 0.9977 | Close Price 1.0900 | Referral Code UMITOI | 05-24 02:46:32 | 🔥 1 ❤️ 1 Janos Today at 2:18 AM: @Paladin [Will not DM] hey, I'm New here, thanks a lot;) [WOW War of Whales 2026 card] SUIUSDT Perp | Buy 20X | +93.38% | [rest of card not in frame] [author not in frame] [closed-positions list screenshot] FILUSDC | Perp | Cross 20x | Realized PNL (USDC) 1.74 | ROI 75.45% | Entry Price 0.96 | Avg. Close Price 0.997 | Opened | Closed || BTCUSDT | Perp | Cross 40x | Realized PNL (USDT) 2.57 | ROI 68.80% | Entry Price 74,710 | Avg. Close Price 76,073.3 | Opened | Closed | 🔥 2 ❤️ 1 --- NEW MESSAGES --- Pollensa [ASTR] Today at 2:45 AM: @Paladin [Will not DM] thanks so much [PrimeXBT card] 0.090 BTC/USDT | Long | +868.26% | +147.08 USDT | Entry price 75,506.4 | Market price 77,140.7 | Shared on 05/23/26, 21:58:00 | Join PrimeXBT | ❤️ 1 | O96: Thank you for your trust guys, lovely to see this 🙏🏻🖤 | P96: Discord: 'Yesterday at 9:55 PM', 'Yesterday at 11:27 PM', date divider 'May 24, 2026', then 'Today at 2:12 AM' through 'Today at 2:45 AM' (phone local time); share-card times: 05/23 16:58:39, 2026-05-23 23:12:26 (UTC+2), 05-24 02:42:37, 05/23 23:12:56, 2026-05-23 17:12:42, 05-24 02:46:32, 05/23/26 21:58:00 | Q96: high | R96: All trades are followers' share cards, not Paladin's own positions. Janos' SUIUSDT card is cut off (no prices/time visible). The author and exchange of the closed-positions list (FILUSDC / BTCUSDT) are not in frame and its 'Opened'/'Closed' date values are not shown; side for those two entries is inferred from close > entry with positive ROI. SirBandylegs' MEXC SUIUSDT card shows no prices. Leverage is not printed on the two PrimeXBT cards. The reaction emoji under hellwavez's post is a custom emoji that could not be identified. Frames 1-2 and 12-13 are identical (static start/end). | S96: 095_2026-05-24_004901_screen-20260524-024824-1779572891354.mp4 | U96: https://discord.com/channels/1042855255089623100/1501271173588193290/1507862949518381066
A97: 96 | B97: 2026-05-24 | C97: 02:33:55 | D97: yes | E97: pnl_share_card | F97: Blofin | G97: 1 | H97: BTCUSDT | M97: Blofin share card for the closed BTCUSDT 150X long: entry 75,197.2, closed at 76,609.2 for +281.65% ROI. Posted with 'Out of BTC completely here, took 25% earlier at 77k' - he scaled out 25% near 77k and closed the rest at 76,609.2 after price pulled back. | N97: WOW WAR OF WHALES 2026 BTCUSDT Perp Buy 150X +281.65% Entry Price 75,197.2 Close Price 76,609.2 Referral Code DwquXN 05-24 04:30:08 | O97: Out of BTC completely here, took 25% earlier at 77k @Paladin Notify | P97: 05-24 04:30:08 | Q97: high | S97: 096_2026-05-24_023355_blofin_1779579009839.png | U97: https://discord.com/channels/1042855255089623100/1501271173588193290/1507889347804790936
A98: 97 | B98: 2026-05-24 | C98: 02:34:56 | D98: yes | E98: closed_pnl_list | F98: Blofin | G98: 1 | H98: BTCUSDT | M98: Exchange order history showing the filled market 'Close Long' order for the small account: 0.0090 BTC closed at avg 76,609.2 on 2026-05-24 04:27:09 for +12.9843 USDT realized PnL (fee 0.4137 USDT). Posted with 'Made 13$ on the 90$ account, 15%. Let's see if we can double it!'. | N98: All | Limit | Market | Last 30 days BTCUSDT Filled > Close Long | Cross | 200X Realized PnL (USDT) +12.98430000 Price (USDT) Market Quantity (BTC) 0.0090 Filled (BTC) 0.0090 Avg. Price (USDT) 76,609.2 Fee (USDT) 0.41368968 Time 2026-05-24 04:27:09 | O98: Made 13$ on the 90$ account, 15% Let's see if we can double it! | P98: 2026-05-24 04:27:09 | Q98: high | R98: Entry price and ROI are not shown on this order record. Platform inferred from the Blofin-style UI. | S98: 097_2026-05-24_023456_Screenshot_20260524-042828.png | U98: https://discord.com/channels/1042855255089623100/1501271173588193290/1507889602613088368
A99: 98 | B99: 2026-05-24 | C99: 07:56:03 | D99: yes | E99: open_positions_screenshot | F99: Blofin | G99: 1 | H99: BTCUSDT | M99: Exchange positions tab showing a new BTCUSDT 200X cross long of 0.0090 BTC entered at 76,754.6 (mark 76,767.0, +3.20% ROI, +0.11 USDT) with stop loss at 74,000.0 and liquidation at 65,738.8. Posted with 'Long BTC' as the entry call for the new position. | N99: BTCUSDT Long | Cross | 200X Unrealized PnL (USDT) +0.1107 ≈ +$0.11 ROI +3.20% Size (BTC) 0.0090 Margin (USDT) 3.8685 Margin Rate 2.06% Entry Price 76,754.6 Mark Price 76,767.0 Est. Liq. Price 65,738.8 Position TP/SL -- / 74,000.0 TP/SL | Add | Close | O99: Long BTC @Paladin Notify | Q99: high | R99: Platform inferred from the Blofin-style UI. | S99: 098_2026-05-24_075603_Screenshot_20260524-095437.png | U99: https://discord.com/channels/1042855255089623100/1501271173588193290/1507970412271763466
A100: 99 | B100: 2026-05-24 | C100: 15:58:06 | D100: yes | E100: pnl_share_card | F100: Blofin | G100: 1 | H100: BTCUSDT | M100: Blofin share card of the open BTCUSDT 150X long from 76,754.6 with mark 77,060.0 (+59.70% ROI). Posted with 'In profits rn so you can adjust' - suggesting followers move stops/partials now that the trade is in profit. | N100: WOW WAR OF WHALES 2026 BTCUSDT Perp Buy 150X +59.70% Entry Price 76,754.6 Mark Price 77,060.0 Referral Code DwquXN 05-24 17:57:54 | O100: In profits rn so you can adjust | P100: 05-24 17:57:54 | Q100: high | S100: 099_2026-05-24_155806_blofin_1779627475232.png | U100: https://discord.com/channels/1042855255089623100/1501271173588193290/1508091726563115028
...

Sheet Charts
A1: Date | B1: Time | C1: Symbol | D1: Timeframe | E1: Platform | F1: Price shown | G1: Indicators | H1: Levels / drawings | I1: Annotations on chart | J1: What it shows | K1: Message posted with image | L1: Image file | M1: Discord link
A2: 2026-05-08 | B2: 19:41:13 | C2: UNIUSDT | D2: 15m | E2: Bybit | F2: Last Traded Price 3.687 (Mark Price 3.689) | G2: EMA7 (3.614); EMA14 (3.577); EMA28 (3.537); volume with MA5 (138.12K) and MA10 (124.64K) | H2: exchange auto high marker 3.698 at the current candle; exchange auto low marker 3.392 near 13:15; current price line 3.687 with countdown 05:13; no user drawings | I2: 3.698 | 3.687 05:13 | 3.392 | BYBIT Demo Trading | J2: UNIUSDT 15m in a vertical breakout: after grinding up along the EMAs all day, price went parabolic from ~3.47 around 18:45 to a new 24h high of 3.698 with a big volume spike on the last candles; EMAs stacked bullishly. He posted this as he exited UNI fully at 3.7, i.e. selling into the spike. | K2: Well UNI blew up, I'm fully out here @ 3.7 for around 1.4 R Think we see 4$ by coming weekend/week @Paladin Notify | L2: 004_2026-05-08_194113_Screenshot_20260508-213947.png | M2: https://discord.com/channels/1042855255089623100/1501271173588193290/1502349669571891250
A3: 2026-05-09 | B3: 02:01:21 | C3: SOLUSDT | D3: 4h | E3: Bybit | F3: Last Traded Price 92.240 (Mark Price 92.240) | G3: EMA7 (90.319); EMA14 (89.347); EMA28 (88.070) | H3: exchange auto high marker 92.760 at the latest candles; exchange auto low marker 82.740 near 05/01-05/02; current price line 92.240 with countdown 01:06:14; no user drawings | I3: 92.760 | 92.240 01:06:14 | 82.740 | BYBIT Demo Trading | J3: SOLUSDT 4h in a steady uptrend from ~82.74 on May 1: base-building, then a strong impulse on May 5-6 to ~90, consolidation around 88-90 along EMA7/EMA14, and a large green 4h candle to a new 24h high 92.760 with the current candle slightly red at 92.240. Posted as one of the alts he said were 'popping off'. | K3: Look at them go, every ALT I mentioned here just popping off even ASTER started moving 🤣 Usually I'm already in too many trades and have to limit myself for giving positions because I feel like people don't care about risk management and jump in all in. But if I ever mention a coin and you can do some analysis, check them out! | L3: 005_2026-05-09_020121_Screenshot_20260509-035346.png | M3: https://discord.com/channels/1042855255089623100/1501271173588193290/1502445332355878943
A4: 2026-05-09 | B4: 02:01:21 | C4: NEARUSDT | D4: 1D | E4: Bybit | F4: Last Traded Price 1.5902 (Mark Price 1.5902) | G4: EMA7 (1.4300); EMA14 (1.3897); EMA28 (1.3631) | H4: exchange auto high marker 1.6069 at the current daily candle; exchange auto low marker 1.1285 near 03/29-03/30; current price line 1.5902 with countdown 01:05:31; no user drawings | I4: 1.6069 | 1.5902 01:05:31 | 1.1285 | BYBIT Demo Trading | J4: NEARUSDT daily: bottom at 1.1285 in late March, rally to ~1.45 by mid-April, a pullback into early May toward ~1.25 (below the EMAs), then two very large green daily candles breaking out to a new high of 1.6069 with price at 1.5902 well above all EMAs. Posted as an example of alts he mentioned 'popping off'. | K4: Look at them go, every ALT I mentioned here just popping off even ASTER started moving 🤣 Usually I'm already in too many trades and have to limit myself for giving positions because I feel like people don't care about risk management and jump in all in. But if I ever mention a coin and you can do some analysis, check them out! | L4: 006_2026-05-09_020121_Screenshot_20260509-035429.png | M4: https://discord.com/channels/1042855255089623100/1501271173588193290/1502445332355878943
A5: 2026-05-09 | B5: 02:01:21 | C5: PUMPFUNUSDT | D5: 4h | E5: Bybit | F5: Last Traded Price 0.0021615 (Mark Price 0.0021615) | G5: EMA7 (0.0020866); EMA14 (0.0020354); EMA28 (0.0019720) | H5: exchange auto high marker 0.0021932 at the current candles; exchange auto low marker 0.0017500 at the far left of the visible range; current price line 0.0021615 with countdown 01:05:12; no user drawings | I5: 0.0021932 | 0.0021615 01:05:12 | 0.0017500 | BYBIT Demo Trading | J5: PUMPFUNUSDT 4h in a clean stair-step uptrend from 0.00175 to a 24h high of 0.0021932: consolidation, impulse, shallow pullbacks holding EMA7/EMA14, then a strong green push; current candle slightly red at 0.0021615 above all EMAs. Posted as an example of alts he mentioned 'popping off'. | K5: Look at them go, every ALT I mentioned here just popping off even ASTER started moving 🤣 Usually I'm already in too many trades and have to limit myself for giving positions because I feel like people don't care about risk management and jump in all in. But if I ever mention a coin and you can do some analysis, check them out! | L5: 007_2026-05-09_020121_Screenshot_20260509-035449.png | M5: https://discord.com/channels/1042855255089623100/1501271173588193290/1502445332355878943
A6: 2026-05-09 | B6: 02:01:21 | C6: ASTERUSDT | D6: 4h | E6: Bybit | F6: Last Traded Price 0.6893 (Mark Price 0.6894) | G6: EMA7 (0.6746); EMA14 (0.6727); EMA28 (0.6719) | H6: exchange auto high marker 0.6992 at the current candle (long upper wick); exchange auto low marker 0.6487 near 05/01-05/02; current price line 0.6893 with countdown 01:04:49; no user drawings | I6: 0.6992 | 0.6893 01:04:49 | 0.6487 | BYBIT Demo Trading | J6: ASTERUSDT 4h: a choppy week-long range roughly 0.655-0.70 with the three EMAs flat and bunched (0.6719-0.6746), a flush to ~0.655 on May 8, then a sharp two-candle rally that spiked to 0.6992 and left a long upper wick with price back at 0.6893. He pointed out that 'even ASTER started moving'. | K6: Look at them go, every ALT I mentioned here just popping off even ASTER started moving 🤣 Usually I'm already in too many trades and have to limit myself for giving positions because I feel like people don't care about risk management and jump in all in. But if I ever mention a coin and you can do some analysis, check them out! | L6: 008_2026-05-09_020121_Screenshot_20260509-035511.png | M6: https://discord.com/channels/1042855255089623100/1501271173588193290/1502445332355878943
A7: 2026-05-12 | B7: 06:51:54 | C7: STABLEUSDT | D7: 1h | E7: Bybit | F7: Last Traded Price 0.037500 (Mark Price 0.037499) | G7: EMA7: 0.035311 (yellow); EMA14: 0.034935 (blue); EMA28: 0.034676 (purple) | H7: auto high label 0.037953 at the top of the last candle; auto low label 0.033704 near 05/11 00:00; current price tag 0.037500 with countdown 16:48 on the right axis; price scale: 0.037953, 0.036890, 0.035828, 0.034766, 0.033704; no user drawings | I7: Last Traded Price 0.037500 | Mark Price 0.037499 | 24h High 0.037953 | 24h Low 0.034025 | 24h Turnover 2.21M | +8.85% | MM 0.49% | EMA7: 0.035311 EMA14: 0.034935 EMA28: 0.034676 | 0.037953 | 0.037500 16:48 | 0.033704 | BYBIT Demo Trading | J7: STABLEUSDT 1h candles on the Bybit app: after ranging roughly 0.0337-0.0355 for two days with the EMAs curling up, the current candle is a huge vertical green spike from ~0.0348 to the 24h high 0.037953 - the pump his long caught. 'Demo Trading' watermark (Bybit demo / CFT funded account). | K7: What a pump caught! | L7: 029_2026-05-12_065154_Screenshot_20260512-0843132.png | M7: https://discord.com/channels/1042855255089623100/1501271173588193290/1503605617204531412
A8: 2026-05-12 | B8: 15:11:23 | C8: STABLEUSDT | D8: 1h | E8: MEXC | F8: Last Price 0.03884 (Fair Price 0.03884) | G8: EMA20: 0.03655 (pink); EMA50: 0.03538 (orange); EMA200: 0.03406 (blue) | H8: dashed green position/entry line at 0.03453 labeled 'PNL +43.1294 | 10,000'; red 'S' trade marker on the large green candle around 0.0378; auto high label 0.03896 on the latest candles; auto low label 0.03378 at the left; current price tag 0.03884 (green box) on the right axis with dashed line; price scale: 0.03900, 0.03750, 0.03600, 0.03450; no user drawings | I8: Last Price 0.03884 ≈0.038 USD +11.09% | Fair Price 0.03884 | 24h High 0.03896 | 24h Low 0.03403 | 24h Vol(STABLE) 12.034M | 24h Vol (USDT) 436.437K | Why is the price of STABLE rising? | EMA20:0.03655 EMA50:0.03538 EMA200:0.03406 | 0.03896 | 0.03884 | PNL +43.1294 | 10,000 | 0.03453 | 0.03378 | MEXC | J8: STABLEUSDT perpetual 1h chart on MEXC: price based around 0.034-0.035 along the EMA50, then exploded in one huge green candle to ~0.0378, pulled back to ~0.036 and continued up to a new high 0.03896. His long entry line at 0.03453 sits at the base, now ~+12% unleveraged with +43.13 USDT open PnL on a 10,000 position. | K8: Guys I would like to clarify something since I shared this screenshot it says DEMO, I got like 5 DMs saying I'm trading on DEMO It is CFT funded account so it shows demo, I trade on other exchanges with real money. Even if it's demo are the trades hitting TPs or not? Just wanted to clarify it once. | L8: 030_2026-05-12_151123_Screenshot_20260512-170605.png | M8: https://discord.com/channels/1042855255089623100/1501271173588193290/1503731313855692950
A9: 2026-05-14 | B9: 17:47:29 | C9: XRPUSDT | D9: 1h | E9: Bybit | F9: Last Traded Price 1.4654 (Mark Price 1.4655) | G9: EMA7: 1.4443 (yellow); EMA14: 1.4385 (blue); EMA28: 1.4366 (purple) | H9: auto high label 1.4661 at the top of the latest candle; current price tag 1.4654 with candle countdown 14:20 on the right axis; price scale: 1.4661, 1.4521, 1.4381, 1.4241; no user drawings; no position line | I9: Last Traded Price 1.4654 | Mark Price 1.4655 | 24h High 1.4661 | 24h Low 1.4101 | 24h Turnover 324.42M | +2.79% | MM 0.74% | EMA7: 1.4443 EMA14: 1.4385 EMA28: 1.4366 | 1.4661 | 1.4654 14:20 | J9: XRPUSDT 1h on the Bybit app: a downtrend into a ~1.41-1.42 low, a slow grind back up through the EMAs (price reclaimed EMA7/14/28, which are now stacked bullishly), then two strong green candles pushing to the 24h high 1.4661 right after he closed his long at 1.4531. The chart has no drawings; the x-axis is cut off. | K9: As soon as I close XRP it booms, I'm pretty sure this will hit our target I exited early because it invalidated my setup, it almost touched my SL so better to be disciplined and get out around BE, much better than SL at least? | L9: 038_2026-05-14_174729_Screenshot_20260514-194541.png | M9: https://discord.com/channels/1042855255089623100/1501271173588193290/1504495374503776269
A10: 2026-05-14 | B10: 21:54:01 | C10: XRPUSDT | D10: 1h | E10: Blofin | F10: 1.5367 | G10: EMA(20): 1.4572; EMA(50): 1.4471; EMA(200): 1.4341 | H10: exchange trade marker 'S' (sell) on a green candle around ~1.47 (estimated); candle high label 1.5431 (top of the rally); candle low label 1.4105 (swing low on the left-middle of the chart); last price tag 1.5367 with dotted line; price axis labels 1.5497, 1.5011, 1.4524, 1.4038; no user-drawn trendlines or zones | I10: 1.5431 / 1.4105 / 1.5367 (auto price labels only; no hand-written text) | J10: XRPUSDT 1h: after a decline to a 1.4105 low and a flat base hugging the 20/50/200 EMAs, price reclaimed all three EMAs and went vertical to 1.5431 (+7.74% on the day). The S marker shows his long was closed early on the first breakout candles, well below the eventual top. | K10: Fumbled XRP, hit full TP, was a great setup closed early but at least the idea was right! | L10: 047_2026-05-14_215401_Screenshot_20260514-235326.png | M10: https://discord.com/channels/1042855255089623100/1501271173588193290/1504557414853115985
A11: 2026-05-23 | B11: 20:17:47 | C11: HYPEUSDT | D11: 15m | E11: Blofin | F11: Last Price 57.636 (≈ $57.57, -0.32%), Mark Price 57.635 | G11: EMA(20): 56.777; EMA(50): 56.203; EMA(200): 56.170 | H11: auto high label 58.102 (swing high of the rally); auto low label 54.506 (swing low before the rally); current price line 57.636; price scale: 58.281, 56.963, 55.644, 54.326 | I11: 58.102 57.636 54.506 | J11: After a choppy decline to the 54.506 low, HYPE rallied impulsively through all three EMAs to 58.102 and is consolidating around 57.6 just under that high, with EMA20 > EMA50 > EMA200 in a bullish stack. It documents his HYPE long (entry ~54.991) having reached the 58 take-profit area. | K11: HYPE TP hit, 3RR without partials, 2 RR with partials if you took it how I mentioned This is when taking 100% TP hurts, I exited at 1.1 R but anyhow I usually always take 100% on first TP @Paladin Notify | L11: 080_2026-05-23_201747_Screenshot_20260523-221619.png | M11: https://discord.com/channels/1042855255089623100/1501271173588193290/1507794690198736996
A12: 2026-05-25 | B12: 22:14:51 | C12: WLDUSDT | D12: 15m | E12: Blofin | F12: 0.3304 | G12: EMA(20): 0.3120 (yellow); EMA(50): 0.3054 (blue); EMA(200): 0.2965 (purple); VOL: 343.757K; MA(5): 286.455K (volume MA); MA(10): 172.871K (volume MA) | H12: three 'S' sell-order markers on the pump candles (approx 0.316-0.325); high label 0.3321 at the top of the last candle; low label 0.2986 at the consolidation low before the pump; current price tag 0.3304 (dotted line); price scale 0.3341 / 0.3193 / 0.3046 / 0.2899; volume scale 423.530K / 0 | I12: 0.3321; 0.3304; 0.2986; 05-25-2026 16:30; 05-25-2026 20:45 | J12: WLDUSDT 15m on Blofin: after hours of sideways consolidation around 0.296-0.300 with price riding the EMA20/EMA50, a near-vertical breakout on sharply rising volume carried price from ~0.300 to the 24h high 0.3321 (+12.53% on the day). His sell markers sit on the way up, i.e. he scaled out of a long into the spike toward his 0.33 target. | K12: As I said show blows up and goes to 0.33 easily, almost 1.5R @Paladin Notify | L12: 103_2026-05-25_221451_Screenshot_20260526-001202.png | M12: https://discord.com/channels/1042855255089623100/1501271173588193290/1508548926666440937
... A19: 2026-06-17 | B19: 19:28:07 | C19: BTCUSDT | D19: 15m | E19: Binance | F19: 66,021.6 (Last Price), Mark Price 66,034.8 | G19: EMA(20) 65,318.1; EMA(50) 65,312.7; EMA(200) 65,577.4 | H19: swing high label 66,090.6 on the latest candle; swing low label 64,525.0 with green 'B' (buy execution) marker at the bottom; current price axis tag 66,021.3 with dashed line; right-axis gridlines 66,168.9 / 65,824.4 / 65,480.0 / 65,135.6 / 64,791.2 / 64,446.7 | I19: EMA(20): 65,318.1 EMA(50): 65,312.7 EMA(200): 65,577.4 | 66,090.6 | 64,525.0 | 66,021.3 | J19: Binance 15m BTCUSDT perp chart showing a V-shaped reversal: sell-off to 64,525 (where his buy marker sits), a short consolidation with one wick back down to ~64.7k (the retest of his entry), then a vertical rally through the EMA(20)/EMA(50)/EMA(200) to 66,090. Posted to show he 'sniped' the low and that price came back to entry exactly once before going higher as he had said. | K19: Sniped it, also it came back to entry exactly once as I said once back to entry than higher @Paladin Notify | L19: 179_2026-06-17_192807_Screenshot_20260617-212705.png | M19: https://discord.com/channels/1042855255089623100/1501271173588193290/1516841886357262448
A20: 2026-06-20 | B20: 16:11:38 | C20: REUSDT | D20: 15m | E20: unknown | F20: Last Price 1.0020 (Mark Price 1.0040) | J20: Top of a mobile exchange chart page for REUSDT: last price 1.0020 (red, i.e. down on the candle) but +28.28% on the 24h, 24h range 0.6671-1.0660, funding -0.0324%. The 15m timeframe tab is selected, so he was watching the intraday leg. | K20: Nearly a 50% move down, exactly a 43% move (0.75 avg) Out 50%, remaining 50% I exit at 2x+ @Paladin Notify | L20: 184_2026-06-20_161138_Screenshot_20260620-180139.png | M20: https://discord.com/channels/1042855255089623100/1501271173588193290/1517879602603884615
A21: 2026-06-28 | B21: 16:24:41 | C21: TOSHIUSDT | D21: 1h | E21: Blofin | F21: 0.0001297 | G21: EMA(20): 0.0001150; EMA(50): 0.0001121; EMA(200): 0.0001146; volume (bottom, partially cut off: Vol / MA(5) / MA(10)) | H21: position entry line at 0.0001101 with PnL tag (value obscured); current price tag 0.0001297 with candle countdown 38:06; swing high label 0.0001375 on the pump wick; swing low label 0.0001078 before the pump; price axis ticks 0.0001389 / 0.0001172 / 0.0001063 | I21: 0.0001375; 0.0001297 38:06; 0.0001101; 0.0001078 | J21: TOSHIUSDT 1h: a long flat base around 0.00011 followed by an almost vertical pump (two large green candles) to a 0.0001375 high, with the current red candle pulling back to 0.0001297. His long entry at 0.0001101 sits right at the base before the pump; all three EMAs are far below price and curling up. | K21: TOSHI up 25% in spot move + 1.5R move @Paladin Notify | L21: 203_2026-06-28_162441_Screenshot_20260628-182154.png | M21: https://discord.com/channels/1042855255089623100/1501271173588193290/1520781991736250500
A22: 2026-07-20 | B22: 03:28:37 | C22: BTCUSDT | D22: 4H | E22: Yubit | F22: 64,883.90 (Last Price), Mark Price 64,884.10 | G22: EMA-20 (64,360.2); EMA-50 (64,016.4); EMA-200 (63,131.6) | H22: swing high marker 65,590.8 (around 7-15/7-16) annotated '65.5k'; swing low marker 62,504.0 (around 7-17/7-18, at the EMA-200) annotated '-> 62k'; text annotation '-> Back on the way to 66k' next to the current candle at 64,883.9; price axis labels 65,765.9 / 64,952.4 / 64,139.0 / 63,325.5 / 62,512.1; current price tag 64,883.9 with candle countdown 03:35:21 | I22: 65.5k -> Back on the way to 66k -> 62k | J22: BTCUSDT Perp 4H candles on Yubit: a push up to 65,590.8, a pullback down to 62,504.0 that tagged the EMA-200, and a recovery back above the EMA-20/EMA-50 with price at 64,883.9 and heading toward 66k. It visualises his Jul 12 prediction (65.3-65.6k -> 62-63k pullback -> 66-67k) playing out step by step. | L22: 246_2026-07-20_032837_Screenshot_20260720-052715.png | M22: https://discord.com/channels/1042855255089623100/1501271173588193290/1528559220172001350
A23: 2026-08-05 | B23: 16:04:08 | C23: ZECUSDT | D23: 1D | E23: unknown | F23: 495.00 (green dashed line label) and 495.68 on the price scale; candle high 494.48 | G23: EMA-200: 478.00; a second indicator value ending in '.51' cut off at the left edge (likely another EMA/MA) | H23: green dashed horizontal line with green price label 495.00 (order/TP line per the message: 'missed TP by 0.5$'); candle high marker labeled 494.48 on the wick of a green candle; price scale label 495.68 just above the 495.00 line | I23: 1D More EMA-200: 478.00 495.68 494.48 495.00 | J23: Tiny crop of a mobile exchange chart (1D timeframe selected) showing the top of a candle whose high printed 494.48, just under a green dashed line at 495.00. Illustrates that the ZEC long missed its TP at 495 by ~0.5 before reversing; EMA-200 sits at 478.00. | K23: ZEC missed TP by 0.5$ cents, hit BE and hit both TPs | L23: 291_2026-08-05_160408_Screenshot_20260804-001735.png | M23: https://discord.com/channels/1042855255089623100/1501271173588193290/1534547559215923331
A24: 2026-08-15 | B24: 15:08:40 | C24: ZECUSDT | D24: 15m | E24: Yubit | F24: Last Price 491.45 (≈$491.45, +0.78%), Mark Price 491.45 | G24: EMA-20: 490.02 (yellow); EMA-50: 490.59 (green); EMA-200: 490.07 (magenta); Volume (VOL: 106.421, MA-5: 264.637, MA-10: 237.315) | H24: 'S' sell marker with horizontal tick at the chart high 498.44 (his exit); chart low label 486.05 at bottom-left; current price tag 491.45 with candle countdown 08:23; price axis labels 499.14 / 495.87 / 492.61 / 489.34 / 486.08; time axis 03:30 / 07:45 / 12:00 / 16:15 / 20:30; no user-drawn lines or zones | I24: S 498.44 | 486.05 | 491.45 08:23 | EMA-20: 490.02 EMA-50: 490.59 EMA-200: 490.07 | VOL: 106.421 MA-5: 264.637 MA-10: 237.315 | J24: ZEC perp 15m: price rallied into 498.44 where his long was sold (S marker), then sold off below the 20/50/200 EMA cluster (~490) to about 486, and has just bounced back above the EMAs with a strong green candle to 491.45. He reads this as the same long setup (EMA reclaim/bounce) forming again for a 'round 2' he is not taking. | K24: Great exit on ZEC, looks ready for a round 2 with same setup I'm not taking but looks valid | L24: 306_2026-08-15_150840_Screenshot_20260815-170636.png | M24: https://discord.com/channels/1042855255089623100/1501271173588193290/1538157479907557397
A25: 2026-08-18 | B25: 17:50:14 | C25: BTCUSDT | D25: 4H | E25: Yubit | F25: Last Price 64,719.50 (≈$64,719.5, +0.86%), Mark Price 64,711.50 | G25: EMA-20: 63,801.2 (yellow); EMA-50: 63,723.1 (green); EMA-200: 63,979.0 (magenta); Volume (VOL: 1.75K, MA-5: 1.70K, MA-10: 2.30K) | H25: chart high label 64,729.3 on the latest candle (equals 24h High 64,729.30); chart low label 62,485.7 on the 8-14/8-15 swing low; current price tag 64,719.5 with candle countdown 01:34:38; price axis labels 64,856.5 / 64,265.3 / 63,674.0 / 63,082.8 / 62,491.5; time axis 8-14 01:00 / 8-15 13:00 / 8-17 01:00 / 8-18 13:00 / 8-20 01:00; no user-drawn lines or zones; the EMA-200 (~63,979) acts as the level being retested | I25: 64,729.3 | 62,485.7 | 64,719.5 01:34:38 | EMA-20: 63,801.2 EMA-50: 63,723.1 EMA-200: 63,979.0 | VOL: 1.75K MA-5: 1.70K MA-10: 2.30K | J25: BTC perp 4H: after basing around 62.5-63k, a strong impulse candle broke above the 4H EMA-200 (~63,979); price pulled back onto the EMA-200 and bounced, and is now pushing to a new local high at 64,729.3. He posted it as an educational example: once EMA 200 is reclaimed it is hard to break back down and you can expect at least two bounces from it on any timeframe. | K25: From an educational point of view this is how EMA 200 acts, if it's reclaims, it's very hard to breakdown, you can expect at least 2 bounce from EMA 200 on any time frame | L25: 311_2026-08-18_175014_Screenshot_20260818-192521.png | M25: https://discord.com/channels/1042855255089623100/1501271173588193290/1539285303523545188
