Workbook

Sheet Summary
A1: Paladin (ScalpX) — reconstructed trade timeline
A2: Built from all 1,005 messages in #paladin (2026-05-06 to 2026-08-21) plus the 320 screenshots he posted. Blank means he never published the number — nothing here is calculated on his behalf.
A4: The record
A5: Positions catalogued | B5: =COUNTA(Positions!C2:C100000) -> 217
A6: …actually taken by him | B6: =COUNTA(Positions!C2:C100000)-COUNTIF(Positions!E2:E100000,"not_taken")-COUNTIF(Positions!E2:E100000,"never_filled") -> 200
A7: …with a knowable outcome | B7: =COUNTIF(Positions!E2:E100000,"win")+COUNTIF(Positions!E2:E100000,"loss")+COUNTIF(Positions!E2:E100000,"breakeven") -> 165
A8: Wins | B8: =COUNTIF(Positions!E2:E100000,"win") -> 120
A9: Losses | B9: =COUNTIF(Positions!E2:E100000,"loss") -> 35
A10: Breakeven | B10: =COUNTIF(Positions!E2:E100000,"breakeven") -> 10
A11: Never resolved in the channel | B11: =COUNTIF(Positions!E2:E100000,"unknown") -> 35
A12: Called but not taken | B12: =COUNTIF(Positions!E2:E100000,"not_taken")+COUNTIF(Positions!E2:E100000,"never_filled") -> 17
A13: Win rate excluding breakeven | B13: =B8/(B8+B9) -> 0.77419355
A14: Win rate including breakeven | B14: =B8/B7 -> 0.72727273
A15: He publicly claimed 85% (May) and 89% (July).
A17: How trades ended
A18: Closed by hand | B18: =COUNTIF(Positions!F2:F100000,"manual_close") -> 62 | C18: =COUNTIFS(Positions!F2:F100000,"manual_close",Positions!E2:E100000,"win") -> 61 | D18: wins, 0 losses
A19: Reached a published target | B19: =COUNTIF(Positions!F2:F100000,"take_profit") -> 45
A20: Hit a stop | B20: =COUNTIF(Positions!F2:F100000,"stop_loss") -> 35 | C20: every loss came this way
A21: Closed flat | B21: =COUNTIF(Positions!F2:F100000,"breakeven") -> 11
A22: Simply stopped being mentioned | B22: =COUNTIF(Positions!F2:F100000,"unknown") -> 43
A24: Did he publish a plan?
A25: Positions with a published stop | B25: =COUNT(Positions!M2:M100000) -> 187
A26: Positions with a published target | B26: =COUNTA(Positions!N2:N100000) -> 122
A27: Positions with a published DCA level | B27: =COUNTA(Positions!L2:L100000) -> 58
A28: …where that DCA actually filled | B28: =COUNTA(Positions!Q2:Q100000) -> 30
A29: Positions where he moved the stop | B29: =COUNTA(Positions!R2:R100000) -> 46
A30: Positions where he took partials | B30: =COUNTA(Positions!T2:T100000) -> 43
A32: Month by month
A33: Month | B33: Wins | C33: Losses | D33: BE | E33: Win rate excl. BE | F33: What he claimed
A34: 2026-05 | B34: =COUNTIFS(Positions!$B$2:$B$100000,"2026-05*",Positions!$E$2:$E$100000,"win") -> 36 | C34: =COUNTIFS(Positions!$B$2:$B$100000,"2026-05*",Positions!$E$2:$E$100000,"loss") -> 13 | D34: =COUNTIFS(Positions!$B$2:$B$100000,"2026-05*",Positions!$E$2:$E$100000,"breakeven") -> 1 | E34: =IFERROR(B34/(B34+C34),"-") -> 0.73469388 | F34: 60 trades, 51W, 9L, 85%, +159.6%
A35: 2026-06 | B35: =COUNTIFS(Positions!$B$2:$B$100000,"2026-06*",Positions!$E$2:$E$100000,"win") -> 34 | C35: =COUNTIFS(Positions!$B$2:$B$100000,"2026-06*",Positions!$E$2:$E$100000,"loss") -> 11 | D35: =COUNTIFS(Positions!$B$2:$B$100000,"2026-06*",Positions!$E$2:$E$100000,"breakeven") -> 4 | E35: =IFERROR(B35/(B35+C35),"-") -> 0.75555556 | F35: no summary ever posted
A36: 2026-07 | B36: =COUNTIFS(Positions!$B$2:$B$100000,"2026-07*",Positions!$E$2:$E$100000,"win") -> 31 | C36: =COUNTIFS(Positions!$B$2:$B$100000,"2026-07*",Positions!$E$2:$E$100000,"loss") -> 7 | D36: =COUNTIFS(Positions!$B$2:$B$100000,"2026-07*",Positions!$E$2:$E$100000,"breakeven") -> 3 | E36: =IFERROR(B36/(B36+C36),"-") -> 0.81578947 | F36: 45 trades, 40W, 5 SLs, 89%, +23.5R
A37: 2026-08 | B37: =COUNTIFS(Positions!$B$2:$B$100000,"2026-08*",Positions!$E$2:$E$100000,"win") -> 19 | C37: =COUNTIFS(Positions!$B$2:$B$100000,"2026-08*",Positions!$E$2:$E$100000,"loss") -> 4 | D37: =COUNTIFS(Positions!$B$2:$B$100000,"2026-08*",Positions!$E$2:$E$100000,"breakeven") -> 2 | E37: =IFERROR(B37/(B37+C37),"-") -> 0.82608696 | F37: log ends 21 Aug
A40: The sheets
A41: Positions — one row per trade, from the call to the exit. The "planned" columns are what he published up front; the "avg entry / partials / exit" columns are what the messages and screenshots show he actually did.
A42: Events — all 1,242 individual actions (calls, entries, DCAs, stop moves, partials, exits) with his exact words and a link to the message.
A43: What he watches — the signals, risk rules, entry patterns and management tactics the record supports, each with his own quotes.
A44: His scoreboard — every performance claim he made, so his numbers can be checked against the Positions sheet.
A45: A "medium" or "low" confidence on a position means part of it was inferred; the Trust notes column says which part.

Sheet Positions
A1: # | B1: First seen | C1: Symbol | D1: Side | E1: Outcome | F1: Exit type | G1: R | H1: Card ROI % | I1: Leverage | J1: Planned entry | K1: Entry note | L1: Planned DCA | M1: Planned stop | N1: Planned targets | O1: Risk note | P1: Avg entry | Q1: DCA filled | R1: Stop moves | S1: Target changes | T1: Partials taken | U1: Exit price | V1: Entry time | W1: Exit time | X1: Held (h) | Y1: Thesis | Z1: What he did | AA1: Indicators | AB1: Market context | AC1: Still open | AD1: Confidence | AE1: Trust notes | AF1: Messages | AG1: First message link
A2: 1 | B2: 2026-05-07 02:34:43 | C2: UNIUSDT | D2: long | E2: win | F2: take_profit | G2: 1.4 | H2: 101.21 | I2: 50 | J2: 3.46 | K2: 3.46 CMP | M2: 3.28 | N2: 3.669 | P2: 3.458 | R2: 3.46 (to_entry) | S2: 3.7/4 | T2: 50% at 3.528 | U2: 3.7 | V2: 2026-05-07 02:34:43 | W2: 2026-05-08 19:41:13 | X2: 41.1 | Y2: Simple long on UNI at market with a first target at 3.669; he took it as a clean setup and later treated it as the channel's first win. | Z2: He called the long at 3.46 CMP with a single 3.669 target and a 3.28 stop, noting he takes TPs manually but followers could set the order. A day and a half later, 0.7R up, he closed 50% and framed it as the channel's first win, lifted his own target to 3.7 (telling followers they could hold for 4) and moved the stop to breakeven at 3.46. An hour later UNI 'blew up' and he took the remainder at 3.7 for around 1.4R. The next morning he re-posted the closed 50x card (entry 3.458, exit 3.528, +101.21%) inside a batch update and said he expected UNI to see $4 by the coming weekend. | AD2: high | AE2: The card re-posted in msg 36 shows exit 3.528, not the 3.7 he announced in text - it documents the 50% partial (its +101.21% matches the ROI attached to that partial), so the partial price is carried from that card. No explicit fill price beyond '@ 3.7' was given for the second half. | AF2: #5, #26, #29, #36 | AG2: https://discord.com/channels/1042855255089623100/1501271173588193290/1501728955470712946
A3: 2 | B3: 2026-05-07 02:35:46 | C3: ETHUSDT | D3: long | E3: loss | F3: stop_loss | J3: 2348 | K3: 2348 CMP; said he takes TP manually so he might close before or after 2420 | M3: 2292 | N3: 2420 | V3: 2026-05-07 02:35:46 | W3: 2026-05-07 19:48:16 | X3: 17.2 | Y3: Plain market long on ETH targeting 2420, with the intention of taking profit manually rather than at a fixed limit. | Z3: He called the long at 2348 CMP with a 2292 stop and a 2420 target, saying he would close manually. The trade first travelled far enough that he describes it as having 'gone BE', then an unexpected drop on 7 May took it out along with his BTC long. He never posted a fill price for the stop-out, only that ETH stopped. He apologised for a rough start to the run. | AB3: unexpected drop; BTC was about to be stopped at the same time | AD3: medium | AE3: No exit price posted, so exit_price is null; the stated stop was 2292. His wording 'Both went BE but didn't expect a drop so stopped' leaves it ambiguous whether he was taken out at the original 2292 stop or at a breakeven stop he had moved up - he treats it as a loss and apologises, so it is recorded as a loss. | AF3: #6, #15 | AG3: https://discord.com/channels/1042855255089623100/1501271173588193290/1501729216969048065
A4: 3 | B4: 2026-05-07 11:06:57 | C4: BTCUSDT | D4: long | E4: loss | F4: stop_loss | J4: 81500 | K4: 50% of size at 81.5k, 50% held back for the 80.8k DCA (msg 9) | L4: 80800 | M4: 79600 | N4: 82500 | O4: Scalp. If he did not update, followers were to trim 20-25% at the first TP (82.5k) | Q4: 80900 (filled manually at 80.9k because price missed his 80.8k limit by about $10) | V4: 2026-05-07 11:06:57 | W4: 2026-05-07 19:48:16 | X4: 8.7 | Y4: A scalp long into the 80k region: he thought BTC could retrace further but expected the 80s to hold and at least a visit to 82k+, which would give a scalp. | Z4: He called the scalp at 81.5k with half the size and the other half saved for a DCA at 80.8k (msgs 8-9), and when price missed that limit by about $10 he filled the second half manually at 80.9k (msg 10). He never posted an average or a card for it. That evening BTC dropped unexpectedly and it was stopped: 'ETH stopped, BTC about to get stopped (on some exchanges maybe it already did). Both went BE but didn't expect a drop so stopped' (msg 15). Followers had been told to trim 20-25% at 82.5k if he went quiet, but price never reached the first target. | AA4: support/resistance | AB4: BTC weak and possibly retracing further; he was already carrying UNI and ETH longs he called risky for the same reason (msg 7). | AD4: medium | AE4: No exit price was ever posted - 79.6k is his published stop, not a confirmed fill, and msg 15 says it was still in the process of being stopped across exchanges. Average entry not stated (50% at 81.5k, 50% at 80.9k), so it is left null rather than blended. 'Both went BE' is ambiguous: if he had moved the stop to breakeven this would be a scratch rather than a loss, but the event is logged as a stop-out so it is recorded as a loss. | AF4: #8, #9, #10, #15 | AG4: https://discord.com/channels/1042855255089623100/1501271173588193290/1501857862148952084
A5: 4 | B5: 2026-05-07 15:32:55 | C5: ZROUSDT | D5: long | E5: win | F5: breakeven | H5: 178.94 | I5: 50 | J5: 1.48 | K5: 1.48 CMP; three minutes later he corrected that CMP was really 1.486 because price moved fast. He advised followers to keep 50-30% back for a DCA but said he was not saving for DCA himself | L5: 1.45 | M5: 1.36 | N5: 1.5523 | O5: Keep 50-30% funds for DCA but optional you can go all in here I'm not saving for DCA personally | P5: 1.4744 | S5: 1.55 | T5: 25% at 1.53 | U5: 1.4744 | V5: 2026-05-07 15:32:55 | W5: 2026-05-11 00:40:45 | X5: 81.1 | Y5: A straight CMP long on ZRO managed by hand, with 1.5523 as the fallback target if he went quiet. He flagged it as the last new position he would open before one of his others exited. | Z5: He called the long at 1.48 CMP and corrected the fill to 1.486 three minutes later after a fast move, advising followers to split 50/50 with a DCA at 1.45 while he took his own size in one go. By the 9 May batch update his 50x card was open at +34.43% (entry 1.4744, mark 1.4849). On 10 May he complained that ZRO had been rejecting from the 1.5523 target for three days and told the room to take profit early on any drop; ninety minutes later he booked 25% at 1.53 for +178.94% and said he would fully exit around 1.55+. The rest was stopped at breakeven just after midnight, straight after TP1 - and in the same message he re-entered the same long. | AD5: high | AE5: His card entry (1.4744) is below both the 1.48 call and the 1.486 corrected CMP, so part of the size filled lower than either quoted price and he never explained it. No exit fill is quoted anywhere: 1.4744 is used because that is his stated entry and a breakeven stop exits there. Msg 57 both closes this position and opens the next ZRO long. | AF5: #11, #12, #13, #36, #53, #54, #57 | AG5: https://discord.com/channels/1042855255089623100/1501271173588193290/1501924796072464426
A6: 5 | B6: 2026-05-07 15:41:53 | C6: GOLD | D6: long | E6: not_taken | F6: not_taken | O6: Declined the setup because he already had too many positions open. | Y6: Gold looked longable to him, but position capacity - not the chart - kept him out. | Z6: He flagged gold as longable and immediately declined it: 'Gold looks Longable but too many positions for now!' No entry, stop or target was published and he never came back to this particular idea; gold does not appear again until a 3R trade he mentions on 28 May. | AD6: high | AE6: An idea floated and dropped in one message - no levels of any kind, so nothing to link a later gold trade to. | AF6: #14 | AG6: https://discord.com/channels/1042855255089623100/1501271173588193290/1501927050284372139
A7: 6 | B7: 2026-05-08 01:40:42 | C7: BTCUSDT | D7: long | E7: win | F7: manual_close | H7: 72.31 | I7: 100 | J7: 79700 | K7: 79.7k CMP | L7: 79469, 78600 | M7: 78500 | N7: 80500 | O7: Soft stop was a 1h close under 79k, hard stop 78.5k; DCAs were equal-sized to the initial entry | P7: 79764.4 | Q7: 79469 (equal-sized DCA filled, blended entry 79590 (breakeven)) | R7: 77600 (widen) | S7: 81000/82000 | T7: 50% at 79590 | U7: 80341.2 | V7: 2026-05-08 01:40:42 | W7: 2026-05-09 06:06:56 | X7: 28.4 | Y7: Long from 79.7k CMP with a conditional invalidation (1h close under 79k) for a push to 80.5k, then held into what he believed would be a hard weekend pump toward the previous daily high. | Z7: He called it at 79.7k CMP with a soft stop (1h close under 79k) and a hard stop at 78.5k (msg 17). With the trade at breakeven he added an equal-sized DCA at 79469 (msg 18), which filled and left the blend at 79590 (msg 19). He then told everyone to take that DCA half back off at breakeven and re-place it as a limit at 78.6k (msgs 19, 21) and widened the stop to 77.6k to sit under the new level - 'I know it's sound messy but I'm confident we will exit this one in green' - and the second DCA never filled. He posted a screenshot showing his own entry at 79,564.80 and offered an optional 20% trim at 80.5k (msg 25), then said he was looking to close in the 81-82k area on a 4h close above 80.5k (msg 33). He closed it manually the next morning at 80.4k - card 79,764.40 to 80,341.20, +72.31% on 100x (msgs 36, 40) - and afterwards clarified that 79.5k was the original entry and it only shows as 79.7k because he added margin (msg 41). | AA7: 1h close, 4h close, previous daily high | AB7: Straight after the previous day's stop-out; he expected a hard weekend pump, with a 4h close above 80.5k opening 81-82k. | AD7: high | AE7: Four entry figures appear for the same trade: 79,590 blended after the DCA (msg 19), 79,564.80 on the 05-08 screenshot (msg 25), 79.5k which he calls the original entry (msgs 33, 41), and 79,764.40 on the closing card, which he explains by having added margin; avg_entry uses the closing card. Both DCA levels were added after the call, not published with it. After closing he twice talked about re-longing (CMP with SL 79k or waiting for ~80.3k in msg 42, then a 79k entry / 78k DCA / 77k SL setup in msg 43 with explicit instructions not to leave limits) but never took either - the next BTC trade was a short on 05-11. | AF7: #17, #18, #19, #21, #25, #33, #36, #40, #41 | AG7: https://discord.com/channels/1042855255089623100/1501271173588193290/1502077749882523759
A8: 7 | B8: 2026-05-08 06:43:06 | C8: AVNTUSDT | D8: long | E8: win | F8: unknown | H8: 246.69 | I8: 50 | J8: 0.158 | K8: 0.158 CMP | M8: 0.1411 | N8: 0.1746, 0.2023 | P8: 0.15851 | S8: 0.1746 | T8: 0.16709 | V8: 2026-05-08 06:43:06 | Y8: No reasoning was published beyond the levels: a plain CMP long on AVNT with a two-step ladder at 0.1746 and 0.2023 and a stop at 0.1411. | Z8: He called it at 0.158 CMP with a 0.1411 stop and targets at 0.1746 and 0.2023. By the 9 May batch update the 50x card was open at +265.55% (entry 0.15851, mark 0.16787) and he told the room to take profit whenever they liked rather than let winners round-trip. On the evening of 10 May he announced TP1 at 0.16709, the card still open at +246.69%, and pulled the plan in - the rest would now come off at 0.1746 instead of running to 0.2023. That final exit is never reported: AVNT does not appear in the log again. | AC8: yes | AD8: medium | AE8: Profit was definitely banked at TP1, which is why this is scored a win, but the size of that partial and the fate of the remainder are both unknown - the position simply drops out of the log after 10 May. Marked still open only because nothing reports it closing. | AF8: #22, #36, #52 | AG8: https://discord.com/channels/1042855255089623100/1501271173588193290/1502153850231193630
A9: 8 | B9: 2026-05-08 18:47:55 | C9: KERNELUSDT | D9: long | E9: win | F9: unknown | H9: 49.35 | I9: 20 | J9: 0.064 | K9: 0.064, confirmed as CMP twelve seconds later | M9: 0.581 | N9: 0.066 | O9: High win rate, low R trade; stop is a 4h close under the level or the hard stop | P9: 0.06454 | R9: None (to_entry) | S9: 0.0673 | T9: 0.06615 | V9: 2026-05-08 18:47:55 | Y9: Explicitly a high win rate, low R trade - a 0.064 CMP long targeting about 0.066 first, managed by hand with a 4h close as the soft stop. | Z9: He called KERNEL at 0.064 CMP as a high win rate / low R trade, with the stop written as a 4h close under 0.59 or a hard stop at 0.581 - both an order of magnitude away from the entry. Ten hours later he announced TP1 at 0.06615 with the 20x card at +49.35% and set the next target at 0.0673. The same card reappeared in his 4:48 batch update, still open, with the room told to take profit whenever they liked. Nine minutes after that he posted the reminder to move the stop to entry after TP1, replying to the KERNEL message. Nothing more about KERNEL is ever posted, so the final exit is unknown. | AA9: 4h close | AC9: yes | AD9: medium | AE9: The published stops (4h close under 0.59, hard stop 0.581) are almost certainly typos for 0.059 / 0.0581 against a 0.064 entry - recorded exactly as posted. The stop-to-entry move is inferred from reply context and carries no level. TP1 was announced but the card still showed the position open and no exit is ever reported, so the win rests on the announced TP1 alone. | AF9: #27, #28, #35, #36, #39 | AG9: https://discord.com/channels/1042855255089623100/1501271173588193290/1502336255449366558
A10: 9 | B10: 2026-05-08 19:49:28 | C10: SNXUSDT | D10: long | E10: win | F10: manual_close | H10: 55.8 | I10: 25 | J10: 0.354 | K10: 0.354 CMP for half the size, the other half reserved for a 0.334 DCA | L10: 0.334 | M10: 0.31 | N10: 0.39 | O10: DCA is 50% of size; TP1 at 0.39 is 1R and closes 50% of the position, TP2 to be given later. | P10: 0.3545 | U10: 0.3626 | V10: 2026-05-08 19:49:28 | W10: 2026-05-10 23:33:31 | X10: 51.7 | Y10: Long SNX at market with a laddered plan - half now, half at 0.334 - and a first target at 0.39 that he defined as 1R. | Z10: He called SNX long at 0.354 CMP with a 0.334 DCA for the second half, TP1 0.39 (1R, 50%) and a 0.31 stop. The DCA never came - SNX went straight up and by the next morning his 25x card was +118.67% (entry 0.3545, mark 0.3727), which he showed in a batch update telling members to take TP whenever they wanted rather than let trades round-trip. Two days later he posted that he was 'this close to closing SNX idk why but I just want to close', and that evening he closed the whole thing at 0.3626 for +55.80%, saying he expected a pullback and would re-open after Monday. | AB10: Expected a broad market pullback at the time he closed. | AD10: high | AE10: Closed on gut feel well short of the 0.39 target; the position had been +118.67% on the card 40 hours before he exited at +55.80%, so he gave back a good part of the move. He never re-opened SNX after Monday in this log. | AF10: #31, #36, #53, #56 | AG10: https://discord.com/channels/1042855255089623100/1501271173588193290/1502351744259063878
A11: 10 | B11: 2026-05-09 04:52:10 | C11: SYRUPUSDT | D11: long | E11: win | F11: manual_close | H11: 67.61 | I11: 25 | P11: 0.25328 | U11: 0.26013 | W11: 2026-05-09 04:52:10 | Y11: A leftover trade from his Journals that he had held for ten days; he still believed it would blow up but closed it out of impatience. | Z11: Only the exit of this trade falls inside the log. The share card shows a 25x long from 0.25328 closed at 0.26013 for +67.61%. He says he had been holding it for about ten days and was closing purely because it was getting annoying, adding that he was sure it would blow up right after he was out. Nothing about the original entry, stop or targets was ever posted here. | AD11: medium | AE11: Entry, stop and targets are unknown - the position was opened in his 'Journals' before this log begins, so entry_time and duration cannot be given. His '10 days' remark puts the entry around 2026-04-29 but he never states a date. | AF11: #38 | AG11: https://discord.com/channels/1042855255089623100/1501271173588193290/1502488322143162518
A12: 11 | B12: 2026-05-09 11:51:05 | C12: STABLEUSDT | D12: long | E12: win | F12: take_profit | H12: 231.02 | I12: 25 | J12: 0.0346 | K12: 0.0346 CMP, flagged as a swing that would take time | M12: 0.03 | N12: 0.04 | P12: 0.03459 | S12: 0.03737 | T12: 100% at 0.03737 | U12: 0.04 | V12: 2026-05-09 11:51:05 | W12: 2026-05-13 06:13:16 | X12: 90.4 | Y12: Swing long on a slow-moving shitcoin from 0.0346 up to the 0.04 round number, explicitly not for scalpers. | Z12: He called STABLE as a swing at 0.0346 CMP with a 0.04 target and a 0.03 stop, warning it would take time - and for three days it did nothing ('STABLE has been really STABLE'). On 12 May he added a first target at 0.03737 with the position +144% at 25x, then accidentally closed 100% of it right at that level for +200.92%, telling followers the 0.04 target was still valid but to take at least 50% there because it is resistance. Screenshots hours later showed he still had a live copy of the same long on MEXC (entry 0.03453, +248%), so he was not actually flat. On 13 May the full 0.04 target printed - a 20% unleveraged move, +231.02% ROI at 20x. | AA12: resistance | AB12: quiet tape; he pointed intraday traders at his BTC scalp instead | AD12: medium | AE12: Same idea run on two exchanges: entry 0.03459 at 25x on the first (closed by accident at 0.03737) and 0.03453 at 20x on MEXC (held to the 0.04 target). Treated as one position. avg_entry/leverage use the first card; the final exit price 0.04 is his stated target level, which he says was hit in full rather than a posted fill. | AF12: #44, #51, #82, #83, #84, #86, #89 | AG12: https://discord.com/channels/1042855255089623100/1501271173588193290/1502593742513635530
A13: 12 | B13: 2026-05-09 13:58:20 | C13: ETHUSDT | D13: long | E13: win | F13: manual_close | H13: 124.58 | I13: 100 | J13: 2310 | K13: 2310 CMP with 50% of size held back for the 2290 DCA | L13: 2290 | M13: 2260 | N13: 2350 | O13: DCA is 50% of size | P13: 2311.73 | S13: 2350 | U13: 2340.53 | V13: 2026-05-09 13:58:20 | W13: 2026-05-10 18:45:44 | X13: 28.8 | Y13: Weekend scalp long on ETH from 2310 CMP with a 50% DCA underneath at 2290. | Z13: He called the long at 2310 CMP with a 2290 DCA and a 2260 stop, and two minutes later put the target at 2350+, saying he would close manually. The position sat through the weekend and on 10 May he closed all of it at 2340.53 from an average of 2311.73 - +124.58% at 100x - calling it good enough for a weekend scalp. Two minutes after the screenshot went out, 2350 traded, so the target he had given was reached anyway. He never used the 2290 DCA. | AB13: weekend session | AD13: high | AE13: The original call carried no target; the 2350 level came two minutes later in MSG 46 and is recorded as the planned take profit. | AF13: #45, #46, #49, #50 | AG13: https://discord.com/channels/1042855255089623100/1501271173588193290/1502625769904406701
A14: 13 | B14: 2026-05-09 14:12:56 | C14: TAKEUSDT | D14: long | E14: not_taken | F14: not_taken | O14: Wanted at least 2 open positions closed before adding new ones. | Y14: TAKE looked good for a long but he was at his self-imposed position limit. | Z14: He posted that TAKE looked good for a long but that too many positions were already running - he wanted at least two closed before opening anything new - and signed off with 'see you at TPs'. No levels were given and TAKE is never mentioned again. | AD14: high | AE14: Pure pass; no entry, stop or target published. | AF14: #48 | AG14: https://discord.com/channels/1042855255089623100/1501271173588193290/1502629441908510731
A15: 14 | B15: 2026-05-11 00:40:45 | C15: ZROUSDT | D15: long | E15: win | F15: take_profit | H15: 215.72 | I15: 50 | J15: 1.486 | K15: re-entered at 1.486 in the same message that reported the previous ZRO position stopping at breakeven | L15: 1.42 | M15: 1.37 | N15: 1.55 | P15: 1.4772 | T15: 20% at 1.5369 | U15: 1.5457 | V15: 2026-05-11 00:40:45 | W15: 2026-05-11 12:32:58 | X15: 11.9 | Y15: An immediate re-entry of the same ZRO long seconds after the first one was stopped at breakeven - same idea and same 1.55 target, with a lower stop and a DCA at 1.42. | Z15: He announced the breakeven stop and the re-entry in the same message at 00:40 on 11 May: long again at 1.486, DCA 1.42, TP1 1.55, SL 1.37 - his card shows the fill at 1.4772. At 09:12 he booked 20% at 1.5369 for +189.93% and made a point of not moving the stop to entry, leaving the original 1.37 in place. Three hours later the 1.55 target filled: the card shows 1.5457 and +215.72%. He noted straight after that this was the second time he had milked the same setup. | AD15: high | AE15: He explicitly refused to move the stop to entry after the 20% partial, so the original 1.37 stood to the end. The 1.42 DCA is never reported as filling. | AF15: #57, #67, #72, #73 | AG15: https://discord.com/channels/1042855255089623100/1501271173588193290/1503149825196036228
A16: 15 | B16: 2026-05-11 02:30:48 | C16: BTCUSDT | D16: short | E16: win | F16: manual_close | H16: 109.47 | I16: 100 | J16: 82300 | K16: 82.3k CMP | L16: 83000 | M16: 83650 | N16: 80000, 81000 | P16: 82202.8 | U16: 81302.9 | V16: 2026-05-11 02:30:48 | W16: 2026-05-11 03:58:37 | X16: 1.5 | Y16: A counter-trend scalp short into the 82.3k spike, looking to cover in the 80-81k region. | Z16: He shorted at 82.3k CMP with a DCA planned higher at 83k and a stop at 83,650 (msg 59), then said he was looking to scalp it around 80-81k (msg 60). BTC sold off immediately so the 83k DCA never came into play, and he covered 88 minutes later at 81,302.90 from 82,202.80 for +109.47% on 100x - 'TPed, fast top short, closed' (msg 61). He banked it above his own 80-81k target zone rather than waiting for it, and immediately said he would flip long once price stabilised around 80k (msg 62). | AB16: He was openly bullish for the week, expecting 84-85k (msg 58), and took this quick top short against his own bias. | AD16: high | AE16: He calls it a TP, but the fill at 81,302.90 is above the 80-81k target zone, so it is recorded as a manual close in profit rather than a take-profit. | AF16: #59, #60, #61 | AG16: https://discord.com/channels/1042855255089623100/1501271173588193290/1503177518499233970
A17: 16 | B17: 2026-05-11 09:13:29 | C17: BTCUSDT | D17: long | E17: win | F17: manual_close | H17: 109.31 | I17: 100 | J17: 80900 | K17: 80.9k CMP in the public call; he had already started scaling in from 80.6k before publishing it (msg 68). No DCA on this one. | M17: 79500 | N17: 81500, 81600 | O17: He kept the wider 79.5k stop, 'playing safe here, scalp'; a tighter optional stop at 79,750 was offered to followers (msg 71) | P17: 80914.2 | S17: 81500/81600 | U17: 81798.7 | V17: 2026-05-11 09:13:29 | W17: 2026-05-11 19:32:08 | X17: 10.3 | Y17: Long the 80k region on the view that if the 80s hold, BTC runs to 84k - traded as a scalp he intended to close manually around 81.5-81.6k. | Z17: He said he would long once BTC stabilised, with the 80k region as the place he wanted (msg 62), then started scaling in privately from 80.6k with a 79.5k stop and posted the running 150x card at +51.78% (msg 68). Once confident he published the formal call at 80.9k CMP with no DCA and the same 79.5k stop (msg 70), offering followers a tighter 79,750 stop while keeping the wider one himself (msg 71). Mid-afternoon he said he would close manually targeting 81.5-81.6k (msg 74). He closed the whole position that evening (msg 75) and posted the proof card: entry 80,914.20, exit 81,798.70, +109.31% on 100x (msg 76) - above his own stated target. | AA17: support/resistance | AB17: Right after covering the top short; he wanted price to stabilise before longing, and read 80k holding as the trigger for a run to 84k. | AD17: high | AE17: One position run on more than one account: the entry card (msg 68) is 150x and the closing card (msg 76) is 100x. Leverage and ROI record the closing card. The 80.6k private scale-in and the 80.9k published entry are the same trade, not two. | AF17: #62, #68, #69, #70, #71, #74, #75, #76 | AG17: https://discord.com/channels/1042855255089623100/1501271173588193290/1503199754027270164
A18: 17 | B18: 2026-05-12 04:30:58 | C18: BTCUSDT | D18: long | E18: loss | F18: stop_loss | J18: 81300 | K18: Half at 81.3k, half at the 80.7k DCA; he flagged it as slightly risky so followers could go half risk or simply enter at the DCA | L18: 80700 | M18: 79500 | O18: Slightly risky - half risk or DCA-only entry suggested for followers | P18: 81000 | Q18: 80700 (DCA leg filled 20 minutes after the call, blended average 81k and already in profit) | S18: 82000 -> 82000 | V18: 2026-05-12 04:30:58 | W18: 2026-05-13 18:15:09 | X18: 37.7 | Y18: Another BTC scalp long, from 81.3k with a DCA at 80.7k, wanting a 4h close above 81.1k to open a run to 82k. | Z18: He called it at 81.3k with a DCA at 80.7k and a 79.5k stop, telling followers it was slightly risky so they could halve risk or just enter at the DCA (msg 79). The DCA filled 20 minutes later at a perfect level - 'if you entered at DCA you sniped' - taking his average to 81k in profit (msgs 80-81). By the next morning it was back around breakeven (msg 90); he said he needed a 4h close above 81.1k to get 82k, then set the official TP at 82k while flagging that he would probably exit early at 81.5-81.6k (msg 98). Price missed that trim level by about $150 and reversed into his stop: 'Sorry guys lost on BTC, stayed above profits for a long time but didn't TP, wanted to trim first @ 81.5k but missed by 150$' (msg 99). He re-entered a new long a minute later. | AA18: 4h close | AB18: Continuation of his bullish 84-85k week view after two profitable BTC scalps. | AD18: high | AE18: The loss is stated plainly but no exit price or card was posted - 79.5k is his published stop, not a confirmed fill. Average entry 81k is his own figure. The call carried no TP; the 82k target only appeared on 05-13. | AF18: #79, #80, #81, #90, #98, #99 | AG18: https://discord.com/channels/1042855255089623100/1501271173588193290/1503570149297360977
A19: 18 | B19: 2026-05-12 15:01:26 | C19: XRPUSDT | D19: long | E19: win | F19: manual_close | H19: 23.45 | I19: 100 | J19: 1.448 | K19: 1.448 CMP | M19: 1.4 | N19: 1.5, 1.525 | P19: 1.4497 | U19: 1.4531 | V19: 2026-05-12 15:01:26 | W19: 2026-05-14 17:30:30 | X19: 50.5 | Y19: Long XRP at market with targets at 1.5 and 1.525 and a 1.4 stop; no reasoning was given with the call. | Z19: He called the long at 1.448 CMP with two targets and a 1.4 stop. It went nowhere for two days and sat around breakeven, and on 14 May price nearly touched his stop, which he read as the setup being invalidated - so he closed at 1.4531 from 1.4497 for a token +23.45% at 100x rather than risk the full stop. Minutes later it broke out, and by that evening it had run to 1.5431, through both of his targets. He posted the chart himself and called it a fumble, saying the idea was right even though he had exited early. | AB19: not stated | AD19: high | AE19: Closed for a tiny profit, so it counts as a win, but he treats it as a fumbled trade because the full target hit after he was out. | AF19: #85, #90, #108, #110, #124 | AG19: https://discord.com/channels/1042855255089623100/1501271173588193290/1503728811768811663
A20: 19 | B20: 2026-05-13 06:41:20 | C20: ETHUSDT | D20: long | E20: unknown | F20: unknown | J20: 2293 | K20: 2293 CMP; the message went out late and he confirmed the entry was still good at 2298 | M20: 2245 | N20: 2336 | O20: Risky trade go half | S20: 2336 | V20: 2026-05-13 06:41:20 | Y20: Risky market long on ETH with a 2245 stop, taken at half size - 'I hate ETH'. | Z20: He called the long at 2293 CMP with a 2245 stop, flagged it as risky and told people to go half size. Eleven seconds later he noted the message had gone out late and that 2298 was still a valid entry. Forty minutes after that he gave the first target, 2336, joking that he would take a break if ETH broke his streak. Nothing in the log ever says how this one ended. | AB20: not stated | AD20: low | AE20: No exit, stop-out or update of any kind after MSG 95. He floats a fresh ETH long idea on 16 May, so this one had presumably been closed or stopped by then, but nothing states it - outcome left unknown. | AF20: #91, #92, #95 | AG20: https://discord.com/channels/1042855255089623100/1501271173588193290/1503965346304884828
A21: 20 | B21: 2026-05-13 06:52:43 | C21: SOLUSDT | D21: long | E21: win | F21: manual_close | H21: 17.79 | I21: 100 | J21: 95.5 | K21: 95.5 CMP | M21: 93.5 | N21: 97 | P21: 95.53 | U21: 95.7 | V21: 2026-05-13 07:02:05 | W21: 2026-05-13 12:11:15 | X21: 5.2 | Y21: He thought SOL was a much better long from CMP than the ETH trade he had already called, so he offered SOL as an optional add-on long. | Z21: Ten minutes after saying SOL looked a lot better to long than the ETH he had already called, he posted the SOL long at 95.5 CMP with TP 97 and SL 93.5, framed as optional ('if anyone's looking long for SOL'). Five hours later he closed it himself at 95.7 for a token +17.79% on 100x, explicitly to stay on the safe side and protect his streak while his other three longs ran. Twenty seconds after that he told risk-tolerant members the setup was still valid and they could keep it running rather than close with him. | AD21: high | AE21: He exited early for streak-protection reasons rather than at the 97 target; the follower guidance (keep it running) differs from his own action and is recorded in the story only. | AF21: #93, #94, #96, #97 | AG21: https://discord.com/channels/1042855255089623100/1501271173588193290/1503968208800190536
A22: 21 | B22: 2026-05-13 18:16:30 | C22: BTCUSDT | D22: long | E22: win | F22: manual_close | H22: 202.99 | I22: 100 | J22: 79400 | K22: CMP entry (msg 101) with about 25% of size held back for the DCA | L22: 79000 | M22: 77900 | N22: 82000 | O22: Save some for DCA - around 25%, half of what you're putting on now | P22: 79284.35 | Q22: 79000 (25% DCA filled - confirmed when he posted the 79.2k average running in heavy profit; the actual fill time was never stated) | U22: 80893.8 | V22: 2026-05-13 18:16:30 | W22: 2026-05-14 18:02:51 | X22: 23.8 | Y22: Immediate re-entry after the stop-out: long 79.4k CMP with 25% kept back for a 79k DCA, targeting 82k, on his scripted path of a dip to 78.5k, a bounce and a news-driven push to 81-82k. | Z22: He called the re-entry within a minute of announcing the previous loss - long 79.4k CMP, 25% saved for a DCA (msgs 100-101) - and gave the DCA level as 79k two minutes later (msg 102). The DCA filled and by the following afternoon he showed the position at an average of 79.2k running in heavy profit (msg 108), with a card at 79,284.35 and +108.28% on 100x (msg 109), noting BTC was moving exactly as he had mapped it (msg 111). He closed the whole position at about 81k for +202.99% on 100x - card 79,284.35 to 80,893.80 - saying it made back the losses from both earlier stop-outs (msg 112). He then posted the same trade from two other accounts: BloFin 30x, 79,313.40 to 80,926.40, +61% (msg 115), and a 250x card at +448.51% (msg 116). | AA22: news | AB22: Clarity-act headlines were the catalyst; he had publicly scripted the move - dip to 78.5k, bounce, news, 81-82k (msgs 111, 121). | AD22: high | AE22: One position run on at least three accounts (100x main, BloFin 30x, 250x) - the three cards are not three trades. He exited at ~81k, below his published 82k target. Stated average 79.2k vs 79,284.35 on the card; the BloFin card shows 79,313.40. | AF22: #100, #101, #102, #108, #109, #111, #112, #115, #116 | AG22: https://discord.com/channels/1042855255089623100/1501271173588193290/1504140287096651806
A23: 22 | B23: 2026-05-14 03:17:11 | C23: SOLUSDT | D23: long | E23: win | F23: manual_close | H23: 45.03 | I23: 100 | J23: 91.25 | K23: 91.25 CMP | M23: 87.5 | O23: Soft stop was a 4h close under 88, with a hard stop at 87.5. | P23: 91.05 | R23: None (tightened_unspecified) | U23: 91.46 | V23: 2026-05-14 03:17:11 | W23: 2026-05-14 17:30:30 | X23: 14.2 | Y23: A second SOL long at market the morning after the first one, with the stop defined on a 4h close under 88 rather than a hard level. | Z23: He longed SOL again at 91.25 CMP, publishing no target and a two-part stop: a 4h close under 88, or a hard 87.5. Thirty-six minutes later he said he had modified the SOL stop because the trade was already in profit, but never gave the new level. That afternoon he closed SOL together with XRP 'in minor profits' - his card shows entry 91.05, close 91.46, +45.03% on 100x. | AA23: 4h close | AD23: high | AE23: The stop move at msg 106 has no level attached - he only said it was modified and that members could adjust too, so 'to' is null. | AF23: #103, #106, #108 | AG23: https://discord.com/channels/1042855255089623100/1501271173588193290/1504276354516910202
A24: 23 | B24: 2026-05-14 03:18:10 | C24: BBUSDT | D24: long | E24: win | F24: manual_close | H24: 116.46 | I24: 25 | J24: 0.03535 | K24: 0.03535 CMP, risky half-margin trade | M24: 0.3 | N24: 0.39, 0.41 | O24: Flagged risky - half margin. | P24: 0.03538 | S24: 0.404 | U24: 0.0371 | V24: 2026-05-14 03:18:10 | W24: 2026-05-15 03:20:30 | X24: 24 | Y24: A deliberately risky, half-margin long on BB taken at market a minute after the SOL long. | Z24: He called BB long at 0.03535 CMP as a risky half-margin trade, posting TP 0.39-0.41 and SL 0.3. Thirty-five minutes later he dropped the first target - 'Remove the first TP 0.039 will take full TP around 0.404' - so his own plan became a single full exit. A day later he admitted he had 'totally forgot about this one' and closed early at 0.0371 for +116.46% on 25x rather than waiting for the target. | AD24: medium | AE24: Levels recorded exactly as posted, but the decimals are almost certainly wrong: with a 0.03535 entry the TP 0.39-0.41 and SL 0.3 should read 0.039-0.041 and 0.03 - his own follow-up message calls the first target '0.039' while the revised full TP is written '0.404'. The exit at 0.0371 sits between the plausible 0.039 target and the entry, consistent with the dropped-decimal reading. | AF24: #104, #105, #127 | AG24: https://discord.com/channels/1042855255089623100/1501271173588193290/1504276604292042863
A25: 24 | B25: 2026-05-14 10:40:51 | C25: ENSUSDT | D25: long | E25: win | F25: manual_close | H25: 161.15 | I25: 50 | J25: 6.89 | K25: 6.89 CMP | M25: 6.3 | N25: 7.69 | P25: 6.9 | T25: 50% at 7.171 | U25: 7.135 | V25: 2026-05-14 10:40:51 | W25: 2026-05-14 19:19:52 | X25: 8.7 | Y25: Long ENS at market towards 7.69, with a soft stop defined as a 1h close under 6.3 rather than a hard level. | Z25: He called ENS long at 6.89 CMP with the stop set as a 1h close under 6.3 and a 7.69 target. By late afternoon it was +141.91% at 50x from 6.900 and he was holding for 'fat profits'. At 7.171 he took 50% off (+190.71%) and told followers they could close the whole thing there. An hour later he was completely out at 7.135 for +161.15%, well short of the 7.69 target. | AA25: 1h close | AB25: not stated | AD25: high | AE25: The 6.3 stop was a 1h-close condition, not a hard level. Exit came at 7.135, below the 7.171 partial, because he closed the rest after a small pullback. | AF25: #107, #109, #113, #120 | AG25: https://discord.com/channels/1042855255089623100/1501271173588193290/1504388009280278589
A26: 25 | B26: 2026-05-14 20:27:12 | C26: BTCUSDT | D26: long | E26: loss | F26: stop_loss | J26: 81300 | K26: 81.3k CMP (msg 123), half margin by his own instruction | L26: 80800 | M26: 79500 | N26: 83000, 84000 | O26: HALF MARGIN, self-declared gamble - 'Don't lose today's profits on it, go low!' | P26: 81300 | V26: 2026-05-14 20:27:12 | W26: 2026-05-16 04:15:48 | X26: 31.8 | Y26: A self-described gamble long at 81.3k straight after the pump to 82k, targeting the daily high around 83k, or 84k if he saw strength. | Z26: He called it at 81.3k CMP with a DCA at 80.8k and 79.5k written as 'Sleep' (his wording for the stop), targeting the daily high at 83k or 84k, and stressed it was a half-margin gamble that should not cost anyone the day's profits (msgs 122-123). Price ran to 82k almost immediately - a clean scalp exit he chose not to take because he was holding out for 83k. He confirmed he was still holding the next morning (msg 127), then BTC rolled over and stopped him: 'Lost the BTC gamble trade. My fault there when we longed from 81.3k it immediately went to 82k, a good TP for scalp I could have exit there but was trying for 83k. My mistake on this one. The good part was I mentioned use less margin on this' (msg 128). | AA26: daily high | AB26: Immediately after the clarity-act pump to 82k that he had called from 79k (msg 121); he expected a slow grind and then a Sunday weekend pump (msg 126). | AD26: high | AE26: No card or exit price was posted; 79.5k is the published stop. Whether the 80.8k DCA filled is never stated - price traded through it on the way down, so the realised loss may be bigger than the call implies. avg_entry 81,300 is his own restatement of the entry in msg 128, not an exchange figure. | AF26: #122, #123, #127, #128 | AG26: https://discord.com/channels/1042855255089623100/1501271173588193290/1504535567663235103
A27: 26 | B27: 2026-05-15 02:59:36 | C27: HBARUSDT | D27: long | E27: loss | F27: stop_loss | J27: 0.0948 | K27: CMP | M27: 0.089 | N27: 0.1, 0.105 | V27: 2026-05-15 02:59:36 | W27: 2026-05-18 03:50:21 | X27: 72.8 | Y27: Straight long on HBAR at market with a 0.1-0.105 target zone; no reasoning beyond the levels was posted. | Z27: He called the long at 0.0948 CMP with a 0.089 stop and targets at 0.1-0.105, and confirmed twenty minutes later that HBAR and BTC were what he was still holding. It went nowhere for a day and a half; on 16 May he said HBAR was grinding back toward his entry and that he would look to close it around breakeven. That never happened - on 18 May he reported 'HBAR hit SL', so it closed at a full loss instead of the breakeven he wanted. | AD27: medium | AE27: He never restated a fill or an exit price, so avg_entry and exit_price are null; his published entry was 0.0948 and his published stop 0.089. The side on the stop-out message is inferred from the original call (the extractor flagged msg 144 as medium confidence). No R figure was given for the loss. | AF27: #125, #127, #139, #144 | AG27: https://discord.com/channels/1042855255089623100/1501271173588193290/1504634318503546950
A28: 27 | B28: 2026-05-16 04:23:08 | C28: PARTIUSDT | D28: long | E28: unknown | F28: unknown | J28: 0.0615 | K28: 0.0615 CMP with a 30% DCA leg below | L28: 0.586 | M28: 0.0525 | N28: 0.07, 0.075 | O28: DCA leg is 30% of the position | P28: 0.606 | Q28: None (fill implied by the average moving to 0.606 (as posted; reads as 0.0606) with the position in profit - he never posted a fill price) | V28: 2026-05-16 04:23:08 | Y28: A PARTI long at market with a 30% DCA leg underneath and targets in the 0.07-0.075 band. No reasoning was published beyond the levels. | Z28: He called it at 0.0615 CMP on the morning of 16 May with a 30% DCA leg (posted as 0.5860, which reads as 0.0586), targets 0.07-0.075 and a 0.0525 stop. Fifteen hours later he reported the average had moved to 0.606 - again a dropped decimal, reading as 0.0606 - and that the position was in profit, which implies the DCA leg filled. PARTI is never mentioned again: no exit, no stop, no result. | AC28: yes | AD28: medium | AE28: Two of his numbers are missing a decimal place - the DCA posted as 0.5860 and the average posted as 0.606 against a 0.0615 entry - and both are recorded exactly as posted rather than corrected. The DCA fill is inferred from the changed average. The position drops out of the log after 16 May with no outcome of any kind. | AF28: #129, #139 | AG28: https://discord.com/channels/1042855255089623100/1501271173588193290/1505017728887689278
A29: 28 | B29: 2026-05-16 04:26:35 | C29: LINKUSDT | D29: long | E29: not_taken | F29: not_taken | K29: CMP, and only if strength appeared in the market | M29: 9.6 | Y29: LINK looked good for a long, but there was no strength in the broader market, so the idea was conditional on strength showing up. | Z29: This was guidance rather than a trade he took: LINK looked good for a long but the market had no strength, so he told the group that if they saw some strength coming they could long it from CMP with a 9.6 stop. He never posted an entry of his own and never followed up, so nothing was managed or closed. | AB29: no strength in the market | AD29: medium | AE29: Conditional follower guidance with a stop but no entry price or target. There is no evidence he took it himself, hence not_taken. The later LINK mentions (msgs 995, 999) are about his spot bag and are tracked as a separate position. | AF29: #130 | AG29: https://discord.com/channels/1042855255089623100/1501271173588193290/1505018596701638706
A30: 29 | B30: 2026-05-16 12:58:40 | C30: ETHUSDT | D30: long | E30: breakeven | F30: breakeven | I30: 100 | J30: 2170 | K30: floated as a 5m-timeframe idea at 2170 CMP, then actually entered at 2172 CMP with 0.5% margin/risk | M30: 2145 | O30: Just an idea, won't count TP or SL, not an official trade; entered with 0.5% margin/risk only - SCALP and SMALL margin | P30: 2173.61 | T30: 25% at 2194.45 | V30: 2026-05-16 13:35:54 | W30: 2026-05-18 03:50:15 | X30: 38.2 | Y30: A low-timeframe (5m) ETH long for people who like LTF entries, deliberately not counted as an official call and taken with tiny margin. | Z30: He floated the 5m long at 2170 with a 2145 stop as 'just an idea, not an official trade', then 37 minutes later actually entered at 2172 using only 0.5% margin, stressing it was a scalp on small size. That evening the bounce looked weak and he offered anyone in small profit the chance to exit, saying he was taking his chance; the next day it was still crawling ('shits always the slowest'). On 17 May it went past 1R at 2194.45 (+90.57% at 100x) and he told followers they could take 25-50% off there, and later that the entry was still valid with the same 2145 stop. It then round-tripped and closed flat - 'ETH hit BE' - on 18 May. | AA30: 5m timeframe | AB30: weak bounce, he expected lower prices | AD30: medium | AE30: The 25% partial at 1R is phrased as advice to followers ('you can take 25-50% here'), so whether he trimmed himself is unclear; if he did, the net result is a small win rather than flat. He posted no breakeven price. Recorded as breakeven because that is how he reported the close. | AF30: #135, #136, #137, #138, #139, #140, #142, #143 | AG30: https://discord.com/channels/1042855255089623100/1501271173588193290/1505147469187645451
A31: 30 | B31: 2026-05-16 12:58:40 | C31: BTCUSDT | D31: long | E31: unknown | F31: unknown | J31: 78000 | K31: CMP at the time (78k), a 5m-timeframe entry for people who like LTF entries | M31: 77700 | O31: Explicitly not an official trade - 'Just an idea won't count TP or SL' | Y31: A 5m-timeframe scalp long inside the 77.7-78.1k weekend reversal zone he had flagged that morning. | Z31: In the morning he said the weekend reversal zone should be 77.7-78.1k and that he would try a scalp there, re-posting the plan as a screenshot (msgs 133-134). At 12:58 he gave the entry for LTF traders - long at CMP 78k with a 77.7k stop - but framed it explicitly as an idea that would not count as an official trade with a TP or SL (msg 135). No fill, result or close was ever posted for it, and the next BTC idea came six hours later with a different (76.9k) stop. | AA31: 5m timeframe, 4h close | AB31: Weekend. He expected 77.7-78.1k to be the reversal zone, a bounce there to target 79-80k, and a 4h close below 77.7k to open 75-76k (msgs 133-134). | AD31: low | AE31: Kept as a position because it was published as a call with an entry and a stop, but he said it would not count and no fill or exit was ever posted, so outcome is not_taken. It may in fact be the trade behind the 78,041.30 / 150x card in msg 141, which is attached here to the later msg 139 idea. Separately that morning he published a conditional plan to limit-long 76,850 with TP 80-82k and SL 75k if BTC lost the level (msgs 131-132); BTC bottomed around 77.7k so that limit never came into play and it is not recorded as a position. [AUDIT] Audit: he never refused this trade — "won't count TP or SL, not an official trade" is a stats disclaimer, and MSG 141 shows his own 150x card from 78,041.3 at this level. Outcome changed from not_taken to unknown. | AF31: #133, #134, #135 | AG31: https://discord.com/channels/1042855255089623100/1501271173588193290/1505102808389783632
A32: 31 | B32: 2026-05-16 19:29:46 | C32: BTCUSDT | D32: long | E32: unknown | F32: unknown | I32: 150 | K32: CMP at 05-16 19:29 - no price given in the call; the card he posted the next day shows an entry of 78,041.30 | M32: 76900 | O32: Offered as an optional idea - 'if anyone wants to try BTC long' | P32: 78041.3 | V32: 2026-05-16 19:29:46 | Y32: He thought BTC had bottomed for the weekend, so he offered a long from market with a stop under 76.9k. | Z32: He posted it as an optional idea: 'If anyone wants to try BTC long you can from CMP with SL 76.9k think we bottomed for weekend' (msg 139). The next afternoon he showed it running in profit - 150x card, entry 78,041.30 against 78,494.90, +87.18% - with 'BTC moving too if anyone took that idea' (msg 141), and said the entry was still valid from there with the same stop even though price was up from it (msg 142). The following evening he added that probably nobody took it although it was near the bottom and valid, and used it to explain that he often runs two BTC setups at once: scalps he does very often (high win rate, low RR) and swings (low win rate, high RR) (msg 149). No exit, close or result was ever posted for this one. | AB32: Weekend bottom-fishing after the gamble long was stopped; BTC was holding the 4h support / 200 EMA region around 77.7k. | AD32: low | AE32: Outcome unknown - he never closed it publicly and never referred to it again after msg 149, while separately running the 05-18 long. The 78,041.30 / 150x card is linked here because msg 142 repeats the 76.9k stop of this idea, but it could equally belong to the msg 135 LTF idea at 78k. still_open_at_end is false because nothing in the log tracks it any further, not because a close was stated. | AF32: #139, #141, #142, #149 | AG32: https://discord.com/channels/1042855255089623100/1501271173588193290/1505245889567002787
A33: 32 | B33: 2026-05-18 03:50:36 | C33: BTCUSDT | D33: long | E33: win | F33: manual_close | G33: 1 | H33: 219.32 | I33: 150 | J33: 77000 | K33: 77k CMP; 50% of size held back for the 76.4k DCA | L33: 76400 | M33: 75400 | P33: 76704.7 | Q33: 76400 (50% DCA filled, average entry 76.7k and in profit) | S33: 77800 -> 78500 | U33: 77826.3 | V33: 2026-05-18 03:50:36 | W33: 2026-05-21 04:30:48 | X33: 72.7 | Y33: Swing long from 77k with a 76.4k DCA, playing the weekend bottom and the reclaim of the 200 EMA on lower timeframes for a move to 78k+. | Z33: He called it at 77k CMP with a 75.4k stop and no target (msg 145), adding a 50% DCA at 76.4k a minute later (msg 146). Being busy that day, he left contingency instructions for followers - take 20-25% around 77.8k and move the stop to entry if he did not update (msg 147) - but kept managing it himself and reported no changes that evening (msg 148). The DCA filled at 76.4k, taking his average to 76.7k in profit (msg 152). He held through the weekend showing the 150x card at 76,704.70 (msg 160) and pointed to the 200 EMA reclaim as confirmation (msg 162). At around 1R he told members to take partials whenever they liked while stating he personally avoids partials, especially on BTC, and that he was holding for about 78.5k (msg 167). He closed the whole position the next morning at 77,826.30 for +219.32% on 150x: 'BTC closed here, over 1R + with a DCA great profits for me' (msg 170). | AA33: EMA 200 | AB33: After the weekend flush; BTC reclaimed the 200 EMA on lower timeframes after about two days, which he read as bullish for the position. | AD33: high | AE33: r_multiple is his own words - 'over 1R' - recorded as 1.0, which understates it slightly; it is not computed from prices. The 77.8k trim and the stop-to-entry move (msg 147) were contingency guidance for followers - he took no partials and never posted a stop move himself. Around this trade (msg 149) he explained he sometimes runs a scalp and a swing BTC setup at the same time, which is why an earlier 05-16 idea may still have been open alongside it. | AF33: #145, #146, #147, #148, #152, #160, #162, #167, #170 | AG33: https://discord.com/channels/1042855255089623100/1501271173588193290/1505734318432059444
A34: 33 | B34: 2026-05-18 17:05:56 | C34: BOMEUSDT | D34: long | E34: win | F34: take_profit | H34: 165.91 | I34: 25 | J34: 0.000599 | K34: 0.000599 CMP, framed as a scalp on a shitcoin | M34: 0.00053 | N34: 0.00064, 0.000669 | O34: manage your risk; small accounts should close entirely at the first partial | P34: 0.0005998 | R34: 0.0005998 (to_entry) | T34: 25% at 0.0006203 | V34: 2026-05-18 17:05:56 | W34: 2026-05-19 10:30:37 | X34: 17.4 | Y34: A scalp on a shitcoin - long BOME at 0.000599 towards 0.00064-0.000669, with the stop set as a 4h close under 0.00055 or a hard 0.00053. | Z34: He opened the scalp at 0.000599 CMP with targets at 0.00064-0.000669 and a hard stop at 0.00053. Twenty minutes in he pointed out BOME was holding its level despite the BTC dump but warned it could still turn. Overnight he banked 25% at 0.0006203 (+80.8% at 25x) and moved the stop to entry, telling small accounts to just close the whole thing there or exit at the first target. By late morning BOME had exploded through the first target and he took profit at 0.000643 for +165.91%. | AA34: 4h close | AB34: BTC dumping while BOME held up | AD34: medium | AE34: He does not say whether the 'TP' at 0.000643 closed the rest of the position or was another partial, so the exit is recorded at that level. On 3 Aug (MSG 866) he mentions seeing a BOME short opportunity but explicitly does not take it - no position from that. [AUDIT] Audit: 0.000643 is the mark price on an open-position ROI card, not a close — exit_price cleared to null. The 25% partial comes from "Take 25%" (follower instruction), so it may not be his own action. | AF34: #150, #151, #154, #156 | AG34: https://discord.com/channels/1042855255089623100/1501271173588193290/1505934468681306273
A35: 34 | B35: 2026-05-18 22:14:08 | C35: ZECUSDT | D35: long | E35: win | F35: take_profit | G35: 1 | H35: 493.44 | I35: 75 | J35: 544 | K35: 544 CMP | M35: 505 | N35: 580, 600 | P35: 545.99 | Q35: 582 ('saw strength and added alot at 582' - the added leg's own card shows entry 580.25. The add happened before this message, which is where he explains the changed average) | R35: 545.99 (to_entry) | S35: 592 | T35: 20% at 572.12 | 581.92 | U35: 592 | V35: 2026-05-18 22:14:08 | W35: 2026-05-20 09:20:47 | X35: 35.1 | Y35: Long ZEC at 544 for a push into the 580-600 band - and when it got there he added heavily on strength rather than getting out, then took the whole thing off at 592. | Z35: He called it at 544 CMP with a 505 stop and 580-600 targets. Six hours in, with the 75x card at +358.87%, he took 20% at 572.12 and moved the stop to his 545.99 entry, saving the majority for the targets. At 21:04 the first target hit at 581.92 for what he called about 1R and he booked the majority there, naming 592 as the full exit. He then added a lot at 582 on strength, changing his average - a second card shows that leg entered at 580.25. On the morning of 20 May the 592 exit filled and he was fully out, saying he believed it would go higher but was happy to leave. The added leg's card confirms it closed at 591.75 for +148.59%. | AB35: shit market | AD35: high | AE35: Two entry figures coexist: the card's 545.99 and his own 'the original entry was from 540'. The 1R is his description of the 581.92 take-profit, not a final tally for the trade. Msg 166 is a verbatim repost of msg 163, so the 582 add is counted once. | AF35: #153, #155, #158, #163, #164, #165, #166 | AG35: https://discord.com/channels/1042855255089623100/1501271173588193290/1506012029968977950
A36: 35 | B36: 2026-05-19 10:48:14 | C36: SUIUSDT | D36: long | E36: win | F36: take_profit | H36: 308.25 | I36: 50 | J36: 1.09 | K36: 1.09 CMP, deliberately taken small so there was room to add | M36: 1.01 | O36: Personally took a small position, scalp; the DCA was optional and only for anyone not already sized up | P36: 1.0738 | Q36: None (a small 25% DCA - he only gave the resulting average, 1.076. The separate DCA card in msg 173 shows a 100x leg entered at 1.0481) | R36: 1.0 (widened) | S36: 1.14/1.23 | U36: 1.14 | V36: 2026-05-19 10:48:14 | W36: 2026-05-21 05:57:24 | X36: 43.2 | Y36: A small scalp long on SUI at 1.09, sized down on purpose so he had room to add into weakness rather than defend a big position. | Z36: He called it as a small scalp at 1.09 CMP with a 1.01 stop and no target. Overnight he widened the stop to 1.00, saying the position was small enough to absorb it, and on the morning of 20 May added a small 25% DCA that brought his average to 1.076 - optional, and only for anyone not already in heavy. On 21 May he finally gave targets: 1.14 for himself, 1.23 for anyone holding longer, with the 50x card at +170.83%. The 1.14 filled less than an hour after he posted it and he called it a good start to the day. A second card shows the DCA leg, a 100x from 1.0481, closing at 1.1401 for +877.77%. | AD36: high | AE36: He ran this on two cards at once - a 50x leg (entry 1.0738) and a 100x DCA leg (entry 1.0481) - which is one position, not two. His stated average after the DCA (1.076) matches neither card exactly, and the DCA fill price was never posted. | AF36: #157, #159, #161, #171, #172, #173 | AG36: https://discord.com/channels/1042855255089623100/1501271173588193290/1506201807385264220
A37: 36 | B37: 2026-05-20 20:35:41 | C37: BONKUSDT | D37: long | E37: win | F37: unknown | H37: 199.88 | I37: 75 | J37: 0.614 | K37: 0.614 CMP in his quoted scale; he later apologised that the posted entry may be off because of a sharp pump | M37: 0.578 | N37: 0.6323 | P37: 0.006158 | T37: 20% at 0.006323 | V37: 2026-05-20 20:35:41 | Y37: Long BONK at market with a first target at 0.6323 and a 0.578 stop; no reasoning given beyond the momentum. | Z37: He called BONK long at 0.614 CMP with a first target at 0.6323 and a 0.578 stop, then apologised six minutes later that a wicked pump may have made the posted entry unreachable, telling people to take only a small amount of profit at the level given and promising to post when he took a proper TP or exited. Two days later the first target printed and he booked 20-25% at 0.006323 (+199.88% at 75x on his 1000BONK card), explicitly keeping the majority running. He never posted the promised exit for that remainder. | AB37: sharp pump right as the call went out | AD37: medium | AE37: Price scale differs between his call and his card: the call quotes 0.614 / 0.6323 / 0.578 while the share card is 1000BONKUSDT at 1/100 of those numbers (entry 0.006158, TP 0.006323). Same trade, two scales - planned_* are in his quoted scale, avg_entry and the partial are card prices. Outcome recorded as a win because he banked a profitable partial; the fate of the majority he 'saved' is never reported. [AUDIT] Audit: outcome graded win is slightly overstated — only 20-25% was booked and the "majority saved" is never accounted for. | AF37: #168, #169, #186 | AG37: https://discord.com/channels/1042855255089623100/1501271173588193290/1506712029807775888
A38: 37 | B38: 2026-05-21 15:31:36 | C38: BTCUSDT | D38: long | E38: loss | F38: stop_loss | I38: 150 | J38: 77000 | K38: 77k CMP (msg 178), with a 76k DCA leg | L38: 76000 | M38: 75300 | N38: 78000 | P38: 77065.1 | S38: 78400 | V38: 2026-05-21 15:31:36 | W38: 2026-05-23 08:19:49 | X38: 40.8 | Y38: The same setup that had just worked - long 77k with a 76k DCA targeting 78k+ - on a bullish-into-the-weekend view he intended to hold until the 24th-25th. | Z38: He called it at 77k CMP with a DCA at 76k and a 75.3k stop (msgs 177-178) and set the target at 78k+, calling it 'the same last setup playing again' (msg 179). That evening he posted the open card at 77,065.10, +153.7% on 150x, to answer chat claims he was getting rekt (msg 180). He told members they could TP as they liked or bank 10% to cover fees and move the stop to entry (msg 181), but was explicit that he had not taken profit and would not move his own stop: 'Personally didn't move SL to entry, will play full setup either SL or TP (78.4k+)' (msg 182). BTC crashed overnight on the 23rd and this was one of the stops: 'we had a couple stop losses on the crash last night ... BTC hurt especially since it missed our TP by 200$ many times' (msg 193). He then said he was waiting for 74k to long and make the BTC SL back. | AB38: He was publicly bullish on BTC until the weekend of the 24th-25th (msg 176) and was being told in chat he was getting rekt for being long while everyone else was shorting (msg 180). | AD38: medium | AE38: The loss is implied rather than stated for this position - msg 193 reports 'a couple stop losses on the crash' and singles BTC out, and msg 198 talks about making the BTC SL back. No exit price or card was posted; 75.3k is the published stop, and the exit time is the announcement, not the actual overnight fill. Whether the 76k DCA filled during the crash is never stated, so the realised loss may be larger than the call implies. | AF38: #177, #178, #179, #180, #181, #182, #193 | AG38: https://discord.com/channels/1042855255089623100/1501271173588193290/1506997895264600195
A39: 38 | B39: 2026-05-22 11:51:14 | C39: WLDUSDT | D39: long | E39: win | F39: take_profit | G39: 1 | H39: 542.25 | I39: 100 | J39: 0.284 | K39: two options - 0.279 on limit or 0.284 at market; his own card shows the 0.284 CMP entry | L39: 0.279 | M39: 0.265 | N39: 0.3, 0.32 | O39: Risky because I kept SL closer than usual but worth a shot | P39: 0.284 | R39: 0.284 (to_entry) | T39: 25% at 0.2908 | V39: 2026-05-22 11:51:14 | W39: 2026-05-22 18:35:51 | X39: 6.7 | Y39: Long WLD with a tighter-than-usual stop, playing for the 0.3-0.32 area. | Z39: He posted the long with two entry options - 0.279 on limit or 0.284 at market - and flagged it as risky because the 0.265 stop was tighter than he normally keeps. Five hours later WLD came within 0.002 of the target without filling it: he told members to bank 25-50% and moved the stop to entry, noting the move was worth 1.5R from the limit entry but only 0.9R from CMP, then added that anyone filled on the limit was already above 1R and could simply close the lot. Two hours after that the first target filled and he closed his whole position - 1.5R from limit, 1R from CMP - while saying he was confident the weekend might still give the full target. | AB39: he expected the weekend to extend the move | AD39: medium | AE39: His own entry was the 0.284 CMP fill shown on his card, so his personal result is the 1R figure; the 1.5R he quotes belongs to anyone filled on the 0.279 limit. He never restated the exit price - the closing card shows +542.25% on 100x and the call's first target was 0.3. The 25% partial is recorded from the same message in which he told members to take 25-50%, so his own partial size is uncertain. | AF39: #183, #190, #191, #192 | AG39: https://discord.com/channels/1042855255089623100/1501271173588193290/1507304822351855667
A40: 39 | B40: 2026-05-22 12:23:13 | C40: XPLUSDT | D40: long | E40: loss | F40: stop_loss | J40: 0.089 | K40: 0.089 CMP | M40: 0.0836 | N40: 0.0946 | V40: 2026-05-22 12:23:13 | Y40: A long on XPL at 0.089 for a push to 0.0946. No reasoning was published beyond the levels. | Z40: He called it at 0.089 CMP with a 0.0836 stop and a single 0.0946 target on 22 May, and then never managed it in public. The only trace of how it ended comes the next morning, after an overnight crash, when he mentions in passing that he has 'recovered yesterday's AVAX+XPL loss'. So it was a stop-out - but the exit time, the fill and the size of the loss were never posted. | AB40: overnight crash | AD40: medium | AE40: The loss is only ever confirmed retroactively and in passing, inside a message about a different trade. No exit price, exit time or R exists for it, so exit_time is left null rather than set to the confirmation message. | AF40: #185, #210 | AG40: https://discord.com/channels/1042855255089623100/1501271173588193290/1507312875109355660
A41: 40 | B41: 2026-05-22 16:19:59 | C41: AVAXUSDT | D41: long | E41: loss | F41: stop_loss | J41: 9.569 | K41: 9.569 CMP | M41: 9.13 | N41: 10 | V41: 2026-05-22 16:19:59 | Y41: A slow-mover long on AVAX that looked constructive on all timeframes, targeting the round 10. | Z41: He called AVAX long at 9.569 CMP for a move to 10 with the stop at 9.13, describing it as a slow mover that looked good on all timeframes. The trade is never updated; the only evidence of how it ended is a line the next morning - 'Recovered yesterday's AVAX+XPL loss' - which confirms retroactively that AVAX was a loser on the overnight move. | AB41: An overnight crash took it out. | AD41: medium | AE41: The loss is only known from a retrospective one-liner; no exit price, exit time or R was ever posted, so exit_time is null (the stop happened on 22 May, before the 23 May message that reports it). The published 9.13 stop is in planned_stop. | AF41: #188, #210 | AG41: https://discord.com/channels/1042855255089623100/1501271173588193290/1507372458070773830
A42: 41 | B42: 2026-05-23 08:33:37 | C42: BEATUSDT | D42: short | E42: win | F42: breakeven | G42: 1 | H42: 921.08 | I42: 100 | J42: 1.286 | K42: 1.286 CMP | M42: 1.39 | N42: 1.08 | O42: Short BEAT (risky) - risky setup but almost 2R TP, worth a shot | P42: 1.2875 | R42: 1.27 (into_profit) | T42: 60% at 1.169 | V42: 2026-05-23 08:33:37 | W42: 2026-05-23 11:51:29 | X42: 3.3 | Y42: A risky short on BEAT at 1.286 - he said the setup was shaky but the 1.08 target was worth almost 2R, so it was worth a shot. | Z42: He called the short at 1.286 CMP, flagging the setup as risky but pointing out the 1.08 target was worth almost 2R. Within an hour it was 1.5R in his favour and he took 60% off at 1.169 (+921.08% on the 100x) specifically to recover one previous stop-loss, then moved the stop into profit at 1.27. It went on to run 2R before coming all the way back, and by late morning the remainder had closed at what he described as breakeven - leaving about 1R banked from the trade as a whole. | AD42: high | AE42: He calls the exit 'BE' even though his stop was at 1.27, which is slightly in profit against the 1.286 entry; no exit fill is ever quoted, so exit_price is left null. The 1R is his own net tally for the trade, and it is scored a win because the 60% at 1.5R was banked. | AF42: #194, #195, #196, #210 | AG42: https://discord.com/channels/1042855255089623100/1501271173588193290/1507617478283628544
A43: 42 | B43: 2026-05-23 10:35:06 | C43: JCTUSDT | D43: short | E43: win | F43: unknown | I43: 50 | J43: 0.004 | K43: CMP | M43: 0.00426 | N43: 0.00369 | O43: Half risk trade | P43: 0.004 | R43: 0.004 (to_entry) | S43: 0.00375 | T43: 10% at 0.00387 | V43: 2026-05-23 10:35:06 | Y43: Short JCT at market on half risk, targeting 0.00369. | Z43: He shorted JCT at 0.004 CMP on half risk with a 0.00426 stop and a 0.00369 target. Eighteen minutes later it had dumped nearly 0.5R; because BTC looked like it might bounce he secured the trade - took 10% off at 0.00387, moved his stop to entry at 0.004 and told members to take 10-20% at most. An hour later he confirmed he was still in, that breakeven had not been hit, moved the target up to 0.00375 for a clean 1R and warned that the setup was no longer valid to enter because the stop now sat at entry. That is the last JCT event in the file; the trade is never reported as closed, stopped or TP'd. | AB43: BTC approaching a possible bounce zone, so he was securing his shorts | AD43: low | AE43: Recorded as a win only because he banked a 10% partial in profit and then had his stop at entry, so the remainder could not lose; the real size of the result is unknown. The file goes silent on JCT after 11:59 on 23 May and never mentions it again in the following three months, so it is treated as ended at an unreported price rather than still running. | AF43: #197, #204, #211 | AG43: https://discord.com/channels/1042855255089623100/1501271173588193290/1507648051228180510
A44: 43 | B44: 2026-05-23 10:40:27 | C44: ATOMUSDT | D44: short | E44: not_taken | F44: not_taken | Y44: He wanted to short ATOM alongside his other shorts but held off because BTC was approaching a zone where it might bounce. | Z44: He said he kind of wanted to short ATOM too but passed because BTC was approaching its bounce zone. Fourteen minutes later he posted 'Should have shorted' - the move went without him. No entry, stop or target was ever published and no position was opened. | AB44: BTC approaching bounce zone | AD44: medium | AE44: Not a formal call - no levels were published, just an idea he declined and then regretted. Included as a not_taken record because it is a directional idea he explicitly considered and skipped. | AF44: #201, #205 | AG44: https://discord.com/channels/1042855255089623100/1501271173588193290/1507649400069951499
A45: 44 | B45: 2026-05-23 10:45:52 | C45: HYPEUSDT | D45: long | E45: win | F45: manual_close | G45: 1.2 | H45: 204.57 | I45: 100 | J45: 54.8 | K45: CMP; his own fill came a few minutes after he posted, at 54.991 | M45: 53.9 | N45: 56.4 | O45: Manual close so small margin - the stop was a 4h close under 53.9, not a resting order | P45: 54.991 | S45: 58 | V45: 2026-05-23 10:45:52 | W45: 2026-05-23 11:50:21 | X45: 1.1 | Y45: Long HYPE at market with a soft 4h-close stop under 53.9; because the stop had to be managed by hand he told everyone to keep the margin small. | Z45: He called the long at 54.8 CMP with a 56.4 target and a stop defined as a 4h close under 53.9, warning that because the stop was manual the margin should be small. He clarified that 54.8 was current price, then admitted his own fill came late at 54.991 so followers probably had a better entry. Within twelve minutes it was 0.5R up, and about an hour after the call he closed the whole thing at 1.2R, leaving 58 as the next target for anyone still holding. That evening he told holders to trim with 58 as the final target, and the 58 print came at 20:17 - 3R for anyone who held with no partials, 2R for those who trimmed as instructed. He turned it into a lesson: 'this is when taking 100% TP hurts, I exited at 1.1R', while admitting he almost always takes 100% at the first TP. | AA45: 4h close | AD45: high | AE45: He quotes his own exit as 1.2R at the time (msg 209) and as 1.1R when reviewing it later (msg 230); the live 1.2R figure is recorded. No exit price was posted - the closing card shows +204.57% on 100x from 54.991. The 2.5R and 3R figures in msgs 229-230 belong to holders who stayed in after he was out. | AF45: #202, #203, #206, #207, #209, #229, #230 | AG45: https://discord.com/channels/1042855255089623100/1501271173588193290/1507650763307094026
A46: 45 | B46: 2026-05-23 11:13:43 | C46: SUIUSDT | D46: long | E46: win | F46: take_profit | G46: 2 | H46: 874.77 | I46: 100 | J46: 1 | K46: entry 1, taken on half risk | M46: 0.95 | N46: 1.05, 1.11 | O46: Half risk - BTC is weak but expecting relief. Followers told to take only 25-40% at TP1 and save the majority for his exit; he takes no partials himself | P46: 1.0014 | S46: 1.1 | T46: 1.0539 | U46: 1.089 | V46: 2026-05-23 11:13:43 | W46: 2026-05-24 00:09:16 | X46: 12.9 | Y46: A half-risk long on SUI at 1.00: BTC was weak but he expected a relief bounce, and he had passed on the same setup the day before only because he already had three trades running. | Z46: He had flagged SUI as looking too good on the daily on 22 May but passed because three trades were already running. He took it the next morning at 1.00 on half risk, targets 1.05-1.11, stop 0.95, and by mid-afternoon the 100x card was at +150.91% and he re-posted the call as his only running trade. As it neared TP1 he told the room to take only 25-40% and keep the rest for his exit, saying he takes no partials himself - then when TP1 printed he took nothing at all, saying he would take 25% only when it came back. He did take some at 1.0539 (+524.3%) an hour later and admitted he was close to closing the lot, but held on for what he thought would be a Sunday pump. It ran to 1.0803 (+788.77%) with the target raised to 1.1+, and just after midnight the full target hit for 2R - worth much more than usual, as he pointed out, because they had barely taken anything at TP1. The closing card shows the 100x out at 1.089 for +874.77%. | AB46: BTC weak but he expects relief; he also expected a Sunday pump into the weekend | AD46: high | AE46: Run on two accounts at once - a 100x card (entry 1.0014, closed 1.089) and a 250x card (entry 1.0006, mark 1.0909) - which is one position, not two. Msg 187 is the previous day's pass on the same setup, included as the run-up rather than as a separate not-taken position. The size of the 1.0539 partial is never confirmed, and his '1R soon' card figure is ROI, not R. | AF46: #187, #208, #212, #220, #226, #231, #232, #233, #236, #241, #242 | AG46: https://discord.com/channels/1042855255089623100/1501271173588193290/1507368753677992070
A47: 46 | B47: 2026-05-23 17:16:47 | C47: BTCUSDT | D47: long | E47: win | F47: manual_close | H47: 281.65 | I47: 150 | J47: 75100 | K47: 75.1k CMP in the written call; his own fill on the challenge account was 75,166.50 and the main-account card shows 75,197.20 | L47: 74300 | M47: 72200 | N47: 76600, 78000 | O47: On the 89 USDT challenge account he said he would risk 10-20% per trade and that it must not be copied on a main account (msg 221); the written call is the main-account version. At the first target he told followers to take nothing or 20% at most and wait for him (msg 228). | P47: 75197.2 | R47: 72220 (adjustment) | T47: 25% at 77000 | U47: 76609.2 | V47: 2026-05-23 17:16:47 | W47: 2026-05-24 02:33:55 | X47: 9.3 | Y47: Buy the crash to make the BTC stop-loss back - long the 75.1k area with a 74.3k DCA, targeting 76.6-78k with a wide 72.2k stop. It doubled as the first trade of his for-fun 89 USDT BTC-scalp challenge. | Z47: After the crash he said he was waiting for 74k to long and told the group 'No longs before 74k' (msgs 198, 200), then found an 89.36 USDT account and announced a for-fun BTC-scalps-only challenge to double it, warning it should not be copied on main accounts (msg 221). The first scalp went on at 75,166.50 - 0.0090 BTC with a 72.2k stop (msg 222) - with the DCA at 74.3k and the stop restated as 72,220 (msg 223), and he wrote the same trade out as a formal call for main accounts: entry 75.1k CMP, DCA 74.3k, targeting 76.6-78k, SL 72.2k (msgs 224-225). BTC ran straight up without touching the DCA: he told members to take nothing at 76.6k or 20% at most and wait for him (msg 228), then posted the main position at +340% on 150x inviting people to trim wherever they liked (msg 235) and the challenge account up about 20% of its balance at +507% on 200x (msg 239), saying he would stay long into the weekend (msg 240). He trimmed 25% around 77k without announcing it at the time, and closed the rest at 76,609.20 for +281.65% on 150x (msg 246); the challenge account closed for +$12.98, about 15% (msg 247). | AB47: After the overnight crash he expected 72-74k first and then a move to the high 80s (msg 199). | AD47: high | AE47: One position across two accounts - the 89 USDT challenge account (0.0090 BTC, entry 75,166.50) and his main account (75,197.20) - confirmed as 'the same trade I just wrote together for the people taking it on their main accounts' (msg 225), so it is not duplicated. Leverage is inconsistent in his own screenshots: the entry screenshot shows 20x and the later card 200x for the same challenge-account position, while the main card is 150x. He entered at 75.1k after telling the group there should be no longs before 74k. The 25% trim at 77k is above the exit price of the remainder. | AF47: #198, #200, #221, #222, #223, #224, #225, #228, #235, #239, #240, #246, #247 | AG47: https://discord.com/channels/1042855255089623100/1501271173588193290/1507648122581680128
A48: 47 | B48: 2026-05-23 18:13:54 | C48: FILUSDT | D48: long | E48: win | F48: take_profit | H48: 14.13 | I48: 3 | J48: 0.955 | K48: 0.946 limit or 0.955 CMP; the CMP option is the one his closed card shows | M48: 0.892 | N48: 1.0 | P48: 0.955 | U48: 1 | V48: 2026-05-23 18:13:54 | W48: 2026-05-23 23:42:34 | X48: 5.5 | Y48: Long FIL into the 1.00 round number from 0.946-0.955, stop 0.892. | Z48: He called FIL long from either 0.946 or 0.955 CMP with a single target at the 1.00 round number and a 0.892 stop. It ran the same evening: five and a half hours later the target filled and the closed card showed entry 0.955, close 1.000, +14.13% at 3x leverage. Clean call, no management in between. | AB48: not stated | AD48: high | AE48: Unusually low leverage (3x) compared with the rest of his cards. | AF48: #227, #234 | AG48: https://discord.com/channels/1042855255089623100/1501271173588193290/1507763514410930216
A49: 48 | B49: 2026-05-24 07:56:03 | C49: BTCUSDT | D49: long | E49: win | F49: take_profit | H49: 225.07 | I49: 150 | J49: 76750 | K49: 76,750 CMP; he had said he wanted 75.7k (msg 248) but entered a full 1k higher five hours later | L49: 75500 | M49: 74000 | N49: 78000 | O49: Mid-trade he told followers to DCA 25% at 75.5k (half the current margin) and keep another 25% back for a further DCA (msg 256) | P49: 76754.6 | U49: 77906.3 | V49: 2026-05-24 07:56:03 | W49: 2026-05-26 17:27:42 | X49: 57.5 | Y49: Re-long straight after taking profit because he still thought BTC went to 78-80k, targeting 78k+, with a 4h close above 78.3k opening the 80s. | Z49: Minutes after closing the previous long he said BTC still went higher to 78-80k and that he wanted to re-enter at 75.7k (msg 248), but five hours later he took it 1k higher at 76,754.60 with a 74k stop (msg 249), writing it up as entry 76,750 / DCA 75.5k / SL 74k (msg 250) and targeting 78k+ (msg 252), on both his main account and the 89 USDT mini account (msg 251). During the day he told members to DCA 25% at 75.5k and save another 25% for later (msg 256) - the level never traded, so nothing filled - and pointed out the position was already in profit so sizing could be adjusted (msg 257). He went quiet for a day with personal problems, still holding and waiting for a 4h close above the 200 EMA (msg 258), confirmed he was still in on the 26th (msg 274), and closed that afternoon (msg 275): the main card shows 76,754.60 to 77,906.30, +225.07% on 150x (msg 276), while his 78k TP actually filled at 78,012.90, which he blamed on Blofin closing late (msg 277). The mini account closed the same 0.0090 BTC at 78,012.90 for +11.32 USDT (msgs 278-279), and the fill landed on a single-candle spike to 78,049 that instantly retraced to 76,806 - 'What an EXIT boys! Gotta love this memecoin' (msg 280). | AA49: 4h close, EMA 200 | AB49: Bullish weekend continuation - he expected 78.8-79.5k on a pump and ultimately the 80s, most likely 82-84k, and wanted a 4h close above the 200 EMA to speed it up. | AD49: high | AE49: Two different exit prints for the same trade: 77,906.30 on the main 150x card (msg 276) and 78,012.90 where the 78k TP filled on Blofin / the mini account (msgs 277, 279); exit_price uses the main card. Exit time is his 'BTC closed' announcement, not the card timestamp. The 75.5k DCA he instructed never traded. One trade across the main account and the 89 USDT challenge account, not two. The exit sits in the LATER CONTEXT section of the log. | AF49: #248, #249, #250, #251, #252, #253, #254, #255, #256, #257, #258, #274, #275, #276, #277, #278, #279, #280 | AG49: https://discord.com/channels/1042855255089623100/1501271173588193290/1507889791742644235
A50: 49 | B50: 2026-05-25 12:08:46 | C50: WLDUSDT | D50: long | E50: win | F50: take_profit | G50: 1 | H50: 416.8 | I50: 75 | K50: he flagged CMP with a 0.28 stop for anyone who wanted it, but said he would wait for a better entry himself and would signal - he got in at 0.302 | M50: 0.28 | O50: half risk trade - only because he was saving 50% for a DCA; he told others they could take normal risk | P50: 0.3023 | S50: 0.32/0.33 | T50: 30% at 0.3117 | U50: 0.32 | V50: 2026-05-25 13:51:28 | W50: 2026-05-25 21:35:21 | X50: 7.7 | Y50: He thought WLD looked really bullish and would go at least 0.32+, so he waited for a better entry than the CMP he flagged to the group and took it on half risk. | Z50: He told the group WLD looked really bullish and that anyone who wanted could long from CMP with a 0.28 stop, while he waited for a better entry and promised to signal his own. Two hours later he was in at 0.302 on half risk with that same stop, explaining that the half size was only because he was holding 50% back for a DCA and that he expected at least 0.32+. In the evening he took 30% off at 0.3117, set 0.32-0.33 for the rest and said the remainder would be exited whole there. TP2 at 0.32 printed on most exchanges (Blofin's feed missed it) and he closed fully at 0.32 for almost 1R, telling followers they could take 50-70% and leave runners for 0.33-0.34. Forty minutes later WLD reached 0.33 - almost 1.5R for anyone with runners - and he admitted he had scalped it because that is simply what he likes to do. | AD50: high | AE50: The closing card reads 0.3191 while he says he was 'fully out at 0.32'; his stated 0.32 is recorded as the exit. He says he took 30% off and then minutes later refers to '50% remaining', which does not add up - one of the two figures is loose. The DCA he was saving 50% for never happened and no level was ever published. The 1.5R in msg 266 belongs to followers who kept runners. | AF50: #259, #260, #261, #262, #263, #264, #265, #266 | AG50: https://discord.com/channels/1042855255089623100/1501271173588193290/1508396400071938109
A51: 50 | B51: 2026-05-26 08:42:49 | C51: TAOUSDT | D51: long | E51: loss | F51: stop_loss | I51: 100 | J51: 287 | K51: CMP, 50% of size at the call with the other 50% reserved for a DCA around 270-275 | M51: 268 | N51: 300.0, 315.0 | O51: half size at entry, 50% held back for the DCA | P51: 276.63 | Q51: 271.1 (the reserved 50% add, inside the 270-275 zone he had flagged; confirmed filled in msg 286 where his card shows the blended entry at 276.63) | R51: 265 (tighten) -> 263 (widen) | S51: 282/286 | T51: 10% at 280.0 | V51: 2026-05-26 08:42:49 | W51: 2026-05-28 07:43:24 | X51: 47 | Y51: Long TAO at 287 targeting 300-315, sized half at entry with the other half reserved to average in around 270-275. | Z51: He called TAO long at 287 with a 268 stop and 300-315 targets, telling everyone to enter half size because he would add the other half around 270-275. He confirmed he was holding through the 26th; early on the 27th he called the DCA at 271.1 and tightened the stop to 265, and his card then showed the blended entry at 276.63 with the position back in profit. That evening he offloaded just 10% at 280 - purely because the position had got heavy after the DCA - explicitly refused to move the stop to entry since price action was strong, and pulled his exit zone in from 300-315 to 282-286. Overnight he widened the stop again, saying he would hold TAO down to 263 because BTC might bounce from there. It did not: on the morning of the 28th TAO and BTC both stopped out in what he called an insane dump, which he framed as part of the game after a winning streak. | AB51: he expected BTC to bounce; instead an insane dump took both out | AD51: high | AE51: No exit price or R figure was posted for the stop-out; his last stated stop was 263 (msg 288), loosened from the 265 he set at the DCA. The DCA was announced as a 270-275 zone rather than a level, so no planned DCA price is recorded. | AF51: #268, #269, #274, #285, #286, #287, #288, #290 | AG51: https://discord.com/channels/1042855255089623100/1501271173588193290/1508706959384117248
A52: 51 | B52: 2026-05-26 10:46:30 | C52: RENDERUSDT | D52: long | E52: loss | F52: stop_loss | I52: 90 | J52: 2.33 | K52: 2.33 CMP with 50% of size now and 50% saved for a later DCA whose level was never given | M52: 2.13 | O52: Don't go too heavy, already too pumped | P52: 2.333 | T52: 50% at 2.416 | V52: 2026-05-26 10:46:30 | W52: 2026-05-26 15:22:22 | X52: 4.6 | Y52: He normally only longs supports, but AI coins were pumping hard, so he took RENDER at market anyway with half size and a warning not to go heavy. | Z52: He longed RENDER at 2.33 CMP with only half size deployed and half kept for a DCA he never named, stop 2.13, flagging that the coin was already too pumped for his usual support-buying style. Twenty-six seconds later he posted the management plan: a small trim at 0.5R with the majority saved for 1R+. Three hours in he took 50% off at 2.416 for +320.66% at 90x. An hour and a half after that the rest was stopped at 2.13 - 'RENDER stopped after taking 50%' - and he suggested, without taking it himself, that anyone still bullish could re-long with a 2.26 stop for 2.5. | AA52: support | AB52: AI coins pumping hard; RENDER already extended | AD52: medium | AE52: Net result depends on sizing he never published: he banked 50% at +320.66% ROI but the remaining half was stopped at a level much further from entry than the trim, so it is recorded as a loss in line with his own framing ('RENDER stopped'). The 0.5R trim plan in MSG 271 is a symbol guess - it was posted 26 seconds after this call but could belong to the TAO long opened two hours earlier. The re-long idea with 2.26 stop for 2.5 is follower guidance he explicitly did not take. exit_price is the stop level from his own call, not a posted fill. [AUDIT] Audit: 2.13 was his stop level, not a posted fill — exit_price cleared to null. | AF52: #270, #271, #273, #274 | AG52: https://discord.com/channels/1042855255089623100/1501271173588193290/1508738085016567928
A53: 52 | B53: 2026-05-27 03:18:30 | C53: BTCUSDT | D53: long | E53: loss | F53: stop_loss | J53: 75900 | K53: 75.9k CMP for 50% of size, 25% for the DCA at 75k, 25% held in reserve | L53: 75000 | M53: 73500 | N53: 77000 | O53: Scaled entry 50/25/25. A second, higher-risk version of the same idea (full size at CMP, SL 74k, no DCA) was run on one of his accounts, but he said he would only count the first setup. | V53: 2026-05-27 03:18:30 | W53: 2026-05-28 07:43:24 | X53: 28.4 | Y53: Buy the dip again straight after banking the previous BTC long at 78k - scale in from 75.9k with a DCA underneath and look for a push back to 77k. | Z53: Roughly ten hours after banking the previous BTC long he called a new one, structured as 50% at 75.9k CMP, 25% at a 75k DCA and 25% kept in reserve, targeting 77k with a 73.5k stop, and gave exact sizes for the 89$ challenge account (0.011 / DCA1 0.006 / DCA2 0.005). Six minutes later he posted a tighter alternative for the aggressive crowd - full size at CMP, no DCA, stop at 74k - saying he was running that version personally on one account but would only score the first setup. Early on the 28th he told the channel BTC might bounce from where it was; about four hours after that the trade was gone: 'TAO and BTC stopped guys, insane dump.' No fill price and no stop-out price were ever posted. | AB53: BTC rolling over after the late-May run to 78k; he had closed the prior long into a single-candle spike the evening before and stayed bullish. | AD53: medium | AE53: No exit price given - he only announced the stop, so exit_price is null. Two versions of the same setup were live on different accounts (73.5k stop for the counted setup, 74k stop for his personal high-risk one) and the stop announcement does not say which is being reported; the graded setup is the 73.5k one. Whether the 75k DCA filled is never confirmed, so no average entry is recorded. MSG 288 ('BTC may bounce from here') is assigned here because it falls while this long was open. | AF53: #281, #282, #283, #288, #290 | AG53: https://discord.com/channels/1042855255089623100/1501271173588193290/1508987730477060248
A54: 53 | B54: 2026-05-28 07:44:12 | C54: BTCUSDT | D54: long | E54: loss | F54: stop_loss | I54: 150 | J54: 73000 | K54: 73k, taken within a minute of the previous long being stopped; 'go lower than usual' | M54: 72000 | N54: 75000, 76000 | O54: Half risk - 'This is RISKY that's why I mentioned lower risk, half risk.' Size on the small gamble account was 0.02. | P54: 73141.2 | S54: 74200/75000/76000 -> 74300/75000 -> 74500 | T54: 25% at 74200 | V54: 2026-05-28 07:44:12 | W54: 2026-06-01 16:56:20 | X54: 105.2 | Y54: Immediate re-attempt of the long he had just been stopped on, at half size and $2k lower, on the view that BTC should print at least 75k before going down further. | Z54: Under a minute after announcing the previous stop he was back in: 'Trying a BTC long again here @ 73k, SL @ 72k, half risk trade, go lower than usual.' He set the target zone at 75-76k for 'a decent R' and held it through the weekend, reporting he was still in on the 29th. That evening the 150x card showed the position 1R up from 73,141.2 and he offered partials to anyone who wanted them, adding an ideal first TP at 74.2k; a few hours later he took that 25% at 74.2k and stated plainly that the rest would be either a full TP or the stop - 'not moving SL to entry.' On the 31st he published a ladder for anyone still fully in (25% at 74.3k, 75% at 75k) and said he would trim on the smaller account too, then on 1 June nudged his own first tranche up to 74.5k while telling followers 74.3k was the better level. Later that day it was over: 'BTC stopped after TP1 @ 74.2k, held 3 days, above 1R just to get stopped.' | AB54: 'Insane dump' on 28 May; he expected one more push into 75-76k over the weekend before further downside. | AD54: medium | AE54: Graded a loss rather than a win even though 25% came off in profit at 74.2k: the remaining 75% was stopped at the 72k he had explicitly refused to move, and his own accounting treats it as a stop ('above 1R just to get stopped'), with the June win streak he counts later starting after this trade. No stop-out fill price was posted, so exit_price is null - the stop level was 72k and was never moved. Also run on a smaller account alongside the main one. | AF54: #291, #292, #293, #294, #301, #303, #306, #311, #312, #313 | AG54: https://discord.com/channels/1042855255089623100/1501271173588193290/1509416983815393310
A55: 54 | B55: 2026-05-28 17:16:30 | C55: GOLD | E55: win | F55: unknown | G55: 3 | W55: 2026-05-28 17:16:30 | Y55: A gold trade he ran off-channel; the only thing he says about it is the result. | Z55: He mentioned after the fact that he had 'just did 3R on Gold' and had been about to post it in the channel but was too busy. Nothing else about this trade - direction, entry, stop, target, timing - was ever published; only the 3R result. | AD55: medium | AE55: Side unknown (never stated). Entry time unknown, so duration is null; exit_time is the timestamp of the message reporting it, which is contemporaneous ('just did'). The 3R is his own figure. | AF55: #294 | AG55: https://discord.com/channels/1042855255089623100/1501271173588193290/1509561007306051786
A56: 55 | B56: 2026-05-28 18:48:42 | C56: ETHUSDT | D56: long | E56: win | F56: unknown | H56: 132.39 | I56: 100 | K56: no entry level was published with the idea - only a 1950 stop; his own fill (1988.23) surfaced two hours later in a share card | M56: 1950 | N56: 2020, 2030 | O56: just enter small, half risk on trades, market's weak | P56: 1988.23 | R56: 1988.23 (to_entry) | S56: 2020/2030 | T56: 20% at 2015.08 | V56: 2026-05-28 20:49:03 | Y56: Offered an ETH long with a 1950 stop despite hating the asset, sized small because the market was weak - then turned out to be in it himself. | Z56: He floated the long with only a 1950 stop and told people to enter small at half risk; two hours later a share card gave him away - he was in it at 1988.23 at 100x and already +165.82%, while mocking ETH as an asset. Next morning he moved the stop to breakeven at his entry because bearish signs had returned after being up well, and by midday he was still holding alongside BTC and ADA. At 12:40 he took 20% off at 2015.08 (+132.39%) with the stop at entry, saying he would exit fully around 2020-2030. That final exit was never posted. | AB56: weak market | AD56: medium | AE56: Recorded as a win because he booked a 20% partial at +132.39% with the stop already at entry, so the remainder was at worst flat - but he never posted the full exit, so exit_price/exit_time are null and the final result is not stated. He calls a fresh ETH long on 18 June, so this had ended by then. | AF56: #296, #298, #300, #301, #302 | AG56: https://discord.com/channels/1042855255089623100/1501271173588193290/1509584210560815294
A57: 56 | B57: 2026-05-28 20:23:18 | C57: ADAUSDT | D57: long | E57: win | F57: take_profit | H57: 134.44 | I57: 75 | J57: 0.234 | K57: 0.234 CMP | M57: 0.226 | N57: 0.2386, 0.246 | O57: 50% off at the 0.6R level, full exit at 0.246 | P57: 0.2343 | S57: 0.2386/0.246 | U57: 0.2385 | V57: 2026-05-28 20:23:18 | W57: 2026-05-30 08:32:55 | X57: 36.2 | Y57: A plain CMP long on ADA at 0.234 with a tight 0.226 stop, run as a small-R trade with half planned off at the 0.6R level. | Z57: He called it at 0.234 CMP with a 0.226 stop, and an hour later published the ladder: 50% off at 0.2386, about 0.6R, and a full exit at 0.246. ADA ran at the target overnight and came back without filling, which he noted with some annoyance, and the next morning he confirmed he was still in it alongside BTC and ETH. On 30 May it finally got there - but the card shows the whole 75x position closed at 0.2385 for +134.44%, so everything came off at the 0.6R step rather than the 50/50 ladder he had published. | AD57: high | AE57: Plan and execution differ: he published 50% at 0.2386 and a full exit at 0.246, but the card shows the entire position closed at 0.2385. He never stated a realised R - the 0.6R belongs to the planned level - so none is recorded. | AF57: #297, #299, #300, #301, #307 | AG57: https://discord.com/channels/1042855255089623100/1501271173588193290/1509608015559397406
A58: 57 | B58: 2026-05-29 19:10:23 | C58: NEARUSDT | D58: long | E58: not_taken | F58: not_taken | J58: 2.56 | K58: 2.56 CMP; billed as the last signal of the month | M58: 2.392 | Y58: A NEAR long at market meant to be the final signal of May, withdrawn a minute later when price ran away from the entry. | Z58: He posted 'Long NEAR, Entry: 2.56 CMP, SL: 2.392, Last signal do the month' and sixty-four seconds later pulled it: 'Sorry guys pumped too fast, you can skip this one, apologies', with price already at 2.603. The signal was withdrawn before anyone could reasonably fill it and NEAR is not mentioned again for four days. | AD58: low | AE58: The retraction message carries an entry figure of 2.565 and a price of 2.603, which may mean he had a fill of his own at 2.565 before withdrawing the call - he never says. Treated as not_taken because he cancelled the idea and never referred to a NEAR position from it. | AF58: #304, #305 | AG58: https://discord.com/channels/1042855255089623100/1501271173588193290/1509952053508706365
A59: 58 | B59: 2026-05-30 08:46:54 | C59: XPLUSDT | D59: long | E59: win | F59: take_profit | G59: 0.8 | H59: 318.52 | I59: 75 | J59: 0.0916 | K59: 0.0916 CMP | M59: 0.0846 | O59: half risk himself because XPL is his bad luck coin | P59: 0.0918 | S59: 0.0965 | U59: 0.0958 | V59: 2026-05-30 08:46:54 | W59: 2026-06-02 07:06:26 | X59: 70.3 | Y59: A second attempt at the XPL long a week after the first was stopped out, taken at half risk because he calls XPL his bad luck coin. | Z59: He called it at 0.0916 CMP with a 0.0846 stop, at half risk because XPL had burned him before - the previous attempt had been stopped out eight days earlier. The 0.0965 target came two hours later. It survived the dump at the start of June: on 1 June he noted the alts were green again and gave XPL credit for pumping and holding up through the drop, while complaining that it never hits his target. On 2 June it finally did, closing at 0.0958 for 0.8R and +318.52% on the 75x, and he announced he was done with the coin. | AB59: took it through the start-of-June dump | AD59: high | AE59: The 0.0965 target was never quite reached - the card shows the close at 0.0958, which he counted as the TP and as 0.8R. | AF59: #308, #309, #320, #327 | AG59: https://discord.com/channels/1042855255089623100/1501271173588193290/1510157536307839146
A60: 59 | B60: 2026-05-31 15:24:11 | C60: SOLUSDT | D60: long | E60: loss | F60: stop_loss | J60: 82.69 | K60: 82.69 CMP, swing | M60: 78 | N60: 87.69 | V60: 2026-05-31 15:24:11 | Y60: A swing long on SOL from 82.69 with a 5-point target and a wide 78 stop. | Z60: He called the SOL swing long at 82.69 CMP, TP 87.69, SL 78, and then never updated it. The stop-out surfaces only in a month-to-date tally two days later - 'The month just started, 3 TPs (XPL, RAY, BNB), 1 SL (SOL) so far' - which is the sole record that this trade was the loser. | AD60: medium | AE60: Outcome inferred from the 2 June recap naming SOL as June's only SL; no exit price or timestamp was ever posted, so exit_time and duration are null. The published 78 stop is in planned_stop. | AF60: #310, #335 | AG60: https://discord.com/channels/1042855255089623100/1501271173588193290/1510619906905735301
A61: 60 | B61: 2026-06-01 16:57:12 | C61: RAYUSDT | D61: long | E61: win | F61: manual_close | H61: 35.2 | I61: 20 | J61: 0.697 | K61: 0.697 CMP; he later noted followers likely got a better fill near 0.69 because it dumped as the call went out | M61: 0.6746 | N61: 0.719, 0.731 | P61: 0.7005 | U61: 0.7128 | V61: 2026-06-01 16:57:12 | W61: 2026-06-01 21:18:51 | X61: 4.4 | Y61: Long RAY from 0.697 CMP towards 0.719-0.731 with a 0.6746 stop; no reasoning published. | Z61: He called RAY long at 0.697 CMP with targets at 0.719-0.731. It dipped first, then came back green along with his other alts by evening. His TP1 limit missed filling by 0.0001, so he took profit manually at 0.7128 from an average of 0.7005 for +35.2% at 20x. He shrugged it off as not the best trade but all he could get in that market, and pointed out that anyone who took the call after the dump to 0.69 had a better entry than his. | AB61: poor market - 'going to take whatever I can get in this market' | AD61: medium | AE61: The close message carries no portion figure; read as a full exit since he calls it 'taking TP here' and never mentions RAY again. | AF61: #314, #320, #323, #324 | AG61: https://discord.com/channels/1042855255089623100/1501271173588193290/1511005703178031205
A62: 61 | B62: 2026-06-01 17:50:57 | C62: BNBUSDT | D62: long | E62: win | F62: take_profit | I62: 75 | J62: 680 | K62: 680, initially posted as an idea he was not taking himself | M62: 652 | O62: Explicitly 'not a signal'; when he did enter he told members to manage risk and not to be a hero. | P62: 676.49 | S62: 700 | T62: 20% at None | V62: 2026-06-01 19:23:14 | Y62: BNB looked like a good long around 680 with a 652 stop - offered to members hunting longs before he talked himself into taking it. | Z62: He posted BNB at 680 with SL 652 as an explicit non-signal - 'I'm not personally taking it but if anyone wants to try' - then an hour and a half later changed his mind: 'Okay I'm trying this too, just manage your risk guys, no need to be a hero.' By evening BNB was back green alongside XPL and RAY, and at nearly 1R up (card: 75x, entry 676.49, mark 693.96, +193.70%) he told members to take TP whenever they were happy while he aimed for 700+. At 1.2R, with the mark at 701.97, he advised taking only 10-20% and saving the majority; the next midday he confirmed his own trim - 'I'll keep BNB running, till SL or TP, took 20% on top.' The runner's exit was never posted, but the 2 June month-to-date recap counts BNB among the three TPs of the month. | AD62: medium | AE62: No closing price or time was ever published for the 80% runner - the win is read from the 2 June recap ('3 TPs (XPL, RAY, BNB)'), which is also why exit_time is null. It is unclear whether the 20% he reports on 2 June is the same trim as the 10-20% he advised at 1.2R the night before, so only one partial is recorded. His stated 1.0R and 1.2R marks are progress figures, not a result, so r_multiple is left null. | AF62: #317, #319, #320, #325, #326, #330, #335 | AG62: https://discord.com/channels/1042855255089623100/1501271173588193290/1511019230542299289
A63: 62 | B63: 2026-06-01 20:37:01 | C63: BTCUSDT | D63: long | E63: breakeven | F63: manual_close | H63: 7.63 | I63: 150 | J63: 71500 | K63: 71.5k CMP | M63: 70000 | N63: 74000, 75000 | O63: 'Catching a falling knife here but can get a nice R' | P63: 71514.9 | U63: 71551.3 | V63: 2026-06-01 20:37:01 | W63: 2026-06-01 21:12:12 | X63: 0.6 | Y63: Knife-catch long into the sell-off at 71.5k for a quick run at 74-75k, taken knowing it was against the trend. | Z63: Under four hours after the previous BTC long stopped he called another at 71.5k CMP with a 70k stop and 74-75k targets, admitting outright that he was catching a falling knife but liked the R. Thirty-five minutes later he pulled it: 'Closing BTC here, will long again after daily closing better play safe too many trades running.' The card shows entry 71,514.9, close 71,551.3, +7.63% at 150x - effectively flat. He never did re-enter after the daily close; the next BTC idea, published the following morning, was $2k lower. | AA63: daily close | AB63: Sharp downtrend; he had just been stopped on the 73k long a few hours earlier and had too many other trades running. | AD63: high | AE63: Closed marginally green (+7.63% leveraged ROI, about $36 of BTC price), so it is recorded as breakeven rather than a win. This is consistent with his own accounting: on 5 June he calls the trade he was about to take a shot at a '3rd win in a row', which counts back only to the two 4 June trades, not to this one. | AF63: #321, #322 | AG63: https://discord.com/channels/1042855255089623100/1501271173588193290/1511061018749571203
A64: 63 | B64: 2026-06-02 08:31:10 | C64: FETUSDT | D64: long | E64: unknown | F64: unknown | J64: 0.276 | K64: 0.276 CMP, taken late in the move | M64: 0.249 | N64: 0.3, 0.35 | O64: better if you use half risk here as it's already too pumped, but your choice | V64: 2026-06-02 08:31:10 | Y64: A bit late to the party on the AI move, so he took a swing long on FET at 0.276 towards 0.3-0.35 with halved size. | Z64: He posted the swing long at 0.276 CMP with targets at 0.3-0.35 and a 0.249 stop, telling people to use half risk because the coin was already too pumped. There is no follow-up of any kind in the log - no update, no partial, no stop-out, no close. | AB64: FET already extended - 'a bit late to the party' | AD64: low | AE64: Single event for this symbol in the whole log. No fill, no exit, no outcome is ever stated. | AF64: #328 | AG64: https://discord.com/channels/1042855255089623100/1501271173588193290/1511240742251663465
A65: 64 | B65: 2026-06-02 11:51:30 | C65: BTCUSDT | D65: long | E65: unknown | F65: unknown | J65: 69300 | K65: 69.3k CMP, corrected to 69.4k four minutes later; first published 73 minutes earlier as a 69,446 idea he said he was not taking | M65: 66500 | N65: 73000 | O65: The version he published for followers at 11:51 was half risk with a 68k stop and 73-74k targets, 'if I enter you can increase it to normal sized'. When he did enter he ran a much wider 66.5k stop. | P65: 69400 | V65: 2026-06-02 13:04:58 | Y65: Long BTC from just under 69.5k for a run back to 73k after the slide - floated first as an idea for the group, then taken himself an hour later. | Z65: At 11:51 he posted the level as something for other people - entry 69,446, TPs 73-74k, SL 68k - and said explicitly 'I'm not entering this myself but I think it's worth a try', telling followers to halve risk unless he joined. Seventy-three minutes later he joined: 'Long BTC / Entry: 69.3k CMP / TP: 73k / SL: 66.5k', corrected four minutes after that to 69.4k. Then nothing. The log contains no close, no stop announcement and no PnL card for this trade. The next BTC message, more than twenty hours later, is a fresh call for a long at 67.3k with its own targets and stop, and BTC went on to trade under 65k by the following morning - well through the 66.5k stop. | AB65: BTC grinding lower through early June; he kept trying longs into weakness on successively lower levels. | AD65: low | AE65: The single genuinely unresolved position in this window. The events never say how it ended, so outcome is 'unknown' - but price traded far below the stated 66.5k stop within about a day, no card matching a ~69.4k entry appears in the ten-card win-streak recap of 12 June, and he never counts it as a win, so a silent stop-out is by far the most likely ending. The 11:51 plan (msg 329) is folded in here rather than recorded as a separate 'not_taken' call, because it is the same idea at the same level that he took himself an hour later; note that the follower version carried a tighter 68k stop and wider 73-74k targets than what he actually ran. | AF65: #329, #331, #332 | AG65: https://discord.com/channels/1042855255089623100/1501271173588193290/1511291159975035012
A66: 65 | B66: 2026-06-02 17:35:43 | C66: SEIUSDT | D66: long | E66: unknown | F66: unknown | J66: 0.067 | K66: 0.067 CMP | M66: 0.0632 | N66: 0.07, 0.072 | O66: Split exit planned: 25% at 0.070, 75% at 0.072. | R66: 0.0627 (hard_stop_widened) | V66: 2026-06-02 17:35:43 | Y66: Long SEI from 0.067 with a two-stage exit, backed by an expected bounce off the 200 EMA. | Z66: He called SEI long at 0.067 CMP with TPs at 0.070 (25%) and 0.072 (75%) and a 0.0632 stop. Five hours later, with the trade offside, he said he would wait for the 4h close and close manually for breakeven, would exit if the 4h closed under 0.064, and expected a bounce back to entry off the 200 EMA. Ten minutes after that he widened the hard stop slightly to 0.0627 so a crash wick could not liquidate anyone. Nothing more about SEI is ever posted. | AA66: 4h close, 200 EMA | AD66: low | AE66: The log simply drops this trade after 2 June - no close, no stop-out, no mention in any later recap - so the outcome is unknown. still_open_at_end is set false because he clearly was not carrying it through the following months, not because a close was recorded. | AF66: #333, #337, #338 | AG66: https://discord.com/channels/1042855255089623100/1501271173588193290/1511377784063262893
A67: 66 | B67: 2026-06-02 20:57:49 | C67: NEARUSDT | D67: long | E67: win | F67: take_profit | G67: 1.6 | H67: 720.77 | I67: 75 | J67: 2.64 | K67: 2.64 CMP, offered as an idea rather than an official signal | M67: 2.43 | N67: 2.9, 3.0 | O67: Offered as 'if anyone wants to try'; he said he would not count it in his official stats. | P67: 2.643 | U67: 2.897 | V67: 2026-06-02 23:06:42 | W67: 2026-06-03 13:55:38 | X67: 14.8 | Y67: He expected NEAR to pump about 10% if BTC stabilised, and turned that view into a long with the stop under the recent low at 2.43, riding toward 2.9-3. | Z67: Two hours after saying NEAR would pump around +10% if BTC stabilised, he framed the trade: stop under the recent low at 2.43, CMP 2.64, ride until 2.9-3 while taking TPs along the way. By the next morning it was 1R up (his 75x card: entry 2.643, mark 2.845, +574.24%) and he told anyone who had taken it to book 50% there, while stating that he himself would close the full position around 3. He held the lot and exited everything at 2.897 that afternoon - 'TP hit... pumped exactly 10% as mentioned!' - and two minutes later put the result at 1.6R, worth about two stop-losses, but said he would not count it because it had been an idea rather than a signal. | AA67: recent low | AB67: Conditional on BTC stabilising. | AD67: high | AE67: The 50% partial at 1R was guidance for followers - he explicitly said he would close full around 3 - so no partial is recorded against his own execution. He excludes this trade from his official TP/SL record. | AF67: #336, #339, #342, #347, #349 | AG67: https://discord.com/channels/1042855255089623100/1501271173588193290/1511428643211972619
A68: 67 | B68: 2026-06-03 09:39:45 | C68: BTCUSDT | D68: long | E68: loss | F68: stop_loss | J68: 67300 | K68: 67.3k CMP - he had to clarify twice that it was a market long, blaming a typing mistake | L68: 66550 | M68: 64400 | N68: 69000, 70000 | O68: Opened with a soft stop only (manual close on a 4h close under 64.4k), swapped for a hard 65.3k 'to improve R and avoid soft SL', then back to a soft 4h-close stop at 64.6k plus an unspecified hard stop 'somewhere around 63-64k' purely to avoid a liquidation wick. | R68: 65300 (tighten_hard_stop) -> 65000 (tighten) -> 64600 (soft_4h_close) -> 63000 (widen_personal_hold) | S68: 69300 | V68: 2026-06-03 09:39:45 | W68: 2026-06-04 03:03:12 | X68: 17.4 | Y68: Another dip-buy on the way down: long from 67.3k with a 66,550 DCA underneath, on the view that 64.6k was 'the last near biggest support of BTC' and had to hold. | Z68: He called the long at 67.3k CMP with 69-70k targets and only a soft invalidation - a manual close on a 4h close under 64.4k. Three hours later he restructured it: a 50% DCA at 66,550, the target tightened to a single 69.3k, and the soft stop replaced by a hard 65.3k 'to improve R and avoid soft SL'. He tightened again to 65k that evening, then reversed near midnight and went back to a soft line - a 4h close under 64.6k - advising a hard stop somewhere around 63-64k only to avoid a liquidation wick. At 03:03 on the 4th the candle closed below it: 'BTC closed below the manual SL you guys can exit if you can't risk no more.' He did not exit with them - 'I'LL PERSONALLY HOLD TILL 63K I believe a temporary bounce is coming' - but ninety minutes later he was opening a fresh long at 62.8k, so his own 63k line had gone too. | AA68: 4h close, support/resistance, liquidation levels | AB68: Continued grind lower through 3 June; he was stacking long attempts as price fell. | AD68: medium | AE68: No exit price anywhere; the stop is taken from his own announcement that the manual SL had been broken, and the exit time is that announcement. A clear case of guidance diverging from his own action - he told members to close and kept holding to 63k himself, which price then took out (he was longing at 62.8k an hour and a half later). Whether the 66,550 DCA filled is never confirmed, so no average entry is recorded. Worth flagging that this stop and the 1 June one both contradict his later claim (msg 550, 18 June) of the 'first SL of the month on BTC'. | AF68: #343, #344, #345, #346, #355, #364, #365, #368 | AG68: https://discord.com/channels/1042855255089623100/1501271173588193290/1511620390772801659
A69: 68 | B69: 2026-06-03 14:15:43 | C69: DEXEUSDT | D69: short | E69: win | F69: manual_close | G69: 1.6 | H69: 692.03 | I69: 50 | J69: 21.53 | K69: CMP | M69: 23.56 | N69: 18 | O69: high risk high reward trade | P69: 21.506 | S69: 17.5 | U69: 18.53 | V69: 2026-06-03 14:15:43 | W69: 2026-06-03 19:47:24 | X69: 5.5 | Y69: An updated DEXE short engineered so that the 18 target was worth exactly 2R - high risk, high reward. | Z69: He posted the short at 21.53 CMP with the setup deliberately built so the 18 target paid 2R, stop 23.56. Four hours later DEXE was 1.1R onside and he told members they could trim but no more than 25-30% - he took nothing himself. An hour after that it was 1.6R: he pulled his 18 TP off, saying he would close manually and try for around 3R at 17.5. Forty minutes later he closed the entire short at 18.53 for +1.6R with no partials, explaining that support was forming with the 4h EMA 50 right there and price would hold or bounce if BTC recovered. Under an hour after that 17.464 printed - his extended target - and he admitted he should have held, then moved on. | AA69: support/resistance, EMA | AB69: he expected BTC to recover, which would support DEXE | AD69: high | AE69: The 25-30% trim in msg 354 was guidance for members, not his own action - he confirms at the close that he took no partials and banked the full 1.6R in one go. | AF69: #350, #354, #355, #356, #357, #360 | AG69: https://discord.com/channels/1042855255089623100/1501271173588193290/1511689839416705036
A70: 69 | B70: 2026-06-03 15:59:26 | C70: GOLD | D70: short | E70: never_filled | F70: never_filled | J70: 4474 | K70: Entry limit at 4474 - never filled | M70: 4491 | N70: 4400 | O70: 'RISKY but worth the RR. (Almost 5)'. Posted for the forex traders who asked in chat; he said he would not count it in the crypto TP/SL record. | W70: 2026-06-03 16:49:05 | Y70: A risky but high-RR gold short from a 4474 limit down to 4400, posted for the channel's forex traders. | Z70: He posted a limit short on gold at 4474 with TP 4400 and SL 4491, calling it risky but worth an almost-5 RR, and noted it would not count toward his crypto TP/SL record. Fifty minutes later he cancelled it: price had front-run the entry by $4 and gone without him - 'Cancelled, up 2.5R already, missed by 4$ front ran.' He replaced it half an hour later with a fresh short at market (see the 17:22 position). | AD70: high | AE70: The 2.5R he quotes is what the setup made without him, not a result he banked, so r_multiple stays null. planned_r 5 records his own 'Almost 5' RR estimate. | AF70: #351, #352 | AG70: https://discord.com/channels/1042855255089623100/1501271173588193290/1511715940830547979
A71: 70 | B71: 2026-06-03 17:22:07 | C71: GOLD | D71: short | E71: win | F71: manual_close | G71: 1 | J71: 4452 | K71: 4452 CMP | M71: 4468 | N71: 4427 | O71: Half risk - riskier than the cancelled 4474 setup because the initial entry had already front-run half the target. Not counted in the crypto TP/SL record. | R71: 4452 (to_entry) | V71: 2026-06-03 17:22:07 | W71: 2026-06-03 23:38:18 | X71: 6.3 | Y71: Re-entry of the gold short he had just cancelled, taken at market at 4452 for a shorter 4427 target because the move had already run half its distance without him. | Z71: Half an hour after cancelling the 4474 limit he shorted gold at 4452 CMP with TP 4427 and SL 4468, telling members to use half risk since the move had already front-run half its target. Within two hours it had moved 1R; he told members they could book some and move the stop to entry for safety. An hour later he clarified his own position: 'Still in gold didn't hit BE, it's SL or TP for me' - he was holding the full size for one of the two levels. At 23:38 he called the exit for everyone still in: 'If anyone was hold XAU, exit here, up 1R exactly!' | AD71: high | AE71: He exited at 1R, not at the 4427 target (1R from 4452 with a 4468 stop is around 4436), so this is a manual close rather than a TP. No fill price was ever stated - only 'up 1R exactly', which is his own figure. The book-some-here suggestion at 19:55 was follower guidance; msg 359 shows he took no partial himself. | AF71: #353, #355, #358, #359, #366 | AG71: https://discord.com/channels/1042855255089623100/1501271173588193290/1511736749364351158
A72: 71 | B72: 2026-06-03 21:05:13 | C72: PHAUSDT | D72: long | E72: win | F72: unknown | G72: 0.5 | J72: 0.038 | K72: 0.038 CMP, explicitly a scalp | M72: 0.034 | N72: 0.04, 0.042 | O72: just a scalp, will TP around 0.5-0.7R; cut to half risk after the partial | T72: 30% at 0.04 | V72: 2026-06-03 21:05:13 | Y72: An openly small scalp on PHA at 0.038 with a modest, stated ambition - 0.5-0.7R, roughly 0.04-0.042. | Z72: He called it at 0.038 CMP as an explicit scalp with a 0.034 stop and a stated ambition of 0.5-0.7R, around 0.04-0.042. An hour later it hit 0.04 for 0.5R, he took 30% off and said he would close the rest soon, adding that anyone who dislikes partials could take the whole 0.5R win there. Two hours after that he was still holding, now at half risk, saying the plan was still valid and members could re-enter. The remainder is never resolved - PHA does not appear in the log again. | AC72: yes | AD72: medium | AE72: The 0.5R applies to the 30% he booked, not to the whole trade; the rest was still open when PHA dropped out of the log, so no exit exists. He tells followers he dislikes partials in the same breath as taking one. | AF72: #361, #362, #363, #367 | AG72: https://discord.com/channels/1042855255089623100/1501271173588193290/1511792892069281883
A73: 72 | B73: 2026-06-04 04:33:47 | C73: BTCUSDT | D73: long | E73: win | F73: manual_close | G73: 0.5 | H73: 363.26 | I73: 250 | J73: 62800 | K73: 62.8k, 'Gonna keep longing until I get something'; the stop was edited closer at entry | M73: 60000 | O73: 'I went heavy' - oversized relative to his usual scalp. | P73: 63094.1 | U73: 64082.2 | V73: 2026-06-04 04:33:47 | W73: 2026-06-04 08:52:37 | X73: 4.3 | Y73: Having just been stopped on the 67.3k long, he kept firing long attempts into the flush convinced a temporary bounce was coming - this one caught it from 62.8k. | Z73: Ninety minutes after telling the group his previous BTC long had broken its manual SL, he opened a new one: 'Longed BTC @ 62.8k, SL 60k, Gonna keep longing until I get something', noting he had edited the stop closer. He sized it heavily. Just over four hours later he took the whole thing off into the bounce - 'Closing here for 0.5R, I went heavy' - the 250x card showing average entry 63,094.1, close 64,082.2 and +363.26%. This is the first of the run of BTC wins he counted for the rest of June. | AB73: Capitulation flush into the low 62s on 4 June, immediately after he declared the previous long stopped. | AD73: high | AE73: The announced entry was 62.8k but the closed card averages 63,094.1, so there were fills above the quoted level or an add he did not narrate. The same card is reposted without text on 15 June (msg 487) and is one of the ten enumerated in the 12 June win-streak recap (msg 473). The 0.5R is his own stated figure, not computed. | AF73: #369, #370, #473, #487 | AG73: https://discord.com/channels/1042855255089623100/1501271173588193290/1511905780536967279
A74: 73 | B74: 2026-06-04 13:22:03 | C74: BTCUSDT | D74: long | E74: win | F74: manual_close | H74: 151.99 | I74: 250 | J74: 62800 | K74: 62.8k CMP, 'same setup' as the trade he had just closed; only half the intended size deployed | M74: 59000 | O74: Half size in at entry with 50% held back for a possible DCA - no DCA level was ever published. | P74: 62711.2 | Q74: None (added 25%, average moved to 62.7k - the add price itself was never given) | U74: 63600 | V74: 2026-06-04 13:22:03 | W74: 2026-06-04 15:33:44 | X74: 2.2 | Y74: Immediate re-run of the trade that had just worked - the identical 62.8k long, half size in and half saved to average down, treated openly as a scalp. | Z74: Four and a half hours after banking the first 62.8k long he re-opened the identical setup: 'Longed BTC again from 62.8k same setup, get in CMP', stop 59k, with only half the size deployed because he might DCA. An hour and twenty minutes later he added 25%, taking the average to 62.7k without saying where he added. Fifty minutes after that he was out: 'Closing BTC @ 63.6k with a DCA in, good gains for a scalp!' The announced 250x read +151.99%, and a textless Blofin card twenty minutes later showed the same trade on a second account at 141x, 62,711.2 into 63,567.7 for +192.56%. | AB74: Bounce underway off the 4 June flush; he had banked the same setup four hours earlier. | AD74: high | AE74: Run on at least three accounts: the 250x he announces, the 141x Blofin card (msg 377), and a 250x card in the 12 June recap showing 62,805 into 63,582.5 for +284.66% (msg 473). The quoted ROIs are not mutually consistent for a single price move, so each should be read as that account's own figure. avg_entry is taken from the Blofin card (62,711.2), which matches the 62.7k he stated verbally; exit_price is his own announced 63.6k, with the card showing 63,567.7. | AF74: #371, #372, #373, #374, #375, #376, #377, #473 | AG74: https://discord.com/channels/1042855255089623100/1501271173588193290/1512038721678217308
A75: 74 | B75: 2026-06-05 06:54:21 | C75: DEXEUSDT | D75: short | E75: loss | F75: stop_loss | G75: -1 | J75: 20.63 | K75: CMP | M75: 22.606 | N75: 17.5, 18 | O75: high risk, high reward - he intended to hold for the full 2R rather than trim | P75: 20.63 | S75: 18 | V75: 2026-06-05 06:54:21 | W75: 2026-06-08 14:08:57 | X75: 79.2 | Y75: Round two on the DEXE short after the first one paid, aiming at the same 17.5-18 zone and holding for a full 2R this time. | Z75: Two days after banking the first DEXE short he took round two at 20.63 CMP, targeting 17.5-18 again with a 22.606 stop, and said he would try to take profit at 2R. By Saturday it had moved about 1.1R and he had still taken nothing: he told members they could move their stop to entry if the weekend pump worried them, but that he personally was holding for either the full stop or the full target. On Sunday he restated 18 as a level where members could take 25-30% while he held out for 2R. Monday morning he called the wick up to 22.049 a scam wick and expected a dump - instead the stop went that afternoon. He noted the trade had been 1R in profit and that he took nothing because he was targeting 2, and promised the month would still close at +10R. | AA75: wick | AB75: weekend pump risk | AD75: medium | AE75: The -1R is implied rather than stated: he confirms a full stop-out with no partials on a fixed-R setup. No exit price was restated - his published stop was 22.606. Both the stop-to-entry move (msg 383) and the 18 partial (msg 386) were offered to members, not taken by him. avg_entry 20.63 is his own 'SL to entry' reference; the 8 June chart showed a breakeven line at 20.600. | AF75: #378, #379, #383, #386, #389, #391 | AG75: https://discord.com/channels/1042855255089623100/1501271173588193290/1512303540482347159
A76: 75 | B76: 2026-06-05 11:56:04 | C76: BTCUSDT | D76: long | E76: win | F76: take_profit | H76: 496.61 | I76: 250 | J76: 62300 | K76: 62.3k CMP, with 25-30% held back for a DCA he never used | M76: 59500 | O76: Labelled a 'Risky long'; save 25-30% for a DCA. He later noted that because he did not DCA, a stop at 59k was a straight -1R. | P76: 62300 | R76: 59000 (widen) | S76: 63400 -> 63400/64000 | U76: 64100 | V76: 2026-06-05 11:56:04 | W76: 2026-06-08 01:22:14 | X76: 61.4 | Y76: Third swing at the same idea and an explicit shot at a third BTC win in a row: a risky long at 62.3k expecting the flush to be bought back into the 63-64k area over the weekend. | Z76: He called it a 'Risky long' at 62.3k CMP with a 59.5k stop, telling people to save 25-30% for a DCA and framing it as a shot at a third BTC win in a row. That evening he widened the stop to 59k and said he would personally hold to 58.5k, pointing out that since he had not DCA'd, a 59k stop meant a full -1R. When lows were swept minutes later he told the group a ~25% add was optional but was explicit that he was not adding himself, and that from a 62.3k entry he still expected to close in profit around 63.4k. He carried it through the weekend - 'survived the dump for now' - set the TP at 63.4k, widened the band to 63.4-64k as both his positions came back green, and then took the lot in one go: 'patience fkin paid off, I took 100% at 64.1k', +496.61% on the 250x card, adding 'just to show I didn't take partials, straight away booked at top @ 64!' | AA76: liquidity | AB76: Post-flush chop in the low 60s; he expected a weekend pullback around 63-64k and got it. | AD76: high | AE76: Entry is confirmed by his own words ('If you have entry 62.3k like me') and he stated he never DCA'd, so 62.3k is the true average. The -1R in msg 381 describes what a 59k stop would have cost, not a realised R, so r_multiple is left null. Exit is graded take_profit because 64.1k is at/above the 63.4-64k band he had set, though the close was executed by hand. | AF76: #380, #381, #382, #383, #386, #387, #388 | AG76: https://discord.com/channels/1042855255089623100/1501271173588193290/1512379468772282500
A77: 76 | B77: 2026-06-06 12:10:39 | C77: ETHUSDT | D77: long | E77: unknown | F77: unknown | H77: 20 | J77: 1578 | K77: spot accumulation ladder: 40% at 1578 CMP, 30% at 1370, 30% at 969 | L77: 1370, 969 | O77: not financial advice, his personal spot accumulation plan | V77: 2026-06-06 12:10:39 | Y77: Personal spot accumulation of ETH on a three-step ladder into weakness, held for the bull run rather than traded. | Z77: On 6 June he published his personal spot ladder for ETH: 40% at 1578 CMP, 30% at 1370, 30% at 969. Ten days later he reported the spot bags were nicely up - BTC 8%, ETH 20%, SOL 20% - said he had caught near the bottoms and was holding them all. ETH still appears in the bull-run allocation donut he posted on 20 August at 20.82% of the portfolio, so the bag was never sold in this log. | AB77: buying near what he called the bottoms for big caps | AC77: yes | AD77: medium | AE77: Spot accumulation, not a leveraged call: no stop and no target. Whether the 1370 and 969 rungs ever filled is never stated - only the +20% mark-to-market on 16 June. Outcome left unknown because he never sold. | AF77: #384, #504, #995 | AG77: https://discord.com/channels/1042855255089623100/1501271173588193290/1512745526649684000
A78: 77 | B78: 2026-06-06 12:10:39 | C78: SOLUSDT | D78: long | E78: unknown | F78: unknown | J78: 63 | K78: 63 CMP for 40% of the intended size; spot accumulation, not a leveraged trade | L78: 46, 30 | O78: 'Not any financial advice, just my personal spot accumulation plan I'm sharing.' 40% / 30% / 30% ladder. | V78: 2026-06-06 12:10:39 | Y78: A personal spot accumulation ladder in SOL - buy 40% at 63 and keep dry powder for 46 and 30 - held for the bull run rather than traded. | Z78: He published his personal spot ladder for SOL - 40% at 63 CMP, 30% at 46, 30% at 30 - flagged as not financial advice. Ten days later the first tranche was clearly filled and working: 'our spot bags are nicely up... BTC 8%, ETH 20%, SOL 20%. Caught nearly bottoms... holding them all!' The lower rungs never came. Through August he kept pointing at the bag rather than trading it: on 19 August 'up nearly 30% if you want to take something. I'll TP around new ATH or so'; on 20 August SOL sat at 13.64% of the bull-run allocation donut he posted; on 21 August he noted SOL moving with SUI, AVAX and LINK; and later that day, with SOL around 90, he called 80-90 a decent buying range for a mid to short term hold. The position is still open when the log ends. | AB78: Long-horizon bull-run accumulation alongside BTC, ETH and later HYPE, SUI, AVAX and LINK. | AC78: yes | AD78: medium | AE78: Spot and unleveraged, kept separate from his leveraged SOL trades, several of which ran concurrently. The 46 and 30 DCA rungs never filled. The '+20%' (16 June) and 'up nearly 30%' (19 August) are progress marks on an open bag, not a result, so roi_pct is null - and the 30% figure covers HYPE and SOL together, with only HYPE carrying a share card. His 19 August line about recommending SOL 'for a month now' sits later than this 6 June ladder, so the two may be separate recommendations of the same bag. | AF78: #384, #504, #981, #995, #999, #1002 | AG78: https://discord.com/channels/1042855255089623100/1501271173588193290/1512745526649684000
A79: 78 | B79: 2026-06-06 12:10:39 | C79: BTCUSDT | D79: long | E79: unknown | F79: unknown | J79: 61000 | K79: 61k CMP for 40% of the intended spot allocation | L79: 56000, 46000 | O79: Spot accumulation - no leverage, no stop; posted as his own plan and explicitly not financial advice. | P79: 61000 | V79: 2026-06-06 12:10:39 | Y79: Separate from the leveraged scalp book: accumulate BTC spot in thirds on the way down - 40% at 61k with ladders at 56k and 46k - on the view that the area was close to the bottom. | Z79: He posted the ladder on 6 June - 40% at 61k CMP, 30% at DCA1 56k, 30% at DCA2 46k - for anyone interested in spot accumulation, with no stop and no target. BTC never came near either DCA level in this window, so only the first tranche can have filled. He never mentions selling any of it. Past the end of the window, on 16 June, he reports the spot bags up (BTC +8%, ETH +20%, SOL +20%), says he caught nearly the bottom and is holding them all. | AB79: Early-June washout; he believed the local bottom was in and wanted unlevered exposure alongside the scalps. | AC79: yes | AD79: medium | AE79: Recorded as a position because it is a directional BTC trade he took, but it is spot, not one of his leveraged calls - R, ROI, leverage and stop fields do not apply. Msg 384 is phrased as 'if anyone's interested', so his own participation is confirmed only by later context (msg 504, 16 June: 'our spot bags are nicely up, BTC 8%'); +8% against BTC's ~65.6k price that day back-solves to roughly a 61k entry, which matches the CMP tranche. No exit anywhere in the log, so the position runs past the end of the window. | AF79: #384, #504 | AG79: https://discord.com/channels/1042855255089623100/1501271173588193290/1512745526649684000
A80: 79 | B80: 2026-06-08 14:06:00 | C80: BTCUSDT | D80: short | E80: win | F80: manual_close | H80: 158.99 | I80: 250 | J80: 63123 | K80: 63,123 CMP for 50% of size, with a 50% DCA above at 64,250 | L80: 64250 | M80: 65500 | N80: 61500 | O80: 'A bit risky since I expect pump' - half risk offered to anyone who wanted it. | P80: 63123 | S80: 61800 | U80: 62600 | V80: 2026-06-08 14:06:00 | W80: 2026-06-09 13:54:22 | X80: 23.8 | Y80: The only short in the run, and taken against his own bias purely to get paid down to a level he wanted to buy: 'I'm planning to long at 61.5k so trying to short till there', even though he expected a pump first. | Z80: He shorted at 63,123 CMP with a 50% DCA at 64,250, target 61.5k and stop 65.5k, openly flagging that the trade cut against his own view - the point was to get paid on the way down to the level he wanted to buy. That evening the DCA was 'barely missed', so he nudged it up to 64.3k. By the next morning price had missed it by about $50, which he said would have made the trade 'a total banger', and he warned he might take profit earlier around 61.8k instead of 61.5k. He waited for neither: 'Closing BTC in small profits @ 62.6k, keeps missing DCA and keeps coming back to entry. 4th win a row on BTC though.' | AB80: Chop in the low 60s; he was structurally bullish underneath but wanted a cheaper long entry at 61.5k. | AD80: high | AE80: Neither DCA level (64,250, then 64.3k) ever filled, so the average entry is the 63,123 CMP figure from the call. The 250x card enumerated in the 12 June recap shows 63,068 into 62,699.6 for +135.5%, slightly different from the entry, close and ROI he announced - a second account of the same short. | AF80: #390, #392, #396, #400, #473 | AG80: https://discord.com/channels/1042855255089623100/1501271173588193290/1513499332383473724
A81: 80 | B81: 2026-06-09 03:22:25 | C81: GOLD | D81: short | E81: unknown | F81: unknown | J81: 4325 | K81: 'Entry: 4325 or 4322 CMP' - already shorted when he posted it | M81: 4349 | N81: 4275 | O81: On crypto exchanges he told members to keep the stop $2-3 wider because of price difference and slippage, and to use XAU rather than XAUT. | V81: 2026-06-09 03:22:25 | Y81: A gold short from 4325 toward 4275 posted for the members who trade gold. | Z81: He posted that he had shorted gold at 4325 (or 4322 CMP) with TP 4275 and SL 4349, then followed up with two execution notes for members: gold trades as XAU on crypto exchanges, not XAUT, and the stop should be kept $2-3 wider there because of the price difference and slippage. The short is then never mentioned again - twelve hours later he was long gold from 4340-4342, so it was gone by then, but he never said how. | AD81: low | AE81: No exit of any kind was posted. Two readings: price rose into his 4349 stop (his later long, msg 406, says 'this hit SL again', implying an earlier stop-out), or he closed it manually when he flipped long at 4340-4342 - a level still below the stop. Left unknown rather than guessing; the published 4349 stop is in planned_stop. | AF81: #393, #394, #395 | AG81: https://discord.com/channels/1042855255089623100/1501271173588193290/1513699759133687850
A82: 81 | B82: 2026-06-09 08:08:31 | C82: BEATUSDT | D82: short | E82: loss | F82: stop_loss | G82: -1 | I82: 25 | J82: 4.25 | K82: '4.25 or 4.2 CMP' - his card shows the fill at 4.2 | M82: 4.58 | O82: high risk high reward - either SL or 1.5-2R minimum | P82: 4.2 | U82: 4.58 | V82: 2026-06-09 08:08:31 | W82: 2026-06-09 13:56:55 | X82: 5.8 | Y82: A binary high risk / high reward short on BEAT at 4.25-4.2 - in his own framing, either the stop or 1.5-2R minimum. | Z82: He called the short at 4.25 or 4.2 CMP with a 4.58 stop and no target, framing it as binary: either the stop or 1.5-2R minimum. It worked immediately - while he slept it ran 2.5R, and by 11:14 it was back to 1.8R with the 25x card at +289.79% from 4.2. He told the room to take profit wherever they were happy and said he would post where he closed. He never got the chance: at 13:56 it stopped him out at 4.58 after having moved 2.8R in his favour, and he said he hoped members had taken profits. Three minutes later he asked the channel to vote on whether a trade that went to huge profit before stopping should count as a win or a loss. | AD82: high | AE82: He was himself unsure how to score it and polled the room, because it ran 2.8R before stopping. Recorded as a loss because his own stop-out message gives -1R and he never trimmed. The exit price is the published 4.58 stop level, not a quoted fill. | AF82: #397, #398, #399, #401, #403 | AG82: https://discord.com/channels/1042855255089623100/1501271173588193290/1513771757515968623
A83: 82 | B83: 2026-06-09 15:01:13 | C83: GOLD | D83: long | E83: loss | F83: stop_loss | J83: 4340 | K83: Entry zone 4340-4342 CMP | M83: 4330 | O83: Very tight stop - $10 from entry. | V83: 2026-06-09 15:01:13 | W83: 2026-06-09 16:42:24 | X83: 1.7 | Y83: He flipped from short to long on gold at market with a very tight 4330 stop and no published target. | Z83: Twelve hours after shorting gold he flipped: 'Long GOLD (XAU) again, Entry: 4340-4342 CMP, SL: 4330', and immediately reminded members that gold trades would be kept out of the crypto summary and get their own. Ninety minutes later it was over - 'Sorry guys this hit SL again, moved almost 1R and SL' - and eight minutes after that he posted the salt in the wound: the stop was hit exactly on the wick low and gold then ran what would have been 4R in his direction, price already back at 4361.07. 'Hit my SL exactly to go 4R up, not my day.' | AA83: wick | AD83: high | AE83: A full stop-out at the published 4330 level; he never stated a fill price or an R figure for the loss (the '1R' and '4R' he mentions are the favourable excursion before and after the stop), so exit_price and r_multiple are null. | AF83: #404, #405, #406, #411 | AG83: https://discord.com/channels/1042855255089623100/1501271173588193290/1513875615185502289
A84: 83 | B84: 2026-06-09 17:31:10 | C84: BTCUSDT | D84: long | E84: win | F84: manual_close | J84: 61400 | K84: 61.4k CMP for 75% of size, 25% reserved for the 60.7k DCA | L84: 60700 | M84: 58500 | O84: Explicitly labelled the low-RR / high-win-rate type of trade - he said he would post both types so members could pick. | P84: 61400 | U84: 61600 | V84: 2026-06-09 17:31:10 | W84: 2026-06-10 02:42:36 | X84: 9.2 | Y84: A deliberately low risk-reward, high win-rate BTC scalp from 61.4k - one of the two trade types he said he would alternate so members could take whichever suited them. | Z84: He called the scalp at 61.4k CMP with 75% in and 25% reserved for a 60.7k DCA and a 58.5k stop, labelling it explicitly as the low-RR / high-WR kind of trade. That evening BTC missed the DCA by about $20, which he shrugged off since the tranche was only a quarter. When war headlines hit after midnight he told anyone who could not carry the risk to exit and said he would 'play full setup' himself. Half an hour later he did the opposite: 'Exiting BTC in small profits @ 61.6k will look to enter around DCA, I was planning to keep this but already have a risky trade running no need to risk more. Small win but better than red.' | AA84: news | AB84: War-related headlines broke overnight while the position was open. | AD84: high | AE84: No PnL card was posted for this one, so there is no ROI figure and no leverage; the $200 from 61.4k to 61.6k matches the 'small profits' he describes. The 60.7k DCA never filled, so 61.4k is the average. Worth flagging the gap between guidance and action: he told the group he would play the full setup and closed thirty minutes later. | AF84: #413, #414, #420, #422, #423 | AG84: https://discord.com/channels/1042855255089623100/1501271173588193290/1513913353032958134
A85: 84 | B85: 2026-06-09 19:55:34 | C85: BEATUSDT | D85: short | E85: unknown | F85: unknown | J85: 4.7 | K85: 4.7, confirmed as CMP six seconds later | M85: 5.1 | N85: 3.4 | O85: high risk high reward; half risk, 'it's risky at BE so adjust' | V85: 2026-06-09 19:55:34 | Y85: Straight back into the BEAT short six hours after being stopped, this time from 4.7 with 3.4 as the target - he reckoned 3R was confirmed if it dropped. | Z85: Six hours after the previous BEAT short stopped out he tried again: short at 4.7 CMP, target 3.4, stop 5.1, high risk / high reward. He confirmed the entry was at market, told the room to use half risk because 'it's risky at BE so adjust', and ten minutes later said that if it dropped, 3R was confirmed. That is the last word on it - no fill, no management, no exit. When BEAT next appears in the log, on 27 June, he is buying it in spot at 2.6, far below this short's 3.4 target. | AC85: yes | AD85: medium | AE85: Never resolved in the log: no stop-out, no target fill, no card. Marked still open only because nothing reports it closing - by the time BEAT reappears on 27 June he is trading it from the long side in spot, so it was almost certainly settled off-log. The 3R is his own 'if it drops 3R is confirmed', not a result. | AF85: #416, #417, #418, #419 | AG85: https://discord.com/channels/1042855255089623100/1501271173588193290/1513949690583060540
A86: 85 | B86: 2026-06-10 11:21:57 | C86: ALLOUSDT | D86: short | E86: loss | F86: stop_loss | G86: -1 | I86: 100 | J86: 0.425 | K86: 0.425 CMP with a 25% DCA leg above at 0.44 | L86: 0.44 | M86: 0.468 | N86: 0.3 | O86: High risk high reward trade; he took either the full TP or the stop, no partials, and told followers not to copy him on refusing to move the stop | P86: 0.425 | S86: 0.36 | U86: 0.468 | V86: 2026-06-10 11:21:57 | W86: 2026-06-12 20:16:14 | X86: 56.9 | Y86: A high risk / high reward short on ALLO he had been waiting for since the weekend. He wanted the whole 2R or nothing and refused to trim or move his stop - and it cost him the entire move. | Z86: He had said on 6 June that he would try shorting ALLO if he saw weakness, and took it on 10 June at 0.425 CMP with a 25% DCA planned at 0.44 and a 0.468 stop; the 0.3 target followed half an hour later. By that afternoon it had moved 1.3R for him - and far more for the chat, many of whom had shorted higher and were 4R up - so he pulled the target in to about 0.36, roughly 2R, and said he would take either a full TP there or the stop, no partials, and would post when he closed. Overnight he was 1.5R up on the 100x card (+1037.04%) and hoping for 0.33-0.36. On the morning of 11 June he reminded followers that they could move their stop to entry at 1.5R while making clear he was not moving his own and that they should not be like him. It reached 1.8R, and his end-of-day tally put it at 1.4R. On 12 June it came all the way back and stopped him at the original 0.468 for -1R. He said he had no regrets - he wanted 2R whole or the stop - but noted he had round-tripped big profits while the chat had been up 4-5R. | AB86: slow weekend, nothing much to do | AD86: high | AE86: His entry is his own 'original entry' 0.425 - no fill card was ever posted - and the planned 0.44 DCA is never confirmed as filled. No stop moves are recorded because he explicitly did not move his: the 1.5R stop-to-entry advice at msg 450 was for followers only. Msg 385, four days earlier, is only the intent to look for the trade, so first_seen is the call itself. | AF86: #385, #425, #426, #429, #445, #450, #451, #456, #461, #472 | AG86: https://discord.com/channels/1042855255089623100/1501271173588193290/1512792986805866587
A87: 86 | B87: 2026-06-10 11:49:46 | C87: BTCUSDT | D87: long | E87: win | F87: manual_close | I87: 150 | J87: 61100 | K87: 61.1k CMP with the majority at market and only a 25% DCA at 59.5k | L87: 59500 | M87: 58500 | N87: 63000 | O87: Scalp; majority of size at CMP with a small 25% tranche held for the 59.5k DCA. | P87: 61100 | S87: 62460/63000 | T87: 25% at 62460 | U87: 62700 | V87: 2026-06-10 11:49:46 | W87: 2026-06-10 18:56:57 | X87: 7.1 | Y87: Scalp long into the CPI release from 61.1k, then a nearer first target added at 62,460 once the print pumped it. | Z87: He called the scalp at 61.1k CMP with a small 25% DCA at 59.5k, a 63k target and a 58.5k stop. As CPI pumped it he inserted a nearer first target - 'Pump it boys, first TP @ 62460' - which hit an hour and a quarter later, taking 25% off with the 150x card at +290.59% and keeping the majority for 63k+. He celebrated the move ('1400$ move caught, that's how we trade CPI') and then, two hours later and short of his 63k target, cleared the rest: 'fully out of BTC @ 62.7k don't want to round trip these gains.' He broke it down afterwards - 25% out at 62,460 and 75% at 62,700 from a 61.1k entry, average close 62,668.4 - and said he would look to short the 63.2-64k area next. | AA87: CPI, news | AB87: CPI release day; the print carried BTC roughly $1,400 higher inside a few hours. | AD87: high | AE87: The closed card listed in the 12 June recap (62,141.4 into 62,668.4, +197.68%) has an entry about $1,000 above the 61.1k he repeatedly quotes - either a second account that entered late or a mislabelled card; the 62,668.4 close does match his stated average close. The 59.5k DCA never filled. His follow-on intention to short 63.2-64k (msg 439) was never acted on - he went long again at 62.2k an hour later instead - so it is not recorded as a position of its own. | AF87: #427, #428, #434, #435, #438, #439, #473 | AG87: https://discord.com/channels/1042855255089623100/1501271173588193290/1514189823550947349
A88: 87 | B88: 2026-06-10 16:31:11 | C88: INJUSDT | D88: long | E88: win | F88: manual_close | G88: 0.8 | H88: 216.11 | I88: 75 | J88: 5.14 | K88: CMP | L88: 5.052 | M88: 4.8 | N88: 5.5 | O88: 1R scalp | Q88: 5.052 (the planned DCA filled - he refers to it as filled in msgs 448 and 452 - but he never gives the fill time or the blended average) | T88: 25% at 5.3 | U88: 5.28 | V88: 2026-06-10 16:31:11 | W88: 2026-06-11 11:37:06 | X88: 19.1 | Y88: A 1R scalp long on INJ with a DCA just under the entry. | Z88: He called INJ long at 5.14 CMP with a DCA at 5.052, a 5.5 target and a 4.8 stop, describing it as a 1R scalp. The DCA filled and INJ ran 1R quickly - too quickly for him to update in time - so the next morning he took 25% off at 5.3 and pointed out that he had not moved his stop at all. It stretched to 1.1R, then stalled; by late morning he closed the rest at 5.28, saying INJ was lagging and the DCA had already filled so he was happy with the profits. His end-of-day recap booked it at 0.8R against a best move of 1.2R. | AD88: high | AE88: He never states a blended average after the DCA filled, so avg_entry is null; the published levels were 5.14 and 5.052. The +216.11% card figure appears on both the partial and the final close. | AF88: #430, #431, #448, #451, #452, #461 | AG88: https://discord.com/channels/1042855255089623100/1501271173588193290/1514260647444217999
A89: 88 | B89: 2026-06-10 16:33:14 | C89: WLDUSDT | D89: long | E89: loss | F89: stop_loss | J89: 0.515 | K89: CMP | M89: 0.45 | N89: 0.56, 0.64 | O89: after two adds he was risking 1.3R and told the group not to risk more than 1.5R | P89: 0.484 | Q89: None (first add - he gives only the new average of 0.49, not the fill price) | 0.47 (second add; average down to 0.484 and total risk up to 1.3R) | U89: 0.45 | V89: 2026-06-10 16:33:14 | W89: 2026-06-10 19:16:13 | X89: 2.7 | Y89: Long WLD at market for a run at 0.56-0.64. | Z89: He called the long at 0.515 CMP with a 0.45 stop and 0.56-0.64 targets. It went against him immediately: two hours later he DCAed, giving a new average of 0.49, and eleven minutes after that he added again at 0.47 for an average of 0.484, warning that he was now risking 1.3R and that nobody should risk more than 1.5R. Twenty-three minutes later the 0.45 stop went. He apologised to the group, calling it an abnormal dump and bad luck. | AB89: an abnormal dump on WLD which he put down to bad luck | AD89: high | AE89: He never states the R loss; he had said he was risking 1.3R after the second add, so the damage was probably about that, but it is not recorded. The first DCA's fill price was never given - only the resulting 0.49 average. | AF89: #432, #436, #437, #440 | AG89: https://discord.com/channels/1042855255089623100/1501271173588193290/1514261162919727245
A90: 89 | B90: 2026-06-10 20:04:13 | C90: BTCUSDT | D90: long | E90: win | F90: manual_close | H90: 363.9 | I90: 250 | J90: 62200 | K90: 62.2k CMP for 40%, 40% at a 61k DCA and 20% at 60.7k - 'Entry is small DCA is bigger' | L90: 61000, 60700 | M90: 59000 | N90: 63000, 64000 | O90: Size split 40-40-20 across the entry and two DCAs; targets split 25% at 63k and 75% at 64k. He suggested using ChatGPT to work out the split. | P90: 62200 | R90: 60000 (tighten) | S90: 64200 | T90: 25% at 62946 | U90: 63800 | V90: 2026-06-10 20:04:13 | W90: 2026-06-11 22:38:19 | X90: 26.6 | Y90: Laddered long from 62.2k with most of the intended size sitting lower, targeting 63k and 64k on the post-CPI drift higher. | Z90: He laddered the entry - 40% at 62.2k CMP, 40% at 61k, 20% at 60.7k, stop 59k, targets 63k for a quarter and 64k for the rest. Neither DCA filled; BTC missed the 61k by $50. He deliberately passed on a 62.9k print in the early morning because the move was too quick and he 'didn't want to take TP without you guys', then took the 25% tranche just under target at 62,946 on the 250x card (+315.35%), with a 150x card of the same trade at +245.5% a minute later. He confirmed he was still holding 75% from 62.2k, left the stop alone at first, set a fresh equal-sized DCA at 61.8k, then did raise the stop to 60k and gave anyone who had exited a 40%/60% re-entry plan. That evening he moved the remaining target from 64k up to 64.2k with instructions to book immediately on a rejection at 64k, then closed everything early: 'Fully closed BTC here at 63.8k, going to sleep', leaving a hold-on plan for anyone who wanted to stay in. 'Almost a 1800$ caught. 8/8 wins on BTC.' | AA90: resistance | AB90: Post-CPI grind higher; his BTC win streak stood at six going into this trade and at eight coming out. | AD90: high | AE90: The 0.8R in msg 461 is a running tally while the position was still open, not a realised R, so r_multiple is left null. His narrated numbers (62.2k into 63.8k, +363.9% at 250x) do not reconcile with the card in the 12 June recap (62,314.4 into 63,552.2, +463.21%), which is a different account of the same trade. All three DCA levels - 61k, 60.7k and the later 61.8k - went unfilled, so 62.2k is the average. | AF90: #441, #442, #443, #446, #447, #449, #451, #453, #454, #455, #457, #458, #461, #462, #463, #464, #473 | AG90: https://discord.com/channels/1042855255089623100/1501271173588193290/1514314257548972143
A91: 90 | B91: 2026-06-11 03:10:39 | C91: SOLUSDT | D91: long | E91: win | F91: manual_close | G91: 1.5 | H91: 778.04 | I91: 125 | J91: 63.2 | K91: 63.2 CMP | M91: 60 | N91: 68 | O91: 'High risk high reward trade'. | P91: 63.3 | R91: 63.3 (to_entry) | U91: 67.24 | V91: 2026-06-11 03:10:39 | W91: 2026-06-11 22:42:56 | X91: 19.5 | Y91: A high-risk, high-reward SOL long at market from 63.2 with a 68 target and a 60 stop. | Z91: He called SOL long at 63.2 CMP - TP 68, SL 60, openly high risk high reward. By mid-morning it had moved 1R; by late afternoon a full 1R and he was 'confused if I should close or hold till original TP 68-69'. That evening the card read entry 63.30, mark 66.97, +726.09% on 125x: 'SOL up 1.5R, can take a small TP, already SL at entry, will fully exit at 68', and his day tally a minute later logged SOL at 1.5R. He never got 68 - the recap card two hours later shows the whole 125x position closed at 67.24 for +778.04%. | AD91: medium | AE91: The close is documented only by the share card in the recap (67.24), never stated in text. r_multiple 1.5 is his own figure from the 20:55 tally, taken before the slightly better card close, so the true result is a touch above 1.5R. The 'can take a small TP' line was follower guidance - he exited in one piece. | AF91: #444, #451, #459, #460, #461, #465 | AG91: https://discord.com/channels/1042855255089623100/1501271173588193290/1514421571350167613
A92: 91 | B92: 2026-06-12 11:54:07 | C92: BTCUSDT | D92: long | E92: win | F92: manual_close | H92: 305.06 | I92: 250 | J92: 63400 | K92: 63.4k CMP, with 30-40% saved for a DCA | M92: 60500 | N92: 64900, 65900 | O92: Save 30-40% for a DCA; no DCA level was ever published and none is recorded as filled. | P92: 63477.6 | U92: 64252.2 | V92: 2026-06-12 11:54:07 | W92: 2026-06-12 18:25:45 | X92: 6.5 | Y92: Straight continuation long at 63.4k on the view that 65-66k was coming, targeting 64.9-65.9k. | Z92: He called the long at 63.4k CMP with a 60.5k stop, 64,900-65,900 targets and 30-40% held back for a DCA. Six and a half hours later he was out - 'TPed on BTC personally' - the 250x card at +305.06%, while telling anyone still in that 64,900 remained the target, a line he repeated twice more over the next ten minutes. He said he would go long again on a drop because he believed 65-66k was coming, and flagged 66-66.2k as a place to short and 63-63.4k as a place to buy back. Later that evening he claimed a ten-trade BTC win streak on scalps, backing it with ten closed share cards. | AB92: Steady grind higher through 12 June with his BTC win streak intact. | AD92: medium | AE92: He gave no exit price in the close message. Entry 63,477.6 and close 64,252.2 are taken from the card enumerated in the 12 June recap - the only card in that list matching a 63.4k CMP entry, and consistent with him exiting below the 64,900 he left for holders - but that mapping is an inference, hence medium confidence. Exit type is recorded as manual_close rather than take_profit because the posted 64,900 target was never reached, even though he described it as 'TPed'. | AF92: #467, #468, #469, #471, #473 | AG92: https://discord.com/channels/1042855255089623100/1501271173588193290/1514915694922170429
A93: 92 | B93: 2026-06-13 03:24:26 | C93: BTCUSDT | D93: long | E93: win | F93: manual_close | H93: 228.9 | I93: 250 | J93: 63500 | K93: 63.5k CMP; 30% was to be saved for a DCA but nine minutes later he cut that to 20-25% and went heavy at market | M93: 61500 | N93: 64500, 64700 | O93: The 0.5-0.7R scalp template - 'Same strategy 0.5-0.7R TP, so get out around 64.5-64.7k.' He did not expect the DCA to fill so kept only a 20-25% backup tranche. | P93: 63500 | T93: 40% at 64200 | U93: 64200 | V93: 2026-06-13 03:24:26 | W93: 2026-06-13 21:25:11 | X93: 18 | Y93: The 0.5-0.7R scalp template again from 63.5k, heavy at market because he did not expect a DCA fill, aiming to be out around 64.5-64.7k. | Z93: He called the long at 63.5k CMP with a 61.5k stop and 30% notionally saved for a DCA, then said nine minutes later that he did not expect the DCA to fill so he was keeping only 20-25% as backup and going heavy at market, with the usual 0.5-0.7R exit around 64.5-64.7k. Nearly thirteen hours later, with BTC close to target, he trimmed 40% at 64.2k on the 250x card (+228.9%) and left the rest for 64.5k, explaining the early trim as the consequence of being heavy at market. Five hours after that he cleared the remainder at the same 64.2k because price was 'struggling around resistance', told anyone who wanted to hold to go for it since he felt 66k was coming, and said he would look to re-enter a scalp around 63.3-63.5k. The next morning he confirmed the target was reached without him: 'Well BTC went to TP as expected but got out earlier.' | AA93: resistance | AB93: Grinding toward 64-65k; he thought 66k was coming but did not want to sit through resistance. | AD93: high | AE93: Both the 40% partial and the final exit landed at 64.2k, so the partial price and exit_price are the same figure. The 0.5-0.7R was a published target, not a realised result - he never stated the R he actually got - so it is recorded as planned_r and r_multiple is left null. The targets in planned_take_profits come from msg 477 nine minutes after the call, since the call itself carried none. | AF93: #474, #475, #477, #479, #480, #482, #483 | AG93: https://discord.com/channels/1042855255089623100/1501271173588193290/1515149817633046591
A94: 93 | B94: 2026-06-14 10:20:26 | C94: RENDERUSDT | D94: long | E94: win | F94: manual_close | H94: 91.99 | I94: 90 | J94: 1.76 | K94: 1.76 CMP, flagged as a risky long | M94: 1.6 | N94: 1.9 | O94: Can go half risk as it's risky, your choice | P94: 1.761 | R94: 1.76 (to_entry) | U94: 1.779 | V94: 2026-06-14 10:20:26 | W94: 2026-06-16 00:12:39 | X94: 37.9 | Y94: A second, deliberately risky long on RENDER at 1.76 aiming for 1.9 with a wide 1.6 stop. | Z94: He called the risky long at 1.76 CMP for 1.9 with a 1.6 stop and half risk optional. By the next morning it was up more than 0.7R and he was holding; by that afternoon it had moved a full 1R, and he told members to trim if they wanted but said he avoids partials and planned to exit fully near 1.9. That evening the price action stalled and he pulled the stop up to entry - 'this shit is going no where' - and just after midnight he closed the whole thing at 1.779 from 1.761 for +91.99% at 90x, apologising for the round trip from 1R but saying it beat hitting breakeven. | AB94: AI coins lagged the tape on the day he closed | AD94: high | AE94: The 1R and 0.7R figures are mid-trade marks, not the result - he gave up almost all of it before closing, so r_multiple is left null. | AF94: #484, #492, #498, #499, #503 | AG94: https://discord.com/channels/1042855255089623100/1501271173588193290/1515616893787050035
A95: 94 | B95: 2026-06-14 11:24:29 | C95: PYTHUSDT | D95: long | E95: win | F95: manual_close | H95: 292.53 | I95: 75 | J95: 0.039 | K95: 0.039, confirmed as CMP five seconds later | M95: 0.0363 | N95: 0.04169 | P95: 0.0391 | U95: 0.392 | V95: 2026-06-14 11:24:29 | W95: 2026-06-15 05:45:54 | X95: 18.4 | Y95: A tight long on PYTH from 0.039 with a 0.04169 target and a 0.0363 stop. | Z95: He called PYTH long at 0.039, confirming CMP seconds later, with TP 0.04169 and SL 0.0363. Overnight it went nowhere and he bailed the next morning: 'Closed PYTH in very small profits @ 0.392, it's going no where and I'm afraid when BTC reverses it dies.' Nine hours later he had to eat it - 'Closed PYTH publicly just to see it flying' - posting the closed 75x card showing entry 0.0391 and a 0.04062 close for +292.53%. | AB95: Worried a BTC reversal would kill the trade. | AD95: medium | AE95: Exit price recorded verbatim as he wrote it, 0.392, which is almost certainly a typo for 0.0392 given the 0.039 entry. The card he posted later shows the close at 0.04062, higher than the 0.0392 he announced - possibly a different account or a later fill; the two cannot both be his single exit. | AF95: #485, #486, #492, #494 | AG95: https://discord.com/channels/1042855255089623100/1501271173588193290/1515633013034193059
A96: 95 | B96: 2026-06-15 00:29:37 | C96: OIL | D96: short | E96: win | F96: unknown | H96: 450.98 | I96: 100 | W96: 2026-06-15 00:29:37 | Y96: A WTI oil short he ran without posting it to the channel - the only trace is the closed PnL card. | Z96: The only evidence of this trade is a share card posted with no text: a 100x short on the OIL(WTI)USDT perpetual, closed at +450.98%. He never posted the call, the entry, the stop, the target or the exit here - the following message acknowledges it was a trade he had not shown the channel. | AD96: medium | AE96: Entry price, exit price, entry time and all levels are unknown - only the closed card's +450.98% on 100x is given, which is why the outcome is a win with no supporting numbers. Symbol recorded as it appears in the file (OIL); the card reads OIL(WTI)USDT. | AF96: #488 | AG96: https://discord.com/channels/1042855255089623100/1501271173588193290/1515830600559493281
A97: 96 | B97: 2026-06-15 00:48:17 | C97: LTCUSDT | D97: long | E97: not_taken | F97: not_taken | Y97: He backed a member's LTC long on the view that incoming news would break LTC's daily resistance. | Z97: He recalled that a member had asked the day before whether to long LTC and that he had said go for it, because news would come and break LTC's daily resistance. The screenshot he posted of those earlier messages shows LTC struggling at daily resistance but able to see 45-46 and then 48. He never called LTC in the channel and never showed a position of his own in it. | AA97: daily resistance, news | AD97: medium | AE97: Advice given to one member in chat, recounted after the fact - no entry, stop or size for himself, so recorded as not_taken. The 45-46 and 48 levels come from a screenshot of his earlier posts, not from a published call. | AF97: #491 | AG97: https://discord.com/channels/1042855255089623100/1501271173588193290/1515835294291722241
A98: 97 | B98: 2026-06-15 05:51:14 | C98: BTCUSDT | D98: short | E98: win | F98: take_profit | G98: 0.5 | H98: 160.49 | I98: 250 | J98: 66000 | K98: 66k limit short, to be cancelled if BTC fell to 64.7k before filling | M98: 68000 | O98: don't risk more than 1% on real and 0.3-0.4% funded because the market is highly bullish; he himself started at 0.5R and scaled to a full 1R | P98: 66200 | Q98: None (added a bit more margin, no price given, expecting at least the 65k region) | None (scaled from 0.5R to full 1R risk; told members they could still add because it was above breakeven) | 66400 (50% add at 66.4k, lifting the average entry to 66.2k) | S98: 65500 -> 64800/65300 | V98: 2026-06-15 14:37:24 | W98: 2026-06-16 17:36:35 | X98: 27 | Y98: Fade the rally with a limit short at 66k into a market he himself called highly bullish, cancelling the order if BTC fell to 64.7k first; he expected at least a move back into the 65k region. | Z98: He set a 66k limit short on 06-15 with a 68k stop and a standing instruction to cancel it if BTC fell to 64.7k first; the limit filled at 66k the next afternoon and he immediately told members to keep risk tiny (max 1% real, 0.3-0.4% funded) because the market was still highly bullish. Overnight he added margin twice - once with no price given, then scaling his own risk from 0.5R to a full 1R while telling members they could still add since the trade was above breakeven - and then made a well-timed 50% add at 66.4k that lifted the average to 66.2k. The exit zone moved from 'around 65.5k' down to 64.8-65.3k and the target was hit about eight minutes later for 0.5R, +160.49% on the 250x card. Twenty minutes after that he posted the same trade from his other exchange, a sniper entry at 67,119.9 closed at 65,634.5 for +331.94%, and claimed 12/12 BTC wins for the month. | AB98: highly bullish market on a 11-12 trade BTC win streak; he deliberately kept risk small because he was fading strength | AD98: high | AE98: No exit price was posted for the 250x account - only the +160.49% card - so exit_price is null. The 150x card from his other exchange states a close at 65,634.5, but that is a different fill (67,119.9 entry) and sits above the 64.8-65.3k exit zone he had just announced, so it is not carried over as this position's exit. The two adds at msgs 503 and 508 have no prices. | AF98: #493, #495, #503, #505, #508, #511, #512, #513 | AG98: https://discord.com/channels/1042855255089623100/1501271173588193290/1515911537771024415
A99: 98 | B99: 2026-06-15 20:43:58 | C99: ZECUSDT | D99: short | E99: not_taken | F99: not_taken | J99: 530 | K99: 530 CMP, offered as an optional idea for members - he states plainly that he is not taking it | M99: 550 | N99: 480, 490 | O99: if anyone wants to take it, risk 1-2% max | R99: 559 (widened) -> 530 (to_entry) | S99: 482 | Y99: An optional short idea he floated for members who wanted something to trade - ZEC from 530 down to 480-490 - and explicitly did not take himself. | Z99: He posted it as a trade idea for anyone who wanted to try it: short ZEC at 530 CMP, stop 550, target 480-490. Twenty minutes later he revised it - 559 as a safer stop and around 482 as the target - and said plainly that he was not taking it, and that anyone who did should risk 1-2% at most. The idea worked without him: on the afternoon of 16 June he told the room it had moved more than 1R and they should take the full target or at least 50% and move the stop to entry, and ninety minutes later that it was nearly 2R up, so get out or trim another 25%, with no further updates coming. | AD99: high | AE99: He states outright that he is not taking this one, so every management instruction here is follower guidance rather than his own execution and there is no entry, exit or R for him. The stop and target revisions are recorded because for a not-taken idea the published plan is all there is. The idea itself ran nearly 2R. | AF99: #500, #501, #509, #510 | AG99: https://discord.com/channels/1042855255089623100/1501271173588193290/1516136201973923951
A100: 99 | B100: 2026-06-15 22:08:50 | C100: XMRUSDT | D100: long | E100: unknown | F100: unknown | J100: 357 | K100: CMP | M100: 320 | N100: 400 | O100: soft stop was a 4h close under 330, hard stop 320 | S100: 390/400 -> 392 | V100: 2026-06-15 22:08:50 | Y100: Long XMR at 357 for a run at 400, with a 4h-close stop under 330 and a hard stop at 320. | Z100: He called XMR long at 357 CMP targeting 400, with a soft stop on a 4h close under 330 and a hard stop at 320. Two hours later he said XMR was doing great and that he would take profit around 390-400 instead, then an hour after that fixed the target at 392, which he described as 1R. By the following afternoon the move had gone: 'XMR died lol'. Nothing further is ever posted - no take profit, no stop, no close. | AA100: 4h close | AD100: low | AE100: The outcome is genuinely unreported: after 'XMR died lol' on 16 June the file never mentions XMR again across the remaining two months, so the position is treated as ended at an unknown price rather than still running. He also never confirms his own fill. | AF100: #502, #503, #505, #506 | AG100: https://discord.com/channels/1042855255089623100/1501271173588193290/1516157555687030805
...

Sheet Events
A1: Msg | B1: Timestamp | C1: Event | D1: Symbol | E1: Side | F1: Entry | G1: DCA | H1: Targets | I1: Stop | J1: Portion % | K1: Leverage | L1: R | M1: ROI % | N1: Price referenced | O1: Risk note | P1: Why he did it | Q1: Indicators | R1: Market context | S1: What he wrote | T1: Confidence | U1: Link
A2: 1 | B2: 2026-05-06 23:44:07 | C2: chat | P2: introduction post thanking God, Chento and john.scx for the place in the server | S2: Hello everyone, First I would like to thank God for everything then @Chento (Won’t DM first) who has given me a place in his space, also @john.scx who had been very kind and patient with me! | T2: high | U2: https://discord.com/channels/1042855255089623100/1501271173588193290/1501686019504865280
A3: 1 | B3: 2026-05-06 23:44:07 | C3: education | O3: never ever let go of risk management, hold onto risk management if you want to hold on your money long term | P3: explains he posts both High R / low win-rate and high win-rate / low R trades and will label the type so followers can match their own strategy; only request is that they keep risk management | S3: I do all sorts of trades High R Low Wins and High Win rate and Low R trades, I'll try to write what kind of trade it is so whatever your strategy is you can go with it, my only request from you guys would be never ever let go of risk management, hold onto risk management if you want to hold on your money long term. | T3: high | U3: https://discord.com/channels/1042855255089623100/1501271173588193290/1501686019504865280
A4: 2 | B4: 2026-05-06 23:47:41 | C4: recap | P4: one month of journal trading: 25 trades, 22 wins, 3 BE, 0 losses; screenshot lists the tickers (ASTER, AXS, IRYS, BTC x many, ETH, HYPE, PEPE, SOL, ALGO) | S4: I have been trading for the past month in journals and here's my progress so far **25** trades **22** Wins **3** BE **0** loss | T4: high | U4: https://discord.com/channels/1042855255089623100/1501271173588193290/1501686917828448277
A5: 4 | B5: 2026-05-07 02:33:26 | C5: plan | O5: flags the two upcoming trades as risky | P5: announces he is about to take 2 risky trades; wanted a safe start but could not resist | S5: Guys I'm out taking 2 risky trades here, I wanted a safe start but I can't resist. | T5: high | U5: https://discord.com/channels/1042855255089623100/1501271173588193290/1501728631683027075
A6: 5 | B6: 2026-05-07 02:34:43 | C6: call | D6: UNIUSDT | E6: long | F6: 3.46 | H6: 3.669 | I6: 3.28 | N6: 3.46 | P6: long at current market price; he takes TPs manually but followers can set the order | S6: Long UNI Entry: 3.46 CMP TP1: 3.669 (I take manual TPs but you can set in case) SL: 3.28 | T6: high | U6: https://discord.com/channels/1042855255089623100/1501271173588193290/1501728955470712946
A7: 6 | B7: 2026-05-07 02:35:46 | C7: call | D7: ETHUSDT | E7: long | F7: 2348 | H7: 2420 | I7: 2292 | N7: 2348 | P7: long at CMP; TP taken manually so he may close before or later than 2420 | S7: Long ETH Entry: 2348 CMP TP: 2420 (Again I take manual might close before or later) SL: 2292 | T7: high | U7: https://discord.com/channels/1042855255089623100/1501271173588193290/1501729216969048065
A8: 7 | B8: 2026-05-07 02:36:23 | C8: view | D8: BTCUSDT | O8: labels the UNI and ETH longs risky | P8: the UNI and ETH longs are risky because BTC could retrace further, but he expects the 80k region (80s) to hold and at least a visit to 82k+, which would give a scalp on both | Q8: support/resistance | R8: BTC could retrace more; expects 80s to hold and 82k+ visit | S8: Risky trades because BTC could retrace more but I'm expecting 80s to hold, at least visit 82k+ should give us a scalp opportunity on both! | T8: high | U8: https://discord.com/channels/1042855255089623100/1501271173588193290/1501729374641197106
A9: 8 | B9: 2026-05-07 11:06:57 | C9: call | D9: BTCUSDT | E9: long | F9: 81500 | G9: 80800 | H9: 82500 | I9: 79600 | J9: 20 | O9: if he does not update, trim 20-25% at the first TP | P9: scalp long with a DCA level at 80.8k; manual TP but instructs trimming 20-25% at 82.5k if he goes quiet | S9: Long BTC (scalp) Entry: 81.5k DCA: 80.8k First TP @ 82.5k (Can take manual TP earlier or later but if I don't update trim 20-25% at 82.5k) SL: 79600 | T9: high | U9: https://discord.com/channels/1042855255089623100/1501271173588193290/1501857862148952084
A10: 9 | B10: 2026-05-07 11:07:30 | C10: dca | D10: BTCUSDT | E10: long | J10: 50 | O10: Entry: 50% / DCA: 50% | P10: sizing split for the BTC scalp - half the intended size at entry, half held back for the 80.8k DCA | S10: Entry: 50% DCA: 50% | T10: medium | U10: https://discord.com/channels/1042855255089623100/1501271173588193290/1501858001068228840
A11: 10 | B11: 2026-05-07 12:57:30 | C11: dca | D11: BTCUSDT | E11: long | G11: 80900 | P11: filled the DCA manually at 80.9k because price missed his 80.8k DCA order by about $10 | S11: DCAed manually at 80.9k because missed by 10$ | T11: medium | U11: https://discord.com/channels/1042855255089623100/1501271173588193290/1501885683806240808
A12: 11 | B12: 2026-05-07 15:32:55 | C12: call | D12: ZROUSDT | E12: long | F12: 1.48 | H12: 1.5523 | I12: 1.36 | N12: 1.48 | O12: Keep 50-30% funds for DCA but optional you can go all in here I'm not saving for DCA personally | P12: long at CMP; manual TP but if he goes quiet take profit around 1.5523; says this is the last new position before something exits | S12: Long ZRO Entry: 1.48 CMP Keep 50-30% funds for DCA but optional you can go all in here I'm not saving for DCA personally TP: Manual, IF I don't give TP in a while just TP it around 1.5523 SL: 1.36 | T12: high | U12: https://discord.com/channels/1042855255089623100/1501271173588193290/1501924796072464426
A13: 12 | B13: 2026-05-07 15:35:12 | C13: entry | D13: ZROUSDT | E13: long | F13: 1.486 | N13: 1.486 | P13: corrects the ZRO entry - CMP was actually 1.486 because price moved fast after the call | S13: 1.486 was CMP, moved fast | T13: medium | U13: https://discord.com/channels/1042855255089623100/1501271173588193290/1501925370071355604
A14: 12 | B14: 2026-05-07 15:35:12 | C14: dca | D14: ZROUSDT | E14: long | G14: 1.45 | J14: 50 | O14: enter 50% here, and 50% 1.45, your choice if you want to enter fully here | P14: gives a split entry for ZRO after the fast move - half at market, half at 1.45 | S14: I advise enter 50% here, and 50% 1.45, your choice if you want to enter fully here | T14: medium | U14: https://discord.com/channels/1042855255089623100/1501271173588193290/1501925370071355604
A15: 13 | B15: 2026-05-07 15:35:55 | C15: update | D15: ZROUSDT | E15: long | H15: 1.5523 | P15: reiterates the ZRO fallback TP level in case he does not post a manual TP; no change to the target | S15: IF I don't give TP in a while just TP it around 1.5523 | T15: medium | U15: https://discord.com/channels/1042855255089623100/1501271173588193290/1501925550992654406
A16: 14 | B16: 2026-05-07 15:41:53 | C16: view | D16: GOLD | E16: long | O16: declines the setup because he already has too many positions | P16: gold looks longable but he is not taking it - too many positions open | S16: Gold looks Longable but too many positions for now! | T16: high | U16: https://discord.com/channels/1042855255089623100/1501271173588193290/1501927050284372139
A17: 15 | B17: 2026-05-07 19:48:16 | C17: stopped_out | D17: BTCUSDT | E17: long | P17: the BTC scalp is about to be stopped and may already have been on some exchanges; had gone to BE before the drop | R17: unexpected drop | S17: ETH stopped, BTC about to get stopped (on some exchanges maybe it already did) Both went BE but didn't expect a drop so stopped. | T17: medium | U17: https://discord.com/channels/1042855255089623100/1501271173588193290/1501989056202936340
A18: 15 | B18: 2026-05-07 19:48:16 | C18: stopped_out | D18: ETHUSDT | E18: long | P18: ETH stopped; it had gone to BE first but the unexpected drop took it out - calls it a rough start and apologises | R18: unexpected drop | S18: ETH stopped, BTC about to get stopped (on some exchanges maybe it already did) Both went BE but didn't expect a drop so stopped. | T18: high | U18: https://discord.com/channels/1042855255089623100/1501271173588193290/1501989056202936340
A19: 17 | B19: 2026-05-08 01:40:42 | C19: call | D19: BTCUSDT | E19: long | F19: 79700 | H19: 80500 | I19: 78500 | N19: 79700 | P19: long at CMP with a conditional stop - 1h close under 79k, otherwise the hard stop at 78.5k | Q19: 1h close | S19: Long BTC Entry: 79.7k CMP TP: 80.5k SL: 1h close under 79k or hard SL @ 78.5k | T19: high | U19: https://discord.com/channels/1042855255089623100/1501271173588193290/1502077749882523759
A20: 18 | B20: 2026-05-08 04:08:16 | C20: dca | D20: BTCUSDT | E20: long | G20: 79469 | O20: equal DCA (same size as the initial entry) | P20: places an equal-sized DCA at 79469; position is sitting at breakeven right now so followers can adjust | S20: Putting an equal DCA @ 79469 At BE rn so you can adjust accordingly | T20: high | U20: https://discord.com/channels/1042855255089623100/1501271173588193290/1502114884362702878
A21: 19 | B21: 2026-05-08 06:24:00 | C21: dca | D21: BTCUSDT | E21: long | F21: 79590 | G21: 79469 | P21: the 79469 DCA filled; blended position now sits at breakeven at 79590 | S21: DCA filled and at BE (79590) | T21: high | U21: https://discord.com/channels/1042855255089623100/1501271173588193290/1502149041889218672
A22: 19 | B22: 2026-05-08 06:24:00 | C22: partial_close | D22: BTCUSDT | E22: long | J22: 50 | N22: 79590 | O22: take out your DCA value here | P22: instructs taking the DCA portion back off at breakeven so it can be re-placed lower (clarified in msg 21 as 50%) | S22: Kindly take out your DCA value here. | T22: high | U22: https://discord.com/channels/1042855255089623100/1501271173588193290/1502149041889218672
A23: 19 | B23: 2026-05-08 06:24:00 | C23: dca | D23: BTCUSDT | E23: long | G23: 78600 | O23: equal DCA | P23: re-places the equal DCA lower at 78.6k after taking the filled DCA off at BE; TP to be taken manually; confident the trade exits green | S23: Putting equal DCA @ 78.6k SL @ 77.6k TP MANUALLY! I know it's sound messy but I'm confident we will exit this one in green! | T23: high | U23: https://discord.com/channels/1042855255089623100/1501271173588193290/1502149041889218672
A24: 19 | B24: 2026-05-08 06:24:00 | C24: sl_move | D24: BTCUSDT | E24: long | I24: 77600 | P24: stop widened from 78.5k to 77.6k to sit below the new 78.6k DCA level | S24: SL @ 77.6k | T24: high | U24: https://discord.com/channels/1042855255089623100/1501271173588193290/1502149041889218672
A25: 21 | B25: 2026-05-08 06:24:33 | C25: partial_close | D25: BTCUSDT | E25: long | G25: 78600 | J25: 50 | P25: clarifies msg 19 - take 50% (the filled DCA half) off here and re-place it as a limit at 78.6k | S25: Basically take out 50% DCA here and put it at 78.6k | T25: high | U25: https://discord.com/channels/1042855255089623100/1501271173588193290/1502149183405293568
A26: 22 | B26: 2026-05-08 06:43:06 | C26: call | D26: AVNTUSDT | E26: long | F26: 0.158 | H26: 0.1746, 0.2023 | I26: 0.1411 | N26: 0.158 | P26: long at CMP with two targets | S26: Long AVNT Entry: 0.158 CMP TP: 0.1746 0.2023 SL: 0.1411 | T26: high | U26: https://discord.com/channels/1042855255089623100/1501271173588193290/1502153850231193630
A27: 23 | B27: 2026-05-08 06:43:37 | C27: update | O27: Manage risk. | P27: position roll call - UNI, ZRO, BTC and AVNT all running | S27: We have 4 positions running UNI ZRO BTC AVNT Manage risk. | T27: high | U27: https://discord.com/channels/1042855255089623100/1501271173588193290/1502153981391012050
A28: 23 | B28: 2026-05-08 06:43:37 | C28: education | O28: I risk 2% on normal traders and 1% on risky ones | P28: states his own position sizing rule - 2% risk on normal trades, 1% on the ones he flags as risky | S28: I risk 2% on normal traders and 1% on risky ones! | T28: high | U28: https://discord.com/channels/1042855255089623100/1501271173588193290/1502153981391012050
A29: 24 | B29: 2026-05-08 07:21:04 | C29: view | E29: long | O29: caps himself at 4 open positions | P29: likes SLP and KERNEL as longs too but is holding at four positions until the current TPs come in | S29: I like SLP and KERNEL too but I think 4 are enough for now, let's get these TPs first | T29: high | U29: https://discord.com/channels/1042855255089623100/1501271173588193290/1502163404553715722
A30: 25 | B30: 2026-05-08 13:48:41 | C30: partial_close | D30: BTCUSDT | E30: long | F30: 79564.8 | H30: 80500 | J30: 20 | P30: BTC started moving - optional 20% trim at 80.5k; he will post when he closes. Screenshot shows his entry price 79,564.80 | S30: BTC started moving, you can take 20% @ 80.5k if you want, I'll update whenever I close! | T30: high | U30: https://discord.com/channels/1042855255089623100/1501271173588193290/1502260952098279615
A31: 26 | B31: 2026-05-08 18:44:20 | C31: partial_close | D31: UNIUSDT | E31: long | J31: 50 | K31: 50 | L31: 0.7 | M31: 101.21 | P31: treats UNI as the channel's first win and books half the position at a 0.7R move; PnL card shows the 50x UNI long closed at +101.21% ROI | S31: Okay let's treat as our first win Closing 50% UNI for 0.7 R move | T31: high | U31: https://discord.com/channels/1042855255089623100/1501271173588193290/1502335355628687451
A32: 26 | B32: 2026-05-08 18:44:20 | C32: tp_move | D32: UNIUSDT | E32: long | H32: 3.7, 4 | P32: target lifted from the original 3.669 - he will fully take profit at 3.7 while followers can hold for 4 | S32: I'll take personally fully TP @ 3.7 You can hold till 4 | T32: high | U32: https://discord.com/channels/1042855255089623100/1501271173588193290/1502335355628687451
A33: 26 | B33: 2026-05-08 18:44:20 | C33: sl_move | D33: UNIUSDT | E33: long | F33: 3.46 | I33: 3.46 | P33: stop moved to breakeven at the 3.46 entry after taking the 50% partial | S33: SL @ BE 3.46 | T33: high | U33: https://discord.com/channels/1042855255089623100/1501271173588193290/1502335355628687451
A34: 27 | B34: 2026-05-08 18:47:55 | C34: call | D34: KERNELUSDT | E34: long | F34: 0.064 | H34: 0.066 | I34: 0.581 | P34: high win rate / low R trade; manual TP targeting ~0.066 first, stop is a 4h close under the level or the hard stop. NOTE: he wrote the stops as 0.59 and 0.581, which are recorded verbatim but are almost certainly typos for 0.059 / 0.0581 given the 0.064 entry | Q34: 4h close | S34: Long KERNEL Entry: 0.064 TP: Manually, targeting first around 0.066 SL: 4h under 0.59 or hard SLs at 0.581 High Win rate Low R trade | T34: medium | U34: https://discord.com/channels/1042855255089623100/1501271173588193290/1502336255449366558
A35: 28 | B35: 2026-05-08 18:48:07 | C35: update | D35: KERNELUSDT | E35: long | N35: 0.064 | P35: clarifies that the 0.064 KERNEL entry is at current market price | S35: CMP ^ | T35: medium | U35: https://discord.com/channels/1042855255089623100/1501271173588193290/1502336308406911027
A36: 29 | B36: 2026-05-08 19:41:13 | C36: close | D36: UNIUSDT | E36: long | H36: 3.7 | J36: 100 | L36: 1.4 | N36: 3.7 | P36: UNI broke out ('blew up') and he exited the remainder at his 3.7 target for about 1.4R; chart shows UNIUSDT +7.52% with a parabolic breakout to 3.698 | S36: Well UNI blew up, I'm fully out here @ 3.7 for around 1.4 R | T36: high | U36: https://discord.com/channels/1042855255089623100/1501271173588193290/1502349669571891250
A37: 29 | B37: 2026-05-08 19:41:13 | C37: view | D37: UNIUSDT | E37: long | N37: 4 | P37: expects UNI to reach $4 by the coming weekend or week even though he is out | S37: Think we see 4$ by coming weekend/week | T37: high | U37: https://discord.com/channels/1042855255089623100/1501271173588193290/1502349669571891250
A38: 30 | B38: 2026-05-08 19:41:59 | C38: chat | P38: clarifies the Demo Trading watermark on his screenshots - he trades a CFT funded account on Bybit, not demo | S38: Btw not trading demo it's CFT funded account on Bybit just clarifying | T38: high | U38: https://discord.com/channels/1042855255089623100/1501271173588193290/1502349863180828906
A39: 31 | B39: 2026-05-08 19:49:28 | C39: call | D39: SNXUSDT | E39: long | F39: 0.354 | G39: 0.334 | H39: 0.39 | I39: 0.31 | J39: 50 | L39: 1 | N39: 0.354 | O39: DCA is 50% of size; TP1 closes 50% of the position | P39: long at CMP with a 50% DCA at 0.334; first target 0.39 is 1R and takes half off, second target to be given later | S39: Long SNX Entry: 0.354 CMP DCA: 0.334 (50%) TP: 0.39 (1R) (50%) TP2 later SL: 0.31 | T39: high | U39: https://discord.com/channels/1042855255089623100/1501271173588193290/1502351744259063878
A40: 32 | B40: 2026-05-08 19:54:13 | C40: update | O40: please manage risk 1-2% per trade | P40: position roll call - BTC, KERNEL, ZRO, AVNT and SNX running | S40: Running BTC KERNEL ZRO AVNT SNX | T40: high | U40: https://discord.com/channels/1042855255089623100/1501271173588193290/1502352942743818250
A41: 32 | B41: 2026-05-08 19:54:13 | C41: view | E41: long | O41: will not add them - five positions are enough | P41: sees ASTER, NEAR and SOL as ready for a weekend pump but is not taking them | R41: expects a weekend alt pump | S41: I like many more ALTs that look ready for a weekend PUMP ASTER, NEAR, SOL but these are enough, please manage risk 1-2% per trade. | T41: high | U41: https://discord.com/channels/1042855255089623100/1501271173588193290/1502352942743818250
A42: 33 | B42: 2026-05-08 21:22:35 | C42: plan | D42: BTCUSDT | E42: long | F42: 79500 | H42: 81000, 82000 | P42: expects a hard BTC pump over the weekend to the previous daily high; a 4h close above 80.5k would put 81-82k in play, where he intends to close the long he holds from 79.5k | Q42: 4h close, previous daily high | R42: weekend | S42: I have a feeling we will pump hard on BTC this weekend, can visit previous daily high. 4h close above 80.5k and I would expect 81-82k, where I'll be looking to close my long from 79.5k | T42: high | U42: https://discord.com/channels/1042855255089623100/1501271173588193290/1502375178162933760
A43: 34 | B43: 2026-05-09 02:01:21 | C43: education | O43: limits the number of calls because followers ignore risk management and go all in | P43: the alts he named (SOL, NEAR, PUMPFUN, ASTER charts attached) all popped off; explains he caps his own calls because followers do not manage risk, and tells them to do their own analysis on any coin he mentions | R43: alt market moving up | S43: Look at them go, every ALT I mentioned here just popping off even ASTER started moving Usually I'm already in too many trades and have to limit myself for giving positions because I feel like people don't care about risk management and jump in all in. But if I ever mention a coin and you can do some analysis, check them out! | T43: high | U43: https://discord.com/channels/1042855255089623100/1501271173588193290/1502445332355878943
A44: 35 | B44: 2026-05-09 04:45:42 | C44: tp_hit | D44: KERNELUSDT | E44: long | F44: 0.06454 | H44: 0.066 | K44: 20 | M44: 49.35 | N44: 0.06615 | P44: KERNEL reached the first target; share card shows the 20x long still open, entry 0.06454, mark 0.06615, +49.35% ROI | S44: KERNEL TP1 here, next TP @ 0.0673 | T44: high | U44: https://discord.com/channels/1042855255089623100/1501271173588193290/1502486692232298586
A45: 35 | B45: 2026-05-09 04:45:42 | C45: tp_set | D45: KERNELUSDT | E45: long | H45: 0.0673 | P45: sets the second KERNEL target at 0.0673 after TP1 | S45: next TP @ 0.0673 | T45: high | U45: https://discord.com/channels/1042855255089623100/1501271173588193290/1502486692232298586
A46: 36 | B46: 2026-05-09 04:48:32 | C46: update | D46: AVNTUSDT | E46: long | F46: 0.15851 | K46: 50 | M46: 265.55 | N46: 0.16787 | P46: running-trade card in the batch update - AVNT 50x long open at +265.55% (entry 0.15851, mark 0.16787) | S46: All trades running in good profits, take TP whenever you want, don't let them round trip. I'll update when I close. | T46: high | U46: https://discord.com/channels/1042855255089623100/1501271173588193290/1502487407654862971
A47: 36 | B47: 2026-05-09 04:48:32 | C47: update | D47: BTCUSDT | E47: long | F47: 79764.4 | K47: 100 | M47: 67.25 | N47: 80333.9 | P47: running-trade card in the batch update - BTC 100x long open at +67.25% (entry 79,764.40, mark 80,333.90) | S47: All trades running in good profits, take TP whenever you want, don't let them round trip. I'll update when I close. | T47: high | U47: https://discord.com/channels/1042855255089623100/1501271173588193290/1502487407654862971
A48: 36 | B48: 2026-05-09 04:48:32 | C48: update | D48: KERNELUSDT | E48: long | F48: 0.06454 | K48: 20 | M48: 49.35 | N48: 0.06615 | P48: running-trade card in the batch update - KERNEL 20x long open at +49.35%; tells followers to take TP whenever they want and not let winners round trip | S48: All trades running in good profits, take TP whenever you want, don't let them round trip. I'll update when I close. | T48: high | U48: https://discord.com/channels/1042855255089623100/1501271173588193290/1502487407654862971
A49: 36 | B49: 2026-05-09 04:48:32 | C49: update | D49: SNXUSDT | E49: long | F49: 0.3545 | K49: 25 | M49: 118.67 | N49: 0.3727 | P49: running-trade card in the batch update - SNX 25x long open at +118.67% (entry 0.3545, mark 0.3727) | S49: All trades running in good profits, take TP whenever you want, don't let them round trip. I'll update when I close. | T49: high | U49: https://discord.com/channels/1042855255089623100/1501271173588193290/1502487407654862971
A50: 36 | B50: 2026-05-09 04:48:32 | C50: update | D50: UNIUSDT | E50: long | F50: 3.458 | K50: 50 | M50: 101.21 | N50: 3.528 | P50: re-posted closed card inside the batch - UNI 50x long, entry 3.458, exit 3.528, +101.21%, documenting the earlier partial close | S50: All trades running in good profits, take TP whenever you want, don't let them round trip. I'll update when I close. | T50: medium | U50: https://discord.com/channels/1042855255089623100/1501271173588193290/1502487407654862971
A51: 36 | B51: 2026-05-09 04:48:32 | C51: update | D51: ZROUSDT | E51: long | F51: 1.4744 | K51: 50 | M51: 34.43 | N51: 1.4849 | P51: running-trade card in the batch update - ZRO 50x long open at +34.43% (entry 1.4744, mark 1.4849) | S51: All trades running in good profits, take TP whenever you want, don't let them round trip. I'll update when I close. | T51: high | U51: https://discord.com/channels/1042855255089623100/1501271173588193290/1502487407654862971
A52: 38 | B52: 2026-05-09 04:52:10 | C52: close | D52: SYRUPUSDT | E52: long | F52: 0.25328 | J52: 100 | K52: 25 | M52: 67.61 | N52: 0.26013 | P52: closes an older Journals trade out of impatience after holding it 10 days, despite believing it will blow up; 25x long exited 0.26013 for +67.61% | S52: Also closing this trade from Journals, 100% this is gonna blow up but I have been holding for 10 days, its getting annoying. | T52: high | U52: https://discord.com/channels/1042855255089623100/1501271173588193290/1502488322143162518
A53: 39 | B53: 2026-05-09 04:54:13 | C53: education | O53: SL to Entry after TP1 | P53: general rule reminder - move the stop to entry once TP1 is taken; posted as a reply to the KERNEL TP1 message | S53: Common knowledge but a reminder, SL to Entry after TP1 | T53: high | U53: https://discord.com/channels/1042855255089623100/1501271173588193290/1502488837132259390
A54: 39 | B54: 2026-05-09 04:54:13 | C54: sl_move | D54: KERNELUSDT | E54: long | P54: posted as a reply to the KERNEL TP1 message, so it implies moving the KERNEL stop to entry; he did not restate the entry level so no stop price is recorded | S54: Common knowledge but a reminder, SL to Entry after TP1 | T54: low | U54: https://discord.com/channels/1042855255089623100/1501271173588193290/1502488837132259390
A55: 40 | B55: 2026-05-09 06:06:56 | C55: close | D55: BTCUSDT | E55: long | F55: 79764.4 | J55: 100 | K55: 100 | M55: 72.31 | N55: 80400 | P55: closes the BTC long at 80.4k; card shows the 100x long exited at 80,341.20 from 79,764.40 for +72.31% | S55: Closing BTC @ 80.4k | T55: high | U55: https://discord.com/channels/1042855255089623100/1501271173588193290/1502507137337786561
A56: 41 | B56: 2026-05-09 06:54:44 | C56: update | D56: BTCUSDT | E56: long | F56: 79500 | P56: clarifies the BTC entry - original entry was 79.5k, the card shows 79.7k because he added margin | S56: BTW 79.5k was the original entry I added more margin so it shows 79.7k | T56: high | U56: https://discord.com/channels/1042855255089623100/1501271173588193290/1502519166286954537
A57: 42 | B57: 2026-05-09 07:10:34 | C57: plan | D57: BTCUSDT | E57: long | F57: 80300 | I57: 79000 | P57: wants to re-long BTC because he still believes it pumps hard and makes a new daily high or at least visits the previous high, but would rather wait for a ~80.3k entry than take CMP | Q57: previous daily high | S57: Kinda wanna long BTC again from CMP with SL 79k because as I said earlier I believe BTC will pump hard and might make a new daily High or at least visit previous High but will wait if I can get an entry around 80.3k | T57: high | U57: https://discord.com/channels/1042855255089623100/1501271173588193290/1502523149831634995
A58: 43 | B58: 2026-05-09 09:53:50 | C58: plan | D58: BTCUSDT | E58: long | F58: 79000 | G58: 78000 | I58: 77000 | O58: don't place any limits, wait for his entry confirmation | P58: lower timeframes look bearish so he waits; plans to re-use the previous setup (79k entry, 78k DCA, 77k SL) and will call the entry live rather than have followers leave limit orders | Q58: LTF | R58: LTF looks bearish | S58: LTF looks bearish so waiting for entry, I would like to use the same setup as before, 79k entry, 78k DCA, 77k SL but don't place any limits I'll let you know when I enter. Looking to long in 79k region! | T58: medium | U58: https://discord.com/channels/1042855255089623100/1501271173588193290/1502564237762101269
A59: 44 | B59: 2026-05-09 11:51:05 | C59: call | D59: STABLEUSDT | E59: long | F59: 0.0346 | H59: 0.04 | I59: 0.03 | N59: 0.0346 | P59: swing long at CMP that will take time; intraday/scalp traders should wait for the BTC scalp instead | S59: Long STABLE (Swing) Entry: 0.0346 CMP TP: 0.04 SL: 0.03 Will take some time, if you like intradays/scalps wait for BTC scalp! | T59: high | U59: https://discord.com/channels/1042855255089623100/1501271173588193290/1502593742513635530
A60: 45 | B60: 2026-05-09 13:58:20 | C60: call | D60: ETHUSDT | E60: long | F60: 2310 | G60: 2290 | I60: 2260 | N60: 2310 | O60: DCA is 50% of size | P60: long at CMP with a 50% DCA at 2290; no target given in this message | S60: Long ETH Entry: 2310 CMP DCA: 2290 (50%) SL: 2260 | T60: high | U60: https://discord.com/channels/1042855255089623100/1501271173588193290/1502625769904406701
A61: 46 | B61: 2026-05-09 14:00:58 | C61: tp_set | D61: ETHUSDT | E61: long | H61: 2350 | P61: gives the ETH target - 2350+, closed manually | S61: Will close manually but targeting 2350+ | T61: medium | U61: https://discord.com/channels/1042855255089623100/1501271173588193290/1502626428687220946
A62: 47 | B62: 2026-05-09 14:01:21 | C62: update | P62: position roll call - ZRO, AVNT, STABLE, SNX and ETH running | S62: Trades running ZRO AVNT STABLE SNX ETH | T62: high | U62: https://discord.com/channels/1042855255089623100/1501271173588193290/1502626528754925680
A63: 48 | B63: 2026-05-09 14:12:56 | C63: view | D63: TAKEUSDT | E63: long | O63: wants at least 2 positions closed before opening new ones | P63: TAKE looks good for a long but he is at position capacity | S63: TAKE looking good for long but too many positions running at the moment I want at least 2 out for new trades, see you at TPs | T63: high | U63: https://discord.com/channels/1042855255089623100/1501271173588193290/1502629441908510731
A64: 49 | B64: 2026-05-10 18:45:44 | C64: close | D64: ETHUSDT | E64: long | F64: 2311.73 | J64: 100 | K64: 100 | M64: 124.58 | N64: 2340.53 | P64: closes the ETH long calling it good enough for a weekend scalp; 100x long exited 2340.53 from 2311.73 for +124.58% | R64: weekend | S64: Alright guys good enough for a weekend scalp, closing it here! | T64: high | U64: https://discord.com/channels/1042855255089623100/1501271173588193290/1503060481118568578
A65: 50 | B65: 2026-05-10 18:47:56 | C65: tp_hit | D65: ETHUSDT | E65: long | H65: 2350 | N65: 2350 | P65: the 2350 ETH target printed moments after he closed and posted the screenshot | S65: 2350 was my target, already hit while I was sending the screenshot. | T65: medium | U65: https://discord.com/channels/1042855255089623100/1501271173588193290/1503061037740458126
A66: 51 | B66: 2026-05-10 18:50:39 | C66: update | D66: STABLEUSDT | E66: long | P66: STABLE has not moved - still trading around his entry | S66: STABLE has been really STABLE still around entry | T66: high | U66: https://discord.com/channels/1042855255089623100/1501271173588193290/1503061718493036725
A67: 52 | B67: 2026-05-10 21:01:23 | C67: partial_close | D67: AVNTUSDT | E67: long | F67: 0.15851 | K67: 50 | M67: 246.69 | N67: 0.16709 | P67: takes TP1 on AVNT at the current 0.16709 with the 50x long still open at +246.69%; portion not specified | S67: AVNT TP1 here, fully close @ 0.1746 | T67: medium | U67: https://discord.com/channels/1042855255089623100/1501271173588193290/1503094618345181387
A68: 52 | B68: 2026-05-10 21:01:23 | C68: tp_move | D68: AVNTUSDT | E68: long | H68: 0.1746 | J68: 100 | P68: the rest of AVNT now comes off at 0.1746 rather than being held for the original second target at 0.2023 | S68: AVNT TP1 here, fully close @ 0.1746 | T68: high | U68: https://discord.com/channels/1042855255089623100/1501271173588193290/1503094618345181387
A69: 53 | B69: 2026-05-10 21:02:37 | C69: plan | D69: SNXUSDT | E69: long | P69: close to closing SNX on gut feel with no technical reason given | S69: I'm this close to closing SNX idk why but I just want to close | T69: high | U69: https://discord.com/channels/1042855255089623100/1501271173588193290/1503094928329412670
A70: 53 | B70: 2026-05-10 21:02:37 | C70: update | D70: ZROUSDT | E70: long | H70: 1.5523 | P70: ZRO has been rejecting from the 1.5523 TP for three days; advises taking profit early if a drop appears | S70: ZRO is edging me off keeps coming back from TP @ 1.5523 since 3 days, take TP early if you see a drop. | T70: high | U70: https://discord.com/channels/1042855255089623100/1501271173588193290/1503094928329412670
A71: 54 | B71: 2026-05-10 22:10:30 | C71: partial_close | D71: ZROUSDT | E71: long | F71: 1.4744 | H71: 1.55 | J71: 25 | K71: 50 | M71: 178.94 | N71: 1.53 | P71: books 25% of ZRO at 1.53 (+178.94% on the 50x) and plans the full exit around 1.55+, will update if he sees weakness | S71: 25% here, fully exit around 1.55+ Will update if I see weakness | T71: high | U71: https://discord.com/channels/1042855255089623100/1501271173588193290/1503112014283673735
A72: 55 | B72: 2026-05-10 22:13:10 | C72: recap | P72: claims eight consecutive wins since the rough start | S72: That's 8 wins in a row! | T72: high | U72: https://discord.com/channels/1042855255089623100/1501271173588193290/1503112683346726943
A73: 56 | B73: 2026-05-10 23:33:31 | C73: close | D73: SNXUSDT | E73: long | F73: 0.3545 | J73: 100 | K73: 25 | M73: 55.8 | N73: 0.3626 | P73: closes SNX in profit because he expects a pullback; plans to re-open after Monday. Card: 25x long entry 0.3545, mark 0.3626, +55.80% | R73: expects a market pullback | S73: Closing SNX in some profits, we're gonna have a pullback will open again after Monday | T73: high | U73: https://discord.com/channels/1042855255089623100/1501271173588193290/1503132904983756810
A74: 57 | B74: 2026-05-11 00:40:45 | C74: breakeven | D74: ZROUSDT | E74: long | P74: the remaining ZRO was stopped at breakeven after TP1 had already been taken | S74: ZRO stopped out on BE after TP1 | T74: high | U74: https://discord.com/channels/1042855255089623100/1501271173588193290/1503149825196036228
A75: 57 | B75: 2026-05-11 00:40:45 | C75: call | D75: ZROUSDT | E75: long | F75: 1.486 | G75: 1.42 | H75: 1.55 | I75: 1.37 | P75: immediately re-enters the ZRO long after the BE stop, with a lower DCA at 1.42 and the same 1.55 target | S75: Entered long again Entry: 1.486 DCA: 1.42 TP1: 1.55 SL: 1.37 | T75: high | U75: https://discord.com/channels/1042855255089623100/1501271173588193290/1503149825196036228
A76: 58 | B76: 2026-05-11 01:30:22 | C76: view | D76: BTCUSDT | E76: long | P76: bullish - expects BTC at 84-85k in the coming week | R76: expects 84-85k next week | S76: Expecting 84-85k coming week, I'm bullish. | T76: medium | U76: https://discord.com/channels/1042855255089623100/1501271173588193290/1503162313224749176
A77: 59 | B77: 2026-05-11 02:30:48 | C77: call | D77: BTCUSDT | E77: short | F77: 82300 | G77: 83000 | I77: 83650 | N77: 82300 | P77: counter-trend short at CMP with a DCA higher at 83k; no target in this message | S77: Short BTC Entry: 82.3k CMP DCA: 83k SL: 83650 | T77: high | U77: https://discord.com/channels/1042855255089623100/1501271173588193290/1503177518499233970
A78: 60 | B78: 2026-05-11 02:31:01 | C78: tp_set | D78: BTCUSDT | E78: short | H78: 80000, 81000 | P78: target zone for the BTC short - looking to cover in the 80-81k region | S78: Looking to scalp it around 80-81 | T78: medium | U78: https://discord.com/channels/1042855255089623100/1501271173588193290/1503177573255872696
A79: 61 | B79: 2026-05-11 03:58:37 | C79: close | D79: BTCUSDT | E79: short | F79: 82202.8 | J79: 100 | K79: 100 | M79: 109.47 | N79: 81302.9 | P79: takes profit on the quick top short; 100x short entry 82,202.80, exit 81,302.90, +109.47% | S79: TPed, fast top short, closed. | T79: high | U79: https://discord.com/channels/1042855255089623100/1501271173588193290/1503199620715642910
A80: 62 | B80: 2026-05-11 03:59:09 | C80: plan | D80: BTCUSDT | E80: long | F80: 80000 | P80: will flip long once price stabilises - the 80k region is where he wants the entry | S80: Will long waiting for it to stabilize, 80k region would be a nice place to long. | T80: medium | U80: https://discord.com/channels/1042855255089623100/1501271173588193290/1503199754027270164
A81: 64 | B81: 2026-05-11 04:00:33 | C81: recap | P81: the BTC short close makes it ten straight wins | S81: Guys that's a 10th streak win ^ | T81: high | U81: https://discord.com/channels/1042855255089623100/1501271173588193290/1503200106894069860
A82: 65 | B82: 2026-05-11 04:02:52 | C82: recap | P82: lists the ten-win streak: UNI, SNX, BTC, ASTER, KERNEL, ZRO, AVNT, SYRUP, ETH, BTC (ASTER was never called in this channel) | S82: UNI SNX BTC ASTER KERNEL ZRO AVNT SYRUP ETH BTC **10/10** | T82: high | U82: https://discord.com/channels/1042855255089623100/1501271173588193290/1503200688010952805
A83: 66 | B83: 2026-05-11 04:03:54 | C83: chat | P83: asks followers who profited to post their PnLs in the profit-showcase channel | S83: If you made anything with me so far I would really appreciate the PNLs #💲｜profit-showcase Thankyou! | T83: high | U83: https://discord.com/channels/1042855255089623100/1501271173588193290/1503200948145619104
A84: 67 | B84: 2026-05-11 09:12:24 | C84: partial_close | D84: ZROUSDT | E84: long | F84: 1.4772 | J84: 20 | K84: 50 | M84: 189.93 | N84: 1.5369 | P84: books 20% of the re-entered ZRO long at 1.5369 (+189.93% on the 50x) and deliberately does NOT move the stop to entry, keeping the original stop | S84: And the streak continues, 20% here not moving SL to entry. | T84: high | U84: https://discord.com/channels/1042855255089623100/1501271173588193290/1503278586050777149
